Workbook

Sheet 요약
A1: 외화 IG 크레딧 포트 운용 요약
A2: ="기준일 "&TEXT(설정!$C$4,"yyyy-mm-dd")&" | 펀드: "&IF(설정!$C$5="선택펀드","선택("&TRIM(IF(설정!$G$16="Y",설정!$F$16&" ","")&IF(설정!$G$17="Y",설정!$F$17&" ","")&IF(설정!$G$18="Y",설정!$F$18&" ","")&IF(설정!$G$19="Y",설정!$F$19&" ","")&IF(설정!$G$20="Y",설정!$F$20&" ","")&IF(설정!$G$21="Y",설정!$F$21&" ","")&IF(설정!$G$22="Y",설정!$F$22&" ","")&IF(설정!$G$23="Y",설정!$F$23&" ","")&IF(설정!$G$24="Y",설정!$F$24&" ","")&IF(설정!$G$25="Y",설정!$F$25&" ","")&IF(설정!$G$26="Y",설정!$F$26&" ","")&IF(설정!$G$27="Y",설정!$F$27&" ","")&IF(설정!$G$28="Y",설정!$F$28&" ","")&IF(설정!$G$29="Y",설정!$F$29&" ","")&IF(설정!$G$30="Y",설정!$F$30&" ","")&IF(설정!$G$31="Y",설정!$F$31&" ","")&IF(설정!$G$32="Y",설정!$F$32&" ","")&IF(설정!$G$33="Y",설정!$F$33&" ","")&IF(설정!$G$34="Y",설정!$F$34&" ","")&IF(설정!$G$35="Y",설정!$F$35&" ","")&IF(설정!$G$36="Y",설정!$F$36&" ",""))&")",설정!$C$5&"")&" | 평가금액(USD 환산) 기준" -> 기준일 2026-10-01 | 펀드: 선택(28096 34507 34578 38168) | 평가금액(USD 환산) 기준
A3: =IF(COUNTIF(설정!$M$7:$M$37,"헤더없음")>0,"⚠ 원자료 헤더를 찾지 못한 항목이 있습니다 — [설정] 헤더 매핑 확인","")&IF(INDEX(원자료_잔고!$A$1:$EZ$1500,설정!$L$5+800+1,설정!$L$8)&""<>""," ⚠ 잔고 행 수가 800개를 초과 — 일부 미집계","")
A4: 지표 | B4: 값 | D4: 1년 보유 시나리오 (선형 근사, 볼록성·듀레이션 감소 무시 / 총수익은 차등·비례 쇼크 기준)
A5: 평가금액($M) | B5: =SUMIFS(보유분석!$AA$2:$AA$801,보유분석!$AC$2:$AC$801,1) -> 1409.3986 | D5: 시나리오 | E5: 금리Δ(bp) | F5: 기본 스프레드Δ(bp) | G5: 캐리+롤다운($) | H5: 금리손익($) | I5: 스프레드손익 균등($) | J5: 스프레드손익 차등·비례($) | K5: 총수익($) | L5: 총수익률(%)
A6: 액면($M) | B6: =SUMIFS(보유분석!$X$2:$X$801,보유분석!$AC$2:$AC$801,1) -> 1441.935 | D6: 기본(무변동) | E6: 0 | F6: 0 | G6: =$B$15 -> 82103986 | H6: =-$B$11*E6 -> 0 | I6: =-$B$12*F6 -> 0 | J6: =-$B$19*F6 -> 0 | K6: =G6+H6+J6 -> 82103986 | L6: =K6/($B$5*1000000) -> 0.058254622
A7: 종목수 / 로트수 | B7: =SUMPRODUCT((보유분석!$AC$2:$AC$801=1)/(COUNTIFS(보유분석!$B$2:$B$801,보유분석!$B$2:$B$801,보유분석!$AC$2:$AC$801,1)+(보유분석!$AC$2:$AC$801<>1)))&" / "&COUNTIFS(보유분석!$AC$2:$AC$801,1) -> 134 / 278 | D7: 금리 상승 | E7: =설정!$C$9 -> 50 | F7: 0 | G7: =$B$15 -> 82103986 | H7: =-$B$11*E7 -> -18961159 | I7: =-$B$12*F7 -> 0 | J7: =-$B$19*F7 -> 0 | K7: =G7+H7+J7 -> 63142827 | L7: =K7/($B$5*1000000) -> 0.044801254
A8: 가중 YTM(%) | B8: =SUMIFS(보유분석!$BA$2:$BA$801,보유분석!$AC$2:$AC$801,1)/SUMIFS(보유분석!$BB$2:$BB$801,보유분석!$AC$2:$AC$801,1) -> 5.6600358 | D8: 금리 하락 | E8: =-설정!$C$9 -> -50 | F8: 0 | G8: =$B$15 -> 82103986 | H8: =-$B$11*E8 -> 18961159 | I8: =-$B$12*F8 -> 0 | J8: =-$B$19*F8 -> 0 | K8: =G8+H8+J8 -> 1.0106514e+08 | L8: =K8/($B$5*1000000) -> 0.07170799
A9: 가중 G-spread(bp, 크레딧) | B9: =SUMIFS(보유분석!$BC$2:$BC$801,보유분석!$AC$2:$AC$801,1)/SUMIFS(보유분석!$BD$2:$BD$801,보유분석!$AC$2:$AC$801,1) -> 66.114006 | D9: 스프레드 확대 | E9: 0 | F9: =설정!$C$10 -> 25 | G9: =$B$15 -> 82103986 | H9: =-$B$11*E9 -> 0 | I9: =-$B$12*F9 -> -9219866.1 | J9: =-$B$19*F9 -> -10177025 | K9: =G9+H9+J9 -> 71926960 | L9: =K9/($B$5*1000000) -> 0.051033794
A10: 가중 듀레이션(년) | B10: =SUMIFS(보유분석!$BE$2:$BE$801,보유분석!$AC$2:$AC$801,1)/SUMIFS(보유분석!$BF$2:$BF$801,보유분석!$AC$2:$AC$801,1) -> 2.6906736 | D10: 스프레드 축소 | E10: 0 | F10: =-설정!$C$10 -> -25 | G10: =$B$15 -> 82103986 | H10: =-$B$11*E10 -> 0 | I10: =-$B$12*F10 -> 9219866.1 | J10: =-$B$19*F10 -> 10177025 | K10: =G10+H10+J10 -> 92281011 | L10: =K10/($B$5*1000000) -> 0.06547545
A11: DV01($/bp) | B11: =SUMIFS(보유분석!$AM$2:$AM$801,보유분석!$AC$2:$AC$801,1) -> 379223.18 | D11: 리스크오프(금리↓·스프레드↑) | E11: =-설정!$C$9 -> -50 | F11: =설정!$C$10 -> 25 | G11: =$B$15 -> 82103986 | H11: =-$B$11*E11 -> 18961159 | I11: =-$B$12*F11 -> -9219866.1 | J11: =-$B$19*F11 -> -10177025 | K11: =G11+H11+J11 -> 90888119 | L11: =K11/($B$5*1000000) -> 0.064487162
A12: CR01($/bp, 국채 제외) | B12: =SUMIFS(보유분석!$AN$2:$AN$801,보유분석!$AC$2:$AC$801,1) -> 368794.64 | D12: 스태그(금리↑·스프레드↑) | E12: =설정!$C$9 -> 50 | F12: =설정!$C$10 -> 25 | G12: =$B$15 -> 82103986 | H12: =-$B$11*E12 -> -18961159 | I12: =-$B$12*F12 -> -9219866.1 | J12: =-$B$19*F12 -> -10177025 | K12: =G12+H12+J12 -> 52965802 | L12: =K12/($B$5*1000000) -> 0.037580426
A13: 1Y 캐리($) | B13: =SUMIFS(보유분석!$AO$2:$AO$801,보유분석!$AC$2:$AC$801,1) -> 79772468
A14: 1Y 스프레드 롤다운($) | B14: =SUMIFS(보유분석!$AU$2:$AU$801,보유분석!$AC$2:$AC$801,1) -> 2331517.4 | D14: 손익분기 기본 스프레드 확대폭(bp) — 균등 (캐리+롤다운 ÷ CR01) | L14: =IF(B12=0,"",B15/B12) -> 222.62792
A15: 1Y 기대수익($) = 캐리+롤다운 | B15: =B13+B14 -> 82103986 | D15: 손익분기 기본 스프레드 확대폭(bp) — 차등·비례 (캐리+롤다운 ÷ 조정 CR01) | L15: =IF(B19=0,"",B15/B19) -> 201.68955
A16: 1Y 기대수익률(%, 평가금액 대비) | B16: =B15/(B5*1000000) -> 0.058254622 | D16: 크레딧 손익분기(bp) — (G-spread+롤다운) ÷ 크레딧 듀레이션 | L16: =버킷분석!J16 -> 31.468574
A17: 평가손익($) | B17: =SUMIFS(보유분석!$AP$2:$AP$801,보유분석!$AC$2:$AC$801,1) -> -44901234
A18: 국채 비중 | B18: =SUMIFS(보유분석!$AA$2:$AA$801,보유분석!$AC$2:$AC$801,1,보유분석!$Y$2:$Y$801,1)/B5 -> 0.01199431 | D18: 운용코드별 (잔고 로트 기준 — 펀드별 정확히 분리)
A19: 쇼크조정 CR01($/bp) | B19: =SUMIFS(보유분석!$AZ$2:$AZ$801,보유분석!$AC$2:$AC$801,1) -> 407081.01 | D19: 운용코드 | E19: 평가금액($M) | F19: 가중YTM(%) | G19: 가중G(bp) | H19: 가중듀레이션 | I19: DV01($/bp) | J19: 1Y기대수익률(%) | K19: 종목수
A20: G-spread 커버리지(크레딧 평가금액) | B20: =SUMIFS(보유분석!$BD$2:$BD$801,보유분석!$AC$2:$AC$801,1)/SUMIFS(보유분석!$BI$2:$BI$801,보유분석!$AC$2:$AC$801,1) -> 0.97796717 | D20: 28096 | E20: =SUMPRODUCT((보유분석!$C$2:$C$801=$D20&"")*(보유분석!$Q$2:$Q$801=1)*($D20<>"")*보유분석!$AA$2:$AA$801) -> 498.56029 | F20: =IF(SUMPRODUCT((보유분석!$C$2:$C$801=$D20&"")*(보유분석!$Q$2:$Q$801=1)*($D20<>"")*보유분석!$BB$2:$BB$801)=0,"",SUMPRODUCT((보유분석!$C$2:$C$801=$D20&"")*(보유분석!$Q$2:$Q$801=1)*($D20<>"")*보유분석!$BA$2:$BA$801)/SUMPRODUCT((보유분석!$C$2:$C$801=$D20&"")*(보유분석!$Q$2:$Q$801=1)*($D20<>"")*보유분석!$BB$2:$BB$801)) -> 5.6677356 | G20: =IF(SUMPRODUCT((보유분석!$C$2:$C$801=$D20&"")*(보유분석!$Q$2:$Q$801=1)*($D20<>"")*보유분석!$BD$2:$BD$801)=0,"",SUMPRODUCT((보유분석!$C$2:$C$801=$D20&"")*(보유분석!$Q$2:$Q$801=1)*($D20<>"")*보유분석!$BC$2:$BC$801)/SUMPRODUCT((보유분석!$C$2:$C$801=$D20&"")*(보유분석!$Q$2:$Q$801=1)*($D20<>"")*보유분석!$BD$2:$BD$801)) -> 72.179724 | H20: =IF(SUMPRODUCT((보유분석!$C$2:$C$801=$D20&"")*(보유분석!$Q$2:$Q$801=1)*($D20<>"")*보유분석!$BF$2:$BF$801)=0,"",SUMPRODUCT((보유분석!$C$2:$C$801=$D20&"")*(보유분석!$Q$2:$Q$801=1)*($D20<>"")*보유분석!$BE$2:$BE$801)/SUMPRODUCT((보유분석!$C$2:$C$801=$D20&"")*(보유분석!$Q$2:$Q$801=1)*($D20<>"")*보유분석!$BF$2:$BF$801)) -> 2.6548408 | I20: =SUMPRODUCT((보유분석!$C$2:$C$801=$D20&"")*(보유분석!$Q$2:$Q$801=1)*($D20<>"")*보유분석!$AM$2:$AM$801) -> 132359.82 | J20: =IF(E20=0,"",SUMPRODUCT((보유분석!$C$2:$C$801=$D20&"")*(보유분석!$Q$2:$Q$801=1)*($D20<>"")*보유분석!$AV$2:$AV$801)/(E20*1000000)) -> 0.058033334 | K20: =SUMPRODUCT((보유분석!$C$2:$C$801=$D20&"")*(보유분석!$Q$2:$Q$801=1)*($D20<>"")/(COUNTIFS(보유분석!$C$2:$C$801,보유분석!$C$2:$C$801,보유분석!$B$2:$B$801,보유분석!$B$2:$B$801,보유분석!$Q$2:$Q$801,1)+(보유분석!$Q$2:$Q$801<>1))) -> 54
A21: Cheap 보유 / Rich 보유 로트수 | B21: =COUNTIFS(보유분석!$AC$2:$AC$801,1,보유분석!$AR$2:$AR$801,"Cheap")&" / "&COUNTIFS(보유분석!$AC$2:$AC$801,1,보유분석!$AR$2:$AR$801,"Rich") -> 36 / 10 | D21: 34507 | E21: =SUMPRODUCT((보유분석!$C$2:$C$801=$D21&"")*(보유분석!$Q$2:$Q$801=1)*($D21<>"")*보유분석!$AA$2:$AA$801) -> 322.8779 | F21: =IF(SUMPRODUCT((보유분석!$C$2:$C$801=$D21&"")*(보유분석!$Q$2:$Q$801=1)*($D21<>"")*보유분석!$BB$2:$BB$801)=0,"",SUMPRODUCT((보유분석!$C$2:$C$801=$D21&"")*(보유분석!$Q$2:$Q$801=1)*($D21<>"")*보유분석!$BA$2:$BA$801)/SUMPRODUCT((보유분석!$C$2:$C$801=$D21&"")*(보유분석!$Q$2:$Q$801=1)*($D21<>"")*보유분석!$BB$2:$BB$801)) -> 5.6291576 | G21: =IF(SUMPRODUCT((보유분석!$C$2:$C$801=$D21&"")*(보유분석!$Q$2:$Q$801=1)*($D21<>"")*보유분석!$BD$2:$BD$801)=0,"",SUMPRODUCT((보유분석!$C$2:$C$801=$D21&"")*(보유분석!$Q$2:$Q$801=1)*($D21<>"")*보유분석!$BC$2:$BC$801)/SUMPRODUCT((보유분석!$C$2:$C$801=$D21&"")*(보유분석!$Q$2:$Q$801=1)*($D21<>"")*보유분석!$BD$2:$BD$801)) -> 54.933816 | H21: =IF(SUMPRODUCT((보유분석!$C$2:$C$801=$D21&"")*(보유분석!$Q$2:$Q$801=1)*($D21<>"")*보유분석!$BF$2:$BF$801)=0,"",SUMPRODUCT((보유분석!$C$2:$C$801=$D21&"")*(보유분석!$Q$2:$Q$801=1)*($D21<>"")*보유분석!$BE$2:$BE$801)/SUMPRODUCT((보유분석!$C$2:$C$801=$D21&"")*(보유분석!$Q$2:$Q$801=1)*($D21<>"")*보유분석!$BF$2:$BF$801)) -> 2.8216054 | I21: =SUMPRODUCT((보유분석!$C$2:$C$801=$D21&"")*(보유분석!$Q$2:$Q$801=1)*($D21<>"")*보유분석!$AM$2:$AM$801) -> 91103.403 | J21: =IF(E21=0,"",SUMPRODUCT((보유분석!$C$2:$C$801=$D21&"")*(보유분석!$Q$2:$Q$801=1)*($D21<>"")*보유분석!$AV$2:$AV$801)/(E21*1000000)) -> 0.057510806 | K21: =SUMPRODUCT((보유분석!$C$2:$C$801=$D21&"")*(보유분석!$Q$2:$Q$801=1)*($D21<>"")/(COUNTIFS(보유분석!$C$2:$C$801,보유분석!$C$2:$C$801,보유분석!$B$2:$B$801,보유분석!$B$2:$B$801,보유분석!$Q$2:$Q$801,1)+(보유분석!$Q$2:$Q$801<>1))) -> 49
D22: 10227 | E22: =SUMPRODUCT((보유분석!$C$2:$C$801=$D22&"")*(보유분석!$Q$2:$Q$801=1)*($D22<>"")*보유분석!$AA$2:$AA$801) -> 1.984683 | F22: =IF(SUMPRODUCT((보유분석!$C$2:$C$801=$D22&"")*(보유분석!$Q$2:$Q$801=1)*($D22<>"")*보유분석!$BB$2:$BB$801)=0,"",SUMPRODUCT((보유분석!$C$2:$C$801=$D22&"")*(보유분석!$Q$2:$Q$801=1)*($D22<>"")*보유분석!$BA$2:$BA$801)/SUMPRODUCT((보유분석!$C$2:$C$801=$D22&"")*(보유분석!$Q$2:$Q$801=1)*($D22<>"")*보유분석!$BB$2:$BB$801)) -> 4.9766452 | G22: =IF(SUMPRODUCT((보유분석!$C$2:$C$801=$D22&"")*(보유분석!$Q$2:$Q$801=1)*($D22<>"")*보유분석!$BD$2:$BD$801)=0,"",SUMPRODUCT((보유분석!$C$2:$C$801=$D22&"")*(보유분석!$Q$2:$Q$801=1)*($D22<>"")*보유분석!$BC$2:$BC$801)/SUMPRODUCT((보유분석!$C$2:$C$801=$D22&"")*(보유분석!$Q$2:$Q$801=1)*($D22<>"")*보유분석!$BD$2:$BD$801)) -> -1.9223279 | H22: =IF(SUMPRODUCT((보유분석!$C$2:$C$801=$D22&"")*(보유분석!$Q$2:$Q$801=1)*($D22<>"")*보유분석!$BF$2:$BF$801)=0,"",SUMPRODUCT((보유분석!$C$2:$C$801=$D22&"")*(보유분석!$Q$2:$Q$801=1)*($D22<>"")*보유분석!$BE$2:$BE$801)/SUMPRODUCT((보유분석!$C$2:$C$801=$D22&"")*(보유분석!$Q$2:$Q$801=1)*($D22<>"")*보유분석!$BF$2:$BF$801)) -> 0.95193727 | I22: =SUMPRODUCT((보유분석!$C$2:$C$801=$D22&"")*(보유분석!$Q$2:$Q$801=1)*($D22<>"")*보유분석!$AM$2:$AM$801) -> 188.92937 | J22: =IF(E22=0,"",SUMPRODUCT((보유분석!$C$2:$C$801=$D22&"")*(보유분석!$Q$2:$Q$801=1)*($D22<>"")*보유분석!$AV$2:$AV$801)/(E22*1000000)) -> 0.050151365 | K22: =SUMPRODUCT((보유분석!$C$2:$C$801=$D22&"")*(보유분석!$Q$2:$Q$801=1)*($D22<>"")/(COUNTIFS(보유분석!$C$2:$C$801,보유분석!$C$2:$C$801,보유분석!$B$2:$B$801,보유분석!$B$2:$B$801,보유분석!$Q$2:$Q$801,1)+(보유분석!$Q$2:$Q$801<>1))) -> 2
D23: 34578 | E23: =SUMPRODUCT((보유분석!$C$2:$C$801=$D23&"")*(보유분석!$Q$2:$Q$801=1)*($D23<>"")*보유분석!$AA$2:$AA$801) -> 583.03249 | F23: =IF(SUMPRODUCT((보유분석!$C$2:$C$801=$D23&"")*(보유분석!$Q$2:$Q$801=1)*($D23<>"")*보유분석!$BB$2:$BB$801)=0,"",SUMPRODUCT((보유분석!$C$2:$C$801=$D23&"")*(보유분석!$Q$2:$Q$801=1)*($D23<>"")*보유분석!$BA$2:$BA$801)/SUMPRODUCT((보유분석!$C$2:$C$801=$D23&"")*(보유분석!$Q$2:$Q$801=1)*($D23<>"")*보유분석!$BB$2:$BB$801)) -> 5.6703767 | G23: =IF(SUMPRODUCT((보유분석!$C$2:$C$801=$D23&"")*(보유분석!$Q$2:$Q$801=1)*($D23<>"")*보유분석!$BD$2:$BD$801)=0,"",SUMPRODUCT((보유분석!$C$2:$C$801=$D23&"")*(보유분석!$Q$2:$Q$801=1)*($D23<>"")*보유분석!$BC$2:$BC$801)/SUMPRODUCT((보유분석!$C$2:$C$801=$D23&"")*(보유분석!$Q$2:$Q$801=1)*($D23<>"")*보유분석!$BD$2:$BD$801)) -> 66.601558 | H23: =IF(SUMPRODUCT((보유분석!$C$2:$C$801=$D23&"")*(보유분석!$Q$2:$Q$801=1)*($D23<>"")*보유분석!$BF$2:$BF$801)=0,"",SUMPRODUCT((보유분석!$C$2:$C$801=$D23&"")*(보유분석!$Q$2:$Q$801=1)*($D23<>"")*보유분석!$BE$2:$BE$801)/SUMPRODUCT((보유분석!$C$2:$C$801=$D23&"")*(보유분석!$Q$2:$Q$801=1)*($D23<>"")*보유분석!$BF$2:$BF$801)) -> 2.6406637 | I23: =SUMPRODUCT((보유분석!$C$2:$C$801=$D23&"")*(보유분석!$Q$2:$Q$801=1)*($D23<>"")*보유분석!$AM$2:$AM$801) -> 153959.28 | J23: =IF(E23=0,"",SUMPRODUCT((보유분석!$C$2:$C$801=$D23&"")*(보유분석!$Q$2:$Q$801=1)*($D23<>"")*보유분석!$AV$2:$AV$801)/(E23*1000000)) -> 0.058854187 | K23: =SUMPRODUCT((보유분석!$C$2:$C$801=$D23&"")*(보유분석!$Q$2:$Q$801=1)*($D23<>"")/(COUNTIFS(보유분석!$C$2:$C$801,보유분석!$C$2:$C$801,보유분석!$B$2:$B$801,보유분석!$B$2:$B$801,보유분석!$Q$2:$Q$801,1)+(보유분석!$Q$2:$Q$801<>1))) -> 36
D24: 38038 | E24: =SUMPRODUCT((보유분석!$C$2:$C$801=$D24&"")*(보유분석!$Q$2:$Q$801=1)*($D24<>"")*보유분석!$AA$2:$AA$801) -> 290.42565 | F24: =IF(SUMPRODUCT((보유분석!$C$2:$C$801=$D24&"")*(보유분석!$Q$2:$Q$801=1)*($D24<>"")*보유분석!$BB$2:$BB$801)=0,"",SUMPRODUCT((보유분석!$C$2:$C$801=$D24&"")*(보유분석!$Q$2:$Q$801=1)*($D24<>"")*보유분석!$BA$2:$BA$801)/SUMPRODUCT((보유분석!$C$2:$C$801=$D24&"")*(보유분석!$Q$2:$Q$801=1)*($D24<>"")*보유분석!$BB$2:$BB$801)) -> 5.3548151 | G24: =IF(SUMPRODUCT((보유분석!$C$2:$C$801=$D24&"")*(보유분석!$Q$2:$Q$801=1)*($D24<>"")*보유분석!$BD$2:$BD$801)=0,"",SUMPRODUCT((보유분석!$C$2:$C$801=$D24&"")*(보유분석!$Q$2:$Q$801=1)*($D24<>"")*보유분석!$BC$2:$BC$801)/SUMPRODUCT((보유분석!$C$2:$C$801=$D24&"")*(보유분석!$Q$2:$Q$801=1)*($D24<>"")*보유분석!$BD$2:$BD$801)) -> 78.303108 | H24: =IF(SUMPRODUCT((보유분석!$C$2:$C$801=$D24&"")*(보유분석!$Q$2:$Q$801=1)*($D24<>"")*보유분석!$BF$2:$BF$801)=0,"",SUMPRODUCT((보유분석!$C$2:$C$801=$D24&"")*(보유분석!$Q$2:$Q$801=1)*($D24<>"")*보유분석!$BE$2:$BE$801)/SUMPRODUCT((보유분석!$C$2:$C$801=$D24&"")*(보유분석!$Q$2:$Q$801=1)*($D24<>"")*보유분석!$BF$2:$BF$801)) -> 5.4687482 | I24: =SUMPRODUCT((보유분석!$C$2:$C$801=$D24&"")*(보유분석!$Q$2:$Q$801=1)*($D24<>"")*보유분석!$AM$2:$AM$801) -> 158826.47 | J24: =IF(E24=0,"",SUMPRODUCT((보유분석!$C$2:$C$801=$D24&"")*(보유분석!$Q$2:$Q$801=1)*($D24<>"")*보유분석!$AV$2:$AV$801)/(E24*1000000)) -> 0.05411683 | K24: =SUMPRODUCT((보유분석!$C$2:$C$801=$D24&"")*(보유분석!$Q$2:$Q$801=1)*($D24<>"")/(COUNTIFS(보유분석!$C$2:$C$801,보유분석!$C$2:$C$801,보유분석!$B$2:$B$801,보유분석!$B$2:$B$801,보유분석!$Q$2:$Q$801,1)+(보유분석!$Q$2:$Q$801<>1))) -> 18
D25: 38064 | E25: =SUMPRODUCT((보유분석!$C$2:$C$801=$D25&"")*(보유분석!$Q$2:$Q$801=1)*($D25<>"")*보유분석!$AA$2:$AA$801) -> 8.011592 | F25: =IF(SUMPRODUCT((보유분석!$C$2:$C$801=$D25&"")*(보유분석!$Q$2:$Q$801=1)*($D25<>"")*보유분석!$BB$2:$BB$801)=0,"",SUMPRODUCT((보유분석!$C$2:$C$801=$D25&"")*(보유분석!$Q$2:$Q$801=1)*($D25<>"")*보유분석!$BA$2:$BA$801)/SUMPRODUCT((보유분석!$C$2:$C$801=$D25&"")*(보유분석!$Q$2:$Q$801=1)*($D25<>"")*보유분석!$BB$2:$BB$801)) -> 5.2818 | G25: =IF(SUMPRODUCT((보유분석!$C$2:$C$801=$D25&"")*(보유분석!$Q$2:$Q$801=1)*($D25<>"")*보유분석!$BD$2:$BD$801)=0,"",SUMPRODUCT((보유분석!$C$2:$C$801=$D25&"")*(보유분석!$Q$2:$Q$801=1)*($D25<>"")*보유분석!$BC$2:$BC$801)/SUMPRODUCT((보유분석!$C$2:$C$801=$D25&"")*(보유분석!$Q$2:$Q$801=1)*($D25<>"")*보유분석!$BD$2:$BD$801)) -> -6.955 | H25: =IF(SUMPRODUCT((보유분석!$C$2:$C$801=$D25&"")*(보유분석!$Q$2:$Q$801=1)*($D25<>"")*보유분석!$BF$2:$BF$801)=0,"",SUMPRODUCT((보유분석!$C$2:$C$801=$D25&"")*(보유분석!$Q$2:$Q$801=1)*($D25<>"")*보유분석!$BE$2:$BE$801)/SUMPRODUCT((보유분석!$C$2:$C$801=$D25&"")*(보유분석!$Q$2:$Q$801=1)*($D25<>"")*보유분석!$BF$2:$BF$801)) -> 0.0968 | I25: =SUMPRODUCT((보유분석!$C$2:$C$801=$D25&"")*(보유분석!$Q$2:$Q$801=1)*($D25<>"")*보유분석!$AM$2:$AM$801) -> 77.552211 | J25: =IF(E25=0,"",SUMPRODUCT((보유분석!$C$2:$C$801=$D25&"")*(보유분석!$Q$2:$Q$801=1)*($D25<>"")*보유분석!$AV$2:$AV$801)/(E25*1000000)) -> 0.052818 | K25: =SUMPRODUCT((보유분석!$C$2:$C$801=$D25&"")*(보유분석!$Q$2:$Q$801=1)*($D25<>"")/(COUNTIFS(보유분석!$C$2:$C$801,보유분석!$C$2:$C$801,보유분석!$B$2:$B$801,보유분석!$B$2:$B$801,보유분석!$Q$2:$Q$801,1)+(보유분석!$Q$2:$Q$801<>1))) -> 1
D26: 38070 | E26: =SUMPRODUCT((보유분석!$C$2:$C$801=$D26&"")*(보유분석!$Q$2:$Q$801=1)*($D26<>"")*보유분석!$AA$2:$AA$801) -> 10.563732 | F26: =IF(SUMPRODUCT((보유분석!$C$2:$C$801=$D26&"")*(보유분석!$Q$2:$Q$801=1)*($D26<>"")*보유분석!$BB$2:$BB$801)=0,"",SUMPRODUCT((보유분석!$C$2:$C$801=$D26&"")*(보유분석!$Q$2:$Q$801=1)*($D26<>"")*보유분석!$BA$2:$BA$801)/SUMPRODUCT((보유분석!$C$2:$C$801=$D26&"")*(보유분석!$Q$2:$Q$801=1)*($D26<>"")*보유분석!$BB$2:$BB$801)) -> 3.8967811 | G26: =IF(SUMPRODUCT((보유분석!$C$2:$C$801=$D26&"")*(보유분석!$Q$2:$Q$801=1)*($D26<>"")*보유분석!$BD$2:$BD$801)=0,"",SUMPRODUCT((보유분석!$C$2:$C$801=$D26&"")*(보유분석!$Q$2:$Q$801=1)*($D26<>"")*보유분석!$BC$2:$BC$801)/SUMPRODUCT((보유분석!$C$2:$C$801=$D26&"")*(보유분석!$Q$2:$Q$801=1)*($D26<>"")*보유분석!$BD$2:$BD$801)) -> 75.650222 | H26: =IF(SUMPRODUCT((보유분석!$C$2:$C$801=$D26&"")*(보유분석!$Q$2:$Q$801=1)*($D26<>"")*보유분석!$BF$2:$BF$801)=0,"",SUMPRODUCT((보유분석!$C$2:$C$801=$D26&"")*(보유분석!$Q$2:$Q$801=1)*($D26<>"")*보유분석!$BE$2:$BE$801)/SUMPRODUCT((보유분석!$C$2:$C$801=$D26&"")*(보유분석!$Q$2:$Q$801=1)*($D26<>"")*보유분석!$BF$2:$BF$801)) -> 2.4876688 | I26: =SUMPRODUCT((보유분석!$C$2:$C$801=$D26&"")*(보유분석!$Q$2:$Q$801=1)*($D26<>"")*보유분석!$AM$2:$AM$801) -> 2627.9067 | J26: =IF(E26=0,"",SUMPRODUCT((보유분석!$C$2:$C$801=$D26&"")*(보유분석!$Q$2:$Q$801=1)*($D26<>"")*보유분석!$AV$2:$AV$801)/(E26*1000000)) -> 0.038967811 | K26: =SUMPRODUCT((보유분석!$C$2:$C$801=$D26&"")*(보유분석!$Q$2:$Q$801=1)*($D26<>"")/(COUNTIFS(보유분석!$C$2:$C$801,보유분석!$C$2:$C$801,보유분석!$B$2:$B$801,보유분석!$B$2:$B$801,보유분석!$Q$2:$Q$801,1)+(보유분석!$Q$2:$Q$801<>1))) -> 4
D27: 38088 | E27: =SUMPRODUCT((보유분석!$C$2:$C$801=$D27&"")*(보유분석!$Q$2:$Q$801=1)*($D27<>"")*보유분석!$AA$2:$AA$801) -> 124.56627 | F27: =IF(SUMPRODUCT((보유분석!$C$2:$C$801=$D27&"")*(보유분석!$Q$2:$Q$801=1)*($D27<>"")*보유분석!$BB$2:$BB$801)=0,"",SUMPRODUCT((보유분석!$C$2:$C$801=$D27&"")*(보유분석!$Q$2:$Q$801=1)*($D27<>"")*보유분석!$BA$2:$BA$801)/SUMPRODUCT((보유분석!$C$2:$C$801=$D27&"")*(보유분석!$Q$2:$Q$801=1)*($D27<>"")*보유분석!$BB$2:$BB$801)) -> 5.3442373 | G27: =IF(SUMPRODUCT((보유분석!$C$2:$C$801=$D27&"")*(보유분석!$Q$2:$Q$801=1)*($D27<>"")*보유분석!$BD$2:$BD$801)=0,"",SUMPRODUCT((보유분석!$C$2:$C$801=$D27&"")*(보유분석!$Q$2:$Q$801=1)*($D27<>"")*보유분석!$BC$2:$BC$801)/SUMPRODUCT((보유분석!$C$2:$C$801=$D27&"")*(보유분석!$Q$2:$Q$801=1)*($D27<>"")*보유분석!$BD$2:$BD$801)) -> 47.609006 | H27: =IF(SUMPRODUCT((보유분석!$C$2:$C$801=$D27&"")*(보유분석!$Q$2:$Q$801=1)*($D27<>"")*보유분석!$BF$2:$BF$801)=0,"",SUMPRODUCT((보유분석!$C$2:$C$801=$D27&"")*(보유분석!$Q$2:$Q$801=1)*($D27<>"")*보유분석!$BE$2:$BE$801)/SUMPRODUCT((보유분석!$C$2:$C$801=$D27&"")*(보유분석!$Q$2:$Q$801=1)*($D27<>"")*보유분석!$BF$2:$BF$801)) -> 6.2214607 | I27: =SUMPRODUCT((보유분석!$C$2:$C$801=$D27&"")*(보유분석!$Q$2:$Q$801=1)*($D27<>"")*보유분석!$AM$2:$AM$801) -> 77498.418 | J27: =IF(E27=0,"",SUMPRODUCT((보유분석!$C$2:$C$801=$D27&"")*(보유분석!$Q$2:$Q$801=1)*($D27<>"")*보유분석!$AV$2:$AV$801)/(E27*1000000)) -> 0.053989885 | K27: =SUMPRODUCT((보유분석!$C$2:$C$801=$D27&"")*(보유분석!$Q$2:$Q$801=1)*($D27<>"")/(COUNTIFS(보유분석!$C$2:$C$801,보유분석!$C$2:$C$801,보유분석!$B$2:$B$801,보유분석!$B$2:$B$801,보유분석!$Q$2:$Q$801,1)+(보유분석!$Q$2:$Q$801<>1))) -> 9
D28: 38167 | E28: =SUMPRODUCT((보유분석!$C$2:$C$801=$D28&"")*(보유분석!$Q$2:$Q$801=1)*($D28<>"")*보유분석!$AA$2:$AA$801) -> 11.123963 | F28: =IF(SUMPRODUCT((보유분석!$C$2:$C$801=$D28&"")*(보유분석!$Q$2:$Q$801=1)*($D28<>"")*보유분석!$BB$2:$BB$801)=0,"",SUMPRODUCT((보유분석!$C$2:$C$801=$D28&"")*(보유분석!$Q$2:$Q$801=1)*($D28<>"")*보유분석!$BA$2:$BA$801)/SUMPRODUCT((보유분석!$C$2:$C$801=$D28&"")*(보유분석!$Q$2:$Q$801=1)*($D28<>"")*보유분석!$BB$2:$BB$801)) -> 4.0507118 | G28: =IF(SUMPRODUCT((보유분석!$C$2:$C$801=$D28&"")*(보유분석!$Q$2:$Q$801=1)*($D28<>"")*보유분석!$BD$2:$BD$801)=0,"",SUMPRODUCT((보유분석!$C$2:$C$801=$D28&"")*(보유분석!$Q$2:$Q$801=1)*($D28<>"")*보유분석!$BC$2:$BC$801)/SUMPRODUCT((보유분석!$C$2:$C$801=$D28&"")*(보유분석!$Q$2:$Q$801=1)*($D28<>"")*보유분석!$BD$2:$BD$801)) -> 75.323616 | H28: =IF(SUMPRODUCT((보유분석!$C$2:$C$801=$D28&"")*(보유분석!$Q$2:$Q$801=1)*($D28<>"")*보유분석!$BF$2:$BF$801)=0,"",SUMPRODUCT((보유분석!$C$2:$C$801=$D28&"")*(보유분석!$Q$2:$Q$801=1)*($D28<>"")*보유분석!$BE$2:$BE$801)/SUMPRODUCT((보유분석!$C$2:$C$801=$D28&"")*(보유분석!$Q$2:$Q$801=1)*($D28<>"")*보유분석!$BF$2:$BF$801)) -> 2.5602482 | I28: =SUMPRODUCT((보유분석!$C$2:$C$801=$D28&"")*(보유분석!$Q$2:$Q$801=1)*($D28<>"")*보유분석!$AM$2:$AM$801) -> 2848.0105 | J28: =IF(E28=0,"",SUMPRODUCT((보유분석!$C$2:$C$801=$D28&"")*(보유분석!$Q$2:$Q$801=1)*($D28<>"")*보유분석!$AV$2:$AV$801)/(E28*1000000)) -> 0.040507118 | K28: =SUMPRODUCT((보유분석!$C$2:$C$801=$D28&"")*(보유분석!$Q$2:$Q$801=1)*($D28<>"")/(COUNTIFS(보유분석!$C$2:$C$801,보유분석!$C$2:$C$801,보유분석!$B$2:$B$801,보유분석!$B$2:$B$801,보유분석!$Q$2:$Q$801,1)+(보유분석!$Q$2:$Q$801<>1))) -> 3
D29: 38168 | E29: =SUMPRODUCT((보유분석!$C$2:$C$801=$D29&"")*(보유분석!$Q$2:$Q$801=1)*($D29<>"")*보유분석!$AA$2:$AA$801) -> 4.9279668 | F29: =IF(SUMPRODUCT((보유분석!$C$2:$C$801=$D29&"")*(보유분석!$Q$2:$Q$801=1)*($D29<>"")*보유분석!$BB$2:$BB$801)=0,"",SUMPRODUCT((보유분석!$C$2:$C$801=$D29&"")*(보유분석!$Q$2:$Q$801=1)*($D29<>"")*보유분석!$BA$2:$BA$801)/SUMPRODUCT((보유분석!$C$2:$C$801=$D29&"")*(보유분석!$Q$2:$Q$801=1)*($D29<>"")*보유분석!$BB$2:$BB$801)) -> 5.680743 | G29: =IF(SUMPRODUCT((보유분석!$C$2:$C$801=$D29&"")*(보유분석!$Q$2:$Q$801=1)*($D29<>"")*보유분석!$BD$2:$BD$801)=0,"",SUMPRODUCT((보유분석!$C$2:$C$801=$D29&"")*(보유분석!$Q$2:$Q$801=1)*($D29<>"")*보유분석!$BC$2:$BC$801)/SUMPRODUCT((보유분석!$C$2:$C$801=$D29&"")*(보유분석!$Q$2:$Q$801=1)*($D29<>"")*보유분석!$BD$2:$BD$801)) -> 70.181262 | H29: =IF(SUMPRODUCT((보유분석!$C$2:$C$801=$D29&"")*(보유분석!$Q$2:$Q$801=1)*($D29<>"")*보유분석!$BF$2:$BF$801)=0,"",SUMPRODUCT((보유분석!$C$2:$C$801=$D29&"")*(보유분석!$Q$2:$Q$801=1)*($D29<>"")*보유분석!$BE$2:$BE$801)/SUMPRODUCT((보유분석!$C$2:$C$801=$D29&"")*(보유분석!$Q$2:$Q$801=1)*($D29<>"")*보유분석!$BF$2:$BF$801)) -> 3.6540037 | I29: =SUMPRODUCT((보유분석!$C$2:$C$801=$D29&"")*(보유분석!$Q$2:$Q$801=1)*($D29<>"")*보유분석!$AM$2:$AM$801) -> 1800.6809 | J29: =IF(E29=0,"",SUMPRODUCT((보유분석!$C$2:$C$801=$D29&"")*(보유분석!$Q$2:$Q$801=1)*($D29<>"")*보유분석!$AV$2:$AV$801)/(E29*1000000)) -> 0.058441678 | K29: =SUMPRODUCT((보유분석!$C$2:$C$801=$D29&"")*(보유분석!$Q$2:$Q$801=1)*($D29<>"")/(COUNTIFS(보유분석!$C$2:$C$801,보유분석!$C$2:$C$801,보유분석!$B$2:$B$801,보유분석!$B$2:$B$801,보유분석!$Q$2:$Q$801,1)+(보유분석!$Q$2:$Q$801<>1))) -> 2
D30: 42003 | E30: =SUMPRODUCT((보유분석!$C$2:$C$801=$D30&"")*(보유분석!$Q$2:$Q$801=1)*($D30<>"")*보유분석!$AA$2:$AA$801) -> 305.96496 | F30: =IF(SUMPRODUCT((보유분석!$C$2:$C$801=$D30&"")*(보유분석!$Q$2:$Q$801=1)*($D30<>"")*보유분석!$BB$2:$BB$801)=0,"",SUMPRODUCT((보유분석!$C$2:$C$801=$D30&"")*(보유분석!$Q$2:$Q$801=1)*($D30<>"")*보유분석!$BA$2:$BA$801)/SUMPRODUCT((보유분석!$C$2:$C$801=$D30&"")*(보유분석!$Q$2:$Q$801=1)*($D30<>"")*보유분석!$BB$2:$BB$801)) -> 5.2661961 | G30: =IF(SUMPRODUCT((보유분석!$C$2:$C$801=$D30&"")*(보유분석!$Q$2:$Q$801=1)*($D30<>"")*보유분석!$BD$2:$BD$801)=0,"",SUMPRODUCT((보유분석!$C$2:$C$801=$D30&"")*(보유분석!$Q$2:$Q$801=1)*($D30<>"")*보유분석!$BC$2:$BC$801)/SUMPRODUCT((보유분석!$C$2:$C$801=$D30&"")*(보유분석!$Q$2:$Q$801=1)*($D30<>"")*보유분석!$BD$2:$BD$801)) -> 24.777927 | H30: =IF(SUMPRODUCT((보유분석!$C$2:$C$801=$D30&"")*(보유분석!$Q$2:$Q$801=1)*($D30<>"")*보유분석!$BF$2:$BF$801)=0,"",SUMPRODUCT((보유분석!$C$2:$C$801=$D30&"")*(보유분석!$Q$2:$Q$801=1)*($D30<>"")*보유분석!$BE$2:$BE$801)/SUMPRODUCT((보유분석!$C$2:$C$801=$D30&"")*(보유분석!$Q$2:$Q$801=1)*($D30<>"")*보유분석!$BF$2:$BF$801)) -> 2.8420326 | I30: =SUMPRODUCT((보유분석!$C$2:$C$801=$D30&"")*(보유분석!$Q$2:$Q$801=1)*($D30<>"")*보유분석!$AM$2:$AM$801) -> 86956.238 | J30: =IF(E30=0,"",SUMPRODUCT((보유분석!$C$2:$C$801=$D30&"")*(보유분석!$Q$2:$Q$801=1)*($D30<>"")*보유분석!$AV$2:$AV$801)/(E30*1000000)) -> 0.053847272 | K30: =SUMPRODUCT((보유분석!$C$2:$C$801=$D30&"")*(보유분석!$Q$2:$Q$801=1)*($D30<>"")/(COUNTIFS(보유분석!$C$2:$C$801,보유분석!$C$2:$C$801,보유분석!$B$2:$B$801,보유분석!$B$2:$B$801,보유분석!$Q$2:$Q$801,1)+(보유분석!$Q$2:$Q$801<>1))) -> 81
D31: 42006 | E31: =SUMPRODUCT((보유분석!$C$2:$C$801=$D31&"")*(보유분석!$Q$2:$Q$801=1)*($D31<>"")*보유분석!$AA$2:$AA$801) -> 34.436675 | F31: =IF(SUMPRODUCT((보유분석!$C$2:$C$801=$D31&"")*(보유분석!$Q$2:$Q$801=1)*($D31<>"")*보유분석!$BB$2:$BB$801)=0,"",SUMPRODUCT((보유분석!$C$2:$C$801=$D31&"")*(보유분석!$Q$2:$Q$801=1)*($D31<>"")*보유분석!$BA$2:$BA$801)/SUMPRODUCT((보유분석!$C$2:$C$801=$D31&"")*(보유분석!$Q$2:$Q$801=1)*($D31<>"")*보유분석!$BB$2:$BB$801)) -> 2.1514289 | G31: =IF(SUMPRODUCT((보유분석!$C$2:$C$801=$D31&"")*(보유분석!$Q$2:$Q$801=1)*($D31<>"")*보유분석!$BD$2:$BD$801)=0,"",SUMPRODUCT((보유분석!$C$2:$C$801=$D31&"")*(보유분석!$Q$2:$Q$801=1)*($D31<>"")*보유분석!$BC$2:$BC$801)/SUMPRODUCT((보유분석!$C$2:$C$801=$D31&"")*(보유분석!$Q$2:$Q$801=1)*($D31<>"")*보유분석!$BD$2:$BD$801)) -> 37.267847 | H31: =IF(SUMPRODUCT((보유분석!$C$2:$C$801=$D31&"")*(보유분석!$Q$2:$Q$801=1)*($D31<>"")*보유분석!$BF$2:$BF$801)=0,"",SUMPRODUCT((보유분석!$C$2:$C$801=$D31&"")*(보유분석!$Q$2:$Q$801=1)*($D31<>"")*보유분석!$BE$2:$BE$801)/SUMPRODUCT((보유분석!$C$2:$C$801=$D31&"")*(보유분석!$Q$2:$Q$801=1)*($D31<>"")*보유분석!$BF$2:$BF$801)) -> 1.5502998 | I31: =SUMPRODUCT((보유분석!$C$2:$C$801=$D31&"")*(보유분석!$Q$2:$Q$801=1)*($D31<>"")*보유분석!$AM$2:$AM$801) -> 5338.7171 | J31: =IF(E31=0,"",SUMPRODUCT((보유분석!$C$2:$C$801=$D31&"")*(보유분석!$Q$2:$Q$801=1)*($D31<>"")*보유분석!$AV$2:$AV$801)/(E31*1000000)) -> 0.021514289 | K31: =SUMPRODUCT((보유분석!$C$2:$C$801=$D31&"")*(보유분석!$Q$2:$Q$801=1)*($D31<>"")/(COUNTIFS(보유분석!$C$2:$C$801,보유분석!$C$2:$C$801,보유분석!$B$2:$B$801,보유분석!$B$2:$B$801,보유분석!$Q$2:$Q$801,1)+(보유분석!$Q$2:$Q$801<>1))) -> 5
D32: 42011 | E32: =SUMPRODUCT((보유분석!$C$2:$C$801=$D32&"")*(보유분석!$Q$2:$Q$801=1)*($D32<>"")*보유분석!$AA$2:$AA$801) -> 15.861448 | F32: =IF(SUMPRODUCT((보유분석!$C$2:$C$801=$D32&"")*(보유분석!$Q$2:$Q$801=1)*($D32<>"")*보유분석!$BB$2:$BB$801)=0,"",SUMPRODUCT((보유분석!$C$2:$C$801=$D32&"")*(보유분석!$Q$2:$Q$801=1)*($D32<>"")*보유분석!$BA$2:$BA$801)/SUMPRODUCT((보유분석!$C$2:$C$801=$D32&"")*(보유분석!$Q$2:$Q$801=1)*($D32<>"")*보유분석!$BB$2:$BB$801)) -> 5.3930465 | G32: =IF(SUMPRODUCT((보유분석!$C$2:$C$801=$D32&"")*(보유분석!$Q$2:$Q$801=1)*($D32<>"")*보유분석!$BD$2:$BD$801)=0,"",SUMPRODUCT((보유분석!$C$2:$C$801=$D32&"")*(보유분석!$Q$2:$Q$801=1)*($D32<>"")*보유분석!$BC$2:$BC$801)/SUMPRODUCT((보유분석!$C$2:$C$801=$D32&"")*(보유분석!$Q$2:$Q$801=1)*($D32<>"")*보유분석!$BD$2:$BD$801)) | H32: =IF(SUMPRODUCT((보유분석!$C$2:$C$801=$D32&"")*(보유분석!$Q$2:$Q$801=1)*($D32<>"")*보유분석!$BF$2:$BF$801)=0,"",SUMPRODUCT((보유분석!$C$2:$C$801=$D32&"")*(보유분석!$Q$2:$Q$801=1)*($D32<>"")*보유분석!$BE$2:$BE$801)/SUMPRODUCT((보유분석!$C$2:$C$801=$D32&"")*(보유분석!$Q$2:$Q$801=1)*($D32<>"")*보유분석!$BF$2:$BF$801)) -> 4.1168512 | I32: =SUMPRODUCT((보유분석!$C$2:$C$801=$D32&"")*(보유분석!$Q$2:$Q$801=1)*($D32<>"")*보유분석!$AM$2:$AM$801) -> 6529.9223 | J32: =IF(E32=0,"",SUMPRODUCT((보유분석!$C$2:$C$801=$D32&"")*(보유분석!$Q$2:$Q$801=1)*($D32<>"")*보유분석!$AV$2:$AV$801)/(E32*1000000)) -> 0.053930465 | K32: =SUMPRODUCT((보유분석!$C$2:$C$801=$D32&"")*(보유분석!$Q$2:$Q$801=1)*($D32<>"")/(COUNTIFS(보유분석!$C$2:$C$801,보유분석!$C$2:$C$801,보유분석!$B$2:$B$801,보유분석!$B$2:$B$801,보유분석!$Q$2:$Q$801,1)+(보유분석!$Q$2:$Q$801<>1))) -> 4
E33: =SUMPRODUCT((보유분석!$C$2:$C$801=$D33&"")*(보유분석!$Q$2:$Q$801=1)*($D33<>"")*보유분석!$AA$2:$AA$801) -> 0 | F33: =IF(SUMPRODUCT((보유분석!$C$2:$C$801=$D33&"")*(보유분석!$Q$2:$Q$801=1)*($D33<>"")*보유분석!$BB$2:$BB$801)=0,"",SUMPRODUCT((보유분석!$C$2:$C$801=$D33&"")*(보유분석!$Q$2:$Q$801=1)*($D33<>"")*보유분석!$BA$2:$BA$801)/SUMPRODUCT((보유분석!$C$2:$C$801=$D33&"")*(보유분석!$Q$2:$Q$801=1)*($D33<>"")*보유분석!$BB$2:$BB$801)) | G33: =IF(SUMPRODUCT((보유분석!$C$2:$C$801=$D33&"")*(보유분석!$Q$2:$Q$801=1)*($D33<>"")*보유분석!$BD$2:$BD$801)=0,"",SUMPRODUCT((보유분석!$C$2:$C$801=$D33&"")*(보유분석!$Q$2:$Q$801=1)*($D33<>"")*보유분석!$BC$2:$BC$801)/SUMPRODUCT((보유분석!$C$2:$C$801=$D33&"")*(보유분석!$Q$2:$Q$801=1)*($D33<>"")*보유분석!$BD$2:$BD$801)) | H33: =IF(SUMPRODUCT((보유분석!$C$2:$C$801=$D33&"")*(보유분석!$Q$2:$Q$801=1)*($D33<>"")*보유분석!$BF$2:$BF$801)=0,"",SUMPRODUCT((보유분석!$C$2:$C$801=$D33&"")*(보유분석!$Q$2:$Q$801=1)*($D33<>"")*보유분석!$BE$2:$BE$801)/SUMPRODUCT((보유분석!$C$2:$C$801=$D33&"")*(보유분석!$Q$2:$Q$801=1)*($D33<>"")*보유분석!$BF$2:$BF$801)) | I33: =SUMPRODUCT((보유분석!$C$2:$C$801=$D33&"")*(보유분석!$Q$2:$Q$801=1)*($D33<>"")*보유분석!$AM$2:$AM$801) -> 0 | J33: =IF(E33=0,"",SUMPRODUCT((보유분석!$C$2:$C$801=$D33&"")*(보유분석!$Q$2:$Q$801=1)*($D33<>"")*보유분석!$AV$2:$AV$801)/(E33*1000000)) | K33: =SUMPRODUCT((보유분석!$C$2:$C$801=$D33&"")*(보유분석!$Q$2:$Q$801=1)*($D33<>"")/(COUNTIFS(보유분석!$C$2:$C$801,보유분석!$C$2:$C$801,보유분석!$B$2:$B$801,보유분석!$B$2:$B$801,보유분석!$Q$2:$Q$801,1)+(보유분석!$Q$2:$Q$801<>1))) -> 0
E34: =SUMPRODUCT((보유분석!$C$2:$C$801=$D34&"")*(보유분석!$Q$2:$Q$801=1)*($D34<>"")*보유분석!$AA$2:$AA$801) -> 0 | F34: =IF(SUMPRODUCT((보유분석!$C$2:$C$801=$D34&"")*(보유분석!$Q$2:$Q$801=1)*($D34<>"")*보유분석!$BB$2:$BB$801)=0,"",SUMPRODUCT((보유분석!$C$2:$C$801=$D34&"")*(보유분석!$Q$2:$Q$801=1)*($D34<>"")*보유분석!$BA$2:$BA$801)/SUMPRODUCT((보유분석!$C$2:$C$801=$D34&"")*(보유분석!$Q$2:$Q$801=1)*($D34<>"")*보유분석!$BB$2:$BB$801)) | G34: =IF(SUMPRODUCT((보유분석!$C$2:$C$801=$D34&"")*(보유분석!$Q$2:$Q$801=1)*($D34<>"")*보유분석!$BD$2:$BD$801)=0,"",SUMPRODUCT((보유분석!$C$2:$C$801=$D34&"")*(보유분석!$Q$2:$Q$801=1)*($D34<>"")*보유분석!$BC$2:$BC$801)/SUMPRODUCT((보유분석!$C$2:$C$801=$D34&"")*(보유분석!$Q$2:$Q$801=1)*($D34<>"")*보유분석!$BD$2:$BD$801)) | H34: =IF(SUMPRODUCT((보유분석!$C$2:$C$801=$D34&"")*(보유분석!$Q$2:$Q$801=1)*($D34<>"")*보유분석!$BF$2:$BF$801)=0,"",SUMPRODUCT((보유분석!$C$2:$C$801=$D34&"")*(보유분석!$Q$2:$Q$801=1)*($D34<>"")*보유분석!$BE$2:$BE$801)/SUMPRODUCT((보유분석!$C$2:$C$801=$D34&"")*(보유분석!$Q$2:$Q$801=1)*($D34<>"")*보유분석!$BF$2:$BF$801)) | I34: =SUMPRODUCT((보유분석!$C$2:$C$801=$D34&"")*(보유분석!$Q$2:$Q$801=1)*($D34<>"")*보유분석!$AM$2:$AM$801) -> 0 | J34: =IF(E34=0,"",SUMPRODUCT((보유분석!$C$2:$C$801=$D34&"")*(보유분석!$Q$2:$Q$801=1)*($D34<>"")*보유분석!$AV$2:$AV$801)/(E34*1000000)) | K34: =SUMPRODUCT((보유분석!$C$2:$C$801=$D34&"")*(보유분석!$Q$2:$Q$801=1)*($D34<>"")/(COUNTIFS(보유분석!$C$2:$C$801,보유분석!$C$2:$C$801,보유분석!$B$2:$B$801,보유분석!$B$2:$B$801,보유분석!$Q$2:$Q$801,1)+(보유분석!$Q$2:$Q$801<>1))) -> 0
E35: =SUMPRODUCT((보유분석!$C$2:$C$801=$D35&"")*(보유분석!$Q$2:$Q$801=1)*($D35<>"")*보유분석!$AA$2:$AA$801) -> 0 | F35: =IF(SUMPRODUCT((보유분석!$C$2:$C$801=$D35&"")*(보유분석!$Q$2:$Q$801=1)*($D35<>"")*보유분석!$BB$2:$BB$801)=0,"",SUMPRODUCT((보유분석!$C$2:$C$801=$D35&"")*(보유분석!$Q$2:$Q$801=1)*($D35<>"")*보유분석!$BA$2:$BA$801)/SUMPRODUCT((보유분석!$C$2:$C$801=$D35&"")*(보유분석!$Q$2:$Q$801=1)*($D35<>"")*보유분석!$BB$2:$BB$801)) | G35: =IF(SUMPRODUCT((보유분석!$C$2:$C$801=$D35&"")*(보유분석!$Q$2:$Q$801=1)*($D35<>"")*보유분석!$BD$2:$BD$801)=0,"",SUMPRODUCT((보유분석!$C$2:$C$801=$D35&"")*(보유분석!$Q$2:$Q$801=1)*($D35<>"")*보유분석!$BC$2:$BC$801)/SUMPRODUCT((보유분석!$C$2:$C$801=$D35&"")*(보유분석!$Q$2:$Q$801=1)*($D35<>"")*보유분석!$BD$2:$BD$801)) | H35: =IF(SUMPRODUCT((보유분석!$C$2:$C$801=$D35&"")*(보유분석!$Q$2:$Q$801=1)*($D35<>"")*보유분석!$BF$2:$BF$801)=0,"",SUMPRODUCT((보유분석!$C$2:$C$801=$D35&"")*(보유분석!$Q$2:$Q$801=1)*($D35<>"")*보유분석!$BE$2:$BE$801)/SUMPRODUCT((보유분석!$C$2:$C$801=$D35&"")*(보유분석!$Q$2:$Q$801=1)*($D35<>"")*보유분석!$BF$2:$BF$801)) | I35: =SUMPRODUCT((보유분석!$C$2:$C$801=$D35&"")*(보유분석!$Q$2:$Q$801=1)*($D35<>"")*보유분석!$AM$2:$AM$801) -> 0 | J35: =IF(E35=0,"",SUMPRODUCT((보유분석!$C$2:$C$801=$D35&"")*(보유분석!$Q$2:$Q$801=1)*($D35<>"")*보유분석!$AV$2:$AV$801)/(E35*1000000)) | K35: =SUMPRODUCT((보유분석!$C$2:$C$801=$D35&"")*(보유분석!$Q$2:$Q$801=1)*($D35<>"")/(COUNTIFS(보유분석!$C$2:$C$801,보유분석!$C$2:$C$801,보유분석!$B$2:$B$801,보유분석!$B$2:$B$801,보유분석!$Q$2:$Q$801,1)+(보유분석!$Q$2:$Q$801<>1))) -> 0
E36: =SUMPRODUCT((보유분석!$C$2:$C$801=$D36&"")*(보유분석!$Q$2:$Q$801=1)*($D36<>"")*보유분석!$AA$2:$AA$801) -> 0 | F36: =IF(SUMPRODUCT((보유분석!$C$2:$C$801=$D36&"")*(보유분석!$Q$2:$Q$801=1)*($D36<>"")*보유분석!$BB$2:$BB$801)=0,"",SUMPRODUCT((보유분석!$C$2:$C$801=$D36&"")*(보유분석!$Q$2:$Q$801=1)*($D36<>"")*보유분석!$BA$2:$BA$801)/SUMPRODUCT((보유분석!$C$2:$C$801=$D36&"")*(보유분석!$Q$2:$Q$801=1)*($D36<>"")*보유분석!$BB$2:$BB$801)) | G36: =IF(SUMPRODUCT((보유분석!$C$2:$C$801=$D36&"")*(보유분석!$Q$2:$Q$801=1)*($D36<>"")*보유분석!$BD$2:$BD$801)=0,"",SUMPRODUCT((보유분석!$C$2:$C$801=$D36&"")*(보유분석!$Q$2:$Q$801=1)*($D36<>"")*보유분석!$BC$2:$BC$801)/SUMPRODUCT((보유분석!$C$2:$C$801=$D36&"")*(보유분석!$Q$2:$Q$801=1)*($D36<>"")*보유분석!$BD$2:$BD$801)) | H36: =IF(SUMPRODUCT((보유분석!$C$2:$C$801=$D36&"")*(보유분석!$Q$2:$Q$801=1)*($D36<>"")*보유분석!$BF$2:$BF$801)=0,"",SUMPRODUCT((보유분석!$C$2:$C$801=$D36&"")*(보유분석!$Q$2:$Q$801=1)*($D36<>"")*보유분석!$BE$2:$BE$801)/SUMPRODUCT((보유분석!$C$2:$C$801=$D36&"")*(보유분석!$Q$2:$Q$801=1)*($D36<>"")*보유분석!$BF$2:$BF$801)) | I36: =SUMPRODUCT((보유분석!$C$2:$C$801=$D36&"")*(보유분석!$Q$2:$Q$801=1)*($D36<>"")*보유분석!$AM$2:$AM$801) -> 0 | J36: =IF(E36=0,"",SUMPRODUCT((보유분석!$C$2:$C$801=$D36&"")*(보유분석!$Q$2:$Q$801=1)*($D36<>"")*보유분석!$AV$2:$AV$801)/(E36*1000000)) | K36: =SUMPRODUCT((보유분석!$C$2:$C$801=$D36&"")*(보유분석!$Q$2:$Q$801=1)*($D36<>"")/(COUNTIFS(보유분석!$C$2:$C$801,보유분석!$C$2:$C$801,보유분석!$B$2:$B$801,보유분석!$B$2:$B$801,보유분석!$Q$2:$Q$801,1)+(보유분석!$Q$2:$Q$801<>1))) -> 0

Sheet 버킷분석
A1: 버킷별 포트폴리오 분해 (설정의 펀드 선택 반영, 평가금액 기준)
A2: O열 목표비중은 직접 입력(노란 칸). J열 = (G-spread + 롤다운) ÷ 크레딧 듀레이션. Q열 = 스프레드 쇼크 손실(차등·비례 반영)
A4: ■ 만기 구간 (잔존만기)
A5: 구분 | B5: 평가금액($M) | C5: 비중 | D5: DV01($/bp) | E5: DV01비중 | F5: 가중YTM(%) | G5: 포트대비(bp) | H5: 가중G-spread(bp) | I5: 가중듀레이션 | J5: 손익분기 확대폭(bp) 스프레드+롤다운 | K5: 1Y기대수익률(%) | L5: 평가손익($) | M5: Cheap 보유수 | N5: Rich 보유수 | O5: 목표비중(입력) | P5: 갭(목표-현재) | Q5: 스프레드쇼크 손실($) | R5: 손실비중 | S5: └ 롤다운 기여(bp) | T5: G-spread 커버리지
A6: 1년 이하 | B6: =SUMIFS(보유분석!$AA$2:$AA$801,보유분석!$V$2:$V$801,$A6,보유분석!$AC$2:$AC$801,1) -> 79.051414 | C6: =IF(SUMIFS(보유분석!$AA$2:$AA$801,보유분석!$AC$2:$AC$801,1)=0,0,B6/SUMIFS(보유분석!$AA$2:$AA$801,보유분석!$AC$2:$AC$801,1)) -> 0.056088754 | D6: =SUMIFS(보유분석!$AM$2:$AM$801,보유분석!$V$2:$V$801,$A6,보유분석!$AC$2:$AC$801,1) -> 1280.3866 | E6: =IF(SUMIFS(보유분석!$AM$2:$AM$801,보유분석!$AC$2:$AC$801,1)=0,0,D6/SUMIFS(보유분석!$AM$2:$AM$801,보유분석!$AC$2:$AC$801,1)) -> 0.0033763405 | F6: =IF(SUMIFS(보유분석!$BB$2:$BB$801,보유분석!$V$2:$V$801,$A6,보유분석!$AC$2:$AC$801,1)=0,"",SUMIFS(보유분석!$BA$2:$BA$801,보유분석!$V$2:$V$801,$A6,보유분석!$AC$2:$AC$801,1)/SUMIFS(보유분석!$BB$2:$BB$801,보유분석!$V$2:$V$801,$A6,보유분석!$AC$2:$AC$801,1)) -> 5.2143793 | G6: =IF(F6="","",(F6-(SUMIFS(보유분석!$BA$2:$BA$801,보유분석!$AC$2:$AC$801,1)/SUMIFS(보유분석!$BB$2:$BB$801,보유분석!$AC$2:$AC$801,1)))*100) -> -44.56565 | H6: =IF(SUMIFS(보유분석!$BD$2:$BD$801,보유분석!$V$2:$V$801,$A6,보유분석!$AC$2:$AC$801,1)=0,"",SUMIFS(보유분석!$BC$2:$BC$801,보유분석!$V$2:$V$801,$A6,보유분석!$AC$2:$AC$801,1)/SUMIFS(보유분석!$BD$2:$BD$801,보유분석!$V$2:$V$801,$A6,보유분석!$AC$2:$AC$801,1)) -> -4.5997652 | I6: =IF(SUMIFS(보유분석!$BF$2:$BF$801,보유분석!$V$2:$V$801,$A6,보유분석!$AC$2:$AC$801,1)=0,"",SUMIFS(보유분석!$BE$2:$BE$801,보유분석!$V$2:$V$801,$A6,보유분석!$AC$2:$AC$801,1)/SUMIFS(보유분석!$BF$2:$BF$801,보유분석!$V$2:$V$801,$A6,보유분석!$AC$2:$AC$801,1)) -> 0.16196884 | J6: =IF(SUMIFS(보유분석!$BG$2:$BG$801,보유분석!$V$2:$V$801,$A6,보유분석!$AC$2:$AC$801,1)=0,"",(SUMIFS(보유분석!$BC$2:$BC$801,보유분석!$V$2:$V$801,$A6,보유분석!$AC$2:$AC$801,1)+SUMIFS(보유분석!$BH$2:$BH$801,보유분석!$V$2:$V$801,$A6,보유분석!$AC$2:$AC$801,1))/SUMIFS(보유분석!$BG$2:$BG$801,보유분석!$V$2:$V$801,$A6,보유분석!$AC$2:$AC$801,1)) -> -24.8657 | K6: =IF(B6=0,"",SUMIFS(보유분석!$AV$2:$AV$801,보유분석!$V$2:$V$801,$A6,보유분석!$AC$2:$AC$801,1)/(B6*1000000)) -> 0.052143793 | L6: =SUMIFS(보유분석!$AP$2:$AP$801,보유분석!$V$2:$V$801,$A6,보유분석!$AC$2:$AC$801,1) -> -915055.96 | M6: =COUNTIFS(보유분석!$V$2:$V$801,$A6,보유분석!$AR$2:$AR$801,"Cheap",보유분석!$AC$2:$AC$801,1) -> 0 | N6: =COUNTIFS(보유분석!$V$2:$V$801,$A6,보유분석!$AR$2:$AR$801,"Rich",보유분석!$AC$2:$AC$801,1) -> 1 | P6: =IF(O6="","",O6-C6) | Q6: =-SUMIFS(보유분석!$AZ$2:$AZ$801,보유분석!$V$2:$V$801,$A6,보유분석!$AC$2:$AC$801,1)*설정!$C$10 -> -22052.083 | R6: =IF((-SUMIFS(보유분석!$AZ$2:$AZ$801,보유분석!$AC$2:$AC$801,1)*설정!$C$10)=0,0,Q6/(-SUMIFS(보유분석!$AZ$2:$AZ$801,보유분석!$AC$2:$AC$801,1)*설정!$C$10)) -> 0.0021668496 | S6: =IF(SUMIFS(보유분석!$BG$2:$BG$801,보유분석!$V$2:$V$801,$A6,보유분석!$AC$2:$AC$801,1)=0,"",SUMIFS(보유분석!$BH$2:$BH$801,보유분석!$V$2:$V$801,$A6,보유분석!$AC$2:$AC$801,1)/SUMIFS(보유분석!$BG$2:$BG$801,보유분석!$V$2:$V$801,$A6,보유분석!$AC$2:$AC$801,1)) -> 0 | T6: =IF(SUMIFS(보유분석!$BI$2:$BI$801,보유분석!$V$2:$V$801,$A6,보유분석!$AC$2:$AC$801,1)=0,"",SUMIFS(보유분석!$BD$2:$BD$801,보유분석!$V$2:$V$801,$A6,보유분석!$AC$2:$AC$801,1)/SUMIFS(보유분석!$BI$2:$BI$801,보유분석!$V$2:$V$801,$A6,보유분석!$AC$2:$AC$801,1)) -> 0.8728315
A7: 1-2년 | B7: =SUMIFS(보유분석!$AA$2:$AA$801,보유분석!$V$2:$V$801,$A7,보유분석!$AC$2:$AC$801,1) -> 139.69334 | C7: =IF(SUMIFS(보유분석!$AA$2:$AA$801,보유분석!$AC$2:$AC$801,1)=0,0,B7/SUMIFS(보유분석!$AA$2:$AA$801,보유분석!$AC$2:$AC$801,1)) -> 0.099115562 | D7: =SUMIFS(보유분석!$AM$2:$AM$801,보유분석!$V$2:$V$801,$A7,보유분석!$AC$2:$AC$801,1) -> 20773.224 | E7: =IF(SUMIFS(보유분석!$AM$2:$AM$801,보유분석!$AC$2:$AC$801,1)=0,0,D7/SUMIFS(보유분석!$AM$2:$AM$801,보유분석!$AC$2:$AC$801,1)) -> 0.054778362 | F7: =IF(SUMIFS(보유분석!$BB$2:$BB$801,보유분석!$V$2:$V$801,$A7,보유분석!$AC$2:$AC$801,1)=0,"",SUMIFS(보유분석!$BA$2:$BA$801,보유분석!$V$2:$V$801,$A7,보유분석!$AC$2:$AC$801,1)/SUMIFS(보유분석!$BB$2:$BB$801,보유분석!$V$2:$V$801,$A7,보유분석!$AC$2:$AC$801,1)) -> 5.4787395 | G7: =IF(F7="","",(F7-(SUMIFS(보유분석!$BA$2:$BA$801,보유분석!$AC$2:$AC$801,1)/SUMIFS(보유분석!$BB$2:$BB$801,보유분석!$AC$2:$AC$801,1)))*100) -> -18.129635 | H7: =IF(SUMIFS(보유분석!$BD$2:$BD$801,보유분석!$V$2:$V$801,$A7,보유분석!$AC$2:$AC$801,1)=0,"",SUMIFS(보유분석!$BC$2:$BC$801,보유분석!$V$2:$V$801,$A7,보유분석!$AC$2:$AC$801,1)/SUMIFS(보유분석!$BD$2:$BD$801,보유분석!$V$2:$V$801,$A7,보유분석!$AC$2:$AC$801,1)) -> 59.964449 | I7: =IF(SUMIFS(보유분석!$BF$2:$BF$801,보유분석!$V$2:$V$801,$A7,보유분석!$AC$2:$AC$801,1)=0,"",SUMIFS(보유분석!$BE$2:$BE$801,보유분석!$V$2:$V$801,$A7,보유분석!$AC$2:$AC$801,1)/SUMIFS(보유분석!$BF$2:$BF$801,보유분석!$V$2:$V$801,$A7,보유분석!$AC$2:$AC$801,1)) -> 1.487059 | J7: =IF(SUMIFS(보유분석!$BG$2:$BG$801,보유분석!$V$2:$V$801,$A7,보유분석!$AC$2:$AC$801,1)=0,"",(SUMIFS(보유분석!$BC$2:$BC$801,보유분석!$V$2:$V$801,$A7,보유분석!$AC$2:$AC$801,1)+SUMIFS(보유분석!$BH$2:$BH$801,보유분석!$V$2:$V$801,$A7,보유분석!$AC$2:$AC$801,1))/SUMIFS(보유분석!$BG$2:$BG$801,보유분석!$V$2:$V$801,$A7,보유분석!$AC$2:$AC$801,1)) -> 44.633498 | K7: =IF(B7=0,"",SUMIFS(보유분석!$AV$2:$AV$801,보유분석!$V$2:$V$801,$A7,보유분석!$AC$2:$AC$801,1)/(B7*1000000)) -> 0.055425565 | L7: =SUMIFS(보유분석!$AP$2:$AP$801,보유분석!$V$2:$V$801,$A7,보유분석!$AC$2:$AC$801,1) -> -2715439.1 | M7: =COUNTIFS(보유분석!$V$2:$V$801,$A7,보유분석!$AR$2:$AR$801,"Cheap",보유분석!$AC$2:$AC$801,1) -> 1 | N7: =COUNTIFS(보유분석!$V$2:$V$801,$A7,보유분석!$AR$2:$AR$801,"Rich",보유분석!$AC$2:$AC$801,1) -> 0 | P7: =IF(O7="","",O7-C7) | Q7: =-SUMIFS(보유분석!$AZ$2:$AZ$801,보유분석!$V$2:$V$801,$A7,보유분석!$AC$2:$AC$801,1)*설정!$C$10 -> -477954.3 | R7: =IF((-SUMIFS(보유분석!$AZ$2:$AZ$801,보유분석!$AC$2:$AC$801,1)*설정!$C$10)=0,0,Q7/(-SUMIFS(보유분석!$AZ$2:$AZ$801,보유분석!$AC$2:$AC$801,1)*설정!$C$10)) -> 0.046964047 | S7: =IF(SUMIFS(보유분석!$BG$2:$BG$801,보유분석!$V$2:$V$801,$A7,보유분석!$AC$2:$AC$801,1)=0,"",SUMIFS(보유분석!$BH$2:$BH$801,보유분석!$V$2:$V$801,$A7,보유분석!$AC$2:$AC$801,1)/SUMIFS(보유분석!$BG$2:$BG$801,보유분석!$V$2:$V$801,$A7,보유분석!$AC$2:$AC$801,1)) -> 4.3206979 | T7: =IF(SUMIFS(보유분석!$BI$2:$BI$801,보유분석!$V$2:$V$801,$A7,보유분석!$AC$2:$AC$801,1)=0,"",SUMIFS(보유분석!$BD$2:$BD$801,보유분석!$V$2:$V$801,$A7,보유분석!$AC$2:$AC$801,1)/SUMIFS(보유분석!$BI$2:$BI$801,보유분석!$V$2:$V$801,$A7,보유분석!$AC$2:$AC$801,1)) -> 1
A8: 2-3년 | B8: =SUMIFS(보유분석!$AA$2:$AA$801,보유분석!$V$2:$V$801,$A8,보유분석!$AC$2:$AC$801,1) -> 508.38991 | C8: =IF(SUMIFS(보유분석!$AA$2:$AA$801,보유분석!$AC$2:$AC$801,1)=0,0,B8/SUMIFS(보유분석!$AA$2:$AA$801,보유분석!$AC$2:$AC$801,1)) -> 0.36071406 | D8: =SUMIFS(보유분석!$AM$2:$AM$801,보유분석!$V$2:$V$801,$A8,보유분석!$AC$2:$AC$801,1) -> 110319.63 | E8: =IF(SUMIFS(보유분석!$AM$2:$AM$801,보유분석!$AC$2:$AC$801,1)=0,0,D8/SUMIFS(보유분석!$AM$2:$AM$801,보유분석!$AC$2:$AC$801,1)) -> 0.29090952 | F8: =IF(SUMIFS(보유분석!$BB$2:$BB$801,보유분석!$V$2:$V$801,$A8,보유분석!$AC$2:$AC$801,1)=0,"",SUMIFS(보유분석!$BA$2:$BA$801,보유분석!$V$2:$V$801,$A8,보유분석!$AC$2:$AC$801,1)/SUMIFS(보유분석!$BB$2:$BB$801,보유분석!$V$2:$V$801,$A8,보유분석!$AC$2:$AC$801,1)) -> 5.5984355 | G8: =IF(F8="","",(F8-(SUMIFS(보유분석!$BA$2:$BA$801,보유분석!$AC$2:$AC$801,1)/SUMIFS(보유분석!$BB$2:$BB$801,보유분석!$AC$2:$AC$801,1)))*100) -> -6.1600335 | H8: =IF(SUMIFS(보유분석!$BD$2:$BD$801,보유분석!$V$2:$V$801,$A8,보유분석!$AC$2:$AC$801,1)=0,"",SUMIFS(보유분석!$BC$2:$BC$801,보유분석!$V$2:$V$801,$A8,보유분석!$AC$2:$AC$801,1)/SUMIFS(보유분석!$BD$2:$BD$801,보유분석!$V$2:$V$801,$A8,보유분석!$AC$2:$AC$801,1)) -> 64.795005 | I8: =IF(SUMIFS(보유분석!$BF$2:$BF$801,보유분석!$V$2:$V$801,$A8,보유분석!$AC$2:$AC$801,1)=0,"",SUMIFS(보유분석!$BE$2:$BE$801,보유분석!$V$2:$V$801,$A8,보유분석!$AC$2:$AC$801,1)/SUMIFS(보유분석!$BF$2:$BF$801,보유분석!$V$2:$V$801,$A8,보유분석!$AC$2:$AC$801,1)) -> 2.1699808 | J8: =IF(SUMIFS(보유분석!$BG$2:$BG$801,보유분석!$V$2:$V$801,$A8,보유분석!$AC$2:$AC$801,1)=0,"",(SUMIFS(보유분석!$BC$2:$BC$801,보유분석!$V$2:$V$801,$A8,보유분석!$AC$2:$AC$801,1)+SUMIFS(보유분석!$BH$2:$BH$801,보유분석!$V$2:$V$801,$A8,보유분석!$AC$2:$AC$801,1))/SUMIFS(보유분석!$BG$2:$BG$801,보유분석!$V$2:$V$801,$A8,보유분석!$AC$2:$AC$801,1)) -> 37.365885 | K8: =IF(B8=0,"",SUMIFS(보유분석!$AV$2:$AV$801,보유분석!$V$2:$V$801,$A8,보유분석!$AC$2:$AC$801,1)/(B8*1000000)) -> 0.057604986 | L8: =SUMIFS(보유분석!$AP$2:$AP$801,보유분석!$V$2:$V$801,$A8,보유분석!$AC$2:$AC$801,1) -> -13660126 | M8: =COUNTIFS(보유분석!$V$2:$V$801,$A8,보유분석!$AR$2:$AR$801,"Cheap",보유분석!$AC$2:$AC$801,1) -> 6 | N8: =COUNTIFS(보유분석!$V$2:$V$801,$A8,보유분석!$AR$2:$AR$801,"Rich",보유분석!$AC$2:$AC$801,1) -> 0 | P8: =IF(O8="","",O8-C8) | Q8: =-SUMIFS(보유분석!$AZ$2:$AZ$801,보유분석!$V$2:$V$801,$A8,보유분석!$AC$2:$AC$801,1)*설정!$C$10 -> -2714804.5 | R8: =IF((-SUMIFS(보유분석!$AZ$2:$AZ$801,보유분석!$AC$2:$AC$801,1)*설정!$C$10)=0,0,Q8/(-SUMIFS(보유분석!$AZ$2:$AZ$801,보유분석!$AC$2:$AC$801,1)*설정!$C$10)) -> 0.26675815 | S8: =IF(SUMIFS(보유분석!$BG$2:$BG$801,보유분석!$V$2:$V$801,$A8,보유분석!$AC$2:$AC$801,1)=0,"",SUMIFS(보유분석!$BH$2:$BH$801,보유분석!$V$2:$V$801,$A8,보유분석!$AC$2:$AC$801,1)/SUMIFS(보유분석!$BG$2:$BG$801,보유분석!$V$2:$V$801,$A8,보유분석!$AC$2:$AC$801,1)) -> 7.4899897 | T8: =IF(SUMIFS(보유분석!$BI$2:$BI$801,보유분석!$V$2:$V$801,$A8,보유분석!$AC$2:$AC$801,1)=0,"",SUMIFS(보유분석!$BD$2:$BD$801,보유분석!$V$2:$V$801,$A8,보유분석!$AC$2:$AC$801,1)/SUMIFS(보유분석!$BI$2:$BI$801,보유분석!$V$2:$V$801,$A8,보유분석!$AC$2:$AC$801,1)) -> 0.99765972
A9: 3-4년 | B9: =SUMIFS(보유분석!$AA$2:$AA$801,보유분석!$V$2:$V$801,$A9,보유분석!$AC$2:$AC$801,1) -> 308.28857 | C9: =IF(SUMIFS(보유분석!$AA$2:$AA$801,보유분석!$AC$2:$AC$801,1)=0,0,B9/SUMIFS(보유분석!$AA$2:$AA$801,보유분석!$AC$2:$AC$801,1)) -> 0.21873766 | D9: =SUMIFS(보유분석!$AM$2:$AM$801,보유분석!$V$2:$V$801,$A9,보유분석!$AC$2:$AC$801,1) -> 86820.39 | E9: =IF(SUMIFS(보유분석!$AM$2:$AM$801,보유분석!$AC$2:$AC$801,1)=0,0,D9/SUMIFS(보유분석!$AM$2:$AM$801,보유분석!$AC$2:$AC$801,1)) -> 0.22894273 | F9: =IF(SUMIFS(보유분석!$BB$2:$BB$801,보유분석!$V$2:$V$801,$A9,보유분석!$AC$2:$AC$801,1)=0,"",SUMIFS(보유분석!$BA$2:$BA$801,보유분석!$V$2:$V$801,$A9,보유분석!$AC$2:$AC$801,1)/SUMIFS(보유분석!$BB$2:$BB$801,보유분석!$V$2:$V$801,$A9,보유분석!$AC$2:$AC$801,1)) -> 5.7308698 | G9: =IF(F9="","",(F9-(SUMIFS(보유분석!$BA$2:$BA$801,보유분석!$AC$2:$AC$801,1)/SUMIFS(보유분석!$BB$2:$BB$801,보유분석!$AC$2:$AC$801,1)))*100) -> 7.0833927 | H9: =IF(SUMIFS(보유분석!$BD$2:$BD$801,보유분석!$V$2:$V$801,$A9,보유분석!$AC$2:$AC$801,1)=0,"",SUMIFS(보유분석!$BC$2:$BC$801,보유분석!$V$2:$V$801,$A9,보유분석!$AC$2:$AC$801,1)/SUMIFS(보유분석!$BD$2:$BD$801,보유분석!$V$2:$V$801,$A9,보유분석!$AC$2:$AC$801,1)) -> 67.697295 | I9: =IF(SUMIFS(보유분석!$BF$2:$BF$801,보유분석!$V$2:$V$801,$A9,보유분석!$AC$2:$AC$801,1)=0,"",SUMIFS(보유분석!$BE$2:$BE$801,보유분석!$V$2:$V$801,$A9,보유분석!$AC$2:$AC$801,1)/SUMIFS(보유분석!$BF$2:$BF$801,보유분석!$V$2:$V$801,$A9,보유분석!$AC$2:$AC$801,1)) -> 2.8162053 | J9: =IF(SUMIFS(보유분석!$BG$2:$BG$801,보유분석!$V$2:$V$801,$A9,보유분석!$AC$2:$AC$801,1)=0,"",(SUMIFS(보유분석!$BC$2:$BC$801,보유분석!$V$2:$V$801,$A9,보유분석!$AC$2:$AC$801,1)+SUMIFS(보유분석!$BH$2:$BH$801,보유분석!$V$2:$V$801,$A9,보유분석!$AC$2:$AC$801,1))/SUMIFS(보유분석!$BG$2:$BG$801,보유분석!$V$2:$V$801,$A9,보유분석!$AC$2:$AC$801,1)) -> 31.999892 | K9: =IF(B9=0,"",SUMIFS(보유분석!$AV$2:$AV$801,보유분석!$V$2:$V$801,$A9,보유분석!$AC$2:$AC$801,1)/(B9*1000000)) -> 0.059550795 | L9: =SUMIFS(보유분석!$AP$2:$AP$801,보유분석!$V$2:$V$801,$A9,보유분석!$AC$2:$AC$801,1) -> -11690080 | M9: =COUNTIFS(보유분석!$V$2:$V$801,$A9,보유분석!$AR$2:$AR$801,"Cheap",보유분석!$AC$2:$AC$801,1) -> 4 | N9: =COUNTIFS(보유분석!$V$2:$V$801,$A9,보유분석!$AR$2:$AR$801,"Rich",보유분석!$AC$2:$AC$801,1) -> 3 | P9: =IF(O9="","",O9-C9) | Q9: =-SUMIFS(보유분석!$AZ$2:$AZ$801,보유분석!$V$2:$V$801,$A9,보유분석!$AC$2:$AC$801,1)*설정!$C$10 -> -2257499.5 | R9: =IF((-SUMIFS(보유분석!$AZ$2:$AZ$801,보유분석!$AC$2:$AC$801,1)*설정!$C$10)=0,0,Q9/(-SUMIFS(보유분석!$AZ$2:$AZ$801,보유분석!$AC$2:$AC$801,1)*설정!$C$10)) -> 0.22182312 | S9: =IF(SUMIFS(보유분석!$BG$2:$BG$801,보유분석!$V$2:$V$801,$A9,보유분석!$AC$2:$AC$801,1)=0,"",SUMIFS(보유분석!$BH$2:$BH$801,보유분석!$V$2:$V$801,$A9,보유분석!$AC$2:$AC$801,1)/SUMIFS(보유분석!$BG$2:$BG$801,보유분석!$V$2:$V$801,$A9,보유분석!$AC$2:$AC$801,1)) -> 7.9614118 | T9: =IF(SUMIFS(보유분석!$BI$2:$BI$801,보유분석!$V$2:$V$801,$A9,보유분석!$AC$2:$AC$801,1)=0,"",SUMIFS(보유분석!$BD$2:$BD$801,보유분석!$V$2:$V$801,$A9,보유분석!$AC$2:$AC$801,1)/SUMIFS(보유분석!$BI$2:$BI$801,보유분석!$V$2:$V$801,$A9,보유분석!$AC$2:$AC$801,1)) -> 1
A10: 4-5년 | B10: =SUMIFS(보유분석!$AA$2:$AA$801,보유분석!$V$2:$V$801,$A10,보유분석!$AC$2:$AC$801,1) -> 196.73257 | C10: =IF(SUMIFS(보유분석!$AA$2:$AA$801,보유분석!$AC$2:$AC$801,1)=0,0,B10/SUMIFS(보유분석!$AA$2:$AA$801,보유분석!$AC$2:$AC$801,1)) -> 0.13958618 | D10: =SUMIFS(보유분석!$AM$2:$AM$801,보유분석!$V$2:$V$801,$A10,보유분석!$AC$2:$AC$801,1) -> 72774.59 | E10: =IF(SUMIFS(보유분석!$AM$2:$AM$801,보유분석!$AC$2:$AC$801,1)=0,0,D10/SUMIFS(보유분석!$AM$2:$AM$801,보유분석!$AC$2:$AC$801,1)) -> 0.19190438 | F10: =IF(SUMIFS(보유분석!$BB$2:$BB$801,보유분석!$V$2:$V$801,$A10,보유분석!$AC$2:$AC$801,1)=0,"",SUMIFS(보유분석!$BA$2:$BA$801,보유분석!$V$2:$V$801,$A10,보유분석!$AC$2:$AC$801,1)/SUMIFS(보유분석!$BB$2:$BB$801,보유분석!$V$2:$V$801,$A10,보유분석!$AC$2:$AC$801,1)) -> 5.8300814 | G10: =IF(F10="","",(F10-(SUMIFS(보유분석!$BA$2:$BA$801,보유분석!$AC$2:$AC$801,1)/SUMIFS(보유분석!$BB$2:$BB$801,보유분석!$AC$2:$AC$801,1)))*100) -> 17.004559 | H10: =IF(SUMIFS(보유분석!$BD$2:$BD$801,보유분석!$V$2:$V$801,$A10,보유분석!$AC$2:$AC$801,1)=0,"",SUMIFS(보유분석!$BC$2:$BC$801,보유분석!$V$2:$V$801,$A10,보유분석!$AC$2:$AC$801,1)/SUMIFS(보유분석!$BD$2:$BD$801,보유분석!$V$2:$V$801,$A10,보유분석!$AC$2:$AC$801,1)) -> 80.657112 | I10: =IF(SUMIFS(보유분석!$BF$2:$BF$801,보유분석!$V$2:$V$801,$A10,보유분석!$AC$2:$AC$801,1)=0,"",SUMIFS(보유분석!$BE$2:$BE$801,보유분석!$V$2:$V$801,$A10,보유분석!$AC$2:$AC$801,1)/SUMIFS(보유분석!$BF$2:$BF$801,보유분석!$V$2:$V$801,$A10,보유분석!$AC$2:$AC$801,1)) -> 3.6991632 | J10: =IF(SUMIFS(보유분석!$BG$2:$BG$801,보유분석!$V$2:$V$801,$A10,보유분석!$AC$2:$AC$801,1)=0,"",(SUMIFS(보유분석!$BC$2:$BC$801,보유분석!$V$2:$V$801,$A10,보유분석!$AC$2:$AC$801,1)+SUMIFS(보유분석!$BH$2:$BH$801,보유분석!$V$2:$V$801,$A10,보유분석!$AC$2:$AC$801,1))/SUMIFS(보유분석!$BG$2:$BG$801,보유분석!$V$2:$V$801,$A10,보유분석!$AC$2:$AC$801,1)) -> 27.471664 | K10: =IF(B10=0,"",SUMIFS(보유분석!$AV$2:$AV$801,보유분석!$V$2:$V$801,$A10,보유분석!$AC$2:$AC$801,1)/(B10*1000000)) -> 0.06039732 | L10: =SUMIFS(보유분석!$AP$2:$AP$801,보유분석!$V$2:$V$801,$A10,보유분석!$AC$2:$AC$801,1) -> -6935143.9 | M10: =COUNTIFS(보유분석!$V$2:$V$801,$A10,보유분석!$AR$2:$AR$801,"Cheap",보유분석!$AC$2:$AC$801,1) -> 21 | N10: =COUNTIFS(보유분석!$V$2:$V$801,$A10,보유분석!$AR$2:$AR$801,"Rich",보유분석!$AC$2:$AC$801,1) -> 2 | P10: =IF(O10="","",O10-C10) | Q10: =-SUMIFS(보유분석!$AZ$2:$AZ$801,보유분석!$V$2:$V$801,$A10,보유분석!$AC$2:$AC$801,1)*설정!$C$10 -> -2232476 | R10: =IF((-SUMIFS(보유분석!$AZ$2:$AZ$801,보유분석!$AC$2:$AC$801,1)*설정!$C$10)=0,0,Q10/(-SUMIFS(보유분석!$AZ$2:$AZ$801,보유분석!$AC$2:$AC$801,1)*설정!$C$10)) -> 0.21936429 | S10: =IF(SUMIFS(보유분석!$BG$2:$BG$801,보유분석!$V$2:$V$801,$A10,보유분석!$AC$2:$AC$801,1)=0,"",SUMIFS(보유분석!$BH$2:$BH$801,보유분석!$V$2:$V$801,$A10,보유분석!$AC$2:$AC$801,1)/SUMIFS(보유분석!$BG$2:$BG$801,보유분석!$V$2:$V$801,$A10,보유분석!$AC$2:$AC$801,1)) -> 5.6675128 | T10: =IF(SUMIFS(보유분석!$BI$2:$BI$801,보유분석!$V$2:$V$801,$A10,보유분석!$AC$2:$AC$801,1)=0,"",SUMIFS(보유분석!$BD$2:$BD$801,보유분석!$V$2:$V$801,$A10,보유분석!$AC$2:$AC$801,1)/SUMIFS(보유분석!$BI$2:$BI$801,보유분석!$V$2:$V$801,$A10,보유분석!$AC$2:$AC$801,1)) -> 1
A11: 5-7년 | B11: =SUMIFS(보유분석!$AA$2:$AA$801,보유분석!$V$2:$V$801,$A11,보유분석!$AC$2:$AC$801,1) -> 132.09165 | C11: =IF(SUMIFS(보유분석!$AA$2:$AA$801,보유분석!$AC$2:$AC$801,1)=0,0,B11/SUMIFS(보유분석!$AA$2:$AA$801,보유분석!$AC$2:$AC$801,1)) -> 0.093721991 | D11: =SUMIFS(보유분석!$AM$2:$AM$801,보유분석!$V$2:$V$801,$A11,보유분석!$AC$2:$AC$801,1) -> 53625.85 | E11: =IF(SUMIFS(보유분석!$AM$2:$AM$801,보유분석!$AC$2:$AC$801,1)=0,0,D11/SUMIFS(보유분석!$AM$2:$AM$801,보유분석!$AC$2:$AC$801,1)) -> 0.14140974 | F11: =IF(SUMIFS(보유분석!$BB$2:$BB$801,보유분석!$V$2:$V$801,$A11,보유분석!$AC$2:$AC$801,1)=0,"",SUMIFS(보유분석!$BA$2:$BA$801,보유분석!$V$2:$V$801,$A11,보유분석!$AC$2:$AC$801,1)/SUMIFS(보유분석!$BB$2:$BB$801,보유분석!$V$2:$V$801,$A11,보유분석!$AC$2:$AC$801,1)) -> 5.8555383 | G11: =IF(F11="","",(F11-(SUMIFS(보유분석!$BA$2:$BA$801,보유분석!$AC$2:$AC$801,1)/SUMIFS(보유분석!$BB$2:$BB$801,보유분석!$AC$2:$AC$801,1)))*100) -> 19.550246 | H11: =IF(SUMIFS(보유분석!$BD$2:$BD$801,보유분석!$V$2:$V$801,$A11,보유분석!$AC$2:$AC$801,1)=0,"",SUMIFS(보유분석!$BC$2:$BC$801,보유분석!$V$2:$V$801,$A11,보유분석!$AC$2:$AC$801,1)/SUMIFS(보유분석!$BD$2:$BD$801,보유분석!$V$2:$V$801,$A11,보유분석!$AC$2:$AC$801,1)) -> 83.815774 | I11: =IF(SUMIFS(보유분석!$BF$2:$BF$801,보유분석!$V$2:$V$801,$A11,보유분석!$AC$2:$AC$801,1)=0,"",SUMIFS(보유분석!$BE$2:$BE$801,보유분석!$V$2:$V$801,$A11,보유분석!$AC$2:$AC$801,1)/SUMIFS(보유분석!$BF$2:$BF$801,보유분석!$V$2:$V$801,$A11,보유분석!$AC$2:$AC$801,1)) -> 4.0597457 | J11: =IF(SUMIFS(보유분석!$BG$2:$BG$801,보유분석!$V$2:$V$801,$A11,보유분석!$AC$2:$AC$801,1)=0,"",(SUMIFS(보유분석!$BC$2:$BC$801,보유분석!$V$2:$V$801,$A11,보유분석!$AC$2:$AC$801,1)+SUMIFS(보유분석!$BH$2:$BH$801,보유분석!$V$2:$V$801,$A11,보유분석!$AC$2:$AC$801,1))/SUMIFS(보유분석!$BG$2:$BG$801,보유분석!$V$2:$V$801,$A11,보유분석!$AC$2:$AC$801,1)) -> 25.763764 | K11: =IF(B11=0,"",SUMIFS(보유분석!$AV$2:$AV$801,보유분석!$V$2:$V$801,$A11,보유분석!$AC$2:$AC$801,1)/(B11*1000000)) -> 0.060361974 | L11: =SUMIFS(보유분석!$AP$2:$AP$801,보유분석!$V$2:$V$801,$A11,보유분석!$AC$2:$AC$801,1) -> -5502163.8 | M11: =COUNTIFS(보유분석!$V$2:$V$801,$A11,보유분석!$AR$2:$AR$801,"Cheap",보유분석!$AC$2:$AC$801,1) -> 3 | N11: =COUNTIFS(보유분석!$V$2:$V$801,$A11,보유분석!$AR$2:$AR$801,"Rich",보유분석!$AC$2:$AC$801,1) -> 3 | P11: =IF(O11="","",O11-C11) | Q11: =-SUMIFS(보유분석!$AZ$2:$AZ$801,보유분석!$V$2:$V$801,$A11,보유분석!$AC$2:$AC$801,1)*설정!$C$10 -> -1636355.4 | R11: =IF((-SUMIFS(보유분석!$AZ$2:$AZ$801,보유분석!$AC$2:$AC$801,1)*설정!$C$10)=0,0,Q11/(-SUMIFS(보유분석!$AZ$2:$AZ$801,보유분석!$AC$2:$AC$801,1)*설정!$C$10)) -> 0.16078916 | S11: =IF(SUMIFS(보유분석!$BG$2:$BG$801,보유분석!$V$2:$V$801,$A11,보유분석!$AC$2:$AC$801,1)=0,"",SUMIFS(보유분석!$BH$2:$BH$801,보유분석!$V$2:$V$801,$A11,보유분석!$AC$2:$AC$801,1)/SUMIFS(보유분석!$BG$2:$BG$801,보유분석!$V$2:$V$801,$A11,보유분석!$AC$2:$AC$801,1)) -> 5.197739 | T11: =IF(SUMIFS(보유분석!$BI$2:$BI$801,보유분석!$V$2:$V$801,$A11,보유분석!$AC$2:$AC$801,1)=0,"",SUMIFS(보유분석!$BD$2:$BD$801,보유분석!$V$2:$V$801,$A11,보유분석!$AC$2:$AC$801,1)/SUMIFS(보유분석!$BI$2:$BI$801,보유분석!$V$2:$V$801,$A11,보유분석!$AC$2:$AC$801,1)) -> 0.85284497
A12: 7-10년 | B12: =SUMIFS(보유분석!$AA$2:$AA$801,보유분석!$V$2:$V$801,$A12,보유분석!$AC$2:$AC$801,1) -> 38.766482 | C12: =IF(SUMIFS(보유분석!$AA$2:$AA$801,보유분석!$AC$2:$AC$801,1)=0,0,B12/SUMIFS(보유분석!$AA$2:$AA$801,보유분석!$AC$2:$AC$801,1)) -> 0.02750569 | D12: =SUMIFS(보유분석!$AM$2:$AM$801,보유분석!$V$2:$V$801,$A12,보유분석!$AC$2:$AC$801,1) -> 26299.939 | E12: =IF(SUMIFS(보유분석!$AM$2:$AM$801,보유분석!$AC$2:$AC$801,1)=0,0,D12/SUMIFS(보유분석!$AM$2:$AM$801,보유분석!$AC$2:$AC$801,1)) -> 0.069352141 | F12: =IF(SUMIFS(보유분석!$BB$2:$BB$801,보유분석!$V$2:$V$801,$A12,보유분석!$AC$2:$AC$801,1)=0,"",SUMIFS(보유분석!$BA$2:$BA$801,보유분석!$V$2:$V$801,$A12,보유분석!$AC$2:$AC$801,1)/SUMIFS(보유분석!$BB$2:$BB$801,보유분석!$V$2:$V$801,$A12,보유분석!$AC$2:$AC$801,1)) -> 5.8601636 | G12: =IF(F12="","",(F12-(SUMIFS(보유분석!$BA$2:$BA$801,보유분석!$AC$2:$AC$801,1)/SUMIFS(보유분석!$BB$2:$BB$801,보유분석!$AC$2:$AC$801,1)))*100) -> 20.012779 | H12: =IF(SUMIFS(보유분석!$BD$2:$BD$801,보유분석!$V$2:$V$801,$A12,보유분석!$AC$2:$AC$801,1)=0,"",SUMIFS(보유분석!$BC$2:$BC$801,보유분석!$V$2:$V$801,$A12,보유분석!$AC$2:$AC$801,1)/SUMIFS(보유분석!$BD$2:$BD$801,보유분석!$V$2:$V$801,$A12,보유분석!$AC$2:$AC$801,1)) -> 110.38725 | I12: =IF(SUMIFS(보유분석!$BF$2:$BF$801,보유분석!$V$2:$V$801,$A12,보유분석!$AC$2:$AC$801,1)=0,"",SUMIFS(보유분석!$BE$2:$BE$801,보유분석!$V$2:$V$801,$A12,보유분석!$AC$2:$AC$801,1)/SUMIFS(보유분석!$BF$2:$BF$801,보유분석!$V$2:$V$801,$A12,보유분석!$AC$2:$AC$801,1)) -> 6.7841955 | J12: =IF(SUMIFS(보유분석!$BG$2:$BG$801,보유분석!$V$2:$V$801,$A12,보유분석!$AC$2:$AC$801,1)=0,"",(SUMIFS(보유분석!$BC$2:$BC$801,보유분석!$V$2:$V$801,$A12,보유분석!$AC$2:$AC$801,1)+SUMIFS(보유분석!$BH$2:$BH$801,보유분석!$V$2:$V$801,$A12,보유분석!$AC$2:$AC$801,1))/SUMIFS(보유분석!$BG$2:$BG$801,보유분석!$V$2:$V$801,$A12,보유분석!$AC$2:$AC$801,1)) -> 20.501076 | K12: =IF(B12=0,"",SUMIFS(보유분석!$AV$2:$AV$801,보유분석!$V$2:$V$801,$A12,보유분석!$AC$2:$AC$801,1)/(B12*1000000)) -> 0.06026933 | L12: =SUMIFS(보유분석!$AP$2:$AP$801,보유분석!$V$2:$V$801,$A12,보유분석!$AC$2:$AC$801,1) -> -2741936.7 | M12: =COUNTIFS(보유분석!$V$2:$V$801,$A12,보유분석!$AR$2:$AR$801,"Cheap",보유분석!$AC$2:$AC$801,1) -> 1 | N12: =COUNTIFS(보유분석!$V$2:$V$801,$A12,보유분석!$AR$2:$AR$801,"Rich",보유분석!$AC$2:$AC$801,1) -> 1 | P12: =IF(O12="","",O12-C12) | Q12: =-SUMIFS(보유분석!$AZ$2:$AZ$801,보유분석!$V$2:$V$801,$A12,보유분석!$AC$2:$AC$801,1)*설정!$C$10 -> -641823.15 | R12: =IF((-SUMIFS(보유분석!$AZ$2:$AZ$801,보유분석!$AC$2:$AC$801,1)*설정!$C$10)=0,0,Q12/(-SUMIFS(보유분석!$AZ$2:$AZ$801,보유분석!$AC$2:$AC$801,1)*설정!$C$10)) -> 0.063065889 | S12: =IF(SUMIFS(보유분석!$BG$2:$BG$801,보유분석!$V$2:$V$801,$A12,보유분석!$AC$2:$AC$801,1)=0,"",SUMIFS(보유분석!$BH$2:$BH$801,보유분석!$V$2:$V$801,$A12,보유분석!$AC$2:$AC$801,1)/SUMIFS(보유분석!$BG$2:$BG$801,보유분석!$V$2:$V$801,$A12,보유분석!$AC$2:$AC$801,1)) -> 4.1833274 | T12: =IF(SUMIFS(보유분석!$BI$2:$BI$801,보유분석!$V$2:$V$801,$A12,보유분석!$AC$2:$AC$801,1)=0,"",SUMIFS(보유분석!$BD$2:$BD$801,보유분석!$V$2:$V$801,$A12,보유분석!$AC$2:$AC$801,1)/SUMIFS(보유분석!$BI$2:$BI$801,보유분석!$V$2:$V$801,$A12,보유분석!$AC$2:$AC$801,1)) -> 1
A13: 10-20년 | B13: =SUMIFS(보유분석!$AA$2:$AA$801,보유분석!$V$2:$V$801,$A13,보유분석!$AC$2:$AC$801,1) -> 2.740295 | C13: =IF(SUMIFS(보유분석!$AA$2:$AA$801,보유분석!$AC$2:$AC$801,1)=0,0,B13/SUMIFS(보유분석!$AA$2:$AA$801,보유분석!$AC$2:$AC$801,1)) -> 0.0019443009 | D13: =SUMIFS(보유분석!$AM$2:$AM$801,보유분석!$V$2:$V$801,$A13,보유분석!$AC$2:$AC$801,1) -> 1919.604 | E13: =IF(SUMIFS(보유분석!$AM$2:$AM$801,보유분석!$AC$2:$AC$801,1)=0,0,D13/SUMIFS(보유분석!$AM$2:$AM$801,보유분석!$AC$2:$AC$801,1)) -> 0.0050619375 | F13: =IF(SUMIFS(보유분석!$BB$2:$BB$801,보유분석!$V$2:$V$801,$A13,보유분석!$AC$2:$AC$801,1)=0,"",SUMIFS(보유분석!$BA$2:$BA$801,보유분석!$V$2:$V$801,$A13,보유분석!$AC$2:$AC$801,1)/SUMIFS(보유분석!$BB$2:$BB$801,보유분석!$V$2:$V$801,$A13,보유분석!$AC$2:$AC$801,1)) -> 6.054946 | G13: =IF(F13="","",(F13-(SUMIFS(보유분석!$BA$2:$BA$801,보유분석!$AC$2:$AC$801,1)/SUMIFS(보유분석!$BB$2:$BB$801,보유분석!$AC$2:$AC$801,1)))*100) -> 39.49102 | H13: =IF(SUMIFS(보유분석!$BD$2:$BD$801,보유분석!$V$2:$V$801,$A13,보유분석!$AC$2:$AC$801,1)=0,"",SUMIFS(보유분석!$BC$2:$BC$801,보유분석!$V$2:$V$801,$A13,보유분석!$AC$2:$AC$801,1)/SUMIFS(보유분석!$BD$2:$BD$801,보유분석!$V$2:$V$801,$A13,보유분석!$AC$2:$AC$801,1)) -> 84.825675 | I13: =IF(SUMIFS(보유분석!$BF$2:$BF$801,보유분석!$V$2:$V$801,$A13,보유분석!$AC$2:$AC$801,1)=0,"",SUMIFS(보유분석!$BE$2:$BE$801,보유분석!$V$2:$V$801,$A13,보유분석!$AC$2:$AC$801,1)/SUMIFS(보유분석!$BF$2:$BF$801,보유분석!$V$2:$V$801,$A13,보유분석!$AC$2:$AC$801,1)) -> 7.0050998 | J13: =IF(SUMIFS(보유분석!$BG$2:$BG$801,보유분석!$V$2:$V$801,$A13,보유분석!$AC$2:$AC$801,1)=0,"",(SUMIFS(보유분석!$BC$2:$BC$801,보유분석!$V$2:$V$801,$A13,보유분석!$AC$2:$AC$801,1)+SUMIFS(보유분석!$BH$2:$BH$801,보유분석!$V$2:$V$801,$A13,보유분석!$AC$2:$AC$801,1))/SUMIFS(보유분석!$BG$2:$BG$801,보유분석!$V$2:$V$801,$A13,보유분석!$AC$2:$AC$801,1)) -> 14.743562 | K13: =IF(B13=0,"",SUMIFS(보유분석!$AV$2:$AV$801,보유분석!$V$2:$V$801,$A13,보유분석!$AC$2:$AC$801,1)/(B13*1000000)) -> 0.062394905 | L13: =SUMIFS(보유분석!$AP$2:$AP$801,보유분석!$V$2:$V$801,$A13,보유분석!$AC$2:$AC$801,1) -> -244509 | M13: =COUNTIFS(보유분석!$V$2:$V$801,$A13,보유분석!$AR$2:$AR$801,"Cheap",보유분석!$AC$2:$AC$801,1) -> 0 | N13: =COUNTIFS(보유분석!$V$2:$V$801,$A13,보유분석!$AR$2:$AR$801,"Rich",보유분석!$AC$2:$AC$801,1) -> 0 | P13: =IF(O13="","",O13-C13) | Q13: =-SUMIFS(보유분석!$AZ$2:$AZ$801,보유분석!$V$2:$V$801,$A13,보유분석!$AC$2:$AC$801,1)*설정!$C$10 -> -61589.087 | R13: =IF((-SUMIFS(보유분석!$AZ$2:$AZ$801,보유분석!$AC$2:$AC$801,1)*설정!$C$10)=0,0,Q13/(-SUMIFS(보유분석!$AZ$2:$AZ$801,보유분석!$AC$2:$AC$801,1)*설정!$C$10)) -> 0.0060517769 | S13: =IF(SUMIFS(보유분석!$BG$2:$BG$801,보유분석!$V$2:$V$801,$A13,보유분석!$AC$2:$AC$801,1)=0,"",SUMIFS(보유분석!$BH$2:$BH$801,보유분석!$V$2:$V$801,$A13,보유분석!$AC$2:$AC$801,1)/SUMIFS(보유분석!$BG$2:$BG$801,보유분석!$V$2:$V$801,$A13,보유분석!$AC$2:$AC$801,1)) -> 2.6344303 | T13: =IF(SUMIFS(보유분석!$BI$2:$BI$801,보유분석!$V$2:$V$801,$A13,보유분석!$AC$2:$AC$801,1)=0,"",SUMIFS(보유분석!$BD$2:$BD$801,보유분석!$V$2:$V$801,$A13,보유분석!$AC$2:$AC$801,1)/SUMIFS(보유분석!$BI$2:$BI$801,보유분석!$V$2:$V$801,$A13,보유분석!$AC$2:$AC$801,1)) -> 1
A14: 20년 이상 | B14: =SUMIFS(보유분석!$AA$2:$AA$801,보유분석!$V$2:$V$801,$A14,보유분석!$AC$2:$AC$801,1) -> 3.6444222 | C14: =IF(SUMIFS(보유분석!$AA$2:$AA$801,보유분석!$AC$2:$AC$801,1)=0,0,B14/SUMIFS(보유분석!$AA$2:$AA$801,보유분석!$AC$2:$AC$801,1)) -> 0.0025857994 | D14: =SUMIFS(보유분석!$AM$2:$AM$801,보유분석!$V$2:$V$801,$A14,보유분석!$AC$2:$AC$801,1) -> 5409.5617 | E14: =IF(SUMIFS(보유분석!$AM$2:$AM$801,보유분석!$AC$2:$AC$801,1)=0,0,D14/SUMIFS(보유분석!$AM$2:$AM$801,보유분석!$AC$2:$AC$801,1)) -> 0.01426485 | F14: =IF(SUMIFS(보유분석!$BB$2:$BB$801,보유분석!$V$2:$V$801,$A14,보유분석!$AC$2:$AC$801,1)=0,"",SUMIFS(보유분석!$BA$2:$BA$801,보유분석!$V$2:$V$801,$A14,보유분석!$AC$2:$AC$801,1)/SUMIFS(보유분석!$BB$2:$BB$801,보유분석!$V$2:$V$801,$A14,보유분석!$AC$2:$AC$801,1)) -> 6.1861 | G14: =IF(F14="","",(F14-(SUMIFS(보유분석!$BA$2:$BA$801,보유분석!$AC$2:$AC$801,1)/SUMIFS(보유분석!$BB$2:$BB$801,보유분석!$AC$2:$AC$801,1)))*100) -> 52.606418 | H14: =IF(SUMIFS(보유분석!$BD$2:$BD$801,보유분석!$V$2:$V$801,$A14,보유분석!$AC$2:$AC$801,1)=0,"",SUMIFS(보유분석!$BC$2:$BC$801,보유분석!$V$2:$V$801,$A14,보유분석!$AC$2:$AC$801,1)/SUMIFS(보유분석!$BD$2:$BD$801,보유분석!$V$2:$V$801,$A14,보유분석!$AC$2:$AC$801,1)) -> 64.761 | I14: =IF(SUMIFS(보유분석!$BF$2:$BF$801,보유분석!$V$2:$V$801,$A14,보유분석!$AC$2:$AC$801,1)=0,"",SUMIFS(보유분석!$BE$2:$BE$801,보유분석!$V$2:$V$801,$A14,보유분석!$AC$2:$AC$801,1)/SUMIFS(보유분석!$BF$2:$BF$801,보유분석!$V$2:$V$801,$A14,보유분석!$AC$2:$AC$801,1)) -> 14.8434 | J14: =IF(SUMIFS(보유분석!$BG$2:$BG$801,보유분석!$V$2:$V$801,$A14,보유분석!$AC$2:$AC$801,1)=0,"",(SUMIFS(보유분석!$BC$2:$BC$801,보유분석!$V$2:$V$801,$A14,보유분석!$AC$2:$AC$801,1)+SUMIFS(보유분석!$BH$2:$BH$801,보유분석!$V$2:$V$801,$A14,보유분석!$AC$2:$AC$801,1))/SUMIFS(보유분석!$BG$2:$BG$801,보유분석!$V$2:$V$801,$A14,보유분석!$AC$2:$AC$801,1)) -> 5.5551675 | K14: =IF(B14=0,"",SUMIFS(보유분석!$AV$2:$AV$801,보유분석!$V$2:$V$801,$A14,보유분석!$AC$2:$AC$801,1)/(B14*1000000)) -> 0.063630657 | L14: =SUMIFS(보유분석!$AP$2:$AP$801,보유분석!$V$2:$V$801,$A14,보유분석!$AC$2:$AC$801,1) -> -496779.68 | M14: =COUNTIFS(보유분석!$V$2:$V$801,$A14,보유분석!$AR$2:$AR$801,"Cheap",보유분석!$AC$2:$AC$801,1) -> 0 | N14: =COUNTIFS(보유분석!$V$2:$V$801,$A14,보유분석!$AR$2:$AR$801,"Rich",보유분석!$AC$2:$AC$801,1) -> 0 | P14: =IF(O14="","",O14-C14) | Q14: =-SUMIFS(보유분석!$AZ$2:$AZ$801,보유분석!$V$2:$V$801,$A14,보유분석!$AC$2:$AC$801,1)*설정!$C$10 -> -132471.41 | R14: =IF((-SUMIFS(보유분석!$AZ$2:$AZ$801,보유분석!$AC$2:$AC$801,1)*설정!$C$10)=0,0,Q14/(-SUMIFS(보유분석!$AZ$2:$AZ$801,보유분석!$AC$2:$AC$801,1)*설정!$C$10)) -> 0.013016712 | S14: =IF(SUMIFS(보유분석!$BG$2:$BG$801,보유분석!$V$2:$V$801,$A14,보유분석!$AC$2:$AC$801,1)=0,"",SUMIFS(보유분석!$BH$2:$BH$801,보유분석!$V$2:$V$801,$A14,보유분석!$AC$2:$AC$801,1)/SUMIFS(보유분석!$BG$2:$BG$801,보유분석!$V$2:$V$801,$A14,보유분석!$AC$2:$AC$801,1)) -> 1.1922183 | T14: =IF(SUMIFS(보유분석!$BI$2:$BI$801,보유분석!$V$2:$V$801,$A14,보유분석!$AC$2:$AC$801,1)=0,"",SUMIFS(보유분석!$BD$2:$BD$801,보유분석!$V$2:$V$801,$A14,보유분석!$AC$2:$AC$801,1)/SUMIFS(보유분석!$BI$2:$BI$801,보유분석!$V$2:$V$801,$A14,보유분석!$AC$2:$AC$801,1)) -> 1
A15: 기타(목록외) | B15: =SUMPRODUCT(ISNA(MATCH(보유분석!$V$2:$V$801,$A$6:$A$14,0))*(보유분석!$AC$2:$AC$801=1)*보유분석!$AA$2:$AA$801) -> 0 | C15: =IF(SUMIFS(보유분석!$AA$2:$AA$801,보유분석!$AC$2:$AC$801,1)=0,0,B15/SUMIFS(보유분석!$AA$2:$AA$801,보유분석!$AC$2:$AC$801,1)) -> 0 | D15: =SUMPRODUCT(ISNA(MATCH(보유분석!$V$2:$V$801,$A$6:$A$14,0))*(보유분석!$AC$2:$AC$801=1)*보유분석!$AM$2:$AM$801) -> 0 | E15: =IF(SUMIFS(보유분석!$AM$2:$AM$801,보유분석!$AC$2:$AC$801,1)=0,0,D15/SUMIFS(보유분석!$AM$2:$AM$801,보유분석!$AC$2:$AC$801,1)) -> 0 | F15: =IF(SUMPRODUCT(ISNA(MATCH(보유분석!$V$2:$V$801,$A$6:$A$14,0))*(보유분석!$AC$2:$AC$801=1)*보유분석!$BB$2:$BB$801)=0,"",SUMPRODUCT(ISNA(MATCH(보유분석!$V$2:$V$801,$A$6:$A$14,0))*(보유분석!$AC$2:$AC$801=1)*보유분석!$BA$2:$BA$801)/SUMPRODUCT(ISNA(MATCH(보유분석!$V$2:$V$801,$A$6:$A$14,0))*(보유분석!$AC$2:$AC$801=1)*보유분석!$BB$2:$BB$801)) | G15: =IF(F15="","",(F15-(SUMIFS(보유분석!$BA$2:$BA$801,보유분석!$AC$2:$AC$801,1)/SUMIFS(보유분석!$BB$2:$BB$801,보유분석!$AC$2:$AC$801,1)))*100) | H15: =IF(SUMPRODUCT(ISNA(MATCH(보유분석!$V$2:$V$801,$A$6:$A$14,0))*(보유분석!$AC$2:$AC$801=1)*보유분석!$BD$2:$BD$801)=0,"",SUMPRODUCT(ISNA(MATCH(보유분석!$V$2:$V$801,$A$6:$A$14,0))*(보유분석!$AC$2:$AC$801=1)*보유분석!$BC$2:$BC$801)/SUMPRODUCT(ISNA(MATCH(보유분석!$V$2:$V$801,$A$6:$A$14,0))*(보유분석!$AC$2:$AC$801=1)*보유분석!$BD$2:$BD$801)) | I15: =IF(SUMPRODUCT(ISNA(MATCH(보유분석!$V$2:$V$801,$A$6:$A$14,0))*(보유분석!$AC$2:$AC$801=1)*보유분석!$BF$2:$BF$801)=0,"",SUMPRODUCT(ISNA(MATCH(보유분석!$V$2:$V$801,$A$6:$A$14,0))*(보유분석!$AC$2:$AC$801=1)*보유분석!$BE$2:$BE$801)/SUMPRODUCT(ISNA(MATCH(보유분석!$V$2:$V$801,$A$6:$A$14,0))*(보유분석!$AC$2:$AC$801=1)*보유분석!$BF$2:$BF$801)) | J15: =IF(SUMPRODUCT(ISNA(MATCH(보유분석!$V$2:$V$801,$A$6:$A$14,0))*(보유분석!$AC$2:$AC$801=1)*보유분석!$BG$2:$BG$801)=0,"",(SUMPRODUCT(ISNA(MATCH(보유분석!$V$2:$V$801,$A$6:$A$14,0))*(보유분석!$AC$2:$AC$801=1)*보유분석!$BC$2:$BC$801)+SUMPRODUCT(ISNA(MATCH(보유분석!$V$2:$V$801,$A$6:$A$14,0))*(보유분석!$AC$2:$AC$801=1)*보유분석!$BH$2:$BH$801))/SUMPRODUCT(ISNA(MATCH(보유분석!$V$2:$V$801,$A$6:$A$14,0))*(보유분석!$AC$2:$AC$801=1)*보유분석!$BG$2:$BG$801)) | K15: =IF(B15=0,"",SUMPRODUCT(ISNA(MATCH(보유분석!$V$2:$V$801,$A$6:$A$14,0))*(보유분석!$AC$2:$AC$801=1)*보유분석!$AV$2:$AV$801)/(B15*1000000)) | L15: =SUMPRODUCT(ISNA(MATCH(보유분석!$V$2:$V$801,$A$6:$A$14,0))*(보유분석!$AC$2:$AC$801=1)*보유분석!$AP$2:$AP$801) -> 0 | M15: =SUMPRODUCT(ISNA(MATCH(보유분석!$V$2:$V$801,$A$6:$A$14,0))*(보유분석!$AC$2:$AC$801=1)*(보유분석!$AR$2:$AR$801="Cheap")) -> 0 | N15: =SUMPRODUCT(ISNA(MATCH(보유분석!$V$2:$V$801,$A$6:$A$14,0))*(보유분석!$AC$2:$AC$801=1)*(보유분석!$AR$2:$AR$801="Rich")) -> 0 | P15: =IF(O15="","",O15-C15) | Q15: =-SUMPRODUCT(ISNA(MATCH(보유분석!$V$2:$V$801,$A$6:$A$14,0))*(보유분석!$AC$2:$AC$801=1)*보유분석!$AZ$2:$AZ$801)*설정!$C$10 -> 0 | R15: =IF((-SUMIFS(보유분석!$AZ$2:$AZ$801,보유분석!$AC$2:$AC$801,1)*설정!$C$10)=0,0,Q15/(-SUMIFS(보유분석!$AZ$2:$AZ$801,보유분석!$AC$2:$AC$801,1)*설정!$C$10)) -> 0 | S15: =IF(SUMPRODUCT(ISNA(MATCH(보유분석!$V$2:$V$801,$A$6:$A$14,0))*(보유분석!$AC$2:$AC$801=1)*보유분석!$BG$2:$BG$801)=0,"",SUMPRODUCT(ISNA(MATCH(보유분석!$V$2:$V$801,$A$6:$A$14,0))*(보유분석!$AC$2:$AC$801=1)*보유분석!$BH$2:$BH$801)/SUMPRODUCT(ISNA(MATCH(보유분석!$V$2:$V$801,$A$6:$A$14,0))*(보유분석!$AC$2:$AC$801=1)*보유분석!$BG$2:$BG$801)) | T15: =IF(SUMPRODUCT(ISNA(MATCH(보유분석!$V$2:$V$801,$A$6:$A$14,0))*(보유분석!$AC$2:$AC$801=1)*보유분석!$BI$2:$BI$801)=0,"",SUMPRODUCT(ISNA(MATCH(보유분석!$V$2:$V$801,$A$6:$A$14,0))*(보유분석!$AC$2:$AC$801=1)*보유분석!$BD$2:$BD$801)/SUMPRODUCT(ISNA(MATCH(보유분석!$V$2:$V$801,$A$6:$A$14,0))*(보유분석!$AC$2:$AC$801=1)*보유분석!$BI$2:$BI$801))
A16: 합계 | B16: =SUM(B6:B15) -> 1409.3986 | C16: =SUM(C6:C15) -> 1 | D16: =SUM(D6:D15) -> 379223.18 | E16: =SUM(E6:E15) -> 1 | F16: =IF(SUMIFS(보유분석!$BB$2:$BB$801,보유분석!$AC$2:$AC$801,1)=0,"",SUMIFS(보유분석!$BA$2:$BA$801,보유분석!$AC$2:$AC$801,1)/SUMIFS(보유분석!$BB$2:$BB$801,보유분석!$AC$2:$AC$801,1)) -> 5.6600358 | H16: =IF(SUMIFS(보유분석!$BD$2:$BD$801,보유분석!$AC$2:$AC$801,1)=0,"",SUMIFS(보유분석!$BC$2:$BC$801,보유분석!$AC$2:$AC$801,1)/SUMIFS(보유분석!$BD$2:$BD$801,보유분석!$AC$2:$AC$801,1)) -> 66.114006 | I16: =IF(SUMIFS(보유분석!$BF$2:$BF$801,보유분석!$AC$2:$AC$801,1)=0,"",SUMIFS(보유분석!$BE$2:$BE$801,보유분석!$AC$2:$AC$801,1)/SUMIFS(보유분석!$BF$2:$BF$801,보유분석!$AC$2:$AC$801,1)) -> 2.6906736 | J16: =IF(SUMIFS(보유분석!$BG$2:$BG$801,보유분석!$AC$2:$AC$801,1)=0,"",(SUMIFS(보유분석!$BC$2:$BC$801,보유분석!$AC$2:$AC$801,1)+SUMIFS(보유분석!$BH$2:$BH$801,보유분석!$AC$2:$AC$801,1))/SUMIFS(보유분석!$BG$2:$BG$801,보유분석!$AC$2:$AC$801,1)) -> 31.468574 | K16: =IF(B16=0,"",SUMIFS(보유분석!$AV$2:$AV$801,보유분석!$AC$2:$AC$801,1)/(B16*1000000)) -> 0.058254622 | L16: =SUM(L6:L15) -> -44901234 | O16: =IF(COUNT(O6:O15)=0,"",SUM(O6:O15)) | Q16: =SUM(Q6:Q15) -> -10177025 | R16: =SUM(R6:R15) -> 1 | S16: =IF(SUMIFS(보유분석!$BG$2:$BG$801,보유분석!$AC$2:$AC$801,1)=0,"",SUMIFS(보유분석!$BH$2:$BH$801,보유분석!$AC$2:$AC$801,1)/SUMIFS(보유분석!$BG$2:$BG$801,보유분석!$AC$2:$AC$801,1)) -> 6.4728238 | T16: =IF(SUMIFS(보유분석!$BI$2:$BI$801,보유분석!$AC$2:$AC$801,1)=0,"",SUMIFS(보유분석!$BD$2:$BD$801,보유분석!$AC$2:$AC$801,1)/SUMIFS(보유분석!$BI$2:$BI$801,보유분석!$AC$2:$AC$801,1)) -> 0.97796717
A19: ■ 국가
A20: 구분 | B20: 평가금액($M) | C20: 비중 | D20: DV01($/bp) | E20: DV01비중 | F20: 가중YTM(%) | G20: 포트대비(bp) | H20: 가중G-spread(bp) | I20: 가중듀레이션 | J20: 손익분기 확대폭(bp) 스프레드+롤다운 | K20: 1Y기대수익률(%) | L20: 평가손익($) | M20: Cheap 보유수 | N20: Rich 보유수 | O20: 목표비중(입력) | P20: 갭(목표-현재) | Q20: 스프레드쇼크 손실($) | R20: 손실비중 | S20: └ 롤다운 기여(bp) | T20: G-spread 커버리지
A21: 한국 | B21: =SUMIFS(보유분석!$AA$2:$AA$801,보유분석!$AI$2:$AI$801,$A21,보유분석!$AC$2:$AC$801,1) -> 763.96143 | C21: =IF(SUMIFS(보유분석!$AA$2:$AA$801,보유분석!$AC$2:$AC$801,1)=0,0,B21/SUMIFS(보유분석!$AA$2:$AA$801,보유분석!$AC$2:$AC$801,1)) -> 0.54204779 | D21: =SUMIFS(보유분석!$AM$2:$AM$801,보유분석!$AI$2:$AI$801,$A21,보유분석!$AC$2:$AC$801,1) -> 195533.53 | E21: =IF(SUMIFS(보유분석!$AM$2:$AM$801,보유분석!$AC$2:$AC$801,1)=0,0,D21/SUMIFS(보유분석!$AM$2:$AM$801,보유분석!$AC$2:$AC$801,1)) -> 0.51561598 | F21: =IF(SUMIFS(보유분석!$BB$2:$BB$801,보유분석!$AI$2:$AI$801,$A21,보유분석!$AC$2:$AC$801,1)=0,"",SUMIFS(보유분석!$BA$2:$BA$801,보유분석!$AI$2:$AI$801,$A21,보유분석!$AC$2:$AC$801,1)/SUMIFS(보유분석!$BB$2:$BB$801,보유분석!$AI$2:$AI$801,$A21,보유분석!$AC$2:$AC$801,1)) -> 5.6599315 | G21: =IF(F21="","",(F21-(SUMIFS(보유분석!$BA$2:$BA$801,보유분석!$AC$2:$AC$801,1)/SUMIFS(보유분석!$BB$2:$BB$801,보유분석!$AC$2:$AC$801,1)))*100) -> -0.010427909 | H21: =IF(SUMIFS(보유분석!$BD$2:$BD$801,보유분석!$AI$2:$AI$801,$A21,보유분석!$AC$2:$AC$801,1)=0,"",SUMIFS(보유분석!$BC$2:$BC$801,보유분석!$AI$2:$AI$801,$A21,보유분석!$AC$2:$AC$801,1)/SUMIFS(보유분석!$BD$2:$BD$801,보유분석!$AI$2:$AI$801,$A21,보유분석!$AC$2:$AC$801,1)) -> 63.69228 | I21: =IF(SUMIFS(보유분석!$BF$2:$BF$801,보유분석!$AI$2:$AI$801,$A21,보유분석!$AC$2:$AC$801,1)=0,"",SUMIFS(보유분석!$BE$2:$BE$801,보유분석!$AI$2:$AI$801,$A21,보유분석!$AC$2:$AC$801,1)/SUMIFS(보유분석!$BF$2:$BF$801,보유분석!$AI$2:$AI$801,$A21,보유분석!$AC$2:$AC$801,1)) -> 2.5594686 | J21: =IF(SUMIFS(보유분석!$BG$2:$BG$801,보유분석!$AI$2:$AI$801,$A21,보유분석!$AC$2:$AC$801,1)=0,"",(SUMIFS(보유분석!$BC$2:$BC$801,보유분석!$AI$2:$AI$801,$A21,보유분석!$AC$2:$AC$801,1)+SUMIFS(보유분석!$BH$2:$BH$801,보유분석!$AI$2:$AI$801,$A21,보유분석!$AC$2:$AC$801,1))/SUMIFS(보유분석!$BG$2:$BG$801,보유분석!$AI$2:$AI$801,$A21,보유분석!$AC$2:$AC$801,1)) -> 30.793963 | K21: =IF(B21=0,"",SUMIFS(보유분석!$AV$2:$AV$801,보유분석!$AI$2:$AI$801,$A21,보유분석!$AC$2:$AC$801,1)/(B21*1000000)) -> 0.05811123 | L21: =SUMIFS(보유분석!$AP$2:$AP$801,보유분석!$AI$2:$AI$801,$A21,보유분석!$AC$2:$AC$801,1) -> -23025676 | M21: =COUNTIFS(보유분석!$AI$2:$AI$801,$A21,보유분석!$AR$2:$AR$801,"Cheap",보유분석!$AC$2:$AC$801,1) -> 20 | N21: =COUNTIFS(보유분석!$AI$2:$AI$801,$A21,보유분석!$AR$2:$AR$801,"Rich",보유분석!$AC$2:$AC$801,1) -> 5 | P21: =IF(O21="","",O21-C21) | Q21: =-SUMIFS(보유분석!$AZ$2:$AZ$801,보유분석!$AI$2:$AI$801,$A21,보유분석!$AC$2:$AC$801,1)*설정!$C$10 -> -5353045.3 | R21: =IF((-SUMIFS(보유분석!$AZ$2:$AZ$801,보유분석!$AC$2:$AC$801,1)*설정!$C$10)=0,0,Q21/(-SUMIFS(보유분석!$AZ$2:$AZ$801,보유분석!$AC$2:$AC$801,1)*설정!$C$10)) -> 0.52599312 | S21: =IF(SUMIFS(보유분석!$BG$2:$BG$801,보유분석!$AI$2:$AI$801,$A21,보유분석!$AC$2:$AC$801,1)=0,"",SUMIFS(보유분석!$BH$2:$BH$801,보유분석!$AI$2:$AI$801,$A21,보유분석!$AC$2:$AC$801,1)/SUMIFS(보유분석!$BG$2:$BG$801,보유분석!$AI$2:$AI$801,$A21,보유분석!$AC$2:$AC$801,1)) -> 5.908732 | T21: =IF(SUMIFS(보유분석!$BI$2:$BI$801,보유분석!$AI$2:$AI$801,$A21,보유분석!$AC$2:$AC$801,1)=0,"",SUMIFS(보유분석!$BD$2:$BD$801,보유분석!$AI$2:$AI$801,$A21,보유분석!$AC$2:$AC$801,1)/SUMIFS(보유분석!$BI$2:$BI$801,보유분석!$AI$2:$AI$801,$A21,보유분석!$AC$2:$AC$801,1)) -> 0.99974206
A22: 미국 | B22: =SUMIFS(보유분석!$AA$2:$AA$801,보유분석!$AI$2:$AI$801,$A22,보유분석!$AC$2:$AC$801,1) -> 346.2105 | C22: =IF(SUMIFS(보유분석!$AA$2:$AA$801,보유분석!$AC$2:$AC$801,1)=0,0,B22/SUMIFS(보유분석!$AA$2:$AA$801,보유분석!$AC$2:$AC$801,1)) -> 0.24564412 | D22: =SUMIFS(보유분석!$AM$2:$AM$801,보유분석!$AI$2:$AI$801,$A22,보유분석!$AC$2:$AC$801,1) -> 103156.98 | E22: =IF(SUMIFS(보유분석!$AM$2:$AM$801,보유분석!$AC$2:$AC$801,1)=0,0,D22/SUMIFS(보유분석!$AM$2:$AM$801,보유분석!$AC$2:$AC$801,1)) -> 0.27202182 | F22: =IF(SUMIFS(보유분석!$BB$2:$BB$801,보유분석!$AI$2:$AI$801,$A22,보유분석!$AC$2:$AC$801,1)=0,"",SUMIFS(보유분석!$BA$2:$BA$801,보유분석!$AI$2:$AI$801,$A22,보유분석!$AC$2:$AC$801,1)/SUMIFS(보유분석!$BB$2:$BB$801,보유분석!$AI$2:$AI$801,$A22,보유분석!$AC$2:$AC$801,1)) -> 5.6446276 | G22: =IF(F22="","",(F22-(SUMIFS(보유분석!$BA$2:$BA$801,보유분석!$AC$2:$AC$801,1)/SUMIFS(보유분석!$BB$2:$BB$801,보유분석!$AC$2:$AC$801,1)))*100) -> -1.54082 | H22: =IF(SUMIFS(보유분석!$BD$2:$BD$801,보유분석!$AI$2:$AI$801,$A22,보유분석!$AC$2:$AC$801,1)=0,"",SUMIFS(보유분석!$BC$2:$BC$801,보유분석!$AI$2:$AI$801,$A22,보유분석!$AC$2:$AC$801,1)/SUMIFS(보유분석!$BD$2:$BD$801,보유분석!$AI$2:$AI$801,$A22,보유분석!$AC$2:$AC$801,1)) -> 66.580415 | I22: =IF(SUMIFS(보유분석!$BF$2:$BF$801,보유분석!$AI$2:$AI$801,$A22,보유분석!$AC$2:$AC$801,1)=0,"",SUMIFS(보유분석!$BE$2:$BE$801,보유분석!$AI$2:$AI$801,$A22,보유분석!$AC$2:$AC$801,1)/SUMIFS(보유분석!$BF$2:$BF$801,보유분석!$AI$2:$AI$801,$A22,보유분석!$AC$2:$AC$801,1)) -> 2.9796029 | J22: =IF(SUMIFS(보유분석!$BG$2:$BG$801,보유분석!$AI$2:$AI$801,$A22,보유분석!$AC$2:$AC$801,1)=0,"",(SUMIFS(보유분석!$BC$2:$BC$801,보유분석!$AI$2:$AI$801,$A22,보유분석!$AC$2:$AC$801,1)+SUMIFS(보유분석!$BH$2:$BH$801,보유분석!$AI$2:$AI$801,$A22,보유분석!$AC$2:$AC$801,1))/SUMIFS(보유분석!$BG$2:$BG$801,보유분석!$AI$2:$AI$801,$A22,보유분석!$AC$2:$AC$801,1)) -> 31.844347 | K22: =IF(B22=0,"",SUMIFS(보유분석!$AV$2:$AV$801,보유분석!$AI$2:$AI$801,$A22,보유분석!$AC$2:$AC$801,1)/(B22*1000000)) -> 0.058315274 | L22: =SUMIFS(보유분석!$AP$2:$AP$801,보유분석!$AI$2:$AI$801,$A22,보유분석!$AC$2:$AC$801,1) -> -12389374 | M22: =COUNTIFS(보유분석!$AI$2:$AI$801,$A22,보유분석!$AR$2:$AR$801,"Cheap",보유분석!$AC$2:$AC$801,1) -> 9 | N22: =COUNTIFS(보유분석!$AI$2:$AI$801,$A22,보유분석!$AR$2:$AR$801,"Rich",보유분석!$AC$2:$AC$801,1) -> 3 | P22: =IF(O22="","",O22-C22) | Q22: =-SUMIFS(보유분석!$AZ$2:$AZ$801,보유분석!$AI$2:$AI$801,$A22,보유분석!$AC$2:$AC$801,1)*설정!$C$10 -> -2496353.9 | R22: =IF((-SUMIFS(보유분석!$AZ$2:$AZ$801,보유분석!$AC$2:$AC$801,1)*설정!$C$10)=0,0,Q22/(-SUMIFS(보유분석!$AZ$2:$AZ$801,보유분석!$AC$2:$AC$801,1)*설정!$C$10)) -> 0.24529308 | S22: =IF(SUMIFS(보유분석!$BG$2:$BG$801,보유분석!$AI$2:$AI$801,$A22,보유분석!$AC$2:$AC$801,1)=0,"",SUMIFS(보유분석!$BH$2:$BH$801,보유분석!$AI$2:$AI$801,$A22,보유분석!$AC$2:$AC$801,1)/SUMIFS(보유분석!$BG$2:$BG$801,보유분석!$AI$2:$AI$801,$A22,보유분석!$AC$2:$AC$801,1)) -> 7.5305611 | T22: =IF(SUMIFS(보유분석!$BI$2:$BI$801,보유분석!$AI$2:$AI$801,$A22,보유분석!$AC$2:$AC$801,1)=0,"",SUMIFS(보유분석!$BD$2:$BD$801,보유분석!$AI$2:$AI$801,$A22,보유분석!$AC$2:$AC$801,1)/SUMIFS(보유분석!$BI$2:$BI$801,보유분석!$AI$2:$AI$801,$A22,보유분석!$AC$2:$AC$801,1)) -> 0.95285844
A23: 일본 | B23: =SUMIFS(보유분석!$AA$2:$AA$801,보유분석!$AI$2:$AI$801,$A23,보유분석!$AC$2:$AC$801,1) -> 47.630173 | C23: =IF(SUMIFS(보유분석!$AA$2:$AA$801,보유분석!$AC$2:$AC$801,1)=0,0,B23/SUMIFS(보유분석!$AA$2:$AA$801,보유분석!$AC$2:$AC$801,1)) -> 0.033794678 | D23: =SUMIFS(보유분석!$AM$2:$AM$801,보유분석!$AI$2:$AI$801,$A23,보유분석!$AC$2:$AC$801,1) -> 12069.734 | E23: =IF(SUMIFS(보유분석!$AM$2:$AM$801,보유분석!$AC$2:$AC$801,1)=0,0,D23/SUMIFS(보유분석!$AM$2:$AM$801,보유분석!$AC$2:$AC$801,1)) -> 0.031827521 | F23: =IF(SUMIFS(보유분석!$BB$2:$BB$801,보유분석!$AI$2:$AI$801,$A23,보유분석!$AC$2:$AC$801,1)=0,"",SUMIFS(보유분석!$BA$2:$BA$801,보유분석!$AI$2:$AI$801,$A23,보유분석!$AC$2:$AC$801,1)/SUMIFS(보유분석!$BB$2:$BB$801,보유분석!$AI$2:$AI$801,$A23,보유분석!$AC$2:$AC$801,1)) -> 5.5997652 | G23: =IF(F23="","",(F23-(SUMIFS(보유분석!$BA$2:$BA$801,보유분석!$AC$2:$AC$801,1)/SUMIFS(보유분석!$BB$2:$BB$801,보유분석!$AC$2:$AC$801,1)))*100) -> -6.0270603 | H23: =IF(SUMIFS(보유분석!$BD$2:$BD$801,보유분석!$AI$2:$AI$801,$A23,보유분석!$AC$2:$AC$801,1)=0,"",SUMIFS(보유분석!$BC$2:$BC$801,보유분석!$AI$2:$AI$801,$A23,보유분석!$AC$2:$AC$801,1)/SUMIFS(보유분석!$BD$2:$BD$801,보유분석!$AI$2:$AI$801,$A23,보유분석!$AC$2:$AC$801,1)) -> 65.823469 | I23: =IF(SUMIFS(보유분석!$BF$2:$BF$801,보유분석!$AI$2:$AI$801,$A23,보유분석!$AC$2:$AC$801,1)=0,"",SUMIFS(보유분석!$BE$2:$BE$801,보유분석!$AI$2:$AI$801,$A23,보유분석!$AC$2:$AC$801,1)/SUMIFS(보유분석!$BF$2:$BF$801,보유분석!$AI$2:$AI$801,$A23,보유분석!$AC$2:$AC$801,1)) -> 2.534052 | J23: =IF(SUMIFS(보유분석!$BG$2:$BG$801,보유분석!$AI$2:$AI$801,$A23,보유분석!$AC$2:$AC$801,1)=0,"",(SUMIFS(보유분석!$BC$2:$BC$801,보유분석!$AI$2:$AI$801,$A23,보유분석!$AC$2:$AC$801,1)+SUMIFS(보유분석!$BH$2:$BH$801,보유분석!$AI$2:$AI$801,$A23,보유분석!$AC$2:$AC$801,1))/SUMIFS(보유분석!$BG$2:$BG$801,보유분석!$AI$2:$AI$801,$A23,보유분석!$AC$2:$AC$801,1)) -> 30.047613 | K23: =IF(B23=0,"",SUMIFS(보유분석!$AV$2:$AV$801,보유분석!$AI$2:$AI$801,$A23,보유분석!$AC$2:$AC$801,1)/(B23*1000000)) -> 0.057029527 | L23: =SUMIFS(보유분석!$AP$2:$AP$801,보유분석!$AI$2:$AI$801,$A23,보유분석!$AC$2:$AC$801,1) -> -927265.08 | M23: =COUNTIFS(보유분석!$AI$2:$AI$801,$A23,보유분석!$AR$2:$AR$801,"Cheap",보유분석!$AC$2:$AC$801,1) -> 3 | N23: =COUNTIFS(보유분석!$AI$2:$AI$801,$A23,보유분석!$AR$2:$AR$801,"Rich",보유분석!$AC$2:$AC$801,1) -> 0 | P23: =IF(O23="","",O23-C23) | Q23: =-SUMIFS(보유분석!$AZ$2:$AZ$801,보유분석!$AI$2:$AI$801,$A23,보유분석!$AC$2:$AC$801,1)*설정!$C$10 -> -324651.85 | R23: =IF((-SUMIFS(보유분석!$AZ$2:$AZ$801,보유분석!$AC$2:$AC$801,1)*설정!$C$10)=0,0,Q23/(-SUMIFS(보유분석!$AZ$2:$AZ$801,보유분석!$AC$2:$AC$801,1)*설정!$C$10)) -> 0.031900466 | S23: =IF(SUMIFS(보유분석!$BG$2:$BG$801,보유분석!$AI$2:$AI$801,$A23,보유분석!$AC$2:$AC$801,1)=0,"",SUMIFS(보유분석!$BH$2:$BH$801,보유분석!$AI$2:$AI$801,$A23,보유분석!$AC$2:$AC$801,1)/SUMIFS(보유분석!$BG$2:$BG$801,보유분석!$AI$2:$AI$801,$A23,보유분석!$AC$2:$AC$801,1)) -> 4.0720336 | T23: =IF(SUMIFS(보유분석!$BI$2:$BI$801,보유분석!$AI$2:$AI$801,$A23,보유분석!$AC$2:$AC$801,1)=0,"",SUMIFS(보유분석!$BD$2:$BD$801,보유분석!$AI$2:$AI$801,$A23,보유분석!$AC$2:$AC$801,1)/SUMIFS(보유분석!$BI$2:$BI$801,보유분석!$AI$2:$AI$801,$A23,보유분석!$AC$2:$AC$801,1)) -> 1
A24: 영국 | B24: =SUMIFS(보유분석!$AA$2:$AA$801,보유분석!$AI$2:$AI$801,$A24,보유분석!$AC$2:$AC$801,1) -> 156.65582 | C24: =IF(SUMIFS(보유분석!$AA$2:$AA$801,보유분석!$AC$2:$AC$801,1)=0,0,B24/SUMIFS(보유분석!$AA$2:$AA$801,보유분석!$AC$2:$AC$801,1)) -> 0.11115082 | D24: =SUMIFS(보유분석!$AM$2:$AM$801,보유분석!$AI$2:$AI$801,$A24,보유분석!$AC$2:$AC$801,1) -> 43050.9 | E24: =IF(SUMIFS(보유분석!$AM$2:$AM$801,보유분석!$AC$2:$AC$801,1)=0,0,D24/SUMIFS(보유분석!$AM$2:$AM$801,보유분석!$AC$2:$AC$801,1)) -> 0.11352392 | F24: =IF(SUMIFS(보유분석!$BB$2:$BB$801,보유분석!$AI$2:$AI$801,$A24,보유분석!$AC$2:$AC$801,1)=0,"",SUMIFS(보유분석!$BA$2:$BA$801,보유분석!$AI$2:$AI$801,$A24,보유분석!$AC$2:$AC$801,1)/SUMIFS(보유분석!$BB$2:$BB$801,보유분석!$AI$2:$AI$801,$A24,보유분석!$AC$2:$AC$801,1)) -> 5.6856112 | G24: =IF(F24="","",(F24-(SUMIFS(보유분석!$BA$2:$BA$801,보유분석!$AC$2:$AC$801,1)/SUMIFS(보유분석!$BB$2:$BB$801,보유분석!$AC$2:$AC$801,1)))*100) -> 2.557533 | H24: =IF(SUMIFS(보유분석!$BD$2:$BD$801,보유분석!$AI$2:$AI$801,$A24,보유분석!$AC$2:$AC$801,1)=0,"",SUMIFS(보유분석!$BC$2:$BC$801,보유분석!$AI$2:$AI$801,$A24,보유분석!$AC$2:$AC$801,1)/SUMIFS(보유분석!$BD$2:$BD$801,보유분석!$AI$2:$AI$801,$A24,보유분석!$AC$2:$AC$801,1)) -> 72.015725 | I24: =IF(SUMIFS(보유분석!$BF$2:$BF$801,보유분석!$AI$2:$AI$801,$A24,보유분석!$AC$2:$AC$801,1)=0,"",SUMIFS(보유분석!$BE$2:$BE$801,보유분석!$AI$2:$AI$801,$A24,보유분석!$AC$2:$AC$801,1)/SUMIFS(보유분석!$BF$2:$BF$801,보유분석!$AI$2:$AI$801,$A24,보유분석!$AC$2:$AC$801,1)) -> 2.7481201 | J24: =IF(SUMIFS(보유분석!$BG$2:$BG$801,보유분석!$AI$2:$AI$801,$A24,보유분석!$AC$2:$AC$801,1)=0,"",(SUMIFS(보유분석!$BC$2:$BC$801,보유분석!$AI$2:$AI$801,$A24,보유분석!$AC$2:$AC$801,1)+SUMIFS(보유분석!$BH$2:$BH$801,보유분석!$AI$2:$AI$801,$A24,보유분석!$AC$2:$AC$801,1))/SUMIFS(보유분석!$BG$2:$BG$801,보유분석!$AI$2:$AI$801,$A24,보유분석!$AC$2:$AC$801,1)) -> 33.579777 | K24: =IF(B24=0,"",SUMIFS(보유분석!$AV$2:$AV$801,보유분석!$AI$2:$AI$801,$A24,보유분석!$AC$2:$AC$801,1)/(B24*1000000)) -> 0.058882665 | L24: =SUMIFS(보유분석!$AP$2:$AP$801,보유분석!$AI$2:$AI$801,$A24,보유분석!$AC$2:$AC$801,1) -> -5593491 | M24: =COUNTIFS(보유분석!$AI$2:$AI$801,$A24,보유분석!$AR$2:$AR$801,"Cheap",보유분석!$AC$2:$AC$801,1) -> 1 | N24: =COUNTIFS(보유분석!$AI$2:$AI$801,$A24,보유분석!$AR$2:$AR$801,"Rich",보유분석!$AC$2:$AC$801,1) -> 2 | P24: =IF(O24="","",O24-C24) | Q24: =-SUMIFS(보유분석!$AZ$2:$AZ$801,보유분석!$AI$2:$AI$801,$A24,보유분석!$AC$2:$AC$801,1)*설정!$C$10 -> -1252257.6 | R24: =IF((-SUMIFS(보유분석!$AZ$2:$AZ$801,보유분석!$AC$2:$AC$801,1)*설정!$C$10)=0,0,Q24/(-SUMIFS(보유분석!$AZ$2:$AZ$801,보유분석!$AC$2:$AC$801,1)*설정!$C$10)) -> 0.1230475 | S24: =IF(SUMIFS(보유분석!$BG$2:$BG$801,보유분석!$AI$2:$AI$801,$A24,보유분석!$AC$2:$AC$801,1)=0,"",SUMIFS(보유분석!$BH$2:$BH$801,보유분석!$AI$2:$AI$801,$A24,보유분석!$AC$2:$AC$801,1)/SUMIFS(보유분석!$BG$2:$BG$801,보유분석!$AI$2:$AI$801,$A24,보유분석!$AC$2:$AC$801,1)) -> 7.3743267 | T24: =IF(SUMIFS(보유분석!$BI$2:$BI$801,보유분석!$AI$2:$AI$801,$A24,보유분석!$AC$2:$AC$801,1)=0,"",SUMIFS(보유분석!$BD$2:$BD$801,보유분석!$AI$2:$AI$801,$A24,보유분석!$AC$2:$AC$801,1)/SUMIFS(보유분석!$BI$2:$BI$801,보유분석!$AI$2:$AI$801,$A24,보유분석!$AC$2:$AC$801,1)) -> 1
A25: 프랑스 | B25: =SUMIFS(보유분석!$AA$2:$AA$801,보유분석!$AI$2:$AI$801,$A25,보유분석!$AC$2:$AC$801,1) -> 35.459857 | C25: =IF(SUMIFS(보유분석!$AA$2:$AA$801,보유분석!$AC$2:$AC$801,1)=0,0,B25/SUMIFS(보유분석!$AA$2:$AA$801,보유분석!$AC$2:$AC$801,1)) -> 0.025159565 | D25: =SUMIFS(보유분석!$AM$2:$AM$801,보유분석!$AI$2:$AI$801,$A25,보유분석!$AC$2:$AC$801,1) -> 7074.4158 | E25: =IF(SUMIFS(보유분석!$AM$2:$AM$801,보유분석!$AC$2:$AC$801,1)=0,0,D25/SUMIFS(보유분석!$AM$2:$AM$801,보유분석!$AC$2:$AC$801,1)) -> 0.018655019 | F25: =IF(SUMIFS(보유분석!$BB$2:$BB$801,보유분석!$AI$2:$AI$801,$A25,보유분석!$AC$2:$AC$801,1)=0,"",SUMIFS(보유분석!$BA$2:$BA$801,보유분석!$AI$2:$AI$801,$A25,보유분석!$AC$2:$AC$801,1)/SUMIFS(보유분석!$BB$2:$BB$801,보유분석!$AI$2:$AI$801,$A25,보유분석!$AC$2:$AC$801,1)) -> 5.6056196 | G25: =IF(F25="","",(F25-(SUMIFS(보유분석!$BA$2:$BA$801,보유분석!$AC$2:$AC$801,1)/SUMIFS(보유분석!$BB$2:$BB$801,보유분석!$AC$2:$AC$801,1)))*100) -> -5.4416214 | H25: =IF(SUMIFS(보유분석!$BD$2:$BD$801,보유분석!$AI$2:$AI$801,$A25,보유분석!$AC$2:$AC$801,1)=0,"",SUMIFS(보유분석!$BC$2:$BC$801,보유분석!$AI$2:$AI$801,$A25,보유분석!$AC$2:$AC$801,1)/SUMIFS(보유분석!$BD$2:$BD$801,보유분석!$AI$2:$AI$801,$A25,보유분석!$AC$2:$AC$801,1)) -> 95.44932 | I25: =IF(SUMIFS(보유분석!$BF$2:$BF$801,보유분석!$AI$2:$AI$801,$A25,보유분석!$AC$2:$AC$801,1)=0,"",SUMIFS(보유분석!$BE$2:$BE$801,보유분석!$AI$2:$AI$801,$A25,보유분석!$AC$2:$AC$801,1)/SUMIFS(보유분석!$BF$2:$BF$801,보유분석!$AI$2:$AI$801,$A25,보유분석!$AC$2:$AC$801,1)) -> 1.9950492 | J25: =IF(SUMIFS(보유분석!$BG$2:$BG$801,보유분석!$AI$2:$AI$801,$A25,보유분석!$AC$2:$AC$801,1)=0,"",(SUMIFS(보유분석!$BC$2:$BC$801,보유분석!$AI$2:$AI$801,$A25,보유분석!$AC$2:$AC$801,1)+SUMIFS(보유분석!$BH$2:$BH$801,보유분석!$AI$2:$AI$801,$A25,보유분석!$AC$2:$AC$801,1))/SUMIFS(보유분석!$BG$2:$BG$801,보유분석!$AI$2:$AI$801,$A25,보유분석!$AC$2:$AC$801,1)) -> 41.574365 | K25: =IF(B25=0,"",SUMIFS(보유분석!$AV$2:$AV$801,보유분석!$AI$2:$AI$801,$A25,보유분석!$AC$2:$AC$801,1)/(B25*1000000)) -> 0.057506823 | L25: =SUMIFS(보유분석!$AP$2:$AP$801,보유분석!$AI$2:$AI$801,$A25,보유분석!$AC$2:$AC$801,1) -> -990577 | M25: =COUNTIFS(보유분석!$AI$2:$AI$801,$A25,보유분석!$AR$2:$AR$801,"Cheap",보유분석!$AC$2:$AC$801,1) -> 3 | N25: =COUNTIFS(보유분석!$AI$2:$AI$801,$A25,보유분석!$AR$2:$AR$801,"Rich",보유분석!$AC$2:$AC$801,1) -> 0 | P25: =IF(O25="","",O25-C25) | Q25: =-SUMIFS(보유분석!$AZ$2:$AZ$801,보유분석!$AI$2:$AI$801,$A25,보유분석!$AC$2:$AC$801,1)*설정!$C$10 -> -269705.89 | R25: =IF((-SUMIFS(보유분석!$AZ$2:$AZ$801,보유분석!$AC$2:$AC$801,1)*설정!$C$10)=0,0,Q25/(-SUMIFS(보유분석!$AZ$2:$AZ$801,보유분석!$AC$2:$AC$801,1)*설정!$C$10)) -> 0.026501446 | S25: =IF(SUMIFS(보유분석!$BG$2:$BG$801,보유분석!$AI$2:$AI$801,$A25,보유분석!$AC$2:$AC$801,1)=0,"",SUMIFS(보유분석!$BH$2:$BH$801,보유분석!$AI$2:$AI$801,$A25,보유분석!$AC$2:$AC$801,1)/SUMIFS(보유분석!$BG$2:$BG$801,보유분석!$AI$2:$AI$801,$A25,보유분석!$AC$2:$AC$801,1)) -> 7.2752672 | T25: =IF(SUMIFS(보유분석!$BI$2:$BI$801,보유분석!$AI$2:$AI$801,$A25,보유분석!$AC$2:$AC$801,1)=0,"",SUMIFS(보유분석!$BD$2:$BD$801,보유분석!$AI$2:$AI$801,$A25,보유분석!$AC$2:$AC$801,1)/SUMIFS(보유분석!$BI$2:$BI$801,보유분석!$AI$2:$AI$801,$A25,보유분석!$AC$2:$AC$801,1)) -> 0.71650055
A26: 스페인 | B26: =SUMIFS(보유분석!$AA$2:$AA$801,보유분석!$AI$2:$AI$801,$A26,보유분석!$AC$2:$AC$801,1) -> 9.58941 | C26: =IF(SUMIFS(보유분석!$AA$2:$AA$801,보유분석!$AC$2:$AC$801,1)=0,0,B26/SUMIFS(보유분석!$AA$2:$AA$801,보유분석!$AC$2:$AC$801,1)) -> 0.0068039018 | D26: =SUMIFS(보유분석!$AM$2:$AM$801,보유분석!$AI$2:$AI$801,$A26,보유분석!$AC$2:$AC$801,1) -> 3713.1154 | E26: =IF(SUMIFS(보유분석!$AM$2:$AM$801,보유분석!$AC$2:$AC$801,1)=0,0,D26/SUMIFS(보유분석!$AM$2:$AM$801,보유분석!$AC$2:$AC$801,1)) -> 0.0097913726 | F26: =IF(SUMIFS(보유분석!$BB$2:$BB$801,보유분석!$AI$2:$AI$801,$A26,보유분석!$AC$2:$AC$801,1)=0,"",SUMIFS(보유분석!$BA$2:$BA$801,보유분석!$AI$2:$AI$801,$A26,보유분석!$AC$2:$AC$801,1)/SUMIFS(보유분석!$BB$2:$BB$801,보유분석!$AI$2:$AI$801,$A26,보유분석!$AC$2:$AC$801,1)) -> 5.9103 | G26: =IF(F26="","",(F26-(SUMIFS(보유분석!$BA$2:$BA$801,보유분석!$AC$2:$AC$801,1)/SUMIFS(보유분석!$BB$2:$BB$801,보유분석!$AC$2:$AC$801,1)))*100) -> 25.026418 | H26: =IF(SUMIFS(보유분석!$BD$2:$BD$801,보유분석!$AI$2:$AI$801,$A26,보유분석!$AC$2:$AC$801,1)=0,"",SUMIFS(보유분석!$BC$2:$BC$801,보유분석!$AI$2:$AI$801,$A26,보유분석!$AC$2:$AC$801,1)/SUMIFS(보유분석!$BD$2:$BD$801,보유분석!$AI$2:$AI$801,$A26,보유분석!$AC$2:$AC$801,1)) -> 85.718 | I26: =IF(SUMIFS(보유분석!$BF$2:$BF$801,보유분석!$AI$2:$AI$801,$A26,보유분석!$AC$2:$AC$801,1)=0,"",SUMIFS(보유분석!$BE$2:$BE$801,보유분석!$AI$2:$AI$801,$A26,보유분석!$AC$2:$AC$801,1)/SUMIFS(보유분석!$BF$2:$BF$801,보유분석!$AI$2:$AI$801,$A26,보유분석!$AC$2:$AC$801,1)) -> 3.8721 | J26: =IF(SUMIFS(보유분석!$BG$2:$BG$801,보유분석!$AI$2:$AI$801,$A26,보유분석!$AC$2:$AC$801,1)=0,"",(SUMIFS(보유분석!$BC$2:$BC$801,보유분석!$AI$2:$AI$801,$A26,보유분석!$AC$2:$AC$801,1)+SUMIFS(보유분석!$BH$2:$BH$801,보유분석!$AI$2:$AI$801,$A26,보유분석!$AC$2:$AC$801,1))/SUMIFS(보유분석!$BG$2:$BG$801,보유분석!$AI$2:$AI$801,$A26,보유분석!$AC$2:$AC$801,1)) -> 28.625705 | K26: =IF(B26=0,"",SUMIFS(보유분석!$AV$2:$AV$801,보유분석!$AI$2:$AI$801,$A26,보유분석!$AC$2:$AC$801,1)/(B26*1000000)) -> 0.061615359 | L26: =SUMIFS(보유분석!$AP$2:$AP$801,보유분석!$AI$2:$AI$801,$A26,보유분석!$AC$2:$AC$801,1) -> -360590 | M26: =COUNTIFS(보유분석!$AI$2:$AI$801,$A26,보유분석!$AR$2:$AR$801,"Cheap",보유분석!$AC$2:$AC$801,1) -> 0 | N26: =COUNTIFS(보유분석!$AI$2:$AI$801,$A26,보유분석!$AR$2:$AR$801,"Rich",보유분석!$AC$2:$AC$801,1) -> 0 | P26: =IF(O26="","",O26-C26) | Q26: =-SUMIFS(보유분석!$AZ$2:$AZ$801,보유분석!$AI$2:$AI$801,$A26,보유분석!$AC$2:$AC$801,1)*설정!$C$10 -> -120353.03 | R26: =IF((-SUMIFS(보유분석!$AZ$2:$AZ$801,보유분석!$AC$2:$AC$801,1)*설정!$C$10)=0,0,Q26/(-SUMIFS(보유분석!$AZ$2:$AZ$801,보유분석!$AC$2:$AC$801,1)*설정!$C$10)) -> 0.011825953 | S26: =IF(SUMIFS(보유분석!$BG$2:$BG$801,보유분석!$AI$2:$AI$801,$A26,보유분석!$AC$2:$AC$801,1)=0,"",SUMIFS(보유분석!$BH$2:$BH$801,보유분석!$AI$2:$AI$801,$A26,보유분석!$AC$2:$AC$801,1)/SUMIFS(보유분석!$BG$2:$BG$801,보유분석!$AI$2:$AI$801,$A26,보유분석!$AC$2:$AC$801,1)) -> 6.4883635 | T26: =IF(SUMIFS(보유분석!$BI$2:$BI$801,보유분석!$AI$2:$AI$801,$A26,보유분석!$AC$2:$AC$801,1)=0,"",SUMIFS(보유분석!$BD$2:$BD$801,보유분석!$AI$2:$AI$801,$A26,보유분석!$AC$2:$AC$801,1)/SUMIFS(보유분석!$BI$2:$BI$801,보유분석!$AI$2:$AI$801,$A26,보유분석!$AC$2:$AC$801,1)) -> 1
A27: 독일 | B27: =SUMIFS(보유분석!$AA$2:$AA$801,보유분석!$AI$2:$AI$801,$A27,보유분석!$AC$2:$AC$801,1) -> 0 | C27: =IF(SUMIFS(보유분석!$AA$2:$AA$801,보유분석!$AC$2:$AC$801,1)=0,0,B27/SUMIFS(보유분석!$AA$2:$AA$801,보유분석!$AC$2:$AC$801,1)) -> 0 | D27: =SUMIFS(보유분석!$AM$2:$AM$801,보유분석!$AI$2:$AI$801,$A27,보유분석!$AC$2:$AC$801,1) -> 0 | E27: =IF(SUMIFS(보유분석!$AM$2:$AM$801,보유분석!$AC$2:$AC$801,1)=0,0,D27/SUMIFS(보유분석!$AM$2:$AM$801,보유분석!$AC$2:$AC$801,1)) -> 0 | F27: =IF(SUMIFS(보유분석!$BB$2:$BB$801,보유분석!$AI$2:$AI$801,$A27,보유분석!$AC$2:$AC$801,1)=0,"",SUMIFS(보유분석!$BA$2:$BA$801,보유분석!$AI$2:$AI$801,$A27,보유분석!$AC$2:$AC$801,1)/SUMIFS(보유분석!$BB$2:$BB$801,보유분석!$AI$2:$AI$801,$A27,보유분석!$AC$2:$AC$801,1)) | G27: =IF(F27="","",(F27-(SUMIFS(보유분석!$BA$2:$BA$801,보유분석!$AC$2:$AC$801,1)/SUMIFS(보유분석!$BB$2:$BB$801,보유분석!$AC$2:$AC$801,1)))*100) | H27: =IF(SUMIFS(보유분석!$BD$2:$BD$801,보유분석!$AI$2:$AI$801,$A27,보유분석!$AC$2:$AC$801,1)=0,"",SUMIFS(보유분석!$BC$2:$BC$801,보유분석!$AI$2:$AI$801,$A27,보유분석!$AC$2:$AC$801,1)/SUMIFS(보유분석!$BD$2:$BD$801,보유분석!$AI$2:$AI$801,$A27,보유분석!$AC$2:$AC$801,1)) | I27: =IF(SUMIFS(보유분석!$BF$2:$BF$801,보유분석!$AI$2:$AI$801,$A27,보유분석!$AC$2:$AC$801,1)=0,"",SUMIFS(보유분석!$BE$2:$BE$801,보유분석!$AI$2:$AI$801,$A27,보유분석!$AC$2:$AC$801,1)/SUMIFS(보유분석!$BF$2:$BF$801,보유분석!$AI$2:$AI$801,$A27,보유분석!$AC$2:$AC$801,1)) | J27: =IF(SUMIFS(보유분석!$BG$2:$BG$801,보유분석!$AI$2:$AI$801,$A27,보유분석!$AC$2:$AC$801,1)=0,"",(SUMIFS(보유분석!$BC$2:$BC$801,보유분석!$AI$2:$AI$801,$A27,보유분석!$AC$2:$AC$801,1)+SUMIFS(보유분석!$BH$2:$BH$801,보유분석!$AI$2:$AI$801,$A27,보유분석!$AC$2:$AC$801,1))/SUMIFS(보유분석!$BG$2:$BG$801,보유분석!$AI$2:$AI$801,$A27,보유분석!$AC$2:$AC$801,1)) | K27: =IF(B27=0,"",SUMIFS(보유분석!$AV$2:$AV$801,보유분석!$AI$2:$AI$801,$A27,보유분석!$AC$2:$AC$801,1)/(B27*1000000)) | L27: =SUMIFS(보유분석!$AP$2:$AP$801,보유분석!$AI$2:$AI$801,$A27,보유분석!$AC$2:$AC$801,1) -> 0 | M27: =COUNTIFS(보유분석!$AI$2:$AI$801,$A27,보유분석!$AR$2:$AR$801,"Cheap",보유분석!$AC$2:$AC$801,1) -> 0 | N27: =COUNTIFS(보유분석!$AI$2:$AI$801,$A27,보유분석!$AR$2:$AR$801,"Rich",보유분석!$AC$2:$AC$801,1) -> 0 | P27: =IF(O27="","",O27-C27) | Q27: =-SUMIFS(보유분석!$AZ$2:$AZ$801,보유분석!$AI$2:$AI$801,$A27,보유분석!$AC$2:$AC$801,1)*설정!$C$10 -> 0 | R27: =IF((-SUMIFS(보유분석!$AZ$2:$AZ$801,보유분석!$AC$2:$AC$801,1)*설정!$C$10)=0,0,Q27/(-SUMIFS(보유분석!$AZ$2:$AZ$801,보유분석!$AC$2:$AC$801,1)*설정!$C$10)) -> 0 | S27: =IF(SUMIFS(보유분석!$BG$2:$BG$801,보유분석!$AI$2:$AI$801,$A27,보유분석!$AC$2:$AC$801,1)=0,"",SUMIFS(보유분석!$BH$2:$BH$801,보유분석!$AI$2:$AI$801,$A27,보유분석!$AC$2:$AC$801,1)/SUMIFS(보유분석!$BG$2:$BG$801,보유분석!$AI$2:$AI$801,$A27,보유분석!$AC$2:$AC$801,1)) | T27: =IF(SUMIFS(보유분석!$BI$2:$BI$801,보유분석!$AI$2:$AI$801,$A27,보유분석!$AC$2:$AC$801,1)=0,"",SUMIFS(보유분석!$BD$2:$BD$801,보유분석!$AI$2:$AI$801,$A27,보유분석!$AC$2:$AC$801,1)/SUMIFS(보유분석!$BI$2:$BI$801,보유분석!$AI$2:$AI$801,$A27,보유분석!$AC$2:$AC$801,1))
A28: 네덜란드 | B28: =SUMIFS(보유분석!$AA$2:$AA$801,보유분석!$AI$2:$AI$801,$A28,보유분석!$AC$2:$AC$801,1) -> 9.5834 | C28: =IF(SUMIFS(보유분석!$AA$2:$AA$801,보유분석!$AC$2:$AC$801,1)=0,0,B28/SUMIFS(보유분석!$AA$2:$AA$801,보유분석!$AC$2:$AC$801,1)) -> 0.0067996376 | D28: =SUMIFS(보유분석!$AM$2:$AM$801,보유분석!$AI$2:$AI$801,$A28,보유분석!$AC$2:$AC$801,1) -> 3758.6095 | E28: =IF(SUMIFS(보유분석!$AM$2:$AM$801,보유분석!$AC$2:$AC$801,1)=0,0,D28/SUMIFS(보유분석!$AM$2:$AM$801,보유분석!$AC$2:$AC$801,1)) -> 0.009911339 | F28: =IF(SUMIFS(보유분석!$BB$2:$BB$801,보유분석!$AI$2:$AI$801,$A28,보유분석!$AC$2:$AC$801,1)=0,"",SUMIFS(보유분석!$BA$2:$BA$801,보유분석!$AI$2:$AI$801,$A28,보유분석!$AC$2:$AC$801,1)/SUMIFS(보유분석!$BB$2:$BB$801,보유분석!$AI$2:$AI$801,$A28,보유분석!$AC$2:$AC$801,1)) -> 5.8188 | G28: =IF(F28="","",(F28-(SUMIFS(보유분석!$BA$2:$BA$801,보유분석!$AC$2:$AC$801,1)/SUMIFS(보유분석!$BB$2:$BB$801,보유분석!$AC$2:$AC$801,1)))*100) -> 15.876418 | H28: =IF(SUMIFS(보유분석!$BD$2:$BD$801,보유분석!$AI$2:$AI$801,$A28,보유분석!$AC$2:$AC$801,1)=0,"",SUMIFS(보유분석!$BC$2:$BC$801,보유분석!$AI$2:$AI$801,$A28,보유분석!$AC$2:$AC$801,1)/SUMIFS(보유분석!$BD$2:$BD$801,보유분석!$AI$2:$AI$801,$A28,보유분석!$AC$2:$AC$801,1)) -> 83.476 | I28: =IF(SUMIFS(보유분석!$BF$2:$BF$801,보유분석!$AI$2:$AI$801,$A28,보유분석!$AC$2:$AC$801,1)=0,"",SUMIFS(보유분석!$BE$2:$BE$801,보유분석!$AI$2:$AI$801,$A28,보유분석!$AC$2:$AC$801,1)/SUMIFS(보유분석!$BF$2:$BF$801,보유분석!$AI$2:$AI$801,$A28,보유분석!$AC$2:$AC$801,1)) -> 3.922 | J28: =IF(SUMIFS(보유분석!$BG$2:$BG$801,보유분석!$AI$2:$AI$801,$A28,보유분석!$AC$2:$AC$801,1)=0,"",(SUMIFS(보유분석!$BC$2:$BC$801,보유분석!$AI$2:$AI$801,$A28,보유분석!$AC$2:$AC$801,1)+SUMIFS(보유분석!$BH$2:$BH$801,보유분석!$AI$2:$AI$801,$A28,보유분석!$AC$2:$AC$801,1))/SUMIFS(보유분석!$BG$2:$BG$801,보유분석!$AI$2:$AI$801,$A28,보유분석!$AC$2:$AC$801,1)) -> 27.719606 | K28: =IF(B28=0,"",SUMIFS(보유분석!$AV$2:$AV$801,보유분석!$AI$2:$AI$801,$A28,보유분석!$AC$2:$AC$801,1)/(B28*1000000)) -> 0.060712029 | L28: =SUMIFS(보유분석!$AP$2:$AP$801,보유분석!$AI$2:$AI$801,$A28,보유분석!$AC$2:$AC$801,1) -> -373100 | M28: =COUNTIFS(보유분석!$AI$2:$AI$801,$A28,보유분석!$AR$2:$AR$801,"Cheap",보유분석!$AC$2:$AC$801,1) -> 0 | N28: =COUNTIFS(보유분석!$AI$2:$AI$801,$A28,보유분석!$AR$2:$AR$801,"Rich",보유분석!$AC$2:$AC$801,1) -> 0 | P28: =IF(O28="","",O28-C28) | Q28: =-SUMIFS(보유분석!$AZ$2:$AZ$801,보유분석!$AI$2:$AI$801,$A28,보유분석!$AC$2:$AC$801,1)*설정!$C$10 -> -118641.16 | R28: =IF((-SUMIFS(보유분석!$AZ$2:$AZ$801,보유분석!$AC$2:$AC$801,1)*설정!$C$10)=0,0,Q28/(-SUMIFS(보유분석!$AZ$2:$AZ$801,보유분석!$AC$2:$AC$801,1)*설정!$C$10)) -> 0.011657744 | S28: =IF(SUMIFS(보유분석!$BG$2:$BG$801,보유분석!$AI$2:$AI$801,$A28,보유분석!$AC$2:$AC$801,1)=0,"",SUMIFS(보유분석!$BH$2:$BH$801,보유분석!$AI$2:$AI$801,$A28,보유분석!$AC$2:$AC$801,1)/SUMIFS(보유분석!$BG$2:$BG$801,보유분석!$AI$2:$AI$801,$A28,보유분석!$AC$2:$AC$801,1)) -> 6.4355673 | T28: =IF(SUMIFS(보유분석!$BI$2:$BI$801,보유분석!$AI$2:$AI$801,$A28,보유분석!$AC$2:$AC$801,1)=0,"",SUMIFS(보유분석!$BD$2:$BD$801,보유분석!$AI$2:$AI$801,$A28,보유분석!$AC$2:$AC$801,1)/SUMIFS(보유분석!$BI$2:$BI$801,보유분석!$AI$2:$AI$801,$A28,보유분석!$AC$2:$AC$801,1)) -> 1
A29: 스위스 | B29: =SUMIFS(보유분석!$AA$2:$AA$801,보유분석!$AI$2:$AI$801,$A29,보유분석!$AC$2:$AC$801,1) -> 15.813569 | C29: =IF(SUMIFS(보유분석!$AA$2:$AA$801,보유분석!$AC$2:$AC$801,1)=0,0,B29/SUMIFS(보유분석!$AA$2:$AA$801,보유분석!$AC$2:$AC$801,1)) -> 0.011220082 | D29: =SUMIFS(보유분석!$AM$2:$AM$801,보유분석!$AI$2:$AI$801,$A29,보유분석!$AC$2:$AC$801,1) -> 4258.2542 | E29: =IF(SUMIFS(보유분석!$AM$2:$AM$801,보유분석!$AC$2:$AC$801,1)=0,0,D29/SUMIFS(보유분석!$AM$2:$AM$801,보유분석!$AC$2:$AC$801,1)) -> 0.011228887 | F29: =IF(SUMIFS(보유분석!$BB$2:$BB$801,보유분석!$AI$2:$AI$801,$A29,보유분석!$AC$2:$AC$801,1)=0,"",SUMIFS(보유분석!$BA$2:$BA$801,보유분석!$AI$2:$AI$801,$A29,보유분석!$AC$2:$AC$801,1)/SUMIFS(보유분석!$BB$2:$BB$801,보유분석!$AI$2:$AI$801,$A29,보유분석!$AC$2:$AC$801,1)) -> 5.6576882 | G29: =IF(F29="","",(F29-(SUMIFS(보유분석!$BA$2:$BA$801,보유분석!$AC$2:$AC$801,1)/SUMIFS(보유분석!$BB$2:$BB$801,보유분석!$AC$2:$AC$801,1)))*100) -> -0.23476681 | H29: =IF(SUMIFS(보유분석!$BD$2:$BD$801,보유분석!$AI$2:$AI$801,$A29,보유분석!$AC$2:$AC$801,1)=0,"",SUMIFS(보유분석!$BC$2:$BC$801,보유분석!$AI$2:$AI$801,$A29,보유분석!$AC$2:$AC$801,1)/SUMIFS(보유분석!$BD$2:$BD$801,보유분석!$AI$2:$AI$801,$A29,보유분석!$AC$2:$AC$801,1)) -> 65.695272 | I29: =IF(SUMIFS(보유분석!$BF$2:$BF$801,보유분석!$AI$2:$AI$801,$A29,보유분석!$AC$2:$AC$801,1)=0,"",SUMIFS(보유분석!$BE$2:$BE$801,보유분석!$AI$2:$AI$801,$A29,보유분석!$AC$2:$AC$801,1)/SUMIFS(보유분석!$BF$2:$BF$801,보유분석!$AI$2:$AI$801,$A29,보유분석!$AC$2:$AC$801,1)) -> 2.692785 | J29: =IF(SUMIFS(보유분석!$BG$2:$BG$801,보유분석!$AI$2:$AI$801,$A29,보유분석!$AC$2:$AC$801,1)=0,"",(SUMIFS(보유분석!$BC$2:$BC$801,보유분석!$AI$2:$AI$801,$A29,보유분석!$AC$2:$AC$801,1)+SUMIFS(보유분석!$BH$2:$BH$801,보유분석!$AI$2:$AI$801,$A29,보유분석!$AC$2:$AC$801,1))/SUMIFS(보유분석!$BG$2:$BG$801,보유분석!$AI$2:$AI$801,$A29,보유분석!$AC$2:$AC$801,1)) -> 37.537895 | K29: =IF(B29=0,"",SUMIFS(보유분석!$AV$2:$AV$801,보유분석!$AI$2:$AI$801,$A29,보유분석!$AC$2:$AC$801,1)/(B29*1000000)) -> 0.058037616 | L29: =SUMIFS(보유분석!$AP$2:$AP$801,보유분석!$AI$2:$AI$801,$A29,보유분석!$AC$2:$AC$801,1) -> -523161 | M29: =COUNTIFS(보유분석!$AI$2:$AI$801,$A29,보유분석!$AR$2:$AR$801,"Cheap",보유분석!$AC$2:$AC$801,1) -> 0 | N29: =COUNTIFS(보유분석!$AI$2:$AI$801,$A29,보유분석!$AR$2:$AR$801,"Rich",보유분석!$AC$2:$AC$801,1) -> 0 | P29: =IF(O29="","",O29-C29) | Q29: =-SUMIFS(보유분석!$AZ$2:$AZ$801,보유분석!$AI$2:$AI$801,$A29,보유분석!$AC$2:$AC$801,1)*설정!$C$10 -> -107688.24 | R29: =IF((-SUMIFS(보유분석!$AZ$2:$AZ$801,보유분석!$AC$2:$AC$801,1)*설정!$C$10)=0,0,Q29/(-SUMIFS(보유분석!$AZ$2:$AZ$801,보유분석!$AC$2:$AC$801,1)*설정!$C$10)) -> 0.010581505 | S29: =IF(SUMIFS(보유분석!$BG$2:$BG$801,보유분석!$AI$2:$AI$801,$A29,보유분석!$AC$2:$AC$801,1)=0,"",SUMIFS(보유분석!$BH$2:$BH$801,보유분석!$AI$2:$AI$801,$A29,보유분석!$AC$2:$AC$801,1)/SUMIFS(보유분석!$BG$2:$BG$801,보유분석!$AI$2:$AI$801,$A29,보유분석!$AC$2:$AC$801,1)) -> 9.1512521 | T29: =IF(SUMIFS(보유분석!$BI$2:$BI$801,보유분석!$AI$2:$AI$801,$A29,보유분석!$AC$2:$AC$801,1)=0,"",SUMIFS(보유분석!$BD$2:$BD$801,보유분석!$AI$2:$AI$801,$A29,보유분석!$AC$2:$AC$801,1)/SUMIFS(보유분석!$BI$2:$BI$801,보유분석!$AI$2:$AI$801,$A29,보유분석!$AC$2:$AC$801,1)) -> 0.68971679
A30: 캐나다 | B30: =SUMIFS(보유분석!$AA$2:$AA$801,보유분석!$AI$2:$AI$801,$A30,보유분석!$AC$2:$AC$801,1) -> 24.4945 | C30: =IF(SUMIFS(보유분석!$AA$2:$AA$801,보유분석!$AC$2:$AC$801,1)=0,0,B30/SUMIFS(보유분석!$AA$2:$AA$801,보유분석!$AC$2:$AC$801,1)) -> 0.017379398 | D30: =SUMIFS(보유분석!$AM$2:$AM$801,보유분석!$AI$2:$AI$801,$A30,보유분석!$AC$2:$AC$801,1) -> 6607.6363 | E30: =IF(SUMIFS(보유분석!$AM$2:$AM$801,보유분석!$AC$2:$AC$801,1)=0,0,D30/SUMIFS(보유분석!$AM$2:$AM$801,보유분석!$AC$2:$AC$801,1)) -> 0.017424136 | F30: =IF(SUMIFS(보유분석!$BB$2:$BB$801,보유분석!$AI$2:$AI$801,$A30,보유분석!$AC$2:$AC$801,1)=0,"",SUMIFS(보유분석!$BA$2:$BA$801,보유분석!$AI$2:$AI$801,$A30,보유분석!$AC$2:$AC$801,1)/SUMIFS(보유분석!$BB$2:$BB$801,보유분석!$AI$2:$AI$801,$A30,보유분석!$AC$2:$AC$801,1)) -> 5.7549 | G30: =IF(F30="","",(F30-(SUMIFS(보유분석!$BA$2:$BA$801,보유분석!$AC$2:$AC$801,1)/SUMIFS(보유분석!$BB$2:$BB$801,보유분석!$AC$2:$AC$801,1)))*100) -> 9.4864175 | H30: =IF(SUMIFS(보유분석!$BD$2:$BD$801,보유분석!$AI$2:$AI$801,$A30,보유분석!$AC$2:$AC$801,1)=0,"",SUMIFS(보유분석!$BC$2:$BC$801,보유분석!$AI$2:$AI$801,$A30,보유분석!$AC$2:$AC$801,1)/SUMIFS(보유분석!$BD$2:$BD$801,보유분석!$AI$2:$AI$801,$A30,보유분석!$AC$2:$AC$801,1)) -> 53.762 | I30: =IF(SUMIFS(보유분석!$BF$2:$BF$801,보유분석!$AI$2:$AI$801,$A30,보유분석!$AC$2:$AC$801,1)=0,"",SUMIFS(보유분석!$BE$2:$BE$801,보유분석!$AI$2:$AI$801,$A30,보유분석!$AC$2:$AC$801,1)/SUMIFS(보유분석!$BF$2:$BF$801,보유분석!$AI$2:$AI$801,$A30,보유분석!$AC$2:$AC$801,1)) -> 2.6976 | J30: =IF(SUMIFS(보유분석!$BG$2:$BG$801,보유분석!$AI$2:$AI$801,$A30,보유분석!$AC$2:$AC$801,1)=0,"",(SUMIFS(보유분석!$BC$2:$BC$801,보유분석!$AI$2:$AI$801,$A30,보유분석!$AC$2:$AC$801,1)+SUMIFS(보유분석!$BH$2:$BH$801,보유분석!$AI$2:$AI$801,$A30,보유분석!$AC$2:$AC$801,1))/SUMIFS(보유분석!$BG$2:$BG$801,보유분석!$AI$2:$AI$801,$A30,보유분석!$AC$2:$AC$801,1)) -> 25.978185 | K30: =IF(B30=0,"",SUMIFS(보유분석!$AV$2:$AV$801,보유분석!$AI$2:$AI$801,$A30,보유분석!$AC$2:$AC$801,1)/(B30*1000000)) -> 0.059180675 | L30: =SUMIFS(보유분석!$AP$2:$AP$801,보유분석!$AI$2:$AI$801,$A30,보유분석!$AC$2:$AC$801,1) -> -718000 | M30: =COUNTIFS(보유분석!$AI$2:$AI$801,$A30,보유분석!$AR$2:$AR$801,"Cheap",보유분석!$AC$2:$AC$801,1) -> 0 | N30: =COUNTIFS(보유분석!$AI$2:$AI$801,$A30,보유분석!$AR$2:$AR$801,"Rich",보유분석!$AC$2:$AC$801,1) -> 0 | P30: =IF(O30="","",O30-C30) | Q30: =-SUMIFS(보유분석!$AZ$2:$AZ$801,보유분석!$AI$2:$AI$801,$A30,보유분석!$AC$2:$AC$801,1)*설정!$C$10 -> -134328.47 | R30: =IF((-SUMIFS(보유분석!$AZ$2:$AZ$801,보유분석!$AC$2:$AC$801,1)*설정!$C$10)=0,0,Q30/(-SUMIFS(보유분석!$AZ$2:$AZ$801,보유분석!$AC$2:$AC$801,1)*설정!$C$10)) -> 0.013199188 | S30: =IF(SUMIFS(보유분석!$BG$2:$BG$801,보유분석!$AI$2:$AI$801,$A30,보유분석!$AC$2:$AC$801,1)=0,"",SUMIFS(보유분석!$BH$2:$BH$801,보유분석!$AI$2:$AI$801,$A30,보유분석!$AC$2:$AC$801,1)/SUMIFS(보유분석!$BG$2:$BG$801,보유분석!$AI$2:$AI$801,$A30,보유분석!$AC$2:$AC$801,1)) -> 6.0486183 | T30: =IF(SUMIFS(보유분석!$BI$2:$BI$801,보유분석!$AI$2:$AI$801,$A30,보유분석!$AC$2:$AC$801,1)=0,"",SUMIFS(보유분석!$BD$2:$BD$801,보유분석!$AI$2:$AI$801,$A30,보유분석!$AC$2:$AC$801,1)/SUMIFS(보유분석!$BI$2:$BI$801,보유분석!$AI$2:$AI$801,$A30,보유분석!$AC$2:$AC$801,1)) -> 1
A31: 뉴질랜드 | B31: =SUMIFS(보유분석!$AA$2:$AA$801,보유분석!$AI$2:$AI$801,$A31,보유분석!$AC$2:$AC$801,1) -> 0 | C31: =IF(SUMIFS(보유분석!$AA$2:$AA$801,보유분석!$AC$2:$AC$801,1)=0,0,B31/SUMIFS(보유분석!$AA$2:$AA$801,보유분석!$AC$2:$AC$801,1)) -> 0 | D31: =SUMIFS(보유분석!$AM$2:$AM$801,보유분석!$AI$2:$AI$801,$A31,보유분석!$AC$2:$AC$801,1) -> 0 | E31: =IF(SUMIFS(보유분석!$AM$2:$AM$801,보유분석!$AC$2:$AC$801,1)=0,0,D31/SUMIFS(보유분석!$AM$2:$AM$801,보유분석!$AC$2:$AC$801,1)) -> 0 | F31: =IF(SUMIFS(보유분석!$BB$2:$BB$801,보유분석!$AI$2:$AI$801,$A31,보유분석!$AC$2:$AC$801,1)=0,"",SUMIFS(보유분석!$BA$2:$BA$801,보유분석!$AI$2:$AI$801,$A31,보유분석!$AC$2:$AC$801,1)/SUMIFS(보유분석!$BB$2:$BB$801,보유분석!$AI$2:$AI$801,$A31,보유분석!$AC$2:$AC$801,1)) | G31: =IF(F31="","",(F31-(SUMIFS(보유분석!$BA$2:$BA$801,보유분석!$AC$2:$AC$801,1)/SUMIFS(보유분석!$BB$2:$BB$801,보유분석!$AC$2:$AC$801,1)))*100) | H31: =IF(SUMIFS(보유분석!$BD$2:$BD$801,보유분석!$AI$2:$AI$801,$A31,보유분석!$AC$2:$AC$801,1)=0,"",SUMIFS(보유분석!$BC$2:$BC$801,보유분석!$AI$2:$AI$801,$A31,보유분석!$AC$2:$AC$801,1)/SUMIFS(보유분석!$BD$2:$BD$801,보유분석!$AI$2:$AI$801,$A31,보유분석!$AC$2:$AC$801,1)) | I31: =IF(SUMIFS(보유분석!$BF$2:$BF$801,보유분석!$AI$2:$AI$801,$A31,보유분석!$AC$2:$AC$801,1)=0,"",SUMIFS(보유분석!$BE$2:$BE$801,보유분석!$AI$2:$AI$801,$A31,보유분석!$AC$2:$AC$801,1)/SUMIFS(보유분석!$BF$2:$BF$801,보유분석!$AI$2:$AI$801,$A31,보유분석!$AC$2:$AC$801,1)) | J31: =IF(SUMIFS(보유분석!$BG$2:$BG$801,보유분석!$AI$2:$AI$801,$A31,보유분석!$AC$2:$AC$801,1)=0,"",(SUMIFS(보유분석!$BC$2:$BC$801,보유분석!$AI$2:$AI$801,$A31,보유분석!$AC$2:$AC$801,1)+SUMIFS(보유분석!$BH$2:$BH$801,보유분석!$AI$2:$AI$801,$A31,보유분석!$AC$2:$AC$801,1))/SUMIFS(보유분석!$BG$2:$BG$801,보유분석!$AI$2:$AI$801,$A31,보유분석!$AC$2:$AC$801,1)) | K31: =IF(B31=0,"",SUMIFS(보유분석!$AV$2:$AV$801,보유분석!$AI$2:$AI$801,$A31,보유분석!$AC$2:$AC$801,1)/(B31*1000000)) | L31: =SUMIFS(보유분석!$AP$2:$AP$801,보유분석!$AI$2:$AI$801,$A31,보유분석!$AC$2:$AC$801,1) -> 0 | M31: =COUNTIFS(보유분석!$AI$2:$AI$801,$A31,보유분석!$AR$2:$AR$801,"Cheap",보유분석!$AC$2:$AC$801,1) -> 0 | N31: =COUNTIFS(보유분석!$AI$2:$AI$801,$A31,보유분석!$AR$2:$AR$801,"Rich",보유분석!$AC$2:$AC$801,1) -> 0 | P31: =IF(O31="","",O31-C31) | Q31: =-SUMIFS(보유분석!$AZ$2:$AZ$801,보유분석!$AI$2:$AI$801,$A31,보유분석!$AC$2:$AC$801,1)*설정!$C$10 -> 0 | R31: =IF((-SUMIFS(보유분석!$AZ$2:$AZ$801,보유분석!$AC$2:$AC$801,1)*설정!$C$10)=0,0,Q31/(-SUMIFS(보유분석!$AZ$2:$AZ$801,보유분석!$AC$2:$AC$801,1)*설정!$C$10)) -> 0 | S31: =IF(SUMIFS(보유분석!$BG$2:$BG$801,보유분석!$AI$2:$AI$801,$A31,보유분석!$AC$2:$AC$801,1)=0,"",SUMIFS(보유분석!$BH$2:$BH$801,보유분석!$AI$2:$AI$801,$A31,보유분석!$AC$2:$AC$801,1)/SUMIFS(보유분석!$BG$2:$BG$801,보유분석!$AI$2:$AI$801,$A31,보유분석!$AC$2:$AC$801,1)) | T31: =IF(SUMIFS(보유분석!$BI$2:$BI$801,보유분석!$AI$2:$AI$801,$A31,보유분석!$AC$2:$AC$801,1)=0,"",SUMIFS(보유분석!$BD$2:$BD$801,보유분석!$AI$2:$AI$801,$A31,보유분석!$AC$2:$AC$801,1)/SUMIFS(보유분석!$BI$2:$BI$801,보유분석!$AI$2:$AI$801,$A31,보유분석!$AC$2:$AC$801,1))
A32: 기타(목록외) | B32: =SUMPRODUCT(ISNA(MATCH(보유분석!$AI$2:$AI$801,$A$21:$A$31,0))*(보유분석!$AC$2:$AC$801=1)*보유분석!$AA$2:$AA$801) -> 0 | C32: =IF(SUMIFS(보유분석!$AA$2:$AA$801,보유분석!$AC$2:$AC$801,1)=0,0,B32/SUMIFS(보유분석!$AA$2:$AA$801,보유분석!$AC$2:$AC$801,1)) -> 0 | D32: =SUMPRODUCT(ISNA(MATCH(보유분석!$AI$2:$AI$801,$A$21:$A$31,0))*(보유분석!$AC$2:$AC$801=1)*보유분석!$AM$2:$AM$801) -> 0 | E32: =IF(SUMIFS(보유분석!$AM$2:$AM$801,보유분석!$AC$2:$AC$801,1)=0,0,D32/SUMIFS(보유분석!$AM$2:$AM$801,보유분석!$AC$2:$AC$801,1)) -> 0 | F32: =IF(SUMPRODUCT(ISNA(MATCH(보유분석!$AI$2:$AI$801,$A$21:$A$31,0))*(보유분석!$AC$2:$AC$801=1)*보유분석!$BB$2:$BB$801)=0,"",SUMPRODUCT(ISNA(MATCH(보유분석!$AI$2:$AI$801,$A$21:$A$31,0))*(보유분석!$AC$2:$AC$801=1)*보유분석!$BA$2:$BA$801)/SUMPRODUCT(ISNA(MATCH(보유분석!$AI$2:$AI$801,$A$21:$A$31,0))*(보유분석!$AC$2:$AC$801=1)*보유분석!$BB$2:$BB$801)) | G32: =IF(F32="","",(F32-(SUMIFS(보유분석!$BA$2:$BA$801,보유분석!$AC$2:$AC$801,1)/SUMIFS(보유분석!$BB$2:$BB$801,보유분석!$AC$2:$AC$801,1)))*100) | H32: =IF(SUMPRODUCT(ISNA(MATCH(보유분석!$AI$2:$AI$801,$A$21:$A$31,0))*(보유분석!$AC$2:$AC$801=1)*보유분석!$BD$2:$BD$801)=0,"",SUMPRODUCT(ISNA(MATCH(보유분석!$AI$2:$AI$801,$A$21:$A$31,0))*(보유분석!$AC$2:$AC$801=1)*보유분석!$BC$2:$BC$801)/SUMPRODUCT(ISNA(MATCH(보유분석!$AI$2:$AI$801,$A$21:$A$31,0))*(보유분석!$AC$2:$AC$801=1)*보유분석!$BD$2:$BD$801)) | I32: =IF(SUMPRODUCT(ISNA(MATCH(보유분석!$AI$2:$AI$801,$A$21:$A$31,0))*(보유분석!$AC$2:$AC$801=1)*보유분석!$BF$2:$BF$801)=0,"",SUMPRODUCT(ISNA(MATCH(보유분석!$AI$2:$AI$801,$A$21:$A$31,0))*(보유분석!$AC$2:$AC$801=1)*보유분석!$BE$2:$BE$801)/SUMPRODUCT(ISNA(MATCH(보유분석!$AI$2:$AI$801,$A$21:$A$31,0))*(보유분석!$AC$2:$AC$801=1)*보유분석!$BF$2:$BF$801)) | J32: =IF(SUMPRODUCT(ISNA(MATCH(보유분석!$AI$2:$AI$801,$A$21:$A$31,0))*(보유분석!$AC$2:$AC$801=1)*보유분석!$BG$2:$BG$801)=0,"",(SUMPRODUCT(ISNA(MATCH(보유분석!$AI$2:$AI$801,$A$21:$A$31,0))*(보유분석!$AC$2:$AC$801=1)*보유분석!$BC$2:$BC$801)+SUMPRODUCT(ISNA(MATCH(보유분석!$AI$2:$AI$801,$A$21:$A$31,0))*(보유분석!$AC$2:$AC$801=1)*보유분석!$BH$2:$BH$801))/SUMPRODUCT(ISNA(MATCH(보유분석!$AI$2:$AI$801,$A$21:$A$31,0))*(보유분석!$AC$2:$AC$801=1)*보유분석!$BG$2:$BG$801)) | K32: =IF(B32=0,"",SUMPRODUCT(ISNA(MATCH(보유분석!$AI$2:$AI$801,$A$21:$A$31,0))*(보유분석!$AC$2:$AC$801=1)*보유분석!$AV$2:$AV$801)/(B32*1000000)) | L32: =SUMPRODUCT(ISNA(MATCH(보유분석!$AI$2:$AI$801,$A$21:$A$31,0))*(보유분석!$AC$2:$AC$801=1)*보유분석!$AP$2:$AP$801) -> 0 | M32: =SUMPRODUCT(ISNA(MATCH(보유분석!$AI$2:$AI$801,$A$21:$A$31,0))*(보유분석!$AC$2:$AC$801=1)*(보유분석!$AR$2:$AR$801="Cheap")) -> 0 | N32: =SUMPRODUCT(ISNA(MATCH(보유분석!$AI$2:$AI$801,$A$21:$A$31,0))*(보유분석!$AC$2:$AC$801=1)*(보유분석!$AR$2:$AR$801="Rich")) -> 0 | P32: =IF(O32="","",O32-C32) | Q32: =-SUMPRODUCT(ISNA(MATCH(보유분석!$AI$2:$AI$801,$A$21:$A$31,0))*(보유분석!$AC$2:$AC$801=1)*보유분석!$AZ$2:$AZ$801)*설정!$C$10 -> 0 | R32: =IF((-SUMIFS(보유분석!$AZ$2:$AZ$801,보유분석!$AC$2:$AC$801,1)*설정!$C$10)=0,0,Q32/(-SUMIFS(보유분석!$AZ$2:$AZ$801,보유분석!$AC$2:$AC$801,1)*설정!$C$10)) -> 0 | S32: =IF(SUMPRODUCT(ISNA(MATCH(보유분석!$AI$2:$AI$801,$A$21:$A$31,0))*(보유분석!$AC$2:$AC$801=1)*보유분석!$BG$2:$BG$801)=0,"",SUMPRODUCT(ISNA(MATCH(보유분석!$AI$2:$AI$801,$A$21:$A$31,0))*(보유분석!$AC$2:$AC$801=1)*보유분석!$BH$2:$BH$801)/SUMPRODUCT(ISNA(MATCH(보유분석!$AI$2:$AI$801,$A$21:$A$31,0))*(보유분석!$AC$2:$AC$801=1)*보유분석!$BG$2:$BG$801)) | T32: =IF(SUMPRODUCT(ISNA(MATCH(보유분석!$AI$2:$AI$801,$A$21:$A$31,0))*(보유분석!$AC$2:$AC$801=1)*보유분석!$BI$2:$BI$801)=0,"",SUMPRODUCT(ISNA(MATCH(보유분석!$AI$2:$AI$801,$A$21:$A$31,0))*(보유분석!$AC$2:$AC$801=1)*보유분석!$BD$2:$BD$801)/SUMPRODUCT(ISNA(MATCH(보유분석!$AI$2:$AI$801,$A$21:$A$31,0))*(보유분석!$AC$2:$AC$801=1)*보유분석!$BI$2:$BI$801))
A33: 합계 | B33: =SUM(B21:B32) -> 1409.3986 | C33: =SUM(C21:C32) -> 1 | D33: =SUM(D21:D32) -> 379223.18 | E33: =SUM(E21:E32) -> 1 | F33: =IF(SUMIFS(보유분석!$BB$2:$BB$801,보유분석!$AC$2:$AC$801,1)=0,"",SUMIFS(보유분석!$BA$2:$BA$801,보유분석!$AC$2:$AC$801,1)/SUMIFS(보유분석!$BB$2:$BB$801,보유분석!$AC$2:$AC$801,1)) -> 5.6600358 | H33: =IF(SUMIFS(보유분석!$BD$2:$BD$801,보유분석!$AC$2:$AC$801,1)=0,"",SUMIFS(보유분석!$BC$2:$BC$801,보유분석!$AC$2:$AC$801,1)/SUMIFS(보유분석!$BD$2:$BD$801,보유분석!$AC$2:$AC$801,1)) -> 66.114006 | I33: =IF(SUMIFS(보유분석!$BF$2:$BF$801,보유분석!$AC$2:$AC$801,1)=0,"",SUMIFS(보유분석!$BE$2:$BE$801,보유분석!$AC$2:$AC$801,1)/SUMIFS(보유분석!$BF$2:$BF$801,보유분석!$AC$2:$AC$801,1)) -> 2.6906736 | J33: =IF(SUMIFS(보유분석!$BG$2:$BG$801,보유분석!$AC$2:$AC$801,1)=0,"",(SUMIFS(보유분석!$BC$2:$BC$801,보유분석!$AC$2:$AC$801,1)+SUMIFS(보유분석!$BH$2:$BH$801,보유분석!$AC$2:$AC$801,1))/SUMIFS(보유분석!$BG$2:$BG$801,보유분석!$AC$2:$AC$801,1)) -> 31.468574 | K33: =IF(B33=0,"",SUMIFS(보유분석!$AV$2:$AV$801,보유분석!$AC$2:$AC$801,1)/(B33*1000000)) -> 0.058254622 | L33: =SUM(L21:L32) -> -44901234 | O33: =IF(COUNT(O21:O32)=0,"",SUM(O21:O32)) | Q33: =SUM(Q21:Q32) -> -10177025 | R33: =SUM(R21:R32) -> 1 | S33: =IF(SUMIFS(보유분석!$BG$2:$BG$801,보유분석!$AC$2:$AC$801,1)=0,"",SUMIFS(보유분석!$BH$2:$BH$801,보유분석!$AC$2:$AC$801,1)/SUMIFS(보유분석!$BG$2:$BG$801,보유분석!$AC$2:$AC$801,1)) -> 6.4728238 | T33: =IF(SUMIFS(보유분석!$BI$2:$BI$801,보유분석!$AC$2:$AC$801,1)=0,"",SUMIFS(보유분석!$BD$2:$BD$801,보유분석!$AC$2:$AC$801,1)/SUMIFS(보유분석!$BI$2:$BI$801,보유분석!$AC$2:$AC$801,1)) -> 0.97796717
A36: ■ 지역
A37: 구분 | B37: 평가금액($M) | C37: 비중 | D37: DV01($/bp) | E37: DV01비중 | F37: 가중YTM(%) | G37: 포트대비(bp) | H37: 가중G-spread(bp) | I37: 가중듀레이션 | J37: 손익분기 확대폭(bp) 스프레드+롤다운 | K37: 1Y기대수익률(%) | L37: 평가손익($) | M37: Cheap 보유수 | N37: Rich 보유수 | O37: 목표비중(입력) | P37: 갭(목표-현재) | Q37: 스프레드쇼크 손실($) | R37: 손실비중 | S37: └ 롤다운 기여(bp) | T37: G-spread 커버리지
A38: 미국 | B38: =SUMIFS(보유분석!$AA$2:$AA$801,보유분석!$AH$2:$AH$801,$A38,보유분석!$AC$2:$AC$801,1) -> 346.2105 | C38: =IF(SUMIFS(보유분석!$AA$2:$AA$801,보유분석!$AC$2:$AC$801,1)=0,0,B38/SUMIFS(보유분석!$AA$2:$AA$801,보유분석!$AC$2:$AC$801,1)) -> 0.24564412 | D38: =SUMIFS(보유분석!$AM$2:$AM$801,보유분석!$AH$2:$AH$801,$A38,보유분석!$AC$2:$AC$801,1) -> 103156.98 | E38: =IF(SUMIFS(보유분석!$AM$2:$AM$801,보유분석!$AC$2:$AC$801,1)=0,0,D38/SUMIFS(보유분석!$AM$2:$AM$801,보유분석!$AC$2:$AC$801,1)) -> 0.27202182 | F38: =IF(SUMIFS(보유분석!$BB$2:$BB$801,보유분석!$AH$2:$AH$801,$A38,보유분석!$AC$2:$AC$801,1)=0,"",SUMIFS(보유분석!$BA$2:$BA$801,보유분석!$AH$2:$AH$801,$A38,보유분석!$AC$2:$AC$801,1)/SUMIFS(보유분석!$BB$2:$BB$801,보유분석!$AH$2:$AH$801,$A38,보유분석!$AC$2:$AC$801,1)) -> 5.6446276 | G38: =IF(F38="","",(F38-(SUMIFS(보유분석!$BA$2:$BA$801,보유분석!$AC$2:$AC$801,1)/SUMIFS(보유분석!$BB$2:$BB$801,보유분석!$AC$2:$AC$801,1)))*100) -> -1.54082 | H38: =IF(SUMIFS(보유분석!$BD$2:$BD$801,보유분석!$AH$2:$AH$801,$A38,보유분석!$AC$2:$AC$801,1)=0,"",SUMIFS(보유분석!$BC$2:$BC$801,보유분석!$AH$2:$AH$801,$A38,보유분석!$AC$2:$AC$801,1)/SUMIFS(보유분석!$BD$2:$BD$801,보유분석!$AH$2:$AH$801,$A38,보유분석!$AC$2:$AC$801,1)) -> 66.580415 | I38: =IF(SUMIFS(보유분석!$BF$2:$BF$801,보유분석!$AH$2:$AH$801,$A38,보유분석!$AC$2:$AC$801,1)=0,"",SUMIFS(보유분석!$BE$2:$BE$801,보유분석!$AH$2:$AH$801,$A38,보유분석!$AC$2:$AC$801,1)/SUMIFS(보유분석!$BF$2:$BF$801,보유분석!$AH$2:$AH$801,$A38,보유분석!$AC$2:$AC$801,1)) -> 2.9796029 | J38: =IF(SUMIFS(보유분석!$BG$2:$BG$801,보유분석!$AH$2:$AH$801,$A38,보유분석!$AC$2:$AC$801,1)=0,"",(SUMIFS(보유분석!$BC$2:$BC$801,보유분석!$AH$2:$AH$801,$A38,보유분석!$AC$2:$AC$801,1)+SUMIFS(보유분석!$BH$2:$BH$801,보유분석!$AH$2:$AH$801,$A38,보유분석!$AC$2:$AC$801,1))/SUMIFS(보유분석!$BG$2:$BG$801,보유분석!$AH$2:$AH$801,$A38,보유분석!$AC$2:$AC$801,1)) -> 31.844347 | K38: =IF(B38=0,"",SUMIFS(보유분석!$AV$2:$AV$801,보유분석!$AH$2:$AH$801,$A38,보유분석!$AC$2:$AC$801,1)/(B38*1000000)) -> 0.058315274 | L38: =SUMIFS(보유분석!$AP$2:$AP$801,보유분석!$AH$2:$AH$801,$A38,보유분석!$AC$2:$AC$801,1) -> -12389374 | M38: =COUNTIFS(보유분석!$AH$2:$AH$801,$A38,보유분석!$AR$2:$AR$801,"Cheap",보유분석!$AC$2:$AC$801,1) -> 9 | N38: =COUNTIFS(보유분석!$AH$2:$AH$801,$A38,보유분석!$AR$2:$AR$801,"Rich",보유분석!$AC$2:$AC$801,1) -> 3 | P38: =IF(O38="","",O38-C38) | Q38: =-SUMIFS(보유분석!$AZ$2:$AZ$801,보유분석!$AH$2:$AH$801,$A38,보유분석!$AC$2:$AC$801,1)*설정!$C$10 -> -2496353.9 | R38: =IF((-SUMIFS(보유분석!$AZ$2:$AZ$801,보유분석!$AC$2:$AC$801,1)*설정!$C$10)=0,0,Q38/(-SUMIFS(보유분석!$AZ$2:$AZ$801,보유분석!$AC$2:$AC$801,1)*설정!$C$10)) -> 0.24529308 | S38: =IF(SUMIFS(보유분석!$BG$2:$BG$801,보유분석!$AH$2:$AH$801,$A38,보유분석!$AC$2:$AC$801,1)=0,"",SUMIFS(보유분석!$BH$2:$BH$801,보유분석!$AH$2:$AH$801,$A38,보유분석!$AC$2:$AC$801,1)/SUMIFS(보유분석!$BG$2:$BG$801,보유분석!$AH$2:$AH$801,$A38,보유분석!$AC$2:$AC$801,1)) -> 7.5305611 | T38: =IF(SUMIFS(보유분석!$BI$2:$BI$801,보유분석!$AH$2:$AH$801,$A38,보유분석!$AC$2:$AC$801,1)=0,"",SUMIFS(보유분석!$BD$2:$BD$801,보유분석!$AH$2:$AH$801,$A38,보유분석!$AC$2:$AC$801,1)/SUMIFS(보유분석!$BI$2:$BI$801,보유분석!$AH$2:$AH$801,$A38,보유분석!$AC$2:$AC$801,1)) -> 0.95285844
A39: 유럽 | B39: =SUMIFS(보유분석!$AA$2:$AA$801,보유분석!$AH$2:$AH$801,$A39,보유분석!$AC$2:$AC$801,1) -> 227.10206 | C39: =IF(SUMIFS(보유분석!$AA$2:$AA$801,보유분석!$AC$2:$AC$801,1)=0,0,B39/SUMIFS(보유분석!$AA$2:$AA$801,보유분석!$AC$2:$AC$801,1)) -> 0.16113401 | D39: =SUMIFS(보유분석!$AM$2:$AM$801,보유분석!$AH$2:$AH$801,$A39,보유분석!$AC$2:$AC$801,1) -> 61855.295 | E39: =IF(SUMIFS(보유분석!$AM$2:$AM$801,보유분석!$AC$2:$AC$801,1)=0,0,D39/SUMIFS(보유분석!$AM$2:$AM$801,보유분석!$AC$2:$AC$801,1)) -> 0.16311053 | F39: =IF(SUMIFS(보유분석!$BB$2:$BB$801,보유분석!$AH$2:$AH$801,$A39,보유분석!$AC$2:$AC$801,1)=0,"",SUMIFS(보유분석!$BA$2:$BA$801,보유분석!$AH$2:$AH$801,$A39,보유분석!$AC$2:$AC$801,1)/SUMIFS(보유분석!$BB$2:$BB$801,보유분석!$AH$2:$AH$801,$A39,보유분석!$AC$2:$AC$801,1)) -> 5.6862848 | G39: =IF(F39="","",(F39-(SUMIFS(보유분석!$BA$2:$BA$801,보유분석!$AC$2:$AC$801,1)/SUMIFS(보유분석!$BB$2:$BB$801,보유분석!$AC$2:$AC$801,1)))*100) -> 2.6248967 | H39: =IF(SUMIFS(보유분석!$BD$2:$BD$801,보유분석!$AH$2:$AH$801,$A39,보유분석!$AC$2:$AC$801,1)=0,"",SUMIFS(보유분석!$BC$2:$BC$801,보유분석!$AH$2:$AH$801,$A39,보유분석!$AC$2:$AC$801,1)/SUMIFS(보유분석!$BD$2:$BD$801,보유분석!$AH$2:$AH$801,$A39,보유분석!$AC$2:$AC$801,1)) -> 75.63436 | I39: =IF(SUMIFS(보유분석!$BF$2:$BF$801,보유분석!$AH$2:$AH$801,$A39,보유분석!$AC$2:$AC$801,1)=0,"",SUMIFS(보유분석!$BE$2:$BE$801,보유분석!$AH$2:$AH$801,$A39,보유분석!$AC$2:$AC$801,1)/SUMIFS(보유분석!$BF$2:$BF$801,보유분석!$AH$2:$AH$801,$A39,보유분석!$AC$2:$AC$801,1)) -> 2.7236784 | J39: =IF(SUMIFS(보유분석!$BG$2:$BG$801,보유분석!$AH$2:$AH$801,$A39,보유분석!$AC$2:$AC$801,1)=0,"",(SUMIFS(보유분석!$BC$2:$BC$801,보유분석!$AH$2:$AH$801,$A39,보유분석!$AC$2:$AC$801,1)+SUMIFS(보유분석!$BH$2:$BH$801,보유분석!$AH$2:$AH$801,$A39,보유분석!$AC$2:$AC$801,1))/SUMIFS(보유분석!$BG$2:$BG$801,보유분석!$AH$2:$AH$801,$A39,보유분석!$AC$2:$AC$801,1)) -> 34.013842 | K39: =IF(B39=0,"",SUMIFS(보유분석!$AV$2:$AV$801,보유분석!$AH$2:$AH$801,$A39,보유분석!$AC$2:$AC$801,1)/(B39*1000000)) -> 0.058801583 | L39: =SUMIFS(보유분석!$AP$2:$AP$801,보유분석!$AH$2:$AH$801,$A39,보유분석!$AC$2:$AC$801,1) -> -7840919 | M39: =COUNTIFS(보유분석!$AH$2:$AH$801,$A39,보유분석!$AR$2:$AR$801,"Cheap",보유분석!$AC$2:$AC$801,1) -> 4 | N39: =COUNTIFS(보유분석!$AH$2:$AH$801,$A39,보유분석!$AR$2:$AR$801,"Rich",보유분석!$AC$2:$AC$801,1) -> 2 | P39: =IF(O39="","",O39-C39) | Q39: =-SUMIFS(보유분석!$AZ$2:$AZ$801,보유분석!$AH$2:$AH$801,$A39,보유분석!$AC$2:$AC$801,1)*설정!$C$10 -> -1868645.9 | R39: =IF((-SUMIFS(보유분석!$AZ$2:$AZ$801,보유분석!$AC$2:$AC$801,1)*설정!$C$10)=0,0,Q39/(-SUMIFS(보유분석!$AZ$2:$AZ$801,보유분석!$AC$2:$AC$801,1)*설정!$C$10)) -> 0.18361415 | S39: =IF(SUMIFS(보유분석!$BG$2:$BG$801,보유분석!$AH$2:$AH$801,$A39,보유분석!$AC$2:$AC$801,1)=0,"",SUMIFS(보유분석!$BH$2:$BH$801,보유분석!$AH$2:$AH$801,$A39,보유분석!$AC$2:$AC$801,1)/SUMIFS(보유분석!$BG$2:$BG$801,보유분석!$AH$2:$AH$801,$A39,보유분석!$AC$2:$AC$801,1)) -> 7.3238716 | T39: =IF(SUMIFS(보유분석!$BI$2:$BI$801,보유분석!$AH$2:$AH$801,$A39,보유분석!$AC$2:$AC$801,1)=0,"",SUMIFS(보유분석!$BD$2:$BD$801,보유분석!$AH$2:$AH$801,$A39,보유분석!$AC$2:$AC$801,1)/SUMIFS(보유분석!$BI$2:$BI$801,보유분석!$AH$2:$AH$801,$A39,보유분석!$AC$2:$AC$801,1)) -> 0.93412858
A40: 아시아/기타 | B40: =SUMIFS(보유분석!$AA$2:$AA$801,보유분석!$AH$2:$AH$801,$A40,보유분석!$AC$2:$AC$801,1) -> 811.5916 | C40: =IF(SUMIFS(보유분석!$AA$2:$AA$801,보유분석!$AC$2:$AC$801,1)=0,0,B40/SUMIFS(보유분석!$AA$2:$AA$801,보유분석!$AC$2:$AC$801,1)) -> 0.57584247 | D40: =SUMIFS(보유분석!$AM$2:$AM$801,보유분석!$AH$2:$AH$801,$A40,보유분석!$AC$2:$AC$801,1) -> 207603.27 | E40: =IF(SUMIFS(보유분석!$AM$2:$AM$801,보유분석!$AC$2:$AC$801,1)=0,0,D40/SUMIFS(보유분석!$AM$2:$AM$801,보유분석!$AC$2:$AC$801,1)) -> 0.54744351 | F40: =IF(SUMIFS(보유분석!$BB$2:$BB$801,보유분석!$AH$2:$AH$801,$A40,보유분석!$AC$2:$AC$801,1)=0,"",SUMIFS(보유분석!$BA$2:$BA$801,보유분석!$AH$2:$AH$801,$A40,보유분석!$AC$2:$AC$801,1)/SUMIFS(보유분석!$BB$2:$BB$801,보유분석!$AH$2:$AH$801,$A40,보유분석!$AC$2:$AC$801,1)) -> 5.6564005 | G40: =IF(F40="","",(F40-(SUMIFS(보유분석!$BA$2:$BA$801,보유분석!$AC$2:$AC$801,1)/SUMIFS(보유분석!$BB$2:$BB$801,보유분석!$AC$2:$AC$801,1)))*100) -> -0.36352822 | H40: =IF(SUMIFS(보유분석!$BD$2:$BD$801,보유분석!$AH$2:$AH$801,$A40,보유분석!$AC$2:$AC$801,1)=0,"",SUMIFS(보유분석!$BC$2:$BC$801,보유분석!$AH$2:$AH$801,$A40,보유분석!$AC$2:$AC$801,1)/SUMIFS(보유분석!$BD$2:$BD$801,보유분석!$AH$2:$AH$801,$A40,보유분석!$AC$2:$AC$801,1)) -> 63.817384 | I40: =IF(SUMIFS(보유분석!$BF$2:$BF$801,보유분석!$AH$2:$AH$801,$A40,보유분석!$AC$2:$AC$801,1)=0,"",SUMIFS(보유분석!$BE$2:$BE$801,보유분석!$AH$2:$AH$801,$A40,보유분석!$AC$2:$AC$801,1)/SUMIFS(보유분석!$BF$2:$BF$801,보유분석!$AH$2:$AH$801,$A40,보유분석!$AC$2:$AC$801,1)) -> 2.557977 | J40: =IF(SUMIFS(보유분석!$BG$2:$BG$801,보유분석!$AH$2:$AH$801,$A40,보유분석!$AC$2:$AC$801,1)=0,"",(SUMIFS(보유분석!$BC$2:$BC$801,보유분석!$AH$2:$AH$801,$A40,보유분석!$AC$2:$AC$801,1)+SUMIFS(보유분석!$BH$2:$BH$801,보유분석!$AH$2:$AH$801,$A40,보유분석!$AC$2:$AC$801,1))/SUMIFS(보유분석!$BG$2:$BG$801,보유분석!$AH$2:$AH$801,$A40,보유분석!$AC$2:$AC$801,1)) -> 30.75056 | K40: =IF(B40=0,"",SUMIFS(보유분석!$AV$2:$AV$801,보유분석!$AH$2:$AH$801,$A40,보유분석!$AC$2:$AC$801,1)/(B40*1000000)) -> 0.058047748 | L40: =SUMIFS(보유분석!$AP$2:$AP$801,보유분석!$AH$2:$AH$801,$A40,보유분석!$AC$2:$AC$801,1) -> -23952941 | M40: =COUNTIFS(보유분석!$AH$2:$AH$801,$A40,보유분석!$AR$2:$AR$801,"Cheap",보유분석!$AC$2:$AC$801,1) -> 23 | N40: =COUNTIFS(보유분석!$AH$2:$AH$801,$A40,보유분석!$AR$2:$AR$801,"Rich",보유분석!$AC$2:$AC$801,1) -> 5 | P40: =IF(O40="","",O40-C40) | Q40: =-SUMIFS(보유분석!$AZ$2:$AZ$801,보유분석!$AH$2:$AH$801,$A40,보유분석!$AC$2:$AC$801,1)*설정!$C$10 -> -5677697.1 | R40: =IF((-SUMIFS(보유분석!$AZ$2:$AZ$801,보유분석!$AC$2:$AC$801,1)*설정!$C$10)=0,0,Q40/(-SUMIFS(보유분석!$AZ$2:$AZ$801,보유분석!$AC$2:$AC$801,1)*설정!$C$10)) -> 0.55789358 | S40: =IF(SUMIFS(보유분석!$BG$2:$BG$801,보유분석!$AH$2:$AH$801,$A40,보유분석!$AC$2:$AC$801,1)=0,"",SUMIFS(보유분석!$BH$2:$BH$801,보유분석!$AH$2:$AH$801,$A40,보유분석!$AC$2:$AC$801,1)/SUMIFS(보유분석!$BG$2:$BG$801,보유분석!$AH$2:$AH$801,$A40,보유분석!$AC$2:$AC$801,1)) -> 5.8019221 | T40: =IF(SUMIFS(보유분석!$BI$2:$BI$801,보유분석!$AH$2:$AH$801,$A40,보유분석!$AC$2:$AC$801,1)=0,"",SUMIFS(보유분석!$BD$2:$BD$801,보유분석!$AH$2:$AH$801,$A40,보유분석!$AC$2:$AC$801,1)/SUMIFS(보유분석!$BI$2:$BI$801,보유분석!$AH$2:$AH$801,$A40,보유분석!$AC$2:$AC$801,1)) -> 0.9997572
A41: 기타 | B41: =SUMIFS(보유분석!$AA$2:$AA$801,보유분석!$AH$2:$AH$801,$A41,보유분석!$AC$2:$AC$801,1) -> 24.4945 | C41: =IF(SUMIFS(보유분석!$AA$2:$AA$801,보유분석!$AC$2:$AC$801,1)=0,0,B41/SUMIFS(보유분석!$AA$2:$AA$801,보유분석!$AC$2:$AC$801,1)) -> 0.017379398 | D41: =SUMIFS(보유분석!$AM$2:$AM$801,보유분석!$AH$2:$AH$801,$A41,보유분석!$AC$2:$AC$801,1) -> 6607.6363 | E41: =IF(SUMIFS(보유분석!$AM$2:$AM$801,보유분석!$AC$2:$AC$801,1)=0,0,D41/SUMIFS(보유분석!$AM$2:$AM$801,보유분석!$AC$2:$AC$801,1)) -> 0.017424136 | F41: =IF(SUMIFS(보유분석!$BB$2:$BB$801,보유분석!$AH$2:$AH$801,$A41,보유분석!$AC$2:$AC$801,1)=0,"",SUMIFS(보유분석!$BA$2:$BA$801,보유분석!$AH$2:$AH$801,$A41,보유분석!$AC$2:$AC$801,1)/SUMIFS(보유분석!$BB$2:$BB$801,보유분석!$AH$2:$AH$801,$A41,보유분석!$AC$2:$AC$801,1)) -> 5.7549 | G41: =IF(F41="","",(F41-(SUMIFS(보유분석!$BA$2:$BA$801,보유분석!$AC$2:$AC$801,1)/SUMIFS(보유분석!$BB$2:$BB$801,보유분석!$AC$2:$AC$801,1)))*100) -> 9.4864175 | H41: =IF(SUMIFS(보유분석!$BD$2:$BD$801,보유분석!$AH$2:$AH$801,$A41,보유분석!$AC$2:$AC$801,1)=0,"",SUMIFS(보유분석!$BC$2:$BC$801,보유분석!$AH$2:$AH$801,$A41,보유분석!$AC$2:$AC$801,1)/SUMIFS(보유분석!$BD$2:$BD$801,보유분석!$AH$2:$AH$801,$A41,보유분석!$AC$2:$AC$801,1)) -> 53.762 | I41: =IF(SUMIFS(보유분석!$BF$2:$BF$801,보유분석!$AH$2:$AH$801,$A41,보유분석!$AC$2:$AC$801,1)=0,"",SUMIFS(보유분석!$BE$2:$BE$801,보유분석!$AH$2:$AH$801,$A41,보유분석!$AC$2:$AC$801,1)/SUMIFS(보유분석!$BF$2:$BF$801,보유분석!$AH$2:$AH$801,$A41,보유분석!$AC$2:$AC$801,1)) -> 2.6976 | J41: =IF(SUMIFS(보유분석!$BG$2:$BG$801,보유분석!$AH$2:$AH$801,$A41,보유분석!$AC$2:$AC$801,1)=0,"",(SUMIFS(보유분석!$BC$2:$BC$801,보유분석!$AH$2:$AH$801,$A41,보유분석!$AC$2:$AC$801,1)+SUMIFS(보유분석!$BH$2:$BH$801,보유분석!$AH$2:$AH$801,$A41,보유분석!$AC$2:$AC$801,1))/SUMIFS(보유분석!$BG$2:$BG$801,보유분석!$AH$2:$AH$801,$A41,보유분석!$AC$2:$AC$801,1)) -> 25.978185 | K41: =IF(B41=0,"",SUMIFS(보유분석!$AV$2:$AV$801,보유분석!$AH$2:$AH$801,$A41,보유분석!$AC$2:$AC$801,1)/(B41*1000000)) -> 0.059180675 | L41: =SUMIFS(보유분석!$AP$2:$AP$801,보유분석!$AH$2:$AH$801,$A41,보유분석!$AC$2:$AC$801,1) -> -718000 | M41: =COUNTIFS(보유분석!$AH$2:$AH$801,$A41,보유분석!$AR$2:$AR$801,"Cheap",보유분석!$AC$2:$AC$801,1) -> 0 | N41: =COUNTIFS(보유분석!$AH$2:$AH$801,$A41,보유분석!$AR$2:$AR$801,"Rich",보유분석!$AC$2:$AC$801,1) -> 0 | P41: =IF(O41="","",O41-C41) | Q41: =-SUMIFS(보유분석!$AZ$2:$AZ$801,보유분석!$AH$2:$AH$801,$A41,보유분석!$AC$2:$AC$801,1)*설정!$C$10 -> -134328.47 | R41: =IF((-SUMIFS(보유분석!$AZ$2:$AZ$801,보유분석!$AC$2:$AC$801,1)*설정!$C$10)=0,0,Q41/(-SUMIFS(보유분석!$AZ$2:$AZ$801,보유분석!$AC$2:$AC$801,1)*설정!$C$10)) -> 0.013199188 | S41: =IF(SUMIFS(보유분석!$BG$2:$BG$801,보유분석!$AH$2:$AH$801,$A41,보유분석!$AC$2:$AC$801,1)=0,"",SUMIFS(보유분석!$BH$2:$BH$801,보유분석!$AH$2:$AH$801,$A41,보유분석!$AC$2:$AC$801,1)/SUMIFS(보유분석!$BG$2:$BG$801,보유분석!$AH$2:$AH$801,$A41,보유분석!$AC$2:$AC$801,1)) -> 6.0486183 | T41: =IF(SUMIFS(보유분석!$BI$2:$BI$801,보유분석!$AH$2:$AH$801,$A41,보유분석!$AC$2:$AC$801,1)=0,"",SUMIFS(보유분석!$BD$2:$BD$801,보유분석!$AH$2:$AH$801,$A41,보유분석!$AC$2:$AC$801,1)/SUMIFS(보유분석!$BI$2:$BI$801,보유분석!$AH$2:$AH$801,$A41,보유분석!$AC$2:$AC$801,1)) -> 1
A42: 기타(목록외) | B42: =SUMPRODUCT(ISNA(MATCH(보유분석!$AH$2:$AH$801,$A$38:$A$41,0))*(보유분석!$AC$2:$AC$801=1)*보유분석!$AA$2:$AA$801) -> 0 | C42: =IF(SUMIFS(보유분석!$AA$2:$AA$801,보유분석!$AC$2:$AC$801,1)=0,0,B42/SUMIFS(보유분석!$AA$2:$AA$801,보유분석!$AC$2:$AC$801,1)) -> 0 | D42: =SUMPRODUCT(ISNA(MATCH(보유분석!$AH$2:$AH$801,$A$38:$A$41,0))*(보유분석!$AC$2:$AC$801=1)*보유분석!$AM$2:$AM$801) -> 0 | E42: =IF(SUMIFS(보유분석!$AM$2:$AM$801,보유분석!$AC$2:$AC$801,1)=0,0,D42/SUMIFS(보유분석!$AM$2:$AM$801,보유분석!$AC$2:$AC$801,1)) -> 0 | F42: =IF(SUMPRODUCT(ISNA(MATCH(보유분석!$AH$2:$AH$801,$A$38:$A$41,0))*(보유분석!$AC$2:$AC$801=1)*보유분석!$BB$2:$BB$801)=0,"",SUMPRODUCT(ISNA(MATCH(보유분석!$AH$2:$AH$801,$A$38:$A$41,0))*(보유분석!$AC$2:$AC$801=1)*보유분석!$BA$2:$BA$801)/SUMPRODUCT(ISNA(MATCH(보유분석!$AH$2:$AH$801,$A$38:$A$41,0))*(보유분석!$AC$2:$AC$801=1)*보유분석!$BB$2:$BB$801)) | G42: =IF(F42="","",(F42-(SUMIFS(보유분석!$BA$2:$BA$801,보유분석!$AC$2:$AC$801,1)/SUMIFS(보유분석!$BB$2:$BB$801,보유분석!$AC$2:$AC$801,1)))*100) | H42: =IF(SUMPRODUCT(ISNA(MATCH(보유분석!$AH$2:$AH$801,$A$38:$A$41,0))*(보유분석!$AC$2:$AC$801=1)*보유분석!$BD$2:$BD$801)=0,"",SUMPRODUCT(ISNA(MATCH(보유분석!$AH$2:$AH$801,$A$38:$A$41,0))*(보유분석!$AC$2:$AC$801=1)*보유분석!$BC$2:$BC$801)/SUMPRODUCT(ISNA(MATCH(보유분석!$AH$2:$AH$801,$A$38:$A$41,0))*(보유분석!$AC$2:$AC$801=1)*보유분석!$BD$2:$BD$801)) | I42: =IF(SUMPRODUCT(ISNA(MATCH(보유분석!$AH$2:$AH$801,$A$38:$A$41,0))*(보유분석!$AC$2:$AC$801=1)*보유분석!$BF$2:$BF$801)=0,"",SUMPRODUCT(ISNA(MATCH(보유분석!$AH$2:$AH$801,$A$38:$A$41,0))*(보유분석!$AC$2:$AC$801=1)*보유분석!$BE$2:$BE$801)/SUMPRODUCT(ISNA(MATCH(보유분석!$AH$2:$AH$801,$A$38:$A$41,0))*(보유분석!$AC$2:$AC$801=1)*보유분석!$BF$2:$BF$801)) | J42: =IF(SUMPRODUCT(ISNA(MATCH(보유분석!$AH$2:$AH$801,$A$38:$A$41,0))*(보유분석!$AC$2:$AC$801=1)*보유분석!$BG$2:$BG$801)=0,"",(SUMPRODUCT(ISNA(MATCH(보유분석!$AH$2:$AH$801,$A$38:$A$41,0))*(보유분석!$AC$2:$AC$801=1)*보유분석!$BC$2:$BC$801)+SUMPRODUCT(ISNA(MATCH(보유분석!$AH$2:$AH$801,$A$38:$A$41,0))*(보유분석!$AC$2:$AC$801=1)*보유분석!$BH$2:$BH$801))/SUMPRODUCT(ISNA(MATCH(보유분석!$AH$2:$AH$801,$A$38:$A$41,0))*(보유분석!$AC$2:$AC$801=1)*보유분석!$BG$2:$BG$801)) | K42: =IF(B42=0,"",SUMPRODUCT(ISNA(MATCH(보유분석!$AH$2:$AH$801,$A$38:$A$41,0))*(보유분석!$AC$2:$AC$801=1)*보유분석!$AV$2:$AV$801)/(B42*1000000)) | L42: =SUMPRODUCT(ISNA(MATCH(보유분석!$AH$2:$AH$801,$A$38:$A$41,0))*(보유분석!$AC$2:$AC$801=1)*보유분석!$AP$2:$AP$801) -> 0 | M42: =SUMPRODUCT(ISNA(MATCH(보유분석!$AH$2:$AH$801,$A$38:$A$41,0))*(보유분석!$AC$2:$AC$801=1)*(보유분석!$AR$2:$AR$801="Cheap")) -> 0 | N42: =SUMPRODUCT(ISNA(MATCH(보유분석!$AH$2:$AH$801,$A$38:$A$41,0))*(보유분석!$AC$2:$AC$801=1)*(보유분석!$AR$2:$AR$801="Rich")) -> 0 | P42: =IF(O42="","",O42-C42) | Q42: =-SUMPRODUCT(ISNA(MATCH(보유분석!$AH$2:$AH$801,$A$38:$A$41,0))*(보유분석!$AC$2:$AC$801=1)*보유분석!$AZ$2:$AZ$801)*설정!$C$10 -> 0 | R42: =IF((-SUMIFS(보유분석!$AZ$2:$AZ$801,보유분석!$AC$2:$AC$801,1)*설정!$C$10)=0,0,Q42/(-SUMIFS(보유분석!$AZ$2:$AZ$801,보유분석!$AC$2:$AC$801,1)*설정!$C$10)) -> 0 | S42: =IF(SUMPRODUCT(ISNA(MATCH(보유분석!$AH$2:$AH$801,$A$38:$A$41,0))*(보유분석!$AC$2:$AC$801=1)*보유분석!$BG$2:$BG$801)=0,"",SUMPRODUCT(ISNA(MATCH(보유분석!$AH$2:$AH$801,$A$38:$A$41,0))*(보유분석!$AC$2:$AC$801=1)*보유분석!$BH$2:$BH$801)/SUMPRODUCT(ISNA(MATCH(보유분석!$AH$2:$AH$801,$A$38:$A$41,0))*(보유분석!$AC$2:$AC$801=1)*보유분석!$BG$2:$BG$801)) | T42: =IF(SUMPRODUCT(ISNA(MATCH(보유분석!$AH$2:$AH$801,$A$38:$A$41,0))*(보유분석!$AC$2:$AC$801=1)*보유분석!$BI$2:$BI$801)=0,"",SUMPRODUCT(ISNA(MATCH(보유분석!$AH$2:$AH$801,$A$38:$A$41,0))*(보유분석!$AC$2:$AC$801=1)*보유분석!$BD$2:$BD$801)/SUMPRODUCT(ISNA(MATCH(보유분석!$AH$2:$AH$801,$A$38:$A$41,0))*(보유분석!$AC$2:$AC$801=1)*보유분석!$BI$2:$BI$801))
A43: 합계 | B43: =SUM(B38:B42) -> 1409.3986 | C43: =SUM(C38:C42) -> 1 | D43: =SUM(D38:D42) -> 379223.18 | E43: =SUM(E38:E42) -> 1 | F43: =IF(SUMIFS(보유분석!$BB$2:$BB$801,보유분석!$AC$2:$AC$801,1)=0,"",SUMIFS(보유분석!$BA$2:$BA$801,보유분석!$AC$2:$AC$801,1)/SUMIFS(보유분석!$BB$2:$BB$801,보유분석!$AC$2:$AC$801,1)) -> 5.6600358 | H43: =IF(SUMIFS(보유분석!$BD$2:$BD$801,보유분석!$AC$2:$AC$801,1)=0,"",SUMIFS(보유분석!$BC$2:$BC$801,보유분석!$AC$2:$AC$801,1)/SUMIFS(보유분석!$BD$2:$BD$801,보유분석!$AC$2:$AC$801,1)) -> 66.114006 | I43: =IF(SUMIFS(보유분석!$BF$2:$BF$801,보유분석!$AC$2:$AC$801,1)=0,"",SUMIFS(보유분석!$BE$2:$BE$801,보유분석!$AC$2:$AC$801,1)/SUMIFS(보유분석!$BF$2:$BF$801,보유분석!$AC$2:$AC$801,1)) -> 2.6906736 | J43: =IF(SUMIFS(보유분석!$BG$2:$BG$801,보유분석!$AC$2:$AC$801,1)=0,"",(SUMIFS(보유분석!$BC$2:$BC$801,보유분석!$AC$2:$AC$801,1)+SUMIFS(보유분석!$BH$2:$BH$801,보유분석!$AC$2:$AC$801,1))/SUMIFS(보유분석!$BG$2:$BG$801,보유분석!$AC$2:$AC$801,1)) -> 31.468574 | K43: =IF(B43=0,"",SUMIFS(보유분석!$AV$2:$AV$801,보유분석!$AC$2:$AC$801,1)/(B43*1000000)) -> 0.058254622 | L43: =SUM(L38:L42) -> -44901234 | O43: =IF(COUNT(O38:O42)=0,"",SUM(O38:O42)) | Q43: =SUM(Q38:Q42) -> -10177025 | R43: =SUM(R38:R42) -> 1 | S43: =IF(SUMIFS(보유분석!$BG$2:$BG$801,보유분석!$AC$2:$AC$801,1)=0,"",SUMIFS(보유분석!$BH$2:$BH$801,보유분석!$AC$2:$AC$801,1)/SUMIFS(보유분석!$BG$2:$BG$801,보유분석!$AC$2:$AC$801,1)) -> 6.4728238 | T43: =IF(SUMIFS(보유분석!$BI$2:$BI$801,보유분석!$AC$2:$AC$801,1)=0,"",SUMIFS(보유분석!$BD$2:$BD$801,보유분석!$AC$2:$AC$801,1)/SUMIFS(보유분석!$BI$2:$BI$801,보유분석!$AC$2:$AC$801,1)) -> 0.97796717
A46: ■ 섹터
A47: 구분 | B47: 평가금액($M) | C47: 비중 | D47: DV01($/bp) | E47: DV01비중 | F47: 가중YTM(%) | G47: 포트대비(bp) | H47: 가중G-spread(bp) | I47: 가중듀레이션 | J47: 손익분기 확대폭(bp) 스프레드+롤다운 | K47: 1Y기대수익률(%) | L47: 평가손익($) | M47: Cheap 보유수 | N47: Rich 보유수 | O47: 목표비중(입력) | P47: 갭(목표-현재) | Q47: 스프레드쇼크 손실($) | R47: 손실비중 | S47: └ 롤다운 기여(bp) | T47: G-spread 커버리지
A48: 금융기관 | B48: =SUMIFS(보유분석!$AA$2:$AA$801,보유분석!$AG$2:$AG$801,$A48,보유분석!$AC$2:$AC$801,1) -> 829.04727 | C48: =IF(SUMIFS(보유분석!$AA$2:$AA$801,보유분석!$AC$2:$AC$801,1)=0,0,B48/SUMIFS(보유분석!$AA$2:$AA$801,보유분석!$AC$2:$AC$801,1)) -> 0.58822766 | D48: =SUMIFS(보유분석!$AM$2:$AM$801,보유분석!$AG$2:$AG$801,$A48,보유분석!$AC$2:$AC$801,1) -> 197863.1 | E48: =IF(SUMIFS(보유분석!$AM$2:$AM$801,보유분석!$AC$2:$AC$801,1)=0,0,D48/SUMIFS(보유분석!$AM$2:$AM$801,보유분석!$AC$2:$AC$801,1)) -> 0.52175899 | F48: =IF(SUMIFS(보유분석!$BB$2:$BB$801,보유분석!$AG$2:$AG$801,$A48,보유분석!$AC$2:$AC$801,1)=0,"",SUMIFS(보유분석!$BA$2:$BA$801,보유분석!$AG$2:$AG$801,$A48,보유분석!$AC$2:$AC$801,1)/SUMIFS(보유분석!$BB$2:$BB$801,보유분석!$AG$2:$AG$801,$A48,보유분석!$AC$2:$AC$801,1)) -> 5.64511 | G48: =IF(F48="","",(F48-(SUMIFS(보유분석!$BA$2:$BA$801,보유분석!$AC$2:$AC$801,1)/SUMIFS(보유분석!$BB$2:$BB$801,보유분석!$AC$2:$AC$801,1)))*100) -> -1.4925785 | H48: =IF(SUMIFS(보유분석!$BD$2:$BD$801,보유분석!$AG$2:$AG$801,$A48,보유분석!$AC$2:$AC$801,1)=0,"",SUMIFS(보유분석!$BC$2:$BC$801,보유분석!$AG$2:$AG$801,$A48,보유분석!$AC$2:$AC$801,1)/SUMIFS(보유분석!$BD$2:$BD$801,보유분석!$AG$2:$AG$801,$A48,보유분석!$AC$2:$AC$801,1)) -> 64.547173 | I48: =IF(SUMIFS(보유분석!$BF$2:$BF$801,보유분석!$AG$2:$AG$801,$A48,보유분석!$AC$2:$AC$801,1)=0,"",SUMIFS(보유분석!$BE$2:$BE$801,보유분석!$AG$2:$AG$801,$A48,보유분석!$AC$2:$AC$801,1)/SUMIFS(보유분석!$BF$2:$BF$801,보유분석!$AG$2:$AG$801,$A48,보유분석!$AC$2:$AC$801,1)) -> 2.3866323 | J48: =IF(SUMIFS(보유분석!$BG$2:$BG$801,보유분석!$AG$2:$AG$801,$A48,보유분석!$AC$2:$AC$801,1)=0,"",(SUMIFS(보유분석!$BC$2:$BC$801,보유분석!$AG$2:$AG$801,$A48,보유분석!$AC$2:$AC$801,1)+SUMIFS(보유분석!$BH$2:$BH$801,보유분석!$AG$2:$AG$801,$A48,보유분석!$AC$2:$AC$801,1))/SUMIFS(보유분석!$BG$2:$BG$801,보유분석!$AG$2:$AG$801,$A48,보유분석!$AC$2:$AC$801,1)) -> 32.322156 | K48: =IF(B48=0,"",SUMIFS(보유분석!$AV$2:$AV$801,보유분석!$AG$2:$AG$801,$A48,보유분석!$AC$2:$AC$801,1)/(B48*1000000)) -> 0.057638666 | L48: =SUMIFS(보유분석!$AP$2:$AP$801,보유분석!$AG$2:$AG$801,$A48,보유분석!$AC$2:$AC$801,1) -> -23163757 | M48: =COUNTIFS(보유분석!$AG$2:$AG$801,$A48,보유분석!$AR$2:$AR$801,"Cheap",보유분석!$AC$2:$AC$801,1) -> 19 | N48: =COUNTIFS(보유분석!$AG$2:$AG$801,$A48,보유분석!$AR$2:$AR$801,"Rich",보유분석!$AC$2:$AC$801,1) -> 3 | P48: =IF(O48="","",O48-C48) | Q48: =-SUMIFS(보유분석!$AZ$2:$AZ$801,보유분석!$AG$2:$AG$801,$A48,보유분석!$AC$2:$AC$801,1)*설정!$C$10 -> -5482514.1 | R48: =IF((-SUMIFS(보유분석!$AZ$2:$AZ$801,보유분석!$AC$2:$AC$801,1)*설정!$C$10)=0,0,Q48/(-SUMIFS(보유분석!$AZ$2:$AZ$801,보유분석!$AC$2:$AC$801,1)*설정!$C$10)) -> 0.53871479 | S48: =IF(SUMIFS(보유분석!$BG$2:$BG$801,보유분석!$AG$2:$AG$801,$A48,보유분석!$AC$2:$AC$801,1)=0,"",SUMIFS(보유분석!$BH$2:$BH$801,보유분석!$AG$2:$AG$801,$A48,보유분석!$AC$2:$AC$801,1)/SUMIFS(보유분석!$BG$2:$BG$801,보유분석!$AG$2:$AG$801,$A48,보유분석!$AC$2:$AC$801,1)) -> 5.1793212 | T48: =IF(SUMIFS(보유분석!$BI$2:$BI$801,보유분석!$AG$2:$AG$801,$A48,보유분석!$AC$2:$AC$801,1)=0,"",SUMIFS(보유분석!$BD$2:$BD$801,보유분석!$AG$2:$AG$801,$A48,보유분석!$AC$2:$AC$801,1)/SUMIFS(보유분석!$BI$2:$BI$801,보유분석!$AG$2:$AG$801,$A48,보유분석!$AC$2:$AC$801,1)) -> 0.96419039
A49: 기본소비재 | B49: =SUMIFS(보유분석!$AA$2:$AA$801,보유분석!$AG$2:$AG$801,$A49,보유분석!$AC$2:$AC$801,1) -> 0 | C49: =IF(SUMIFS(보유분석!$AA$2:$AA$801,보유분석!$AC$2:$AC$801,1)=0,0,B49/SUMIFS(보유분석!$AA$2:$AA$801,보유분석!$AC$2:$AC$801,1)) -> 0 | D49: =SUMIFS(보유분석!$AM$2:$AM$801,보유분석!$AG$2:$AG$801,$A49,보유분석!$AC$2:$AC$801,1) -> 0 | E49: =IF(SUMIFS(보유분석!$AM$2:$AM$801,보유분석!$AC$2:$AC$801,1)=0,0,D49/SUMIFS(보유분석!$AM$2:$AM$801,보유분석!$AC$2:$AC$801,1)) -> 0 | F49: =IF(SUMIFS(보유분석!$BB$2:$BB$801,보유분석!$AG$2:$AG$801,$A49,보유분석!$AC$2:$AC$801,1)=0,"",SUMIFS(보유분석!$BA$2:$BA$801,보유분석!$AG$2:$AG$801,$A49,보유분석!$AC$2:$AC$801,1)/SUMIFS(보유분석!$BB$2:$BB$801,보유분석!$AG$2:$AG$801,$A49,보유분석!$AC$2:$AC$801,1)) | G49: =IF(F49="","",(F49-(SUMIFS(보유분석!$BA$2:$BA$801,보유분석!$AC$2:$AC$801,1)/SUMIFS(보유분석!$BB$2:$BB$801,보유분석!$AC$2:$AC$801,1)))*100) | H49: =IF(SUMIFS(보유분석!$BD$2:$BD$801,보유분석!$AG$2:$AG$801,$A49,보유분석!$AC$2:$AC$801,1)=0,"",SUMIFS(보유분석!$BC$2:$BC$801,보유분석!$AG$2:$AG$801,$A49,보유분석!$AC$2:$AC$801,1)/SUMIFS(보유분석!$BD$2:$BD$801,보유분석!$AG$2:$AG$801,$A49,보유분석!$AC$2:$AC$801,1)) | I49: =IF(SUMIFS(보유분석!$BF$2:$BF$801,보유분석!$AG$2:$AG$801,$A49,보유분석!$AC$2:$AC$801,1)=0,"",SUMIFS(보유분석!$BE$2:$BE$801,보유분석!$AG$2:$AG$801,$A49,보유분석!$AC$2:$AC$801,1)/SUMIFS(보유분석!$BF$2:$BF$801,보유분석!$AG$2:$AG$801,$A49,보유분석!$AC$2:$AC$801,1)) | J49: =IF(SUMIFS(보유분석!$BG$2:$BG$801,보유분석!$AG$2:$AG$801,$A49,보유분석!$AC$2:$AC$801,1)=0,"",(SUMIFS(보유분석!$BC$2:$BC$801,보유분석!$AG$2:$AG$801,$A49,보유분석!$AC$2:$AC$801,1)+SUMIFS(보유분석!$BH$2:$BH$801,보유분석!$AG$2:$AG$801,$A49,보유분석!$AC$2:$AC$801,1))/SUMIFS(보유분석!$BG$2:$BG$801,보유분석!$AG$2:$AG$801,$A49,보유분석!$AC$2:$AC$801,1)) | K49: =IF(B49=0,"",SUMIFS(보유분석!$AV$2:$AV$801,보유분석!$AG$2:$AG$801,$A49,보유분석!$AC$2:$AC$801,1)/(B49*1000000)) | L49: =SUMIFS(보유분석!$AP$2:$AP$801,보유분석!$AG$2:$AG$801,$A49,보유분석!$AC$2:$AC$801,1) -> 0 | M49: =COUNTIFS(보유분석!$AG$2:$AG$801,$A49,보유분석!$AR$2:$AR$801,"Cheap",보유분석!$AC$2:$AC$801,1) -> 0 | N49: =COUNTIFS(보유분석!$AG$2:$AG$801,$A49,보유분석!$AR$2:$AR$801,"Rich",보유분석!$AC$2:$AC$801,1) -> 0 | P49: =IF(O49="","",O49-C49) | Q49: =-SUMIFS(보유분석!$AZ$2:$AZ$801,보유분석!$AG$2:$AG$801,$A49,보유분석!$AC$2:$AC$801,1)*설정!$C$10 -> 0 | R49: =IF((-SUMIFS(보유분석!$AZ$2:$AZ$801,보유분석!$AC$2:$AC$801,1)*설정!$C$10)=0,0,Q49/(-SUMIFS(보유분석!$AZ$2:$AZ$801,보유분석!$AC$2:$AC$801,1)*설정!$C$10)) -> 0 | S49: =IF(SUMIFS(보유분석!$BG$2:$BG$801,보유분석!$AG$2:$AG$801,$A49,보유분석!$AC$2:$AC$801,1)=0,"",SUMIFS(보유분석!$BH$2:$BH$801,보유분석!$AG$2:$AG$801,$A49,보유분석!$AC$2:$AC$801,1)/SUMIFS(보유분석!$BG$2:$BG$801,보유분석!$AG$2:$AG$801,$A49,보유분석!$AC$2:$AC$801,1)) | T49: =IF(SUMIFS(보유분석!$BI$2:$BI$801,보유분석!$AG$2:$AG$801,$A49,보유분석!$AC$2:$AC$801,1)=0,"",SUMIFS(보유분석!$BD$2:$BD$801,보유분석!$AG$2:$AG$801,$A49,보유분석!$AC$2:$AC$801,1)/SUMIFS(보유분석!$BI$2:$BI$801,보유분석!$AG$2:$AG$801,$A49,보유분석!$AC$2:$AC$801,1))
A50: 기술 | B50: =SUMIFS(보유분석!$AA$2:$AA$801,보유분석!$AG$2:$AG$801,$A50,보유분석!$AC$2:$AC$801,1) -> 99.287494 | C50: =IF(SUMIFS(보유분석!$AA$2:$AA$801,보유분석!$AC$2:$AC$801,1)=0,0,B50/SUMIFS(보유분석!$AA$2:$AA$801,보유분석!$AC$2:$AC$801,1)) -> 0.070446707 | D50: =SUMIFS(보유분석!$AM$2:$AM$801,보유분석!$AG$2:$AG$801,$A50,보유분석!$AC$2:$AC$801,1) -> 31866.36 | E50: =IF(SUMIFS(보유분석!$AM$2:$AM$801,보유분석!$AC$2:$AC$801,1)=0,0,D50/SUMIFS(보유분석!$AM$2:$AM$801,보유분석!$AC$2:$AC$801,1)) -> 0.084030623 | F50: =IF(SUMIFS(보유분석!$BB$2:$BB$801,보유분석!$AG$2:$AG$801,$A50,보유분석!$AC$2:$AC$801,1)=0,"",SUMIFS(보유분석!$BA$2:$BA$801,보유분석!$AG$2:$AG$801,$A50,보유분석!$AC$2:$AC$801,1)/SUMIFS(보유분석!$BB$2:$BB$801,보유분석!$AG$2:$AG$801,$A50,보유분석!$AC$2:$AC$801,1)) -> 5.5904396 | G50: =IF(F50="","",(F50-(SUMIFS(보유분석!$BA$2:$BA$801,보유분석!$AC$2:$AC$801,1)/SUMIFS(보유분석!$BB$2:$BB$801,보유분석!$AC$2:$AC$801,1)))*100) -> -6.9596264 | H50: =IF(SUMIFS(보유분석!$BD$2:$BD$801,보유분석!$AG$2:$AG$801,$A50,보유분석!$AC$2:$AC$801,1)=0,"",SUMIFS(보유분석!$BC$2:$BC$801,보유분석!$AG$2:$AG$801,$A50,보유분석!$AC$2:$AC$801,1)/SUMIFS(보유분석!$BD$2:$BD$801,보유분석!$AG$2:$AG$801,$A50,보유분석!$AC$2:$AC$801,1)) -> 56.437294 | I50: =IF(SUMIFS(보유분석!$BF$2:$BF$801,보유분석!$AG$2:$AG$801,$A50,보유분석!$AC$2:$AC$801,1)=0,"",SUMIFS(보유분석!$BE$2:$BE$801,보유분석!$AG$2:$AG$801,$A50,보유분석!$AC$2:$AC$801,1)/SUMIFS(보유분석!$BF$2:$BF$801,보유분석!$AG$2:$AG$801,$A50,보유분석!$AC$2:$AC$801,1)) -> 3.2095039 | J50: =IF(SUMIFS(보유분석!$BG$2:$BG$801,보유분석!$AG$2:$AG$801,$A50,보유분석!$AC$2:$AC$801,1)=0,"",(SUMIFS(보유분석!$BC$2:$BC$801,보유분석!$AG$2:$AG$801,$A50,보유분석!$AC$2:$AC$801,1)+SUMIFS(보유분석!$BH$2:$BH$801,보유분석!$AG$2:$AG$801,$A50,보유분석!$AC$2:$AC$801,1))/SUMIFS(보유분석!$BG$2:$BG$801,보유분석!$AG$2:$AG$801,$A50,보유분석!$AC$2:$AC$801,1)) -> 21.826264 | K50: =IF(B50=0,"",SUMIFS(보유분석!$AV$2:$AV$801,보유분석!$AG$2:$AG$801,$A50,보유분석!$AC$2:$AC$801,1)/(B50*1000000)) -> 0.057265814 | L50: =SUMIFS(보유분석!$AP$2:$AP$801,보유분석!$AG$2:$AG$801,$A50,보유분석!$AC$2:$AC$801,1) -> -3665701 | M50: =COUNTIFS(보유분석!$AG$2:$AG$801,$A50,보유분석!$AR$2:$AR$801,"Cheap",보유분석!$AC$2:$AC$801,1) -> 1 | N50: =COUNTIFS(보유분석!$AG$2:$AG$801,$A50,보유분석!$AR$2:$AR$801,"Rich",보유분석!$AC$2:$AC$801,1) -> 3 | P50: =IF(O50="","",O50-C50) | Q50: =-SUMIFS(보유분석!$AZ$2:$AZ$801,보유분석!$AG$2:$AG$801,$A50,보유분석!$AC$2:$AC$801,1)*설정!$C$10 -> -730276.44 | R50: =IF((-SUMIFS(보유분석!$AZ$2:$AZ$801,보유분석!$AC$2:$AC$801,1)*설정!$C$10)=0,0,Q50/(-SUMIFS(보유분석!$AZ$2:$AZ$801,보유분석!$AC$2:$AC$801,1)*설정!$C$10)) -> 0.071757356 | S50: =IF(SUMIFS(보유분석!$BG$2:$BG$801,보유분석!$AG$2:$AG$801,$A50,보유분석!$AC$2:$AC$801,1)=0,"",SUMIFS(보유분석!$BH$2:$BH$801,보유분석!$AG$2:$AG$801,$A50,보유분석!$AC$2:$AC$801,1)/SUMIFS(보유분석!$BG$2:$BG$801,보유분석!$AG$2:$AG$801,$A50,보유분석!$AC$2:$AC$801,1)) -> 4.2418348 | T50: =IF(SUMIFS(보유분석!$BI$2:$BI$801,보유분석!$AG$2:$AG$801,$A50,보유분석!$AC$2:$AC$801,1)=0,"",SUMIFS(보유분석!$BD$2:$BD$801,보유분석!$AG$2:$AG$801,$A50,보유분석!$AC$2:$AC$801,1)/SUMIFS(보유분석!$BI$2:$BI$801,보유분석!$AG$2:$AG$801,$A50,보유분석!$AC$2:$AC$801,1)) -> 1
A51: 산업 | B51: =SUMIFS(보유분석!$AA$2:$AA$801,보유분석!$AG$2:$AG$801,$A51,보유분석!$AC$2:$AC$801,1) -> 0.6920507 | C51: =IF(SUMIFS(보유분석!$AA$2:$AA$801,보유분석!$AC$2:$AC$801,1)=0,0,B51/SUMIFS(보유분석!$AA$2:$AA$801,보유분석!$AC$2:$AC$801,1)) -> 0.00049102552 | D51: =SUMIFS(보유분석!$AM$2:$AM$801,보유분석!$AG$2:$AG$801,$A51,보유분석!$AC$2:$AC$801,1) -> 125.65268 | E51: =IF(SUMIFS(보유분석!$AM$2:$AM$801,보유분석!$AC$2:$AC$801,1)=0,0,D51/SUMIFS(보유분석!$AM$2:$AM$801,보유분석!$AC$2:$AC$801,1)) -> 0.00033134231 | F51: =IF(SUMIFS(보유분석!$BB$2:$BB$801,보유분석!$AG$2:$AG$801,$A51,보유분석!$AC$2:$AC$801,1)=0,"",SUMIFS(보유분석!$BA$2:$BA$801,보유분석!$AG$2:$AG$801,$A51,보유분석!$AC$2:$AC$801,1)/SUMIFS(보유분석!$BB$2:$BB$801,보유분석!$AG$2:$AG$801,$A51,보유분석!$AC$2:$AC$801,1)) -> 5.4584008 | G51: =IF(F51="","",(F51-(SUMIFS(보유분석!$BA$2:$BA$801,보유분석!$AC$2:$AC$801,1)/SUMIFS(보유분석!$BB$2:$BB$801,보유분석!$AC$2:$AC$801,1)))*100) -> -20.163505 | H51: =IF(SUMIFS(보유분석!$BD$2:$BD$801,보유분석!$AG$2:$AG$801,$A51,보유분석!$AC$2:$AC$801,1)=0,"",SUMIFS(보유분석!$BC$2:$BC$801,보유분석!$AG$2:$AG$801,$A51,보유분석!$AC$2:$AC$801,1)/SUMIFS(보유분석!$BD$2:$BD$801,보유분석!$AG$2:$AG$801,$A51,보유분석!$AC$2:$AC$801,1)) -> 51.003712 | I51: =IF(SUMIFS(보유분석!$BF$2:$BF$801,보유분석!$AG$2:$AG$801,$A51,보유분석!$AC$2:$AC$801,1)=0,"",SUMIFS(보유분석!$BE$2:$BE$801,보유분석!$AG$2:$AG$801,$A51,보유분석!$AC$2:$AC$801,1)/SUMIFS(보유분석!$BF$2:$BF$801,보유분석!$AG$2:$AG$801,$A51,보유분석!$AC$2:$AC$801,1)) -> 1.8156572 | J51: =IF(SUMIFS(보유분석!$BG$2:$BG$801,보유분석!$AG$2:$AG$801,$A51,보유분석!$AC$2:$AC$801,1)=0,"",(SUMIFS(보유분석!$BC$2:$BC$801,보유분석!$AG$2:$AG$801,$A51,보유분석!$AC$2:$AC$801,1)+SUMIFS(보유분석!$BH$2:$BH$801,보유분석!$AG$2:$AG$801,$A51,보유분석!$AC$2:$AC$801,1))/SUMIFS(보유분석!$BG$2:$BG$801,보유분석!$AG$2:$AG$801,$A51,보유분석!$AC$2:$AC$801,1)) -> 36.789747 | K51: =IF(B51=0,"",SUMIFS(보유분석!$AV$2:$AV$801,보유분석!$AG$2:$AG$801,$A51,보유분석!$AC$2:$AC$801,1)/(B51*1000000)) -> 0.056163394 | L51: =SUMIFS(보유분석!$AP$2:$AP$801,보유분석!$AG$2:$AG$801,$A51,보유분석!$AC$2:$AC$801,1) -> -14579.8 | M51: =COUNTIFS(보유분석!$AG$2:$AG$801,$A51,보유분석!$AR$2:$AR$801,"Cheap",보유분석!$AC$2:$AC$801,1) -> 0 | N51: =COUNTIFS(보유분석!$AG$2:$AG$801,$A51,보유분석!$AR$2:$AR$801,"Rich",보유분석!$AC$2:$AC$801,1) -> 0 | P51: =IF(O51="","",O51-C51) | Q51: =-SUMIFS(보유분석!$AZ$2:$AZ$801,보유분석!$AG$2:$AG$801,$A51,보유분석!$AC$2:$AC$801,1)*설정!$C$10 -> -2500.8173 | R51: =IF((-SUMIFS(보유분석!$AZ$2:$AZ$801,보유분석!$AC$2:$AC$801,1)*설정!$C$10)=0,0,Q51/(-SUMIFS(보유분석!$AZ$2:$AZ$801,보유분석!$AC$2:$AC$801,1)*설정!$C$10)) -> 0.00024573165 | S51: =IF(SUMIFS(보유분석!$BG$2:$BG$801,보유분석!$AG$2:$AG$801,$A51,보유분석!$AC$2:$AC$801,1)=0,"",SUMIFS(보유분석!$BH$2:$BH$801,보유분석!$AG$2:$AG$801,$A51,보유분석!$AC$2:$AC$801,1)/SUMIFS(보유분석!$BG$2:$BG$801,보유분석!$AG$2:$AG$801,$A51,보유분석!$AC$2:$AC$801,1)) -> 8.6987007 | T51: =IF(SUMIFS(보유분석!$BI$2:$BI$801,보유분석!$AG$2:$AG$801,$A51,보유분석!$AC$2:$AC$801,1)=0,"",SUMIFS(보유분석!$BD$2:$BD$801,보유분석!$AG$2:$AG$801,$A51,보유분석!$AC$2:$AC$801,1)/SUMIFS(보유분석!$BI$2:$BI$801,보유분석!$AG$2:$AG$801,$A51,보유분석!$AC$2:$AC$801,1)) -> 1
A52: 에너지 | B52: =SUMIFS(보유분석!$AA$2:$AA$801,보유분석!$AG$2:$AG$801,$A52,보유분석!$AC$2:$AC$801,1) -> 7.3672 | C52: =IF(SUMIFS(보유분석!$AA$2:$AA$801,보유분석!$AC$2:$AC$801,1)=0,0,B52/SUMIFS(보유분석!$AA$2:$AA$801,보유분석!$AC$2:$AC$801,1)) -> 0.0052271939 | D52: =SUMIFS(보유분석!$AM$2:$AM$801,보유분석!$AG$2:$AG$801,$A52,보유분석!$AC$2:$AC$801,1) -> 1681.8273 | E52: =IF(SUMIFS(보유분석!$AM$2:$AM$801,보유분석!$AC$2:$AC$801,1)=0,0,D52/SUMIFS(보유분석!$AM$2:$AM$801,보유분석!$AC$2:$AC$801,1)) -> 0.0044349276 | F52: =IF(SUMIFS(보유분석!$BB$2:$BB$801,보유분석!$AG$2:$AG$801,$A52,보유분석!$AC$2:$AC$801,1)=0,"",SUMIFS(보유분석!$BA$2:$BA$801,보유분석!$AG$2:$AG$801,$A52,보유분석!$AC$2:$AC$801,1)/SUMIFS(보유분석!$BB$2:$BB$801,보유분석!$AG$2:$AG$801,$A52,보유분석!$AC$2:$AC$801,1)) -> 5.5094068 | G52: =IF(F52="","",(F52-(SUMIFS(보유분석!$BA$2:$BA$801,보유분석!$AC$2:$AC$801,1)/SUMIFS(보유분석!$BB$2:$BB$801,보유분석!$AC$2:$AC$801,1)))*100) -> -15.0629 | H52: =IF(SUMIFS(보유분석!$BD$2:$BD$801,보유분석!$AG$2:$AG$801,$A52,보유분석!$AC$2:$AC$801,1)=0,"",SUMIFS(보유분석!$BC$2:$BC$801,보유분석!$AG$2:$AG$801,$A52,보유분석!$AC$2:$AC$801,1)/SUMIFS(보유분석!$BD$2:$BD$801,보유분석!$AG$2:$AG$801,$A52,보유분석!$AC$2:$AC$801,1)) -> 58.605627 | I52: =IF(SUMIFS(보유분석!$BF$2:$BF$801,보유분석!$AG$2:$AG$801,$A52,보유분석!$AC$2:$AC$801,1)=0,"",SUMIFS(보유분석!$BE$2:$BE$801,보유분석!$AG$2:$AG$801,$A52,보유분석!$AC$2:$AC$801,1)/SUMIFS(보유분석!$BF$2:$BF$801,보유분석!$AG$2:$AG$801,$A52,보유분석!$AC$2:$AC$801,1)) -> 2.2828583 | J52: =IF(SUMIFS(보유분석!$BG$2:$BG$801,보유분석!$AG$2:$AG$801,$A52,보유분석!$AC$2:$AC$801,1)=0,"",(SUMIFS(보유분석!$BC$2:$BC$801,보유분석!$AG$2:$AG$801,$A52,보유분석!$AC$2:$AC$801,1)+SUMIFS(보유분석!$BH$2:$BH$801,보유분석!$AG$2:$AG$801,$A52,보유분석!$AC$2:$AC$801,1))/SUMIFS(보유분석!$BG$2:$BG$801,보유분석!$AG$2:$AG$801,$A52,보유분석!$AC$2:$AC$801,1)) -> 33.249024 | K52: =IF(B52=0,"",SUMIFS(보유분석!$AV$2:$AV$801,보유분석!$AG$2:$AG$801,$A52,보유분석!$AC$2:$AC$801,1)/(B52*1000000)) -> 0.056823786 | L52: =SUMIFS(보유분석!$AP$2:$AP$801,보유분석!$AG$2:$AG$801,$A52,보유분석!$AC$2:$AC$801,1) -> -114025 | M52: =COUNTIFS(보유분석!$AG$2:$AG$801,$A52,보유분석!$AR$2:$AR$801,"Cheap",보유분석!$AC$2:$AC$801,1) -> 0 | N52: =COUNTIFS(보유분석!$AG$2:$AG$801,$A52,보유분석!$AR$2:$AR$801,"Rich",보유분석!$AC$2:$AC$801,1) -> 0 | P52: =IF(O52="","",O52-C52) | Q52: =-SUMIFS(보유분석!$AZ$2:$AZ$801,보유분석!$AG$2:$AG$801,$A52,보유분석!$AC$2:$AC$801,1)*설정!$C$10 -> -37618.009 | R52: =IF((-SUMIFS(보유분석!$AZ$2:$AZ$801,보유분석!$AC$2:$AC$801,1)*설정!$C$10)=0,0,Q52/(-SUMIFS(보유분석!$AZ$2:$AZ$801,보유분석!$AC$2:$AC$801,1)*설정!$C$10)) -> 0.0036963659 | S52: =IF(SUMIFS(보유분석!$BG$2:$BG$801,보유분석!$AG$2:$AG$801,$A52,보유분석!$AC$2:$AC$801,1)=0,"",SUMIFS(보유분석!$BH$2:$BH$801,보유분석!$AG$2:$AG$801,$A52,보유분석!$AC$2:$AC$801,1)/SUMIFS(보유분석!$BG$2:$BG$801,보유분석!$AG$2:$AG$801,$A52,보유분석!$AC$2:$AC$801,1)) -> 7.5769848 | T52: =IF(SUMIFS(보유분석!$BI$2:$BI$801,보유분석!$AG$2:$AG$801,$A52,보유분석!$AC$2:$AC$801,1)=0,"",SUMIFS(보유분석!$BD$2:$BD$801,보유분석!$AG$2:$AG$801,$A52,보유분석!$AC$2:$AC$801,1)/SUMIFS(보유분석!$BI$2:$BI$801,보유분석!$AG$2:$AG$801,$A52,보유분석!$AC$2:$AC$801,1)) -> 1
A53: 원자재 | B53: =SUMIFS(보유분석!$AA$2:$AA$801,보유분석!$AG$2:$AG$801,$A53,보유분석!$AC$2:$AC$801,1) -> 53.180488 | C53: =IF(SUMIFS(보유분석!$AA$2:$AA$801,보유분석!$AC$2:$AC$801,1)=0,0,B53/SUMIFS(보유분석!$AA$2:$AA$801,보유분석!$AC$2:$AC$801,1)) -> 0.037732751 | D53: =SUMIFS(보유분석!$AM$2:$AM$801,보유분석!$AG$2:$AG$801,$A53,보유분석!$AC$2:$AC$801,1) -> 21192.741 | E53: =IF(SUMIFS(보유분석!$AM$2:$AM$801,보유분석!$AC$2:$AC$801,1)=0,0,D53/SUMIFS(보유분석!$AM$2:$AM$801,보유분석!$AC$2:$AC$801,1)) -> 0.055884613 | F53: =IF(SUMIFS(보유분석!$BB$2:$BB$801,보유분석!$AG$2:$AG$801,$A53,보유분석!$AC$2:$AC$801,1)=0,"",SUMIFS(보유분석!$BA$2:$BA$801,보유분석!$AG$2:$AG$801,$A53,보유분석!$AC$2:$AC$801,1)/SUMIFS(보유분석!$BB$2:$BB$801,보유분석!$AG$2:$AG$801,$A53,보유분석!$AC$2:$AC$801,1)) -> 5.8900335 | G53: =IF(F53="","",(F53-(SUMIFS(보유분석!$BA$2:$BA$801,보유분석!$AC$2:$AC$801,1)/SUMIFS(보유분석!$BB$2:$BB$801,보유분석!$AC$2:$AC$801,1)))*100) -> 22.99977 | H53: =IF(SUMIFS(보유분석!$BD$2:$BD$801,보유분석!$AG$2:$AG$801,$A53,보유분석!$AC$2:$AC$801,1)=0,"",SUMIFS(보유분석!$BC$2:$BC$801,보유분석!$AG$2:$AG$801,$A53,보유분석!$AC$2:$AC$801,1)/SUMIFS(보유분석!$BD$2:$BD$801,보유분석!$AG$2:$AG$801,$A53,보유분석!$AC$2:$AC$801,1)) -> 82.834818 | I53: =IF(SUMIFS(보유분석!$BF$2:$BF$801,보유분석!$AG$2:$AG$801,$A53,보유분석!$AC$2:$AC$801,1)=0,"",SUMIFS(보유분석!$BE$2:$BE$801,보유분석!$AG$2:$AG$801,$A53,보유분석!$AC$2:$AC$801,1)/SUMIFS(보유분석!$BF$2:$BF$801,보유분석!$AG$2:$AG$801,$A53,보유분석!$AC$2:$AC$801,1)) -> 3.9850594 | J53: =IF(SUMIFS(보유분석!$BG$2:$BG$801,보유분석!$AG$2:$AG$801,$A53,보유분석!$AC$2:$AC$801,1)=0,"",(SUMIFS(보유분석!$BC$2:$BC$801,보유분석!$AG$2:$AG$801,$A53,보유분석!$AC$2:$AC$801,1)+SUMIFS(보유분석!$BH$2:$BH$801,보유분석!$AG$2:$AG$801,$A53,보유분석!$AC$2:$AC$801,1))/SUMIFS(보유분석!$BG$2:$BG$801,보유분석!$AG$2:$AG$801,$A53,보유분석!$AC$2:$AC$801,1)) -> 25.950287 | K53: =IF(B53=0,"",SUMIFS(보유분석!$AV$2:$AV$801,보유분석!$AG$2:$AG$801,$A53,보유분석!$AC$2:$AC$801,1)/(B53*1000000)) -> 0.060958197 | L53: =SUMIFS(보유분석!$AP$2:$AP$801,보유분석!$AG$2:$AG$801,$A53,보유분석!$AC$2:$AC$801,1) -> -1922237.2 | M53: =COUNTIFS(보유분석!$AG$2:$AG$801,$A53,보유분석!$AR$2:$AR$801,"Cheap",보유분석!$AC$2:$AC$801,1) -> 9 | N53: =COUNTIFS(보유분석!$AG$2:$AG$801,$A53,보유분석!$AR$2:$AR$801,"Rich",보유분석!$AC$2:$AC$801,1) -> 0 | P53: =IF(O53="","",O53-C53) | Q53: =-SUMIFS(보유분석!$AZ$2:$AZ$801,보유분석!$AG$2:$AG$801,$A53,보유분석!$AC$2:$AC$801,1)*설정!$C$10 -> -708192.13 | R53: =IF((-SUMIFS(보유분석!$AZ$2:$AZ$801,보유분석!$AC$2:$AC$801,1)*설정!$C$10)=0,0,Q53/(-SUMIFS(보유분석!$AZ$2:$AZ$801,보유분석!$AC$2:$AC$801,1)*설정!$C$10)) -> 0.069587341 | S53: =IF(SUMIFS(보유분석!$BG$2:$BG$801,보유분석!$AG$2:$AG$801,$A53,보유분석!$AC$2:$AC$801,1)=0,"",SUMIFS(보유분석!$BH$2:$BH$801,보유분석!$AG$2:$AG$801,$A53,보유분석!$AC$2:$AC$801,1)/SUMIFS(보유분석!$BG$2:$BG$801,보유분석!$AG$2:$AG$801,$A53,보유분석!$AC$2:$AC$801,1)) -> 5.1639426 | T53: =IF(SUMIFS(보유분석!$BI$2:$BI$801,보유분석!$AG$2:$AG$801,$A53,보유분석!$AC$2:$AC$801,1)=0,"",SUMIFS(보유분석!$BD$2:$BD$801,보유분석!$AG$2:$AG$801,$A53,보유분석!$AC$2:$AC$801,1)/SUMIFS(보유분석!$BI$2:$BI$801,보유분석!$AG$2:$AG$801,$A53,보유분석!$AC$2:$AC$801,1)) -> 1
A54: 유틸리티 | B54: =SUMIFS(보유분석!$AA$2:$AA$801,보유분석!$AG$2:$AG$801,$A54,보유분석!$AC$2:$AC$801,1) -> 37.203464 | C54: =IF(SUMIFS(보유분석!$AA$2:$AA$801,보유분석!$AC$2:$AC$801,1)=0,0,B54/SUMIFS(보유분석!$AA$2:$AA$801,보유분석!$AC$2:$AC$801,1)) -> 0.026396693 | D54: =SUMIFS(보유분석!$AM$2:$AM$801,보유분석!$AG$2:$AG$801,$A54,보유분석!$AC$2:$AC$801,1) -> 11786.792 | E54: =IF(SUMIFS(보유분석!$AM$2:$AM$801,보유분석!$AC$2:$AC$801,1)=0,0,D54/SUMIFS(보유분석!$AM$2:$AM$801,보유분석!$AC$2:$AC$801,1)) -> 0.031081412 | F54: =IF(SUMIFS(보유분석!$BB$2:$BB$801,보유분석!$AG$2:$AG$801,$A54,보유분석!$AC$2:$AC$801,1)=0,"",SUMIFS(보유분석!$BA$2:$BA$801,보유분석!$AG$2:$AG$801,$A54,보유분석!$AC$2:$AC$801,1)/SUMIFS(보유분석!$BB$2:$BB$801,보유분석!$AG$2:$AG$801,$A54,보유분석!$AC$2:$AC$801,1)) -> 5.3649847 | G54: =IF(F54="","",(F54-(SUMIFS(보유분석!$BA$2:$BA$801,보유분석!$AC$2:$AC$801,1)/SUMIFS(보유분석!$BB$2:$BB$801,보유분석!$AC$2:$AC$801,1)))*100) -> -29.50511 | H54: =IF(SUMIFS(보유분석!$BD$2:$BD$801,보유분석!$AG$2:$AG$801,$A54,보유분석!$AC$2:$AC$801,1)=0,"",SUMIFS(보유분석!$BC$2:$BC$801,보유분석!$AG$2:$AG$801,$A54,보유분석!$AC$2:$AC$801,1)/SUMIFS(보유분석!$BD$2:$BD$801,보유분석!$AG$2:$AG$801,$A54,보유분석!$AC$2:$AC$801,1)) -> 35.815043 | I54: =IF(SUMIFS(보유분석!$BF$2:$BF$801,보유분석!$AG$2:$AG$801,$A54,보유분석!$AC$2:$AC$801,1)=0,"",SUMIFS(보유분석!$BE$2:$BE$801,보유분석!$AG$2:$AG$801,$A54,보유분석!$AC$2:$AC$801,1)/SUMIFS(보유분석!$BF$2:$BF$801,보유분석!$AG$2:$AG$801,$A54,보유분석!$AC$2:$AC$801,1)) -> 3.1681975 | J54: =IF(SUMIFS(보유분석!$BG$2:$BG$801,보유분석!$AG$2:$AG$801,$A54,보유분석!$AC$2:$AC$801,1)=0,"",(SUMIFS(보유분석!$BC$2:$BC$801,보유분석!$AG$2:$AG$801,$A54,보유분석!$AC$2:$AC$801,1)+SUMIFS(보유분석!$BH$2:$BH$801,보유분석!$AG$2:$AG$801,$A54,보유분석!$AC$2:$AC$801,1))/SUMIFS(보유분석!$BG$2:$BG$801,보유분석!$AG$2:$AG$801,$A54,보유분석!$AC$2:$AC$801,1)) -> 20.44725 | K54: =IF(B54=0,"",SUMIFS(보유분석!$AV$2:$AV$801,보유분석!$AG$2:$AG$801,$A54,보유분석!$AC$2:$AC$801,1)/(B54*1000000)) -> 0.056546436 | L54: =SUMIFS(보유분석!$AP$2:$AP$801,보유분석!$AG$2:$AG$801,$A54,보유분석!$AC$2:$AC$801,1) -> -1303521.4 | M54: =COUNTIFS(보유분석!$AG$2:$AG$801,$A54,보유분석!$AR$2:$AR$801,"Cheap",보유분석!$AC$2:$AC$801,1) -> 0 | N54: =COUNTIFS(보유분석!$AG$2:$AG$801,$A54,보유분석!$AR$2:$AR$801,"Rich",보유분석!$AC$2:$AC$801,1) -> 0 | P54: =IF(O54="","",O54-C54) | Q54: =-SUMIFS(보유분석!$AZ$2:$AZ$801,보유분석!$AG$2:$AG$801,$A54,보유분석!$AC$2:$AC$801,1)*설정!$C$10 -> -167655.29 | R54: =IF((-SUMIFS(보유분석!$AZ$2:$AZ$801,보유분석!$AC$2:$AC$801,1)*설정!$C$10)=0,0,Q54/(-SUMIFS(보유분석!$AZ$2:$AZ$801,보유분석!$AC$2:$AC$801,1)*설정!$C$10)) -> 0.016473899 | S54: =IF(SUMIFS(보유분석!$BG$2:$BG$801,보유분석!$AG$2:$AG$801,$A54,보유분석!$AC$2:$AC$801,1)=0,"",SUMIFS(보유분석!$BH$2:$BH$801,보유분석!$AG$2:$AG$801,$A54,보유분석!$AC$2:$AC$801,1)/SUMIFS(보유분석!$BG$2:$BG$801,보유분석!$AG$2:$AG$801,$A54,보유분석!$AC$2:$AC$801,1)) -> 9.1427015 | T54: =IF(SUMIFS(보유분석!$BI$2:$BI$801,보유분석!$AG$2:$AG$801,$A54,보유분석!$AC$2:$AC$801,1)=0,"",SUMIFS(보유분석!$BD$2:$BD$801,보유분석!$AG$2:$AG$801,$A54,보유분석!$AC$2:$AC$801,1)/SUMIFS(보유분석!$BI$2:$BI$801,보유분석!$AG$2:$AG$801,$A54,보유분석!$AC$2:$AC$801,1)) -> 1
A55: 자유 소비재 | B55: =SUMIFS(보유분석!$AA$2:$AA$801,보유분석!$AG$2:$AG$801,$A55,보유분석!$AC$2:$AC$801,1) -> 350.96179 | C55: =IF(SUMIFS(보유분석!$AA$2:$AA$801,보유분석!$AC$2:$AC$801,1)=0,0,B55/SUMIFS(보유분석!$AA$2:$AA$801,보유분석!$AC$2:$AC$801,1)) -> 0.24901527 | D55: =SUMIFS(보유분석!$AM$2:$AM$801,보유분석!$AG$2:$AG$801,$A55,보유분석!$AC$2:$AC$801,1) -> 94583.082 | E55: =IF(SUMIFS(보유분석!$AM$2:$AM$801,보유분석!$AC$2:$AC$801,1)=0,0,D55/SUMIFS(보유분석!$AM$2:$AM$801,보유분석!$AC$2:$AC$801,1)) -> 0.24941272 | F55: =IF(SUMIFS(보유분석!$BB$2:$BB$801,보유분석!$AG$2:$AG$801,$A55,보유분석!$AC$2:$AC$801,1)=0,"",SUMIFS(보유분석!$BA$2:$BA$801,보유분석!$AG$2:$AG$801,$A55,보유분석!$AC$2:$AC$801,1)/SUMIFS(보유분석!$BB$2:$BB$801,보유분석!$AG$2:$AG$801,$A55,보유분석!$AC$2:$AC$801,1)) -> 5.7280541 | G55: =IF(F55="","",(F55-(SUMIFS(보유분석!$BA$2:$BA$801,보유분석!$AC$2:$AC$801,1)/SUMIFS(보유분석!$BB$2:$BB$801,보유분석!$AC$2:$AC$801,1)))*100) -> 6.8018245 | H55: =IF(SUMIFS(보유분석!$BD$2:$BD$801,보유분석!$AG$2:$AG$801,$A55,보유분석!$AC$2:$AC$801,1)=0,"",SUMIFS(보유분석!$BC$2:$BC$801,보유분석!$AG$2:$AG$801,$A55,보유분석!$AC$2:$AC$801,1)/SUMIFS(보유분석!$BD$2:$BD$801,보유분석!$AG$2:$AG$801,$A55,보유분석!$AC$2:$AC$801,1)) -> 72.936263 | I55: =IF(SUMIFS(보유분석!$BF$2:$BF$801,보유분석!$AG$2:$AG$801,$A55,보유분석!$AC$2:$AC$801,1)=0,"",SUMIFS(보유분석!$BE$2:$BE$801,보유분석!$AG$2:$AG$801,$A55,보유분석!$AC$2:$AC$801,1)/SUMIFS(보유분석!$BF$2:$BF$801,보유분석!$AG$2:$AG$801,$A55,보유분석!$AC$2:$AC$801,1)) -> 2.6949681 | J55: =IF(SUMIFS(보유분석!$BG$2:$BG$801,보유분석!$AG$2:$AG$801,$A55,보유분석!$AC$2:$AC$801,1)=0,"",(SUMIFS(보유분석!$BC$2:$BC$801,보유분석!$AG$2:$AG$801,$A55,보유분석!$AC$2:$AC$801,1)+SUMIFS(보유분석!$BH$2:$BH$801,보유분석!$AG$2:$AG$801,$A55,보유분석!$AC$2:$AC$801,1))/SUMIFS(보유분석!$BG$2:$BG$801,보유분석!$AG$2:$AG$801,$A55,보유분석!$AC$2:$AC$801,1)) -> 37.142222 | K55: =IF(B55=0,"",SUMIFS(보유분석!$AV$2:$AV$801,보유분석!$AG$2:$AG$801,$A55,보유분석!$AC$2:$AC$801,1)/(B55*1000000)) -> 0.059989184 | L55: =SUMIFS(보유분석!$AP$2:$AP$801,보유분석!$AG$2:$AG$801,$A55,보유분석!$AC$2:$AC$801,1) -> -12384412 | M55: =COUNTIFS(보유분석!$AG$2:$AG$801,$A55,보유분석!$AR$2:$AR$801,"Cheap",보유분석!$AC$2:$AC$801,1) -> 6 | N55: =COUNTIFS(보유분석!$AG$2:$AG$801,$A55,보유분석!$AR$2:$AR$801,"Rich",보유분석!$AC$2:$AC$801,1) -> 1 | P55: =IF(O55="","",O55-C55) | Q55: =-SUMIFS(보유분석!$AZ$2:$AZ$801,보유분석!$AG$2:$AG$801,$A55,보유분석!$AC$2:$AC$801,1)*설정!$C$10 -> -2784233.5 | R55: =IF((-SUMIFS(보유분석!$AZ$2:$AZ$801,보유분석!$AC$2:$AC$801,1)*설정!$C$10)=0,0,Q55/(-SUMIFS(보유분석!$AZ$2:$AZ$801,보유분석!$AC$2:$AC$801,1)*설정!$C$10)) -> 0.27358029 | S55: =IF(SUMIFS(보유분석!$BG$2:$BG$801,보유분석!$AG$2:$AG$801,$A55,보유분석!$AC$2:$AC$801,1)=0,"",SUMIFS(보유분석!$BH$2:$BH$801,보유분석!$AG$2:$AG$801,$A55,보유분석!$AC$2:$AC$801,1)/SUMIFS(보유분석!$BG$2:$BG$801,보유분석!$AG$2:$AG$801,$A55,보유분석!$AC$2:$AC$801,1)) -> 10.07901 | T55: =IF(SUMIFS(보유분석!$BI$2:$BI$801,보유분석!$AG$2:$AG$801,$A55,보유분석!$AC$2:$AC$801,1)=0,"",SUMIFS(보유분석!$BD$2:$BD$801,보유분석!$AG$2:$AG$801,$A55,보유분석!$AC$2:$AC$801,1)/SUMIFS(보유분석!$BI$2:$BI$801,보유분석!$AG$2:$AG$801,$A55,보유분석!$AC$2:$AC$801,1)) -> 0.99717143
A56: 정부 | B56: =SUMIFS(보유분석!$AA$2:$AA$801,보유분석!$AG$2:$AG$801,$A56,보유분석!$AC$2:$AC$801,1) -> 24.462366 | C56: =IF(SUMIFS(보유분석!$AA$2:$AA$801,보유분석!$AC$2:$AC$801,1)=0,0,B56/SUMIFS(보유분석!$AA$2:$AA$801,보유분석!$AC$2:$AC$801,1)) -> 0.017356598 | D56: =SUMIFS(보유분석!$AM$2:$AM$801,보유분석!$AG$2:$AG$801,$A56,보유분석!$AC$2:$AC$801,1) -> 17374.663 | E56: =IF(SUMIFS(보유분석!$AM$2:$AM$801,보유분석!$AC$2:$AC$801,1)=0,0,D56/SUMIFS(보유분석!$AM$2:$AM$801,보유분석!$AC$2:$AC$801,1)) -> 0.045816459 | F56: =IF(SUMIFS(보유분석!$BB$2:$BB$801,보유분석!$AG$2:$AG$801,$A56,보유분석!$AC$2:$AC$801,1)=0,"",SUMIFS(보유분석!$BA$2:$BA$801,보유분석!$AG$2:$AG$801,$A56,보유분석!$AC$2:$AC$801,1)/SUMIFS(보유분석!$BB$2:$BB$801,보유분석!$AG$2:$AG$801,$A56,보유분석!$AC$2:$AC$801,1)) -> 5.3048856 | G56: =IF(F56="","",(F56-(SUMIFS(보유분석!$BA$2:$BA$801,보유분석!$AC$2:$AC$801,1)/SUMIFS(보유분석!$BB$2:$BB$801,보유분석!$AC$2:$AC$801,1)))*100) -> -35.51502 | H56: =IF(SUMIFS(보유분석!$BD$2:$BD$801,보유분석!$AG$2:$AG$801,$A56,보유분석!$AC$2:$AC$801,1)=0,"",SUMIFS(보유분석!$BC$2:$BC$801,보유분석!$AG$2:$AG$801,$A56,보유분석!$AC$2:$AC$801,1)/SUMIFS(보유분석!$BD$2:$BD$801,보유분석!$AG$2:$AG$801,$A56,보유분석!$AC$2:$AC$801,1)) -> 34.465087 | I56: =IF(SUMIFS(보유분석!$BF$2:$BF$801,보유분석!$AG$2:$AG$801,$A56,보유분석!$AC$2:$AC$801,1)=0,"",SUMIFS(보유분석!$BE$2:$BE$801,보유분석!$AG$2:$AG$801,$A56,보유분석!$AC$2:$AC$801,1)/SUMIFS(보유분석!$BF$2:$BF$801,보유분석!$AG$2:$AG$801,$A56,보유분석!$AC$2:$AC$801,1)) -> 7.1026093 | J56: =IF(SUMIFS(보유분석!$BG$2:$BG$801,보유분석!$AG$2:$AG$801,$A56,보유분석!$AC$2:$AC$801,1)=0,"",(SUMIFS(보유분석!$BC$2:$BC$801,보유분석!$AG$2:$AG$801,$A56,보유분석!$AC$2:$AC$801,1)+SUMIFS(보유분석!$BH$2:$BH$801,보유분석!$AG$2:$AG$801,$A56,보유분석!$AC$2:$AC$801,1))/SUMIFS(보유분석!$BG$2:$BG$801,보유분석!$AG$2:$AG$801,$A56,보유분석!$AC$2:$AC$801,1)) -> 5.9464853 | K56: =IF(B56=0,"",SUMIFS(보유분석!$AV$2:$AV$801,보유분석!$AG$2:$AG$801,$A56,보유분석!$AC$2:$AC$801,1)/(B56*1000000)) -> 0.053537069 | L56: =SUMIFS(보유분석!$AP$2:$AP$801,보유분석!$AG$2:$AG$801,$A56,보유분석!$AC$2:$AC$801,1) -> -1966685.2 | M56: =COUNTIFS(보유분석!$AG$2:$AG$801,$A56,보유분석!$AR$2:$AR$801,"Cheap",보유분석!$AC$2:$AC$801,1) -> 0 | N56: =COUNTIFS(보유분석!$AG$2:$AG$801,$A56,보유분석!$AR$2:$AR$801,"Rich",보유분석!$AC$2:$AC$801,1) -> 2 | P56: =IF(O56="","",O56-C56) | Q56: =-SUMIFS(보유분석!$AZ$2:$AZ$801,보유분석!$AG$2:$AG$801,$A56,보유분석!$AC$2:$AC$801,1)*설정!$C$10 -> -138590.88 | R56: =IF((-SUMIFS(보유분석!$AZ$2:$AZ$801,보유분석!$AC$2:$AC$801,1)*설정!$C$10)=0,0,Q56/(-SUMIFS(보유분석!$AZ$2:$AZ$801,보유분석!$AC$2:$AC$801,1)*설정!$C$10)) -> 0.013618014 | S56: =IF(SUMIFS(보유분석!$BG$2:$BG$801,보유분석!$AG$2:$AG$801,$A56,보유분석!$AC$2:$AC$801,1)=0,"",SUMIFS(보유분석!$BH$2:$BH$801,보유분석!$AG$2:$AG$801,$A56,보유분석!$AC$2:$AC$801,1)/SUMIFS(보유분석!$BG$2:$BG$801,보유분석!$AG$2:$AG$801,$A56,보유분석!$AC$2:$AC$801,1)) -> 1.8693751 | T56: =IF(SUMIFS(보유분석!$BI$2:$BI$801,보유분석!$AG$2:$AG$801,$A56,보유분석!$AC$2:$AC$801,1)=0,"",SUMIFS(보유분석!$BD$2:$BD$801,보유분석!$AG$2:$AG$801,$A56,보유분석!$AC$2:$AC$801,1)/SUMIFS(보유분석!$BI$2:$BI$801,보유분석!$AG$2:$AG$801,$A56,보유분석!$AC$2:$AC$801,1)) -> 1
A57: 통신 | B57: =SUMIFS(보유분석!$AA$2:$AA$801,보유분석!$AG$2:$AG$801,$A57,보유분석!$AC$2:$AC$801,1) -> 7.196521 | C57: =IF(SUMIFS(보유분석!$AA$2:$AA$801,보유분석!$AC$2:$AC$801,1)=0,0,B57/SUMIFS(보유분석!$AA$2:$AA$801,보유분석!$AC$2:$AC$801,1)) -> 0.0051060933 | D57: =SUMIFS(보유분석!$AM$2:$AM$801,보유분석!$AG$2:$AG$801,$A57,보유분석!$AC$2:$AC$801,1) -> 2748.957 | E57: =IF(SUMIFS(보유분석!$AM$2:$AM$801,보유분석!$AC$2:$AC$801,1)=0,0,D57/SUMIFS(보유분석!$AM$2:$AM$801,보유분석!$AC$2:$AC$801,1)) -> 0.0072489161 | F57: =IF(SUMIFS(보유분석!$BB$2:$BB$801,보유분석!$AG$2:$AG$801,$A57,보유분석!$AC$2:$AC$801,1)=0,"",SUMIFS(보유분석!$BA$2:$BA$801,보유분석!$AG$2:$AG$801,$A57,보유분석!$AC$2:$AC$801,1)/SUMIFS(보유분석!$BB$2:$BB$801,보유분석!$AG$2:$AG$801,$A57,보유분석!$AC$2:$AC$801,1)) -> 6.2290632 | G57: =IF(F57="","",(F57-(SUMIFS(보유분석!$BA$2:$BA$801,보유분석!$AC$2:$AC$801,1)/SUMIFS(보유분석!$BB$2:$BB$801,보유분석!$AC$2:$AC$801,1)))*100) -> 56.902734 | H57: =IF(SUMIFS(보유분석!$BD$2:$BD$801,보유분석!$AG$2:$AG$801,$A57,보유분석!$AC$2:$AC$801,1)=0,"",SUMIFS(보유분석!$BC$2:$BC$801,보유분석!$AG$2:$AG$801,$A57,보유분석!$AC$2:$AC$801,1)/SUMIFS(보유분석!$BD$2:$BD$801,보유분석!$AG$2:$AG$801,$A57,보유분석!$AC$2:$AC$801,1)) -> 117.33717 | I57: =IF(SUMIFS(보유분석!$BF$2:$BF$801,보유분석!$AG$2:$AG$801,$A57,보유분석!$AC$2:$AC$801,1)=0,"",SUMIFS(보유분석!$BE$2:$BE$801,보유분석!$AG$2:$AG$801,$A57,보유분석!$AC$2:$AC$801,1)/SUMIFS(보유분석!$BF$2:$BF$801,보유분석!$AG$2:$AG$801,$A57,보유분석!$AC$2:$AC$801,1)) -> 3.8198416 | J57: =IF(SUMIFS(보유분석!$BG$2:$BG$801,보유분석!$AG$2:$AG$801,$A57,보유분석!$AC$2:$AC$801,1)=0,"",(SUMIFS(보유분석!$BC$2:$BC$801,보유분석!$AG$2:$AG$801,$A57,보유분석!$AC$2:$AC$801,1)+SUMIFS(보유분석!$BH$2:$BH$801,보유분석!$AG$2:$AG$801,$A57,보유분석!$AC$2:$AC$801,1))/SUMIFS(보유분석!$BG$2:$BG$801,보유분석!$AG$2:$AG$801,$A57,보유분석!$AC$2:$AC$801,1)) -> 37.333681 | K57: =IF(B57=0,"",SUMIFS(보유분석!$AV$2:$AV$801,보유분석!$AG$2:$AG$801,$A57,보유분석!$AC$2:$AC$801,1)/(B57*1000000)) -> 0.064817789 | L57: =SUMIFS(보유분석!$AP$2:$AP$801,보유분석!$AG$2:$AG$801,$A57,보유분석!$AC$2:$AC$801,1) -> -366316 | M57: =COUNTIFS(보유분석!$AG$2:$AG$801,$A57,보유분석!$AR$2:$AR$801,"Cheap",보유분석!$AC$2:$AC$801,1) -> 1 | N57: =COUNTIFS(보유분석!$AG$2:$AG$801,$A57,보유분석!$AR$2:$AR$801,"Rich",보유분석!$AC$2:$AC$801,1) -> 1 | P57: =IF(O57="","",O57-C57) | Q57: =-SUMIFS(보유분석!$AZ$2:$AZ$801,보유분석!$AG$2:$AG$801,$A57,보유분석!$AC$2:$AC$801,1)*설정!$C$10 -> -125444.18 | R57: =IF((-SUMIFS(보유분석!$AZ$2:$AZ$801,보유분석!$AC$2:$AC$801,1)*설정!$C$10)=0,0,Q57/(-SUMIFS(보유분석!$AZ$2:$AZ$801,보유분석!$AC$2:$AC$801,1)*설정!$C$10)) -> 0.012326213 | S57: =IF(SUMIFS(보유분석!$BG$2:$BG$801,보유분석!$AG$2:$AG$801,$A57,보유분석!$AC$2:$AC$801,1)=0,"",SUMIFS(보유분석!$BH$2:$BH$801,보유분석!$AG$2:$AG$801,$A57,보유분석!$AC$2:$AC$801,1)/SUMIFS(보유분석!$BG$2:$BG$801,보유분석!$AG$2:$AG$801,$A57,보유분석!$AC$2:$AC$801,1)) -> 6.6158705 | T57: =IF(SUMIFS(보유분석!$BI$2:$BI$801,보유분석!$AG$2:$AG$801,$A57,보유분석!$AC$2:$AC$801,1)=0,"",SUMIFS(보유분석!$BD$2:$BD$801,보유분석!$AG$2:$AG$801,$A57,보유분석!$AC$2:$AC$801,1)/SUMIFS(보유분석!$BI$2:$BI$801,보유분석!$AG$2:$AG$801,$A57,보유분석!$AC$2:$AC$801,1)) -> 1
A58: 기타(목록외) | B58: =SUMPRODUCT(ISNA(MATCH(보유분석!$AG$2:$AG$801,$A$48:$A$57,0))*(보유분석!$AC$2:$AC$801=1)*보유분석!$AA$2:$AA$801) -> 0 | C58: =IF(SUMIFS(보유분석!$AA$2:$AA$801,보유분석!$AC$2:$AC$801,1)=0,0,B58/SUMIFS(보유분석!$AA$2:$AA$801,보유분석!$AC$2:$AC$801,1)) -> 0 | D58: =SUMPRODUCT(ISNA(MATCH(보유분석!$AG$2:$AG$801,$A$48:$A$57,0))*(보유분석!$AC$2:$AC$801=1)*보유분석!$AM$2:$AM$801) -> 0 | E58: =IF(SUMIFS(보유분석!$AM$2:$AM$801,보유분석!$AC$2:$AC$801,1)=0,0,D58/SUMIFS(보유분석!$AM$2:$AM$801,보유분석!$AC$2:$AC$801,1)) -> 0 | F58: =IF(SUMPRODUCT(ISNA(MATCH(보유분석!$AG$2:$AG$801,$A$48:$A$57,0))*(보유분석!$AC$2:$AC$801=1)*보유분석!$BB$2:$BB$801)=0,"",SUMPRODUCT(ISNA(MATCH(보유분석!$AG$2:$AG$801,$A$48:$A$57,0))*(보유분석!$AC$2:$AC$801=1)*보유분석!$BA$2:$BA$801)/SUMPRODUCT(ISNA(MATCH(보유분석!$AG$2:$AG$801,$A$48:$A$57,0))*(보유분석!$AC$2:$AC$801=1)*보유분석!$BB$2:$BB$801)) | G58: =IF(F58="","",(F58-(SUMIFS(보유분석!$BA$2:$BA$801,보유분석!$AC$2:$AC$801,1)/SUMIFS(보유분석!$BB$2:$BB$801,보유분석!$AC$2:$AC$801,1)))*100) | H58: =IF(SUMPRODUCT(ISNA(MATCH(보유분석!$AG$2:$AG$801,$A$48:$A$57,0))*(보유분석!$AC$2:$AC$801=1)*보유분석!$BD$2:$BD$801)=0,"",SUMPRODUCT(ISNA(MATCH(보유분석!$AG$2:$AG$801,$A$48:$A$57,0))*(보유분석!$AC$2:$AC$801=1)*보유분석!$BC$2:$BC$801)/SUMPRODUCT(ISNA(MATCH(보유분석!$AG$2:$AG$801,$A$48:$A$57,0))*(보유분석!$AC$2:$AC$801=1)*보유분석!$BD$2:$BD$801)) | I58: =IF(SUMPRODUCT(ISNA(MATCH(보유분석!$AG$2:$AG$801,$A$48:$A$57,0))*(보유분석!$AC$2:$AC$801=1)*보유분석!$BF$2:$BF$801)=0,"",SUMPRODUCT(ISNA(MATCH(보유분석!$AG$2:$AG$801,$A$48:$A$57,0))*(보유분석!$AC$2:$AC$801=1)*보유분석!$BE$2:$BE$801)/SUMPRODUCT(ISNA(MATCH(보유분석!$AG$2:$AG$801,$A$48:$A$57,0))*(보유분석!$AC$2:$AC$801=1)*보유분석!$BF$2:$BF$801)) | J58: =IF(SUMPRODUCT(ISNA(MATCH(보유분석!$AG$2:$AG$801,$A$48:$A$57,0))*(보유분석!$AC$2:$AC$801=1)*보유분석!$BG$2:$BG$801)=0,"",(SUMPRODUCT(ISNA(MATCH(보유분석!$AG$2:$AG$801,$A$48:$A$57,0))*(보유분석!$AC$2:$AC$801=1)*보유분석!$BC$2:$BC$801)+SUMPRODUCT(ISNA(MATCH(보유분석!$AG$2:$AG$801,$A$48:$A$57,0))*(보유분석!$AC$2:$AC$801=1)*보유분석!$BH$2:$BH$801))/SUMPRODUCT(ISNA(MATCH(보유분석!$AG$2:$AG$801,$A$48:$A$57,0))*(보유분석!$AC$2:$AC$801=1)*보유분석!$BG$2:$BG$801)) | K58: =IF(B58=0,"",SUMPRODUCT(ISNA(MATCH(보유분석!$AG$2:$AG$801,$A$48:$A$57,0))*(보유분석!$AC$2:$AC$801=1)*보유분석!$AV$2:$AV$801)/(B58*1000000)) | L58: =SUMPRODUCT(ISNA(MATCH(보유분석!$AG$2:$AG$801,$A$48:$A$57,0))*(보유분석!$AC$2:$AC$801=1)*보유분석!$AP$2:$AP$801) -> 0 | M58: =SUMPRODUCT(ISNA(MATCH(보유분석!$AG$2:$AG$801,$A$48:$A$57,0))*(보유분석!$AC$2:$AC$801=1)*(보유분석!$AR$2:$AR$801="Cheap")) -> 0 | N58: =SUMPRODUCT(ISNA(MATCH(보유분석!$AG$2:$AG$801,$A$48:$A$57,0))*(보유분석!$AC$2:$AC$801=1)*(보유분석!$AR$2:$AR$801="Rich")) -> 0 | P58: =IF(O58="","",O58-C58) | Q58: =-SUMPRODUCT(ISNA(MATCH(보유분석!$AG$2:$AG$801,$A$48:$A$57,0))*(보유분석!$AC$2:$AC$801=1)*보유분석!$AZ$2:$AZ$801)*설정!$C$10 -> 0 | R58: =IF((-SUMIFS(보유분석!$AZ$2:$AZ$801,보유분석!$AC$2:$AC$801,1)*설정!$C$10)=0,0,Q58/(-SUMIFS(보유분석!$AZ$2:$AZ$801,보유분석!$AC$2:$AC$801,1)*설정!$C$10)) -> 0 | S58: =IF(SUMPRODUCT(ISNA(MATCH(보유분석!$AG$2:$AG$801,$A$48:$A$57,0))*(보유분석!$AC$2:$AC$801=1)*보유분석!$BG$2:$BG$801)=0,"",SUMPRODUCT(ISNA(MATCH(보유분석!$AG$2:$AG$801,$A$48:$A$57,0))*(보유분석!$AC$2:$AC$801=1)*보유분석!$BH$2:$BH$801)/SUMPRODUCT(ISNA(MATCH(보유분석!$AG$2:$AG$801,$A$48:$A$57,0))*(보유분석!$AC$2:$AC$801=1)*보유분석!$BG$2:$BG$801)) | T58: =IF(SUMPRODUCT(ISNA(MATCH(보유분석!$AG$2:$AG$801,$A$48:$A$57,0))*(보유분석!$AC$2:$AC$801=1)*보유분석!$BI$2:$BI$801)=0,"",SUMPRODUCT(ISNA(MATCH(보유분석!$AG$2:$AG$801,$A$48:$A$57,0))*(보유분석!$AC$2:$AC$801=1)*보유분석!$BD$2:$BD$801)/SUMPRODUCT(ISNA(MATCH(보유분석!$AG$2:$AG$801,$A$48:$A$57,0))*(보유분석!$AC$2:$AC$801=1)*보유분석!$BI$2:$BI$801))
A59: 합계 | B59: =SUM(B48:B58) -> 1409.3986 | C59: =SUM(C48:C58) -> 1 | D59: =SUM(D48:D58) -> 379223.18 | E59: =SUM(E48:E58) -> 1 | F59: =IF(SUMIFS(보유분석!$BB$2:$BB$801,보유분석!$AC$2:$AC$801,1)=0,"",SUMIFS(보유분석!$BA$2:$BA$801,보유분석!$AC$2:$AC$801,1)/SUMIFS(보유분석!$BB$2:$BB$801,보유분석!$AC$2:$AC$801,1)) -> 5.6600358 | H59: =IF(SUMIFS(보유분석!$BD$2:$BD$801,보유분석!$AC$2:$AC$801,1)=0,"",SUMIFS(보유분석!$BC$2:$BC$801,보유분석!$AC$2:$AC$801,1)/SUMIFS(보유분석!$BD$2:$BD$801,보유분석!$AC$2:$AC$801,1)) -> 66.114006 | I59: =IF(SUMIFS(보유분석!$BF$2:$BF$801,보유분석!$AC$2:$AC$801,1)=0,"",SUMIFS(보유분석!$BE$2:$BE$801,보유분석!$AC$2:$AC$801,1)/SUMIFS(보유분석!$BF$2:$BF$801,보유분석!$AC$2:$AC$801,1)) -> 2.6906736 | J59: =IF(SUMIFS(보유분석!$BG$2:$BG$801,보유분석!$AC$2:$AC$801,1)=0,"",(SUMIFS(보유분석!$BC$2:$BC$801,보유분석!$AC$2:$AC$801,1)+SUMIFS(보유분석!$BH$2:$BH$801,보유분석!$AC$2:$AC$801,1))/SUMIFS(보유분석!$BG$2:$BG$801,보유분석!$AC$2:$AC$801,1)) -> 31.468574 | K59: =IF(B59=0,"",SUMIFS(보유분석!$AV$2:$AV$801,보유분석!$AC$2:$AC$801,1)/(B59*1000000)) -> 0.058254622 | L59: =SUM(L48:L58) -> -44901234 | O59: =IF(COUNT(O48:O58)=0,"",SUM(O48:O58)) | Q59: =SUM(Q48:Q58) -> -10177025 | R59: =SUM(R48:R58) -> 1 | S59: =IF(SUMIFS(보유분석!$BG$2:$BG$801,보유분석!$AC$2:$AC$801,1)=0,"",SUMIFS(보유분석!$BH$2:$BH$801,보유분석!$AC$2:$AC$801,1)/SUMIFS(보유분석!$BG$2:$BG$801,보유분석!$AC$2:$AC$801,1)) -> 6.4728238 | T59: =IF(SUMIFS(보유분석!$BI$2:$BI$801,보유분석!$AC$2:$AC$801,1)=0,"",SUMIFS(보유분석!$BD$2:$BD$801,보유분석!$AC$2:$AC$801,1)/SUMIFS(보유분석!$BI$2:$BI$801,보유분석!$AC$2:$AC$801,1)) -> 0.97796717
A62: ■ 등급군 (S&P→Fitch→Moody's)
A63: 구분 | B63: 평가금액($M) | C63: 비중 | D63: DV01($/bp) | E63: DV01비중 | F63: 가중YTM(%) | G63: 포트대비(bp) | H63: 가중G-spread(bp) | I63: 가중듀레이션 | J63: 손익분기 확대폭(bp) 스프레드+롤다운 | K63: 1Y기대수익률(%) | L63: 평가손익($) | M63: Cheap 보유수 | N63: Rich 보유수 | O63: 목표비중(입력) | P63: 갭(목표-현재) | Q63: 스프레드쇼크 손실($) | R63: 손실비중 | S63: └ 롤다운 기여(bp) | T63: G-spread 커버리지
A64: AA이상 | B64: =SUMIFS(보유분석!$AA$2:$AA$801,보유분석!$AK$2:$AK$801,$A64,보유분석!$AC$2:$AC$801,1) -> 72.178661 | C64: =IF(SUMIFS(보유분석!$AA$2:$AA$801,보유분석!$AC$2:$AC$801,1)=0,0,B64/SUMIFS(보유분석!$AA$2:$AA$801,보유분석!$AC$2:$AC$801,1)) -> 0.051212381 | D64: =SUMIFS(보유분석!$AM$2:$AM$801,보유분석!$AK$2:$AK$801,$A64,보유분석!$AC$2:$AC$801,1) -> 29498.355 | E64: =IF(SUMIFS(보유분석!$AM$2:$AM$801,보유분석!$AC$2:$AC$801,1)=0,0,D64/SUMIFS(보유분석!$AM$2:$AM$801,보유분석!$AC$2:$AC$801,1)) -> 0.077786267 | F64: =IF(SUMIFS(보유분석!$BB$2:$BB$801,보유분석!$AK$2:$AK$801,$A64,보유분석!$AC$2:$AC$801,1)=0,"",SUMIFS(보유분석!$BA$2:$BA$801,보유분석!$AK$2:$AK$801,$A64,보유분석!$AC$2:$AC$801,1)/SUMIFS(보유분석!$BB$2:$BB$801,보유분석!$AK$2:$AK$801,$A64,보유분석!$AC$2:$AC$801,1)) -> 5.2930239 | G64: =IF(F64="","",(F64-(SUMIFS(보유분석!$BA$2:$BA$801,보유분석!$AC$2:$AC$801,1)/SUMIFS(보유분석!$BB$2:$BB$801,보유분석!$AC$2:$AC$801,1)))*100) -> -36.701191 | H64: =IF(SUMIFS(보유분석!$BD$2:$BD$801,보유분석!$AK$2:$AK$801,$A64,보유분석!$AC$2:$AC$801,1)=0,"",SUMIFS(보유분석!$BC$2:$BC$801,보유분석!$AK$2:$AK$801,$A64,보유분석!$AC$2:$AC$801,1)/SUMIFS(보유분석!$BD$2:$BD$801,보유분석!$AK$2:$AK$801,$A64,보유분석!$AC$2:$AC$801,1)) -> 35.899427 | I64: =IF(SUMIFS(보유분석!$BF$2:$BF$801,보유분석!$AK$2:$AK$801,$A64,보유분석!$AC$2:$AC$801,1)=0,"",SUMIFS(보유분석!$BE$2:$BE$801,보유분석!$AK$2:$AK$801,$A64,보유분석!$AC$2:$AC$801,1)/SUMIFS(보유분석!$BF$2:$BF$801,보유분석!$AK$2:$AK$801,$A64,보유분석!$AC$2:$AC$801,1)) -> 4.0868527 | J64: =IF(SUMIFS(보유분석!$BG$2:$BG$801,보유분석!$AK$2:$AK$801,$A64,보유분석!$AC$2:$AC$801,1)=0,"",(SUMIFS(보유분석!$BC$2:$BC$801,보유분석!$AK$2:$AK$801,$A64,보유분석!$AC$2:$AC$801,1)+SUMIFS(보유분석!$BH$2:$BH$801,보유분석!$AK$2:$AK$801,$A64,보유분석!$AC$2:$AC$801,1))/SUMIFS(보유분석!$BG$2:$BG$801,보유분석!$AK$2:$AK$801,$A64,보유분석!$AC$2:$AC$801,1)) -> 15.302751 | K64: =IF(B64=0,"",SUMIFS(보유분석!$AV$2:$AV$801,보유분석!$AK$2:$AK$801,$A64,보유분석!$AC$2:$AC$801,1)/(B64*1000000)) -> 0.054605079 | L64: =SUMIFS(보유분석!$AP$2:$AP$801,보유분석!$AK$2:$AK$801,$A64,보유분석!$AC$2:$AC$801,1) -> -3360910.6 | M64: =COUNTIFS(보유분석!$AK$2:$AK$801,$A64,보유분석!$AR$2:$AR$801,"Cheap",보유분석!$AC$2:$AC$801,1) -> 0 | N64: =COUNTIFS(보유분석!$AK$2:$AK$801,$A64,보유분석!$AR$2:$AR$801,"Rich",보유분석!$AC$2:$AC$801,1) -> 3 | P64: =IF(O64="","",O64-C64) | Q64: =-SUMIFS(보유분석!$AZ$2:$AZ$801,보유분석!$AK$2:$AK$801,$A64,보유분석!$AC$2:$AC$801,1)*설정!$C$10 -> -328627.26 | R64: =IF((-SUMIFS(보유분석!$AZ$2:$AZ$801,보유분석!$AC$2:$AC$801,1)*설정!$C$10)=0,0,Q64/(-SUMIFS(보유분석!$AZ$2:$AZ$801,보유분석!$AC$2:$AC$801,1)*설정!$C$10)) -> 0.032291091 | S64: =IF(SUMIFS(보유분석!$BG$2:$BG$801,보유분석!$AK$2:$AK$801,$A64,보유분석!$AC$2:$AC$801,1)=0,"",SUMIFS(보유분석!$BH$2:$BH$801,보유분석!$AK$2:$AK$801,$A64,보유분석!$AC$2:$AC$801,1)/SUMIFS(보유분석!$BG$2:$BG$801,보유분석!$AK$2:$AK$801,$A64,보유분석!$AC$2:$AC$801,1)) -> 6.5315217 | T64: =IF(SUMIFS(보유분석!$BI$2:$BI$801,보유분석!$AK$2:$AK$801,$A64,보유분석!$AC$2:$AC$801,1)=0,"",SUMIFS(보유분석!$BD$2:$BD$801,보유분석!$AK$2:$AK$801,$A64,보유분석!$AC$2:$AC$801,1)/SUMIFS(보유분석!$BI$2:$BI$801,보유분석!$AK$2:$AK$801,$A64,보유분석!$AC$2:$AC$801,1)) -> 0.81812662
A65: A | B65: =SUMIFS(보유분석!$AA$2:$AA$801,보유분석!$AK$2:$AK$801,$A65,보유분석!$AC$2:$AC$801,1) -> 604.66357 | C65: =IF(SUMIFS(보유분석!$AA$2:$AA$801,보유분석!$AC$2:$AC$801,1)=0,0,B65/SUMIFS(보유분석!$AA$2:$AA$801,보유분석!$AC$2:$AC$801,1)) -> 0.42902239 | D65: =SUMIFS(보유분석!$AM$2:$AM$801,보유분석!$AK$2:$AK$801,$A65,보유분석!$AC$2:$AC$801,1) -> 173848.74 | E65: =IF(SUMIFS(보유분석!$AM$2:$AM$801,보유분석!$AC$2:$AC$801,1)=0,0,D65/SUMIFS(보유분석!$AM$2:$AM$801,보유분석!$AC$2:$AC$801,1)) -> 0.45843386 | F65: =IF(SUMIFS(보유분석!$BB$2:$BB$801,보유분석!$AK$2:$AK$801,$A65,보유분석!$AC$2:$AC$801,1)=0,"",SUMIFS(보유분석!$BA$2:$BA$801,보유분석!$AK$2:$AK$801,$A65,보유분석!$AC$2:$AC$801,1)/SUMIFS(보유분석!$BB$2:$BB$801,보유분석!$AK$2:$AK$801,$A65,보유분석!$AC$2:$AC$801,1)) -> 5.6626624 | G65: =IF(F65="","",(F65-(SUMIFS(보유분석!$BA$2:$BA$801,보유분석!$AC$2:$AC$801,1)/SUMIFS(보유분석!$BB$2:$BB$801,보유분석!$AC$2:$AC$801,1)))*100) -> 0.26265849 | H65: =IF(SUMIFS(보유분석!$BD$2:$BD$801,보유분석!$AK$2:$AK$801,$A65,보유분석!$AC$2:$AC$801,1)=0,"",SUMIFS(보유분석!$BC$2:$BC$801,보유분석!$AK$2:$AK$801,$A65,보유분석!$AC$2:$AC$801,1)/SUMIFS(보유분석!$BD$2:$BD$801,보유분석!$AK$2:$AK$801,$A65,보유분석!$AC$2:$AC$801,1)) -> 66.275607 | I65: =IF(SUMIFS(보유분석!$BF$2:$BF$801,보유분석!$AK$2:$AK$801,$A65,보유분석!$AC$2:$AC$801,1)=0,"",SUMIFS(보유분석!$BE$2:$BE$801,보유분석!$AK$2:$AK$801,$A65,보유분석!$AC$2:$AC$801,1)/SUMIFS(보유분석!$BF$2:$BF$801,보유분석!$AK$2:$AK$801,$A65,보유분석!$AC$2:$AC$801,1)) -> 2.8751318 | J65: =IF(SUMIFS(보유분석!$BG$2:$BG$801,보유분석!$AK$2:$AK$801,$A65,보유분석!$AC$2:$AC$801,1)=0,"",(SUMIFS(보유분석!$BC$2:$BC$801,보유분석!$AK$2:$AK$801,$A65,보유분석!$AC$2:$AC$801,1)+SUMIFS(보유분석!$BH$2:$BH$801,보유분석!$AK$2:$AK$801,$A65,보유분석!$AC$2:$AC$801,1))/SUMIFS(보유분석!$BG$2:$BG$801,보유분석!$AK$2:$AK$801,$A65,보유분석!$AC$2:$AC$801,1)) -> 30.122928 | K65: =IF(B65=0,"",SUMIFS(보유분석!$AV$2:$AV$801,보유분석!$AK$2:$AK$801,$A65,보유분석!$AC$2:$AC$801,1)/(B65*1000000)) -> 0.058486209 | L65: =SUMIFS(보유분석!$AP$2:$AP$801,보유분석!$AK$2:$AK$801,$A65,보유분석!$AC$2:$AC$801,1) -> -20623335 | M65: =COUNTIFS(보유분석!$AK$2:$AK$801,$A65,보유분석!$AR$2:$AR$801,"Cheap",보유분석!$AC$2:$AC$801,1) -> 10 | N65: =COUNTIFS(보유분석!$AK$2:$AK$801,$A65,보유분석!$AR$2:$AR$801,"Rich",보유분석!$AC$2:$AC$801,1) -> 7 | P65: =IF(O65="","",O65-C65) | Q65: =-SUMIFS(보유분석!$AZ$2:$AZ$801,보유분석!$AK$2:$AK$801,$A65,보유분석!$AC$2:$AC$801,1)*설정!$C$10 -> -4586836.9 | R65: =IF((-SUMIFS(보유분석!$AZ$2:$AZ$801,보유분석!$AC$2:$AC$801,1)*설정!$C$10)=0,0,Q65/(-SUMIFS(보유분석!$AZ$2:$AZ$801,보유분석!$AC$2:$AC$801,1)*설정!$C$10)) -> 0.45070507 | S65: =IF(SUMIFS(보유분석!$BG$2:$BG$801,보유분석!$AK$2:$AK$801,$A65,보유분석!$AC$2:$AC$801,1)=0,"",SUMIFS(보유분석!$BH$2:$BH$801,보유분석!$AK$2:$AK$801,$A65,보유분석!$AC$2:$AC$801,1)/SUMIFS(보유분석!$BG$2:$BG$801,보유분석!$AK$2:$AK$801,$A65,보유분석!$AC$2:$AC$801,1)) -> 6.7789809 | T65: =IF(SUMIFS(보유분석!$BI$2:$BI$801,보유분석!$AK$2:$AK$801,$A65,보유분석!$AC$2:$AC$801,1)=0,"",SUMIFS(보유분석!$BD$2:$BD$801,보유분석!$AK$2:$AK$801,$A65,보유분석!$AC$2:$AC$801,1)/SUMIFS(보유분석!$BI$2:$BI$801,보유분석!$AK$2:$AK$801,$A65,보유분석!$AC$2:$AC$801,1)) -> 0.96621151
A66: BBB | B66: =SUMIFS(보유분석!$AA$2:$AA$801,보유분석!$AK$2:$AK$801,$A66,보유분석!$AC$2:$AC$801,1) -> 609.78364 | C66: =IF(SUMIFS(보유분석!$AA$2:$AA$801,보유분석!$AC$2:$AC$801,1)=0,0,B66/SUMIFS(보유분석!$AA$2:$AA$801,보유분석!$AC$2:$AC$801,1)) -> 0.43265519 | D66: =SUMIFS(보유분석!$AM$2:$AM$801,보유분석!$AK$2:$AK$801,$A66,보유분석!$AC$2:$AC$801,1) -> 149212.22 | E66: =IF(SUMIFS(보유분석!$AM$2:$AM$801,보유분석!$AC$2:$AC$801,1)=0,0,D66/SUMIFS(보유분석!$AM$2:$AM$801,보유분석!$AC$2:$AC$801,1)) -> 0.3934681 | F66: =IF(SUMIFS(보유분석!$BB$2:$BB$801,보유분석!$AK$2:$AK$801,$A66,보유분석!$AC$2:$AC$801,1)=0,"",SUMIFS(보유분석!$BA$2:$BA$801,보유분석!$AK$2:$AK$801,$A66,보유분석!$AC$2:$AC$801,1)/SUMIFS(보유분석!$BB$2:$BB$801,보유분석!$AK$2:$AK$801,$A66,보유분석!$AC$2:$AC$801,1)) -> 5.7081561 | G66: =IF(F66="","",(F66-(SUMIFS(보유분석!$BA$2:$BA$801,보유분석!$AC$2:$AC$801,1)/SUMIFS(보유분석!$BB$2:$BB$801,보유분석!$AC$2:$AC$801,1)))*100) -> 4.812027 | H66: =IF(SUMIFS(보유분석!$BD$2:$BD$801,보유분석!$AK$2:$AK$801,$A66,보유분석!$AC$2:$AC$801,1)=0,"",SUMIFS(보유분석!$BC$2:$BC$801,보유분석!$AK$2:$AK$801,$A66,보유분석!$AC$2:$AC$801,1)/SUMIFS(보유분석!$BD$2:$BD$801,보유분석!$AK$2:$AK$801,$A66,보유분석!$AC$2:$AC$801,1)) -> 68.872385 | I66: =IF(SUMIFS(보유분석!$BF$2:$BF$801,보유분석!$AK$2:$AK$801,$A66,보유분석!$AC$2:$AC$801,1)=0,"",SUMIFS(보유분석!$BE$2:$BE$801,보유분석!$AK$2:$AK$801,$A66,보유분석!$AC$2:$AC$801,1)/SUMIFS(보유분석!$BF$2:$BF$801,보유분석!$AK$2:$AK$801,$A66,보유분석!$AC$2:$AC$801,1)) -> 2.4469699 | J66: =IF(SUMIFS(보유분석!$BG$2:$BG$801,보유분석!$AK$2:$AK$801,$A66,보유분석!$AC$2:$AC$801,1)=0,"",(SUMIFS(보유분석!$BC$2:$BC$801,보유분석!$AK$2:$AK$801,$A66,보유분석!$AC$2:$AC$801,1)+SUMIFS(보유분석!$BH$2:$BH$801,보유분석!$AK$2:$AK$801,$A66,보유분석!$AC$2:$AC$801,1))/SUMIFS(보유분석!$BG$2:$BG$801,보유분석!$AK$2:$AK$801,$A66,보유분석!$AC$2:$AC$801,1)) -> 34.745956 | K66: =IF(B66=0,"",SUMIFS(보유분석!$AV$2:$AV$801,보유분석!$AK$2:$AK$801,$A66,보유분석!$AC$2:$AC$801,1)/(B66*1000000)) -> 0.058696553 | L66: =SUMIFS(보유분석!$AP$2:$AP$801,보유분석!$AK$2:$AK$801,$A66,보유분석!$AC$2:$AC$801,1) -> -17525152 | M66: =COUNTIFS(보유분석!$AK$2:$AK$801,$A66,보유분석!$AR$2:$AR$801,"Cheap",보유분석!$AC$2:$AC$801,1) -> 26 | N66: =COUNTIFS(보유분석!$AK$2:$AK$801,$A66,보유분석!$AR$2:$AR$801,"Rich",보유분석!$AC$2:$AC$801,1) -> 0 | P66: =IF(O66="","",O66-C66) | Q66: =-SUMIFS(보유분석!$AZ$2:$AZ$801,보유분석!$AK$2:$AK$801,$A66,보유분석!$AC$2:$AC$801,1)*설정!$C$10 -> -4637731.8 | R66: =IF((-SUMIFS(보유분석!$AZ$2:$AZ$801,보유분석!$AC$2:$AC$801,1)*설정!$C$10)=0,0,Q66/(-SUMIFS(보유분석!$AZ$2:$AZ$801,보유분석!$AC$2:$AC$801,1)*설정!$C$10)) -> 0.45570602 | S66: =IF(SUMIFS(보유분석!$BG$2:$BG$801,보유분석!$AK$2:$AK$801,$A66,보유분석!$AC$2:$AC$801,1)=0,"",SUMIFS(보유분석!$BH$2:$BH$801,보유분석!$AK$2:$AK$801,$A66,보유분석!$AC$2:$AC$801,1)/SUMIFS(보유분석!$BG$2:$BG$801,보유분석!$AK$2:$AK$801,$A66,보유분석!$AC$2:$AC$801,1)) -> 6.5999687 | T66: =IF(SUMIFS(보유분석!$BI$2:$BI$801,보유분석!$AK$2:$AK$801,$A66,보유분석!$AC$2:$AC$801,1)=0,"",SUMIFS(보유분석!$BD$2:$BD$801,보유분석!$AK$2:$AK$801,$A66,보유분석!$AC$2:$AC$801,1)/SUMIFS(보유분석!$BI$2:$BI$801,보유분석!$AK$2:$AK$801,$A66,보유분석!$AC$2:$AC$801,1)) -> 1
A67: HY | B67: =SUMIFS(보유분석!$AA$2:$AA$801,보유분석!$AK$2:$AK$801,$A67,보유분석!$AC$2:$AC$801,1) -> 0 | C67: =IF(SUMIFS(보유분석!$AA$2:$AA$801,보유분석!$AC$2:$AC$801,1)=0,0,B67/SUMIFS(보유분석!$AA$2:$AA$801,보유분석!$AC$2:$AC$801,1)) -> 0 | D67: =SUMIFS(보유분석!$AM$2:$AM$801,보유분석!$AK$2:$AK$801,$A67,보유분석!$AC$2:$AC$801,1) -> 0 | E67: =IF(SUMIFS(보유분석!$AM$2:$AM$801,보유분석!$AC$2:$AC$801,1)=0,0,D67/SUMIFS(보유분석!$AM$2:$AM$801,보유분석!$AC$2:$AC$801,1)) -> 0 | F67: =IF(SUMIFS(보유분석!$BB$2:$BB$801,보유분석!$AK$2:$AK$801,$A67,보유분석!$AC$2:$AC$801,1)=0,"",SUMIFS(보유분석!$BA$2:$BA$801,보유분석!$AK$2:$AK$801,$A67,보유분석!$AC$2:$AC$801,1)/SUMIFS(보유분석!$BB$2:$BB$801,보유분석!$AK$2:$AK$801,$A67,보유분석!$AC$2:$AC$801,1)) | G67: =IF(F67="","",(F67-(SUMIFS(보유분석!$BA$2:$BA$801,보유분석!$AC$2:$AC$801,1)/SUMIFS(보유분석!$BB$2:$BB$801,보유분석!$AC$2:$AC$801,1)))*100) | H67: =IF(SUMIFS(보유분석!$BD$2:$BD$801,보유분석!$AK$2:$AK$801,$A67,보유분석!$AC$2:$AC$801,1)=0,"",SUMIFS(보유분석!$BC$2:$BC$801,보유분석!$AK$2:$AK$801,$A67,보유분석!$AC$2:$AC$801,1)/SUMIFS(보유분석!$BD$2:$BD$801,보유분석!$AK$2:$AK$801,$A67,보유분석!$AC$2:$AC$801,1)) | I67: =IF(SUMIFS(보유분석!$BF$2:$BF$801,보유분석!$AK$2:$AK$801,$A67,보유분석!$AC$2:$AC$801,1)=0,"",SUMIFS(보유분석!$BE$2:$BE$801,보유분석!$AK$2:$AK$801,$A67,보유분석!$AC$2:$AC$801,1)/SUMIFS(보유분석!$BF$2:$BF$801,보유분석!$AK$2:$AK$801,$A67,보유분석!$AC$2:$AC$801,1)) | J67: =IF(SUMIFS(보유분석!$BG$2:$BG$801,보유분석!$AK$2:$AK$801,$A67,보유분석!$AC$2:$AC$801,1)=0,"",(SUMIFS(보유분석!$BC$2:$BC$801,보유분석!$AK$2:$AK$801,$A67,보유분석!$AC$2:$AC$801,1)+SUMIFS(보유분석!$BH$2:$BH$801,보유분석!$AK$2:$AK$801,$A67,보유분석!$AC$2:$AC$801,1))/SUMIFS(보유분석!$BG$2:$BG$801,보유분석!$AK$2:$AK$801,$A67,보유분석!$AC$2:$AC$801,1)) | K67: =IF(B67=0,"",SUMIFS(보유분석!$AV$2:$AV$801,보유분석!$AK$2:$AK$801,$A67,보유분석!$AC$2:$AC$801,1)/(B67*1000000)) | L67: =SUMIFS(보유분석!$AP$2:$AP$801,보유분석!$AK$2:$AK$801,$A67,보유분석!$AC$2:$AC$801,1) -> 0 | M67: =COUNTIFS(보유분석!$AK$2:$AK$801,$A67,보유분석!$AR$2:$AR$801,"Cheap",보유분석!$AC$2:$AC$801,1) -> 0 | N67: =COUNTIFS(보유분석!$AK$2:$AK$801,$A67,보유분석!$AR$2:$AR$801,"Rich",보유분석!$AC$2:$AC$801,1) -> 0 | P67: =IF(O67="","",O67-C67) | Q67: =-SUMIFS(보유분석!$AZ$2:$AZ$801,보유분석!$AK$2:$AK$801,$A67,보유분석!$AC$2:$AC$801,1)*설정!$C$10 -> 0 | R67: =IF((-SUMIFS(보유분석!$AZ$2:$AZ$801,보유분석!$AC$2:$AC$801,1)*설정!$C$10)=0,0,Q67/(-SUMIFS(보유분석!$AZ$2:$AZ$801,보유분석!$AC$2:$AC$801,1)*설정!$C$10)) -> 0 | S67: =IF(SUMIFS(보유분석!$BG$2:$BG$801,보유분석!$AK$2:$AK$801,$A67,보유분석!$AC$2:$AC$801,1)=0,"",SUMIFS(보유분석!$BH$2:$BH$801,보유분석!$AK$2:$AK$801,$A67,보유분석!$AC$2:$AC$801,1)/SUMIFS(보유분석!$BG$2:$BG$801,보유분석!$AK$2:$AK$801,$A67,보유분석!$AC$2:$AC$801,1)) | T67: =IF(SUMIFS(보유분석!$BI$2:$BI$801,보유분석!$AK$2:$AK$801,$A67,보유분석!$AC$2:$AC$801,1)=0,"",SUMIFS(보유분석!$BD$2:$BD$801,보유분석!$AK$2:$AK$801,$A67,보유분석!$AC$2:$AC$801,1)/SUMIFS(보유분석!$BI$2:$BI$801,보유분석!$AK$2:$AK$801,$A67,보유분석!$AC$2:$AC$801,1))
A68: 무등급 | B68: =SUMIFS(보유분석!$AA$2:$AA$801,보유분석!$AK$2:$AK$801,$A68,보유분석!$AC$2:$AC$801,1) -> 122.77278 | C68: =IF(SUMIFS(보유분석!$AA$2:$AA$801,보유분석!$AC$2:$AC$801,1)=0,0,B68/SUMIFS(보유분석!$AA$2:$AA$801,보유분석!$AC$2:$AC$801,1)) -> 0.087110043 | D68: =SUMIFS(보유분석!$AM$2:$AM$801,보유분석!$AK$2:$AK$801,$A68,보유분석!$AC$2:$AC$801,1) -> 26663.855 | E68: =IF(SUMIFS(보유분석!$AM$2:$AM$801,보유분석!$AC$2:$AC$801,1)=0,0,D68/SUMIFS(보유분석!$AM$2:$AM$801,보유분석!$AC$2:$AC$801,1)) -> 0.070311776 | F68: =IF(SUMIFS(보유분석!$BB$2:$BB$801,보유분석!$AK$2:$AK$801,$A68,보유분석!$AC$2:$AC$801,1)=0,"",SUMIFS(보유분석!$BA$2:$BA$801,보유분석!$AK$2:$AK$801,$A68,보유분석!$AC$2:$AC$801,1)/SUMIFS(보유분석!$BB$2:$BB$801,보유분석!$AK$2:$AK$801,$A68,보유분석!$AC$2:$AC$801,1)) -> 5.6238655 | G68: =IF(F68="","",(F68-(SUMIFS(보유분석!$BA$2:$BA$801,보유분석!$AC$2:$AC$801,1)/SUMIFS(보유분석!$BB$2:$BB$801,보유분석!$AC$2:$AC$801,1)))*100) -> -3.6170278 | H68: =IF(SUMIFS(보유분석!$BD$2:$BD$801,보유분석!$AK$2:$AK$801,$A68,보유분석!$AC$2:$AC$801,1)=0,"",SUMIFS(보유분석!$BC$2:$BC$801,보유분석!$AK$2:$AK$801,$A68,보유분석!$AC$2:$AC$801,1)/SUMIFS(보유분석!$BD$2:$BD$801,보유분석!$AK$2:$AK$801,$A68,보유분석!$AC$2:$AC$801,1)) -> 62.768386 | I68: =IF(SUMIFS(보유분석!$BF$2:$BF$801,보유분석!$AK$2:$AK$801,$A68,보유분석!$AC$2:$AC$801,1)=0,"",SUMIFS(보유분석!$BE$2:$BE$801,보유분석!$AK$2:$AK$801,$A68,보유분석!$AC$2:$AC$801,1)/SUMIFS(보유분석!$BF$2:$BF$801,보유분석!$AK$2:$AK$801,$A68,보유분석!$AC$2:$AC$801,1)) -> 2.1718052 | J68: =IF(SUMIFS(보유분석!$BG$2:$BG$801,보유분석!$AK$2:$AK$801,$A68,보유분석!$AC$2:$AC$801,1)=0,"",(SUMIFS(보유분석!$BC$2:$BC$801,보유분석!$AK$2:$AK$801,$A68,보유분석!$AC$2:$AC$801,1)+SUMIFS(보유분석!$BH$2:$BH$801,보유분석!$AK$2:$AK$801,$A68,보유분석!$AC$2:$AC$801,1))/SUMIFS(보유분석!$BG$2:$BG$801,보유분석!$AK$2:$AK$801,$A68,보유분석!$AC$2:$AC$801,1)) -> 32.722867 | K68: =IF(B68=0,"",SUMIFS(보유분석!$AV$2:$AV$801,보유분석!$AK$2:$AK$801,$A68,보유분석!$AC$2:$AC$801,1)/(B68*1000000)) -> 0.057064656 | L68: =SUMIFS(보유분석!$AP$2:$AP$801,보유분석!$AK$2:$AK$801,$A68,보유분석!$AC$2:$AC$801,1) -> -3391837.2 | M68: =COUNTIFS(보유분석!$AK$2:$AK$801,$A68,보유분석!$AR$2:$AR$801,"Cheap",보유분석!$AC$2:$AC$801,1) -> 0 | N68: =COUNTIFS(보유분석!$AK$2:$AK$801,$A68,보유분석!$AR$2:$AR$801,"Rich",보유분석!$AC$2:$AC$801,1) -> 0 | P68: =IF(O68="","",O68-C68) | Q68: =-SUMIFS(보유분석!$AZ$2:$AZ$801,보유분석!$AK$2:$AK$801,$A68,보유분석!$AC$2:$AC$801,1)*설정!$C$10 -> -623829.41 | R68: =IF((-SUMIFS(보유분석!$AZ$2:$AZ$801,보유분석!$AC$2:$AC$801,1)*설정!$C$10)=0,0,Q68/(-SUMIFS(보유분석!$AZ$2:$AZ$801,보유분석!$AC$2:$AC$801,1)*설정!$C$10)) -> 0.061297814 | S68: =IF(SUMIFS(보유분석!$BG$2:$BG$801,보유분석!$AK$2:$AK$801,$A68,보유분석!$AC$2:$AC$801,1)=0,"",SUMIFS(보유분석!$BH$2:$BH$801,보유분석!$AK$2:$AK$801,$A68,보유분석!$AC$2:$AC$801,1)/SUMIFS(보유분석!$BG$2:$BG$801,보유분석!$AK$2:$AK$801,$A68,보유분석!$AC$2:$AC$801,1)) -> 3.8107984 | T68: =IF(SUMIFS(보유분석!$BI$2:$BI$801,보유분석!$AK$2:$AK$801,$A68,보유분석!$AC$2:$AC$801,1)=0,"",SUMIFS(보유분석!$BD$2:$BD$801,보유분석!$AK$2:$AK$801,$A68,보유분석!$AC$2:$AC$801,1)/SUMIFS(보유분석!$BI$2:$BI$801,보유분석!$AK$2:$AK$801,$A68,보유분석!$AC$2:$AC$801,1)) -> 0.99839496
A69: 기타(목록외) | B69: =SUMPRODUCT(ISNA(MATCH(보유분석!$AK$2:$AK$801,$A$64:$A$68,0))*(보유분석!$AC$2:$AC$801=1)*보유분석!$AA$2:$AA$801) -> 0 | C69: =IF(SUMIFS(보유분석!$AA$2:$AA$801,보유분석!$AC$2:$AC$801,1)=0,0,B69/SUMIFS(보유분석!$AA$2:$AA$801,보유분석!$AC$2:$AC$801,1)) -> 0 | D69: =SUMPRODUCT(ISNA(MATCH(보유분석!$AK$2:$AK$801,$A$64:$A$68,0))*(보유분석!$AC$2:$AC$801=1)*보유분석!$AM$2:$AM$801) -> 0 | E69: =IF(SUMIFS(보유분석!$AM$2:$AM$801,보유분석!$AC$2:$AC$801,1)=0,0,D69/SUMIFS(보유분석!$AM$2:$AM$801,보유분석!$AC$2:$AC$801,1)) -> 0 | F69: =IF(SUMPRODUCT(ISNA(MATCH(보유분석!$AK$2:$AK$801,$A$64:$A$68,0))*(보유분석!$AC$2:$AC$801=1)*보유분석!$BB$2:$BB$801)=0,"",SUMPRODUCT(ISNA(MATCH(보유분석!$AK$2:$AK$801,$A$64:$A$68,0))*(보유분석!$AC$2:$AC$801=1)*보유분석!$BA$2:$BA$801)/SUMPRODUCT(ISNA(MATCH(보유분석!$AK$2:$AK$801,$A$64:$A$68,0))*(보유분석!$AC$2:$AC$801=1)*보유분석!$BB$2:$BB$801)) | G69: =IF(F69="","",(F69-(SUMIFS(보유분석!$BA$2:$BA$801,보유분석!$AC$2:$AC$801,1)/SUMIFS(보유분석!$BB$2:$BB$801,보유분석!$AC$2:$AC$801,1)))*100) | H69: =IF(SUMPRODUCT(ISNA(MATCH(보유분석!$AK$2:$AK$801,$A$64:$A$68,0))*(보유분석!$AC$2:$AC$801=1)*보유분석!$BD$2:$BD$801)=0,"",SUMPRODUCT(ISNA(MATCH(보유분석!$AK$2:$AK$801,$A$64:$A$68,0))*(보유분석!$AC$2:$AC$801=1)*보유분석!$BC$2:$BC$801)/SUMPRODUCT(ISNA(MATCH(보유분석!$AK$2:$AK$801,$A$64:$A$68,0))*(보유분석!$AC$2:$AC$801=1)*보유분석!$BD$2:$BD$801)) | I69: =IF(SUMPRODUCT(ISNA(MATCH(보유분석!$AK$2:$AK$801,$A$64:$A$68,0))*(보유분석!$AC$2:$AC$801=1)*보유분석!$BF$2:$BF$801)=0,"",SUMPRODUCT(ISNA(MATCH(보유분석!$AK$2:$AK$801,$A$64:$A$68,0))*(보유분석!$AC$2:$AC$801=1)*보유분석!$BE$2:$BE$801)/SUMPRODUCT(ISNA(MATCH(보유분석!$AK$2:$AK$801,$A$64:$A$68,0))*(보유분석!$AC$2:$AC$801=1)*보유분석!$BF$2:$BF$801)) | J69: =IF(SUMPRODUCT(ISNA(MATCH(보유분석!$AK$2:$AK$801,$A$64:$A$68,0))*(보유분석!$AC$2:$AC$801=1)*보유분석!$BG$2:$BG$801)=0,"",(SUMPRODUCT(ISNA(MATCH(보유분석!$AK$2:$AK$801,$A$64:$A$68,0))*(보유분석!$AC$2:$AC$801=1)*보유분석!$BC$2:$BC$801)+SUMPRODUCT(ISNA(MATCH(보유분석!$AK$2:$AK$801,$A$64:$A$68,0))*(보유분석!$AC$2:$AC$801=1)*보유분석!$BH$2:$BH$801))/SUMPRODUCT(ISNA(MATCH(보유분석!$AK$2:$AK$801,$A$64:$A$68,0))*(보유분석!$AC$2:$AC$801=1)*보유분석!$BG$2:$BG$801)) | K69: =IF(B69=0,"",SUMPRODUCT(ISNA(MATCH(보유분석!$AK$2:$AK$801,$A$64:$A$68,0))*(보유분석!$AC$2:$AC$801=1)*보유분석!$AV$2:$AV$801)/(B69*1000000)) | L69: =SUMPRODUCT(ISNA(MATCH(보유분석!$AK$2:$AK$801,$A$64:$A$68,0))*(보유분석!$AC$2:$AC$801=1)*보유분석!$AP$2:$AP$801) -> 0 | M69: =SUMPRODUCT(ISNA(MATCH(보유분석!$AK$2:$AK$801,$A$64:$A$68,0))*(보유분석!$AC$2:$AC$801=1)*(보유분석!$AR$2:$AR$801="Cheap")) -> 0 | N69: =SUMPRODUCT(ISNA(MATCH(보유분석!$AK$2:$AK$801,$A$64:$A$68,0))*(보유분석!$AC$2:$AC$801=1)*(보유분석!$AR$2:$AR$801="Rich")) -> 0 | P69: =IF(O69="","",O69-C69) | Q69: =-SUMPRODUCT(ISNA(MATCH(보유분석!$AK$2:$AK$801,$A$64:$A$68,0))*(보유분석!$AC$2:$AC$801=1)*보유분석!$AZ$2:$AZ$801)*설정!$C$10 -> 0 | R69: =IF((-SUMIFS(보유분석!$AZ$2:$AZ$801,보유분석!$AC$2:$AC$801,1)*설정!$C$10)=0,0,Q69/(-SUMIFS(보유분석!$AZ$2:$AZ$801,보유분석!$AC$2:$AC$801,1)*설정!$C$10)) -> 0 | S69: =IF(SUMPRODUCT(ISNA(MATCH(보유분석!$AK$2:$AK$801,$A$64:$A$68,0))*(보유분석!$AC$2:$AC$801=1)*보유분석!$BG$2:$BG$801)=0,"",SUMPRODUCT(ISNA(MATCH(보유분석!$AK$2:$AK$801,$A$64:$A$68,0))*(보유분석!$AC$2:$AC$801=1)*보유분석!$BH$2:$BH$801)/SUMPRODUCT(ISNA(MATCH(보유분석!$AK$2:$AK$801,$A$64:$A$68,0))*(보유분석!$AC$2:$AC$801=1)*보유분석!$BG$2:$BG$801)) | T69: =IF(SUMPRODUCT(ISNA(MATCH(보유분석!$AK$2:$AK$801,$A$64:$A$68,0))*(보유분석!$AC$2:$AC$801=1)*보유분석!$BI$2:$BI$801)=0,"",SUMPRODUCT(ISNA(MATCH(보유분석!$AK$2:$AK$801,$A$64:$A$68,0))*(보유분석!$AC$2:$AC$801=1)*보유분석!$BD$2:$BD$801)/SUMPRODUCT(ISNA(MATCH(보유분석!$AK$2:$AK$801,$A$64:$A$68,0))*(보유분석!$AC$2:$AC$801=1)*보유분석!$BI$2:$BI$801))
A70: 합계 | B70: =SUM(B64:B69) -> 1409.3986 | C70: =SUM(C64:C69) -> 1 | D70: =SUM(D64:D69) -> 379223.18 | E70: =SUM(E64:E69) -> 1 | F70: =IF(SUMIFS(보유분석!$BB$2:$BB$801,보유분석!$AC$2:$AC$801,1)=0,"",SUMIFS(보유분석!$BA$2:$BA$801,보유분석!$AC$2:$AC$801,1)/SUMIFS(보유분석!$BB$2:$BB$801,보유분석!$AC$2:$AC$801,1)) -> 5.6600358 | H70: =IF(SUMIFS(보유분석!$BD$2:$BD$801,보유분석!$AC$2:$AC$801,1)=0,"",SUMIFS(보유분석!$BC$2:$BC$801,보유분석!$AC$2:$AC$801,1)/SUMIFS(보유분석!$BD$2:$BD$801,보유분석!$AC$2:$AC$801,1)) -> 66.114006 | I70: =IF(SUMIFS(보유분석!$BF$2:$BF$801,보유분석!$AC$2:$AC$801,1)=0,"",SUMIFS(보유분석!$BE$2:$BE$801,보유분석!$AC$2:$AC$801,1)/SUMIFS(보유분석!$BF$2:$BF$801,보유분석!$AC$2:$AC$801,1)) -> 2.6906736 | J70: =IF(SUMIFS(보유분석!$BG$2:$BG$801,보유분석!$AC$2:$AC$801,1)=0,"",(SUMIFS(보유분석!$BC$2:$BC$801,보유분석!$AC$2:$AC$801,1)+SUMIFS(보유분석!$BH$2:$BH$801,보유분석!$AC$2:$AC$801,1))/SUMIFS(보유분석!$BG$2:$BG$801,보유분석!$AC$2:$AC$801,1)) -> 31.468574 | K70: =IF(B70=0,"",SUMIFS(보유분석!$AV$2:$AV$801,보유분석!$AC$2:$AC$801,1)/(B70*1000000)) -> 0.058254622 | L70: =SUM(L64:L69) -> -44901234 | O70: =IF(COUNT(O64:O69)=0,"",SUM(O64:O69)) | Q70: =SUM(Q64:Q69) -> -10177025 | R70: =SUM(R64:R69) -> 1 | S70: =IF(SUMIFS(보유분석!$BG$2:$BG$801,보유분석!$AC$2:$AC$801,1)=0,"",SUMIFS(보유분석!$BH$2:$BH$801,보유분석!$AC$2:$AC$801,1)/SUMIFS(보유분석!$BG$2:$BG$801,보유분석!$AC$2:$AC$801,1)) -> 6.4728238 | T70: =IF(SUMIFS(보유분석!$BI$2:$BI$801,보유분석!$AC$2:$AC$801,1)=0,"",SUMIFS(보유분석!$BD$2:$BD$801,보유분석!$AC$2:$AC$801,1)/SUMIFS(보유분석!$BI$2:$BI$801,보유분석!$AC$2:$AC$801,1)) -> 0.97796717
A73: ■ 보유목적
A74: 구분 | B74: 평가금액($M) | C74: 비중 | D74: DV01($/bp) | E74: DV01비중 | F74: 가중YTM(%) | G74: 포트대비(bp) | H74: 가중G-spread(bp) | I74: 가중듀레이션 | J74: 손익분기 확대폭(bp) 스프레드+롤다운 | K74: 1Y기대수익률(%) | L74: 평가손익($) | M74: Cheap 보유수 | N74: Rich 보유수 | O74: 목표비중(입력) | P74: 갭(목표-현재) | Q74: 스프레드쇼크 손실($) | R74: 손실비중 | S74: └ 롤다운 기여(bp) | T74: G-spread 커버리지
A75: 기타포괄손익 | B75: =SUMIFS(보유분석!$AA$2:$AA$801,보유분석!$D$2:$D$801,$A75,보유분석!$AC$2:$AC$801,1) -> 0 | C75: =IF(SUMIFS(보유분석!$AA$2:$AA$801,보유분석!$AC$2:$AC$801,1)=0,0,B75/SUMIFS(보유분석!$AA$2:$AA$801,보유분석!$AC$2:$AC$801,1)) -> 0 | D75: =SUMIFS(보유분석!$AM$2:$AM$801,보유분석!$D$2:$D$801,$A75,보유분석!$AC$2:$AC$801,1) -> 0 | E75: =IF(SUMIFS(보유분석!$AM$2:$AM$801,보유분석!$AC$2:$AC$801,1)=0,0,D75/SUMIFS(보유분석!$AM$2:$AM$801,보유분석!$AC$2:$AC$801,1)) -> 0 | F75: =IF(SUMIFS(보유분석!$BB$2:$BB$801,보유분석!$D$2:$D$801,$A75,보유분석!$AC$2:$AC$801,1)=0,"",SUMIFS(보유분석!$BA$2:$BA$801,보유분석!$D$2:$D$801,$A75,보유분석!$AC$2:$AC$801,1)/SUMIFS(보유분석!$BB$2:$BB$801,보유분석!$D$2:$D$801,$A75,보유분석!$AC$2:$AC$801,1)) | G75: =IF(F75="","",(F75-(SUMIFS(보유분석!$BA$2:$BA$801,보유분석!$AC$2:$AC$801,1)/SUMIFS(보유분석!$BB$2:$BB$801,보유분석!$AC$2:$AC$801,1)))*100) | H75: =IF(SUMIFS(보유분석!$BD$2:$BD$801,보유분석!$D$2:$D$801,$A75,보유분석!$AC$2:$AC$801,1)=0,"",SUMIFS(보유분석!$BC$2:$BC$801,보유분석!$D$2:$D$801,$A75,보유분석!$AC$2:$AC$801,1)/SUMIFS(보유분석!$BD$2:$BD$801,보유분석!$D$2:$D$801,$A75,보유분석!$AC$2:$AC$801,1)) | I75: =IF(SUMIFS(보유분석!$BF$2:$BF$801,보유분석!$D$2:$D$801,$A75,보유분석!$AC$2:$AC$801,1)=0,"",SUMIFS(보유분석!$BE$2:$BE$801,보유분석!$D$2:$D$801,$A75,보유분석!$AC$2:$AC$801,1)/SUMIFS(보유분석!$BF$2:$BF$801,보유분석!$D$2:$D$801,$A75,보유분석!$AC$2:$AC$801,1)) | J75: =IF(SUMIFS(보유분석!$BG$2:$BG$801,보유분석!$D$2:$D$801,$A75,보유분석!$AC$2:$AC$801,1)=0,"",(SUMIFS(보유분석!$BC$2:$BC$801,보유분석!$D$2:$D$801,$A75,보유분석!$AC$2:$AC$801,1)+SUMIFS(보유분석!$BH$2:$BH$801,보유분석!$D$2:$D$801,$A75,보유분석!$AC$2:$AC$801,1))/SUMIFS(보유분석!$BG$2:$BG$801,보유분석!$D$2:$D$801,$A75,보유분석!$AC$2:$AC$801,1)) | K75: =IF(B75=0,"",SUMIFS(보유분석!$AV$2:$AV$801,보유분석!$D$2:$D$801,$A75,보유분석!$AC$2:$AC$801,1)/(B75*1000000)) | L75: =SUMIFS(보유분석!$AP$2:$AP$801,보유분석!$D$2:$D$801,$A75,보유분석!$AC$2:$AC$801,1) -> 0 | M75: =COUNTIFS(보유분석!$D$2:$D$801,$A75,보유분석!$AR$2:$AR$801,"Cheap",보유분석!$AC$2:$AC$801,1) -> 0 | N75: =COUNTIFS(보유분석!$D$2:$D$801,$A75,보유분석!$AR$2:$AR$801,"Rich",보유분석!$AC$2:$AC$801,1) -> 0 | P75: =IF(O75="","",O75-C75) | Q75: =-SUMIFS(보유분석!$AZ$2:$AZ$801,보유분석!$D$2:$D$801,$A75,보유분석!$AC$2:$AC$801,1)*설정!$C$10 -> 0 | R75: =IF((-SUMIFS(보유분석!$AZ$2:$AZ$801,보유분석!$AC$2:$AC$801,1)*설정!$C$10)=0,0,Q75/(-SUMIFS(보유분석!$AZ$2:$AZ$801,보유분석!$AC$2:$AC$801,1)*설정!$C$10)) -> 0 | S75: =IF(SUMIFS(보유분석!$BG$2:$BG$801,보유분석!$D$2:$D$801,$A75,보유분석!$AC$2:$AC$801,1)=0,"",SUMIFS(보유분석!$BH$2:$BH$801,보유분석!$D$2:$D$801,$A75,보유분석!$AC$2:$AC$801,1)/SUMIFS(보유분석!$BG$2:$BG$801,보유분석!$D$2:$D$801,$A75,보유분석!$AC$2:$AC$801,1)) | T75: =IF(SUMIFS(보유분석!$BI$2:$BI$801,보유분석!$D$2:$D$801,$A75,보유분석!$AC$2:$AC$801,1)=0,"",SUMIFS(보유분석!$BD$2:$BD$801,보유분석!$D$2:$D$801,$A75,보유분석!$AC$2:$AC$801,1)/SUMIFS(보유분석!$BI$2:$BI$801,보유분석!$D$2:$D$801,$A75,보유분석!$AC$2:$AC$801,1))
A76: 당기손익-TD | B76: =SUMIFS(보유분석!$AA$2:$AA$801,보유분석!$D$2:$D$801,$A76,보유분석!$AC$2:$AC$801,1) -> 1409.3986 | C76: =IF(SUMIFS(보유분석!$AA$2:$AA$801,보유분석!$AC$2:$AC$801,1)=0,0,B76/SUMIFS(보유분석!$AA$2:$AA$801,보유분석!$AC$2:$AC$801,1)) -> 1 | D76: =SUMIFS(보유분석!$AM$2:$AM$801,보유분석!$D$2:$D$801,$A76,보유분석!$AC$2:$AC$801,1) -> 379223.18 | E76: =IF(SUMIFS(보유분석!$AM$2:$AM$801,보유분석!$AC$2:$AC$801,1)=0,0,D76/SUMIFS(보유분석!$AM$2:$AM$801,보유분석!$AC$2:$AC$801,1)) -> 1 | F76: =IF(SUMIFS(보유분석!$BB$2:$BB$801,보유분석!$D$2:$D$801,$A76,보유분석!$AC$2:$AC$801,1)=0,"",SUMIFS(보유분석!$BA$2:$BA$801,보유분석!$D$2:$D$801,$A76,보유분석!$AC$2:$AC$801,1)/SUMIFS(보유분석!$BB$2:$BB$801,보유분석!$D$2:$D$801,$A76,보유분석!$AC$2:$AC$801,1)) -> 5.6600358 | G76: =IF(F76="","",(F76-(SUMIFS(보유분석!$BA$2:$BA$801,보유분석!$AC$2:$AC$801,1)/SUMIFS(보유분석!$BB$2:$BB$801,보유분석!$AC$2:$AC$801,1)))*100) -> 0 | H76: =IF(SUMIFS(보유분석!$BD$2:$BD$801,보유분석!$D$2:$D$801,$A76,보유분석!$AC$2:$AC$801,1)=0,"",SUMIFS(보유분석!$BC$2:$BC$801,보유분석!$D$2:$D$801,$A76,보유분석!$AC$2:$AC$801,1)/SUMIFS(보유분석!$BD$2:$BD$801,보유분석!$D$2:$D$801,$A76,보유분석!$AC$2:$AC$801,1)) -> 66.114006 | I76: =IF(SUMIFS(보유분석!$BF$2:$BF$801,보유분석!$D$2:$D$801,$A76,보유분석!$AC$2:$AC$801,1)=0,"",SUMIFS(보유분석!$BE$2:$BE$801,보유분석!$D$2:$D$801,$A76,보유분석!$AC$2:$AC$801,1)/SUMIFS(보유분석!$BF$2:$BF$801,보유분석!$D$2:$D$801,$A76,보유분석!$AC$2:$AC$801,1)) -> 2.6906736 | J76: =IF(SUMIFS(보유분석!$BG$2:$BG$801,보유분석!$D$2:$D$801,$A76,보유분석!$AC$2:$AC$801,1)=0,"",(SUMIFS(보유분석!$BC$2:$BC$801,보유분석!$D$2:$D$801,$A76,보유분석!$AC$2:$AC$801,1)+SUMIFS(보유분석!$BH$2:$BH$801,보유분석!$D$2:$D$801,$A76,보유분석!$AC$2:$AC$801,1))/SUMIFS(보유분석!$BG$2:$BG$801,보유분석!$D$2:$D$801,$A76,보유분석!$AC$2:$AC$801,1)) -> 31.468574 | K76: =IF(B76=0,"",SUMIFS(보유분석!$AV$2:$AV$801,보유분석!$D$2:$D$801,$A76,보유분석!$AC$2:$AC$801,1)/(B76*1000000)) -> 0.058254622 | L76: =SUMIFS(보유분석!$AP$2:$AP$801,보유분석!$D$2:$D$801,$A76,보유분석!$AC$2:$AC$801,1) -> -44901234 | M76: =COUNTIFS(보유분석!$D$2:$D$801,$A76,보유분석!$AR$2:$AR$801,"Cheap",보유분석!$AC$2:$AC$801,1) -> 36 | N76: =COUNTIFS(보유분석!$D$2:$D$801,$A76,보유분석!$AR$2:$AR$801,"Rich",보유분석!$AC$2:$AC$801,1) -> 10 | P76: =IF(O76="","",O76-C76) | Q76: =-SUMIFS(보유분석!$AZ$2:$AZ$801,보유분석!$D$2:$D$801,$A76,보유분석!$AC$2:$AC$801,1)*설정!$C$10 -> -10177025 | R76: =IF((-SUMIFS(보유분석!$AZ$2:$AZ$801,보유분석!$AC$2:$AC$801,1)*설정!$C$10)=0,0,Q76/(-SUMIFS(보유분석!$AZ$2:$AZ$801,보유분석!$AC$2:$AC$801,1)*설정!$C$10)) -> 1 | S76: =IF(SUMIFS(보유분석!$BG$2:$BG$801,보유분석!$D$2:$D$801,$A76,보유분석!$AC$2:$AC$801,1)=0,"",SUMIFS(보유분석!$BH$2:$BH$801,보유분석!$D$2:$D$801,$A76,보유분석!$AC$2:$AC$801,1)/SUMIFS(보유분석!$BG$2:$BG$801,보유분석!$D$2:$D$801,$A76,보유분석!$AC$2:$AC$801,1)) -> 6.4728238 | T76: =IF(SUMIFS(보유분석!$BI$2:$BI$801,보유분석!$D$2:$D$801,$A76,보유분석!$AC$2:$AC$801,1)=0,"",SUMIFS(보유분석!$BD$2:$BD$801,보유분석!$D$2:$D$801,$A76,보유분석!$AC$2:$AC$801,1)/SUMIFS(보유분석!$BI$2:$BI$801,보유분석!$D$2:$D$801,$A76,보유분석!$AC$2:$AC$801,1)) -> 0.97796717
A77: 기타(목록외) | B77: =SUMPRODUCT(ISNA(MATCH(보유분석!$D$2:$D$801,$A$75:$A$76,0))*(보유분석!$AC$2:$AC$801=1)*보유분석!$AA$2:$AA$801) -> 0 | C77: =IF(SUMIFS(보유분석!$AA$2:$AA$801,보유분석!$AC$2:$AC$801,1)=0,0,B77/SUMIFS(보유분석!$AA$2:$AA$801,보유분석!$AC$2:$AC$801,1)) -> 0 | D77: =SUMPRODUCT(ISNA(MATCH(보유분석!$D$2:$D$801,$A$75:$A$76,0))*(보유분석!$AC$2:$AC$801=1)*보유분석!$AM$2:$AM$801) -> 0 | E77: =IF(SUMIFS(보유분석!$AM$2:$AM$801,보유분석!$AC$2:$AC$801,1)=0,0,D77/SUMIFS(보유분석!$AM$2:$AM$801,보유분석!$AC$2:$AC$801,1)) -> 0 | F77: =IF(SUMPRODUCT(ISNA(MATCH(보유분석!$D$2:$D$801,$A$75:$A$76,0))*(보유분석!$AC$2:$AC$801=1)*보유분석!$BB$2:$BB$801)=0,"",SUMPRODUCT(ISNA(MATCH(보유분석!$D$2:$D$801,$A$75:$A$76,0))*(보유분석!$AC$2:$AC$801=1)*보유분석!$BA$2:$BA$801)/SUMPRODUCT(ISNA(MATCH(보유분석!$D$2:$D$801,$A$75:$A$76,0))*(보유분석!$AC$2:$AC$801=1)*보유분석!$BB$2:$BB$801)) | G77: =IF(F77="","",(F77-(SUMIFS(보유분석!$BA$2:$BA$801,보유분석!$AC$2:$AC$801,1)/SUMIFS(보유분석!$BB$2:$BB$801,보유분석!$AC$2:$AC$801,1)))*100) | H77: =IF(SUMPRODUCT(ISNA(MATCH(보유분석!$D$2:$D$801,$A$75:$A$76,0))*(보유분석!$AC$2:$AC$801=1)*보유분석!$BD$2:$BD$801)=0,"",SUMPRODUCT(ISNA(MATCH(보유분석!$D$2:$D$801,$A$75:$A$76,0))*(보유분석!$AC$2:$AC$801=1)*보유분석!$BC$2:$BC$801)/SUMPRODUCT(ISNA(MATCH(보유분석!$D$2:$D$801,$A$75:$A$76,0))*(보유분석!$AC$2:$AC$801=1)*보유분석!$BD$2:$BD$801)) | I77: =IF(SUMPRODUCT(ISNA(MATCH(보유분석!$D$2:$D$801,$A$75:$A$76,0))*(보유분석!$AC$2:$AC$801=1)*보유분석!$BF$2:$BF$801)=0,"",SUMPRODUCT(ISNA(MATCH(보유분석!$D$2:$D$801,$A$75:$A$76,0))*(보유분석!$AC$2:$AC$801=1)*보유분석!$BE$2:$BE$801)/SUMPRODUCT(ISNA(MATCH(보유분석!$D$2:$D$801,$A$75:$A$76,0))*(보유분석!$AC$2:$AC$801=1)*보유분석!$BF$2:$BF$801)) | J77: =IF(SUMPRODUCT(ISNA(MATCH(보유분석!$D$2:$D$801,$A$75:$A$76,0))*(보유분석!$AC$2:$AC$801=1)*보유분석!$BG$2:$BG$801)=0,"",(SUMPRODUCT(ISNA(MATCH(보유분석!$D$2:$D$801,$A$75:$A$76,0))*(보유분석!$AC$2:$AC$801=1)*보유분석!$BC$2:$BC$801)+SUMPRODUCT(ISNA(MATCH(보유분석!$D$2:$D$801,$A$75:$A$76,0))*(보유분석!$AC$2:$AC$801=1)*보유분석!$BH$2:$BH$801))/SUMPRODUCT(ISNA(MATCH(보유분석!$D$2:$D$801,$A$75:$A$76,0))*(보유분석!$AC$2:$AC$801=1)*보유분석!$BG$2:$BG$801)) | K77: =IF(B77=0,"",SUMPRODUCT(ISNA(MATCH(보유분석!$D$2:$D$801,$A$75:$A$76,0))*(보유분석!$AC$2:$AC$801=1)*보유분석!$AV$2:$AV$801)/(B77*1000000)) | L77: =SUMPRODUCT(ISNA(MATCH(보유분석!$D$2:$D$801,$A$75:$A$76,0))*(보유분석!$AC$2:$AC$801=1)*보유분석!$AP$2:$AP$801) -> 0 | M77: =SUMPRODUCT(ISNA(MATCH(보유분석!$D$2:$D$801,$A$75:$A$76,0))*(보유분석!$AC$2:$AC$801=1)*(보유분석!$AR$2:$AR$801="Cheap")) -> 0 | N77: =SUMPRODUCT(ISNA(MATCH(보유분석!$D$2:$D$801,$A$75:$A$76,0))*(보유분석!$AC$2:$AC$801=1)*(보유분석!$AR$2:$AR$801="Rich")) -> 0 | P77: =IF(O77="","",O77-C77) | Q77: =-SUMPRODUCT(ISNA(MATCH(보유분석!$D$2:$D$801,$A$75:$A$76,0))*(보유분석!$AC$2:$AC$801=1)*보유분석!$AZ$2:$AZ$801)*설정!$C$10 -> 0 | R77: =IF((-SUMIFS(보유분석!$AZ$2:$AZ$801,보유분석!$AC$2:$AC$801,1)*설정!$C$10)=0,0,Q77/(-SUMIFS(보유분석!$AZ$2:$AZ$801,보유분석!$AC$2:$AC$801,1)*설정!$C$10)) -> 0 | S77: =IF(SUMPRODUCT(ISNA(MATCH(보유분석!$D$2:$D$801,$A$75:$A$76,0))*(보유분석!$AC$2:$AC$801=1)*보유분석!$BG$2:$BG$801)=0,"",SUMPRODUCT(ISNA(MATCH(보유분석!$D$2:$D$801,$A$75:$A$76,0))*(보유분석!$AC$2:$AC$801=1)*보유분석!$BH$2:$BH$801)/SUMPRODUCT(ISNA(MATCH(보유분석!$D$2:$D$801,$A$75:$A$76,0))*(보유분석!$AC$2:$AC$801=1)*보유분석!$BG$2:$BG$801)) | T77: =IF(SUMPRODUCT(ISNA(MATCH(보유분석!$D$2:$D$801,$A$75:$A$76,0))*(보유분석!$AC$2:$AC$801=1)*보유분석!$BI$2:$BI$801)=0,"",SUMPRODUCT(ISNA(MATCH(보유분석!$D$2:$D$801,$A$75:$A$76,0))*(보유분석!$AC$2:$AC$801=1)*보유분석!$BD$2:$BD$801)/SUMPRODUCT(ISNA(MATCH(보유분석!$D$2:$D$801,$A$75:$A$76,0))*(보유분석!$AC$2:$AC$801=1)*보유분석!$BI$2:$BI$801))
A78: 합계 | B78: =SUM(B75:B77) -> 1409.3986 | C78: =SUM(C75:C77) -> 1 | D78: =SUM(D75:D77) -> 379223.18 | E78: =SUM(E75:E77) -> 1 | F78: =IF(SUMIFS(보유분석!$BB$2:$BB$801,보유분석!$AC$2:$AC$801,1)=0,"",SUMIFS(보유분석!$BA$2:$BA$801,보유분석!$AC$2:$AC$801,1)/SUMIFS(보유분석!$BB$2:$BB$801,보유분석!$AC$2:$AC$801,1)) -> 5.6600358 | H78: =IF(SUMIFS(보유분석!$BD$2:$BD$801,보유분석!$AC$2:$AC$801,1)=0,"",SUMIFS(보유분석!$BC$2:$BC$801,보유분석!$AC$2:$AC$801,1)/SUMIFS(보유분석!$BD$2:$BD$801,보유분석!$AC$2:$AC$801,1)) -> 66.114006 | I78: =IF(SUMIFS(보유분석!$BF$2:$BF$801,보유분석!$AC$2:$AC$801,1)=0,"",SUMIFS(보유분석!$BE$2:$BE$801,보유분석!$AC$2:$AC$801,1)/SUMIFS(보유분석!$BF$2:$BF$801,보유분석!$AC$2:$AC$801,1)) -> 2.6906736 | J78: =IF(SUMIFS(보유분석!$BG$2:$BG$801,보유분석!$AC$2:$AC$801,1)=0,"",(SUMIFS(보유분석!$BC$2:$BC$801,보유분석!$AC$2:$AC$801,1)+SUMIFS(보유분석!$BH$2:$BH$801,보유분석!$AC$2:$AC$801,1))/SUMIFS(보유분석!$BG$2:$BG$801,보유분석!$AC$2:$AC$801,1)) -> 31.468574 | K78: =IF(B78=0,"",SUMIFS(보유분석!$AV$2:$AV$801,보유분석!$AC$2:$AC$801,1)/(B78*1000000)) -> 0.058254622 | L78: =SUM(L75:L77) -> -44901234 | O78: =IF(COUNT(O75:O77)=0,"",SUM(O75:O77)) | Q78: =SUM(Q75:Q77) -> -10177025 | R78: =SUM(R75:R77) -> 1 | S78: =IF(SUMIFS(보유분석!$BG$2:$BG$801,보유분석!$AC$2:$AC$801,1)=0,"",SUMIFS(보유분석!$BH$2:$BH$801,보유분석!$AC$2:$AC$801,1)/SUMIFS(보유분석!$BG$2:$BG$801,보유분석!$AC$2:$AC$801,1)) -> 6.4728238 | T78: =IF(SUMIFS(보유분석!$BI$2:$BI$801,보유분석!$AC$2:$AC$801,1)=0,"",SUMIFS(보유분석!$BD$2:$BD$801,보유분석!$AC$2:$AC$801,1)/SUMIFS(보유분석!$BI$2:$BI$801,보유분석!$AC$2:$AC$801,1)) -> 0.97796717
A81: ■ 통화
A82: 구분 | B82: 평가금액($M) | C82: 비중 | D82: DV01($/bp) | E82: DV01비중 | F82: 가중YTM(%) | G82: 포트대비(bp) | H82: 가중G-spread(bp) | I82: 가중듀레이션 | J82: 손익분기 확대폭(bp) 스프레드+롤다운 | K82: 1Y기대수익률(%) | L82: 평가손익($) | M82: Cheap 보유수 | N82: Rich 보유수 | O82: 목표비중(입력) | P82: 갭(목표-현재) | Q82: 스프레드쇼크 손실($) | R82: 손실비중 | S82: └ 롤다운 기여(bp) | T82: G-spread 커버리지
A83: USD | B83: =SUMIFS(보유분석!$AA$2:$AA$801,보유분석!$W$2:$W$801,$A83,보유분석!$AC$2:$AC$801,1) -> 1409.3986 | C83: =IF(SUMIFS(보유분석!$AA$2:$AA$801,보유분석!$AC$2:$AC$801,1)=0,0,B83/SUMIFS(보유분석!$AA$2:$AA$801,보유분석!$AC$2:$AC$801,1)) -> 1 | D83: =SUMIFS(보유분석!$AM$2:$AM$801,보유분석!$W$2:$W$801,$A83,보유분석!$AC$2:$AC$801,1) -> 379223.18 | E83: =IF(SUMIFS(보유분석!$AM$2:$AM$801,보유분석!$AC$2:$AC$801,1)=0,0,D83/SUMIFS(보유분석!$AM$2:$AM$801,보유분석!$AC$2:$AC$801,1)) -> 1 | F83: =IF(SUMIFS(보유분석!$BB$2:$BB$801,보유분석!$W$2:$W$801,$A83,보유분석!$AC$2:$AC$801,1)=0,"",SUMIFS(보유분석!$BA$2:$BA$801,보유분석!$W$2:$W$801,$A83,보유분석!$AC$2:$AC$801,1)/SUMIFS(보유분석!$BB$2:$BB$801,보유분석!$W$2:$W$801,$A83,보유분석!$AC$2:$AC$801,1)) -> 5.6600358 | G83: =IF(F83="","",(F83-(SUMIFS(보유분석!$BA$2:$BA$801,보유분석!$AC$2:$AC$801,1)/SUMIFS(보유분석!$BB$2:$BB$801,보유분석!$AC$2:$AC$801,1)))*100) -> 0 | H83: =IF(SUMIFS(보유분석!$BD$2:$BD$801,보유분석!$W$2:$W$801,$A83,보유분석!$AC$2:$AC$801,1)=0,"",SUMIFS(보유분석!$BC$2:$BC$801,보유분석!$W$2:$W$801,$A83,보유분석!$AC$2:$AC$801,1)/SUMIFS(보유분석!$BD$2:$BD$801,보유분석!$W$2:$W$801,$A83,보유분석!$AC$2:$AC$801,1)) -> 66.114006 | I83: =IF(SUMIFS(보유분석!$BF$2:$BF$801,보유분석!$W$2:$W$801,$A83,보유분석!$AC$2:$AC$801,1)=0,"",SUMIFS(보유분석!$BE$2:$BE$801,보유분석!$W$2:$W$801,$A83,보유분석!$AC$2:$AC$801,1)/SUMIFS(보유분석!$BF$2:$BF$801,보유분석!$W$2:$W$801,$A83,보유분석!$AC$2:$AC$801,1)) -> 2.6906736 | J83: =IF(SUMIFS(보유분석!$BG$2:$BG$801,보유분석!$W$2:$W$801,$A83,보유분석!$AC$2:$AC$801,1)=0,"",(SUMIFS(보유분석!$BC$2:$BC$801,보유분석!$W$2:$W$801,$A83,보유분석!$AC$2:$AC$801,1)+SUMIFS(보유분석!$BH$2:$BH$801,보유분석!$W$2:$W$801,$A83,보유분석!$AC$2:$AC$801,1))/SUMIFS(보유분석!$BG$2:$BG$801,보유분석!$W$2:$W$801,$A83,보유분석!$AC$2:$AC$801,1)) -> 31.468574 | K83: =IF(B83=0,"",SUMIFS(보유분석!$AV$2:$AV$801,보유분석!$W$2:$W$801,$A83,보유분석!$AC$2:$AC$801,1)/(B83*1000000)) -> 0.058254622 | L83: =SUMIFS(보유분석!$AP$2:$AP$801,보유분석!$W$2:$W$801,$A83,보유분석!$AC$2:$AC$801,1) -> -44901234 | M83: =COUNTIFS(보유분석!$W$2:$W$801,$A83,보유분석!$AR$2:$AR$801,"Cheap",보유분석!$AC$2:$AC$801,1) -> 36 | N83: =COUNTIFS(보유분석!$W$2:$W$801,$A83,보유분석!$AR$2:$AR$801,"Rich",보유분석!$AC$2:$AC$801,1) -> 10 | P83: =IF(O83="","",O83-C83) | Q83: =-SUMIFS(보유분석!$AZ$2:$AZ$801,보유분석!$W$2:$W$801,$A83,보유분석!$AC$2:$AC$801,1)*설정!$C$10 -> -10177025 | R83: =IF((-SUMIFS(보유분석!$AZ$2:$AZ$801,보유분석!$AC$2:$AC$801,1)*설정!$C$10)=0,0,Q83/(-SUMIFS(보유분석!$AZ$2:$AZ$801,보유분석!$AC$2:$AC$801,1)*설정!$C$10)) -> 1 | S83: =IF(SUMIFS(보유분석!$BG$2:$BG$801,보유분석!$W$2:$W$801,$A83,보유분석!$AC$2:$AC$801,1)=0,"",SUMIFS(보유분석!$BH$2:$BH$801,보유분석!$W$2:$W$801,$A83,보유분석!$AC$2:$AC$801,1)/SUMIFS(보유분석!$BG$2:$BG$801,보유분석!$W$2:$W$801,$A83,보유분석!$AC$2:$AC$801,1)) -> 6.4728238 | T83: =IF(SUMIFS(보유분석!$BI$2:$BI$801,보유분석!$W$2:$W$801,$A83,보유분석!$AC$2:$AC$801,1)=0,"",SUMIFS(보유분석!$BD$2:$BD$801,보유분석!$W$2:$W$801,$A83,보유분석!$AC$2:$AC$801,1)/SUMIFS(보유분석!$BI$2:$BI$801,보유분석!$W$2:$W$801,$A83,보유분석!$AC$2:$AC$801,1)) -> 0.97796717
A84: EUR | B84: =SUMIFS(보유분석!$AA$2:$AA$801,보유분석!$W$2:$W$801,$A84,보유분석!$AC$2:$AC$801,1) -> 0 | C84: =IF(SUMIFS(보유분석!$AA$2:$AA$801,보유분석!$AC$2:$AC$801,1)=0,0,B84/SUMIFS(보유분석!$AA$2:$AA$801,보유분석!$AC$2:$AC$801,1)) -> 0 | D84: =SUMIFS(보유분석!$AM$2:$AM$801,보유분석!$W$2:$W$801,$A84,보유분석!$AC$2:$AC$801,1) -> 0 | E84: =IF(SUMIFS(보유분석!$AM$2:$AM$801,보유분석!$AC$2:$AC$801,1)=0,0,D84/SUMIFS(보유분석!$AM$2:$AM$801,보유분석!$AC$2:$AC$801,1)) -> 0 | F84: =IF(SUMIFS(보유분석!$BB$2:$BB$801,보유분석!$W$2:$W$801,$A84,보유분석!$AC$2:$AC$801,1)=0,"",SUMIFS(보유분석!$BA$2:$BA$801,보유분석!$W$2:$W$801,$A84,보유분석!$AC$2:$AC$801,1)/SUMIFS(보유분석!$BB$2:$BB$801,보유분석!$W$2:$W$801,$A84,보유분석!$AC$2:$AC$801,1)) | G84: =IF(F84="","",(F84-(SUMIFS(보유분석!$BA$2:$BA$801,보유분석!$AC$2:$AC$801,1)/SUMIFS(보유분석!$BB$2:$BB$801,보유분석!$AC$2:$AC$801,1)))*100) | H84: =IF(SUMIFS(보유분석!$BD$2:$BD$801,보유분석!$W$2:$W$801,$A84,보유분석!$AC$2:$AC$801,1)=0,"",SUMIFS(보유분석!$BC$2:$BC$801,보유분석!$W$2:$W$801,$A84,보유분석!$AC$2:$AC$801,1)/SUMIFS(보유분석!$BD$2:$BD$801,보유분석!$W$2:$W$801,$A84,보유분석!$AC$2:$AC$801,1)) | I84: =IF(SUMIFS(보유분석!$BF$2:$BF$801,보유분석!$W$2:$W$801,$A84,보유분석!$AC$2:$AC$801,1)=0,"",SUMIFS(보유분석!$BE$2:$BE$801,보유분석!$W$2:$W$801,$A84,보유분석!$AC$2:$AC$801,1)/SUMIFS(보유분석!$BF$2:$BF$801,보유분석!$W$2:$W$801,$A84,보유분석!$AC$2:$AC$801,1)) | J84: =IF(SUMIFS(보유분석!$BG$2:$BG$801,보유분석!$W$2:$W$801,$A84,보유분석!$AC$2:$AC$801,1)=0,"",(SUMIFS(보유분석!$BC$2:$BC$801,보유분석!$W$2:$W$801,$A84,보유분석!$AC$2:$AC$801,1)+SUMIFS(보유분석!$BH$2:$BH$801,보유분석!$W$2:$W$801,$A84,보유분석!$AC$2:$AC$801,1))/SUMIFS(보유분석!$BG$2:$BG$801,보유분석!$W$2:$W$801,$A84,보유분석!$AC$2:$AC$801,1)) | K84: =IF(B84=0,"",SUMIFS(보유분석!$AV$2:$AV$801,보유분석!$W$2:$W$801,$A84,보유분석!$AC$2:$AC$801,1)/(B84*1000000)) | L84: =SUMIFS(보유분석!$AP$2:$AP$801,보유분석!$W$2:$W$801,$A84,보유분석!$AC$2:$AC$801,1) -> 0 | M84: =COUNTIFS(보유분석!$W$2:$W$801,$A84,보유분석!$AR$2:$AR$801,"Cheap",보유분석!$AC$2:$AC$801,1) -> 0 | N84: =COUNTIFS(보유분석!$W$2:$W$801,$A84,보유분석!$AR$2:$AR$801,"Rich",보유분석!$AC$2:$AC$801,1) -> 0 | P84: =IF(O84="","",O84-C84) | Q84: =-SUMIFS(보유분석!$AZ$2:$AZ$801,보유분석!$W$2:$W$801,$A84,보유분석!$AC$2:$AC$801,1)*설정!$C$10 -> 0 | R84: =IF((-SUMIFS(보유분석!$AZ$2:$AZ$801,보유분석!$AC$2:$AC$801,1)*설정!$C$10)=0,0,Q84/(-SUMIFS(보유분석!$AZ$2:$AZ$801,보유분석!$AC$2:$AC$801,1)*설정!$C$10)) -> 0 | S84: =IF(SUMIFS(보유분석!$BG$2:$BG$801,보유분석!$W$2:$W$801,$A84,보유분석!$AC$2:$AC$801,1)=0,"",SUMIFS(보유분석!$BH$2:$BH$801,보유분석!$W$2:$W$801,$A84,보유분석!$AC$2:$AC$801,1)/SUMIFS(보유분석!$BG$2:$BG$801,보유분석!$W$2:$W$801,$A84,보유분석!$AC$2:$AC$801,1)) | T84: =IF(SUMIFS(보유분석!$BI$2:$BI$801,보유분석!$W$2:$W$801,$A84,보유분석!$AC$2:$AC$801,1)=0,"",SUMIFS(보유분석!$BD$2:$BD$801,보유분석!$W$2:$W$801,$A84,보유분석!$AC$2:$AC$801,1)/SUMIFS(보유분석!$BI$2:$BI$801,보유분석!$W$2:$W$801,$A84,보유분석!$AC$2:$AC$801,1))
A85: JPY | B85: =SUMIFS(보유분석!$AA$2:$AA$801,보유분석!$W$2:$W$801,$A85,보유분석!$AC$2:$AC$801,1) -> 0 | C85: =IF(SUMIFS(보유분석!$AA$2:$AA$801,보유분석!$AC$2:$AC$801,1)=0,0,B85/SUMIFS(보유분석!$AA$2:$AA$801,보유분석!$AC$2:$AC$801,1)) -> 0 | D85: =SUMIFS(보유분석!$AM$2:$AM$801,보유분석!$W$2:$W$801,$A85,보유분석!$AC$2:$AC$801,1) -> 0 | E85: =IF(SUMIFS(보유분석!$AM$2:$AM$801,보유분석!$AC$2:$AC$801,1)=0,0,D85/SUMIFS(보유분석!$AM$2:$AM$801,보유분석!$AC$2:$AC$801,1)) -> 0 | F85: =IF(SUMIFS(보유분석!$BB$2:$BB$801,보유분석!$W$2:$W$801,$A85,보유분석!$AC$2:$AC$801,1)=0,"",SUMIFS(보유분석!$BA$2:$BA$801,보유분석!$W$2:$W$801,$A85,보유분석!$AC$2:$AC$801,1)/SUMIFS(보유분석!$BB$2:$BB$801,보유분석!$W$2:$W$801,$A85,보유분석!$AC$2:$AC$801,1)) | G85: =IF(F85="","",(F85-(SUMIFS(보유분석!$BA$2:$BA$801,보유분석!$AC$2:$AC$801,1)/SUMIFS(보유분석!$BB$2:$BB$801,보유분석!$AC$2:$AC$801,1)))*100) | H85: =IF(SUMIFS(보유분석!$BD$2:$BD$801,보유분석!$W$2:$W$801,$A85,보유분석!$AC$2:$AC$801,1)=0,"",SUMIFS(보유분석!$BC$2:$BC$801,보유분석!$W$2:$W$801,$A85,보유분석!$AC$2:$AC$801,1)/SUMIFS(보유분석!$BD$2:$BD$801,보유분석!$W$2:$W$801,$A85,보유분석!$AC$2:$AC$801,1)) | I85: =IF(SUMIFS(보유분석!$BF$2:$BF$801,보유분석!$W$2:$W$801,$A85,보유분석!$AC$2:$AC$801,1)=0,"",SUMIFS(보유분석!$BE$2:$BE$801,보유분석!$W$2:$W$801,$A85,보유분석!$AC$2:$AC$801,1)/SUMIFS(보유분석!$BF$2:$BF$801,보유분석!$W$2:$W$801,$A85,보유분석!$AC$2:$AC$801,1)) | J85: =IF(SUMIFS(보유분석!$BG$2:$BG$801,보유분석!$W$2:$W$801,$A85,보유분석!$AC$2:$AC$801,1)=0,"",(SUMIFS(보유분석!$BC$2:$BC$801,보유분석!$W$2:$W$801,$A85,보유분석!$AC$2:$AC$801,1)+SUMIFS(보유분석!$BH$2:$BH$801,보유분석!$W$2:$W$801,$A85,보유분석!$AC$2:$AC$801,1))/SUMIFS(보유분석!$BG$2:$BG$801,보유분석!$W$2:$W$801,$A85,보유분석!$AC$2:$AC$801,1)) | K85: =IF(B85=0,"",SUMIFS(보유분석!$AV$2:$AV$801,보유분석!$W$2:$W$801,$A85,보유분석!$AC$2:$AC$801,1)/(B85*1000000)) | L85: =SUMIFS(보유분석!$AP$2:$AP$801,보유분석!$W$2:$W$801,$A85,보유분석!$AC$2:$AC$801,1) -> 0 | M85: =COUNTIFS(보유분석!$W$2:$W$801,$A85,보유분석!$AR$2:$AR$801,"Cheap",보유분석!$AC$2:$AC$801,1) -> 0 | N85: =COUNTIFS(보유분석!$W$2:$W$801,$A85,보유분석!$AR$2:$AR$801,"Rich",보유분석!$AC$2:$AC$801,1) -> 0 | P85: =IF(O85="","",O85-C85) | Q85: =-SUMIFS(보유분석!$AZ$2:$AZ$801,보유분석!$W$2:$W$801,$A85,보유분석!$AC$2:$AC$801,1)*설정!$C$10 -> 0 | R85: =IF((-SUMIFS(보유분석!$AZ$2:$AZ$801,보유분석!$AC$2:$AC$801,1)*설정!$C$10)=0,0,Q85/(-SUMIFS(보유분석!$AZ$2:$AZ$801,보유분석!$AC$2:$AC$801,1)*설정!$C$10)) -> 0 | S85: =IF(SUMIFS(보유분석!$BG$2:$BG$801,보유분석!$W$2:$W$801,$A85,보유분석!$AC$2:$AC$801,1)=0,"",SUMIFS(보유분석!$BH$2:$BH$801,보유분석!$W$2:$W$801,$A85,보유분석!$AC$2:$AC$801,1)/SUMIFS(보유분석!$BG$2:$BG$801,보유분석!$W$2:$W$801,$A85,보유분석!$AC$2:$AC$801,1)) | T85: =IF(SUMIFS(보유분석!$BI$2:$BI$801,보유분석!$W$2:$W$801,$A85,보유분석!$AC$2:$AC$801,1)=0,"",SUMIFS(보유분석!$BD$2:$BD$801,보유분석!$W$2:$W$801,$A85,보유분석!$AC$2:$AC$801,1)/SUMIFS(보유분석!$BI$2:$BI$801,보유분석!$W$2:$W$801,$A85,보유분석!$AC$2:$AC$801,1))
A86: 기타(목록외) | B86: =SUMPRODUCT(ISNA(MATCH(보유분석!$W$2:$W$801,$A$83:$A$85,0))*(보유분석!$AC$2:$AC$801=1)*보유분석!$AA$2:$AA$801) -> 0 | C86: =IF(SUMIFS(보유분석!$AA$2:$AA$801,보유분석!$AC$2:$AC$801,1)=0,0,B86/SUMIFS(보유분석!$AA$2:$AA$801,보유분석!$AC$2:$AC$801,1)) -> 0 | D86: =SUMPRODUCT(ISNA(MATCH(보유분석!$W$2:$W$801,$A$83:$A$85,0))*(보유분석!$AC$2:$AC$801=1)*보유분석!$AM$2:$AM$801) -> 0 | E86: =IF(SUMIFS(보유분석!$AM$2:$AM$801,보유분석!$AC$2:$AC$801,1)=0,0,D86/SUMIFS(보유분석!$AM$2:$AM$801,보유분석!$AC$2:$AC$801,1)) -> 0 | F86: =IF(SUMPRODUCT(ISNA(MATCH(보유분석!$W$2:$W$801,$A$83:$A$85,0))*(보유분석!$AC$2:$AC$801=1)*보유분석!$BB$2:$BB$801)=0,"",SUMPRODUCT(ISNA(MATCH(보유분석!$W$2:$W$801,$A$83:$A$85,0))*(보유분석!$AC$2:$AC$801=1)*보유분석!$BA$2:$BA$801)/SUMPRODUCT(ISNA(MATCH(보유분석!$W$2:$W$801,$A$83:$A$85,0))*(보유분석!$AC$2:$AC$801=1)*보유분석!$BB$2:$BB$801)) | G86: =IF(F86="","",(F86-(SUMIFS(보유분석!$BA$2:$BA$801,보유분석!$AC$2:$AC$801,1)/SUMIFS(보유분석!$BB$2:$BB$801,보유분석!$AC$2:$AC$801,1)))*100) | H86: =IF(SUMPRODUCT(ISNA(MATCH(보유분석!$W$2:$W$801,$A$83:$A$85,0))*(보유분석!$AC$2:$AC$801=1)*보유분석!$BD$2:$BD$801)=0,"",SUMPRODUCT(ISNA(MATCH(보유분석!$W$2:$W$801,$A$83:$A$85,0))*(보유분석!$AC$2:$AC$801=1)*보유분석!$BC$2:$BC$801)/SUMPRODUCT(ISNA(MATCH(보유분석!$W$2:$W$801,$A$83:$A$85,0))*(보유분석!$AC$2:$AC$801=1)*보유분석!$BD$2:$BD$801)) | I86: =IF(SUMPRODUCT(ISNA(MATCH(보유분석!$W$2:$W$801,$A$83:$A$85,0))*(보유분석!$AC$2:$AC$801=1)*보유분석!$BF$2:$BF$801)=0,"",SUMPRODUCT(ISNA(MATCH(보유분석!$W$2:$W$801,$A$83:$A$85,0))*(보유분석!$AC$2:$AC$801=1)*보유분석!$BE$2:$BE$801)/SUMPRODUCT(ISNA(MATCH(보유분석!$W$2:$W$801,$A$83:$A$85,0))*(보유분석!$AC$2:$AC$801=1)*보유분석!$BF$2:$BF$801)) | J86: =IF(SUMPRODUCT(ISNA(MATCH(보유분석!$W$2:$W$801,$A$83:$A$85,0))*(보유분석!$AC$2:$AC$801=1)*보유분석!$BG$2:$BG$801)=0,"",(SUMPRODUCT(ISNA(MATCH(보유분석!$W$2:$W$801,$A$83:$A$85,0))*(보유분석!$AC$2:$AC$801=1)*보유분석!$BC$2:$BC$801)+SUMPRODUCT(ISNA(MATCH(보유분석!$W$2:$W$801,$A$83:$A$85,0))*(보유분석!$AC$2:$AC$801=1)*보유분석!$BH$2:$BH$801))/SUMPRODUCT(ISNA(MATCH(보유분석!$W$2:$W$801,$A$83:$A$85,0))*(보유분석!$AC$2:$AC$801=1)*보유분석!$BG$2:$BG$801)) | K86: =IF(B86=0,"",SUMPRODUCT(ISNA(MATCH(보유분석!$W$2:$W$801,$A$83:$A$85,0))*(보유분석!$AC$2:$AC$801=1)*보유분석!$AV$2:$AV$801)/(B86*1000000)) | L86: =SUMPRODUCT(ISNA(MATCH(보유분석!$W$2:$W$801,$A$83:$A$85,0))*(보유분석!$AC$2:$AC$801=1)*보유분석!$AP$2:$AP$801) -> 0 | M86: =SUMPRODUCT(ISNA(MATCH(보유분석!$W$2:$W$801,$A$83:$A$85,0))*(보유분석!$AC$2:$AC$801=1)*(보유분석!$AR$2:$AR$801="Cheap")) -> 0 | N86: =SUMPRODUCT(ISNA(MATCH(보유분석!$W$2:$W$801,$A$83:$A$85,0))*(보유분석!$AC$2:$AC$801=1)*(보유분석!$AR$2:$AR$801="Rich")) -> 0 | P86: =IF(O86="","",O86-C86) | Q86: =-SUMPRODUCT(ISNA(MATCH(보유분석!$W$2:$W$801,$A$83:$A$85,0))*(보유분석!$AC$2:$AC$801=1)*보유분석!$AZ$2:$AZ$801)*설정!$C$10 -> 0 | R86: =IF((-SUMIFS(보유분석!$AZ$2:$AZ$801,보유분석!$AC$2:$AC$801,1)*설정!$C$10)=0,0,Q86/(-SUMIFS(보유분석!$AZ$2:$AZ$801,보유분석!$AC$2:$AC$801,1)*설정!$C$10)) -> 0 | S86: =IF(SUMPRODUCT(ISNA(MATCH(보유분석!$W$2:$W$801,$A$83:$A$85,0))*(보유분석!$AC$2:$AC$801=1)*보유분석!$BG$2:$BG$801)=0,"",SUMPRODUCT(ISNA(MATCH(보유분석!$W$2:$W$801,$A$83:$A$85,0))*(보유분석!$AC$2:$AC$801=1)*보유분석!$BH$2:$BH$801)/SUMPRODUCT(ISNA(MATCH(보유분석!$W$2:$W$801,$A$83:$A$85,0))*(보유분석!$AC$2:$AC$801=1)*보유분석!$BG$2:$BG$801)) | T86: =IF(SUMPRODUCT(ISNA(MATCH(보유분석!$W$2:$W$801,$A$83:$A$85,0))*(보유분석!$AC$2:$AC$801=1)*보유분석!$BI$2:$BI$801)=0,"",SUMPRODUCT(ISNA(MATCH(보유분석!$W$2:$W$801,$A$83:$A$85,0))*(보유분석!$AC$2:$AC$801=1)*보유분석!$BD$2:$BD$801)/SUMPRODUCT(ISNA(MATCH(보유분석!$W$2:$W$801,$A$83:$A$85,0))*(보유분석!$AC$2:$AC$801=1)*보유분석!$BI$2:$BI$801))
A87: 합계 | B87: =SUM(B83:B86) -> 1409.3986 | C87: =SUM(C83:C86) -> 1 | D87: =SUM(D83:D86) -> 379223.18 | E87: =SUM(E83:E86) -> 1 | F87: =IF(SUMIFS(보유분석!$BB$2:$BB$801,보유분석!$AC$2:$AC$801,1)=0,"",SUMIFS(보유분석!$BA$2:$BA$801,보유분석!$AC$2:$AC$801,1)/SUMIFS(보유분석!$BB$2:$BB$801,보유분석!$AC$2:$AC$801,1)) -> 5.6600358 | H87: =IF(SUMIFS(보유분석!$BD$2:$BD$801,보유분석!$AC$2:$AC$801,1)=0,"",SUMIFS(보유분석!$BC$2:$BC$801,보유분석!$AC$2:$AC$801,1)/SUMIFS(보유분석!$BD$2:$BD$801,보유분석!$AC$2:$AC$801,1)) -> 66.114006 | I87: =IF(SUMIFS(보유분석!$BF$2:$BF$801,보유분석!$AC$2:$AC$801,1)=0,"",SUMIFS(보유분석!$BE$2:$BE$801,보유분석!$AC$2:$AC$801,1)/SUMIFS(보유분석!$BF$2:$BF$801,보유분석!$AC$2:$AC$801,1)) -> 2.6906736 | J87: =IF(SUMIFS(보유분석!$BG$2:$BG$801,보유분석!$AC$2:$AC$801,1)=0,"",(SUMIFS(보유분석!$BC$2:$BC$801,보유분석!$AC$2:$AC$801,1)+SUMIFS(보유분석!$BH$2:$BH$801,보유분석!$AC$2:$AC$801,1))/SUMIFS(보유분석!$BG$2:$BG$801,보유분석!$AC$2:$AC$801,1)) -> 31.468574 | K87: =IF(B87=0,"",SUMIFS(보유분석!$AV$2:$AV$801,보유분석!$AC$2:$AC$801,1)/(B87*1000000)) -> 0.058254622 | L87: =SUM(L83:L86) -> -44901234 | O87: =IF(COUNT(O83:O86)=0,"",SUM(O83:O86)) | Q87: =SUM(Q83:Q86) -> -10177025 | R87: =SUM(R83:R86) -> 1 | S87: =IF(SUMIFS(보유분석!$BG$2:$BG$801,보유분석!$AC$2:$AC$801,1)=0,"",SUMIFS(보유분석!$BH$2:$BH$801,보유분석!$AC$2:$AC$801,1)/SUMIFS(보유분석!$BG$2:$BG$801,보유분석!$AC$2:$AC$801,1)) -> 6.4728238 | T87: =IF(SUMIFS(보유분석!$BI$2:$BI$801,보유분석!$AC$2:$AC$801,1)=0,"",SUMIFS(보유분석!$BD$2:$BD$801,보유분석!$AC$2:$AC$801,1)/SUMIFS(보유분석!$BI$2:$BI$801,보유분석!$AC$2:$AC$801,1)) -> 0.97796717

Sheet 매매후보
A1: 매매 후보 — 피어커브 대비 상대가치(z) 기준 (시장데이터 유니버스)
A2: 매수: Cheap & 제약통과(FRN·BBB0미만 제외, 보유여부 무관) / 매도: Rich & 선택 펀드 보유. 발행자내 상대잔차 = 같은 발행자 커브 안에서의 상대위치(+ 싸다)
A4: ▲ 매수/증액 후보 (Cheap 상위 20)
A5: 순위 | B5: 채권명 | C5: 발행자 | D5: 국가 | E5: 섹터 | F5: 등급 | G5: 듀레이션 | H5: YTM(%) | I5: G-spread | J5: 적정G | K5: 잔차(bp) | L5: z | M5: 발행자내 상대잔차 | N5: 보유 평가금액($M) | O5: 제약점검
A6: 1 | B6: =IF($R6="","",IF(INDEX(시장분석!$A$2:$A$601,$R6)="","",INDEX(시장분석!$A$2:$A$601,$R6))) -> SPCX 5.35 07/15/31 | C6: =IF($R6="","",IF(INDEX(시장분석!$B$2:$B$601,$R6)="","",INDEX(시장분석!$B$2:$B$601,$R6))) -> SPACE EXPLORATION TECH | D6: =IF($R6="","",IF(INDEX(시장분석!$W$2:$W$601,$R6)="","",INDEX(시장분석!$W$2:$W$601,$R6))) -> 미국 | E6: =IF($R6="","",IF(INDEX(시장분석!$L$2:$L$601,$R6)="","",INDEX(시장분석!$L$2:$L$601,$R6))) -> 통신 | F6: =IF($R6="","",IF(INDEX(시장분석!$M$2:$M$601,$R6)="","",INDEX(시장분석!$M$2:$M$601,$R6))) -> BBB | G6: =IF($R6="","",IF(INDEX(시장분석!$K$2:$K$601,$R6)="","",INDEX(시장분석!$K$2:$K$601,$R6))) -> 4.21 | H6: =IF($R6="","",IF(INDEX(시장분석!$D$2:$D$601,$R6)="","",INDEX(시장분석!$D$2:$D$601,$R6))) -> 6.533 | I6: =IF($R6="","",IF(INDEX(시장분석!$E$2:$E$601,$R6)="","",INDEX(시장분석!$E$2:$E$601,$R6))) -> 144.658 | J6: =IF($R6="","",IF(INDEX(시장분석!$AI$2:$AI$601,$R6)="","",INDEX(시장분석!$AI$2:$AI$601,$R6))) -> 80.351918 | K6: =IF($R6="","",IF(INDEX(시장분석!$AJ$2:$AJ$601,$R6)="","",INDEX(시장분석!$AJ$2:$AJ$601,$R6))) -> 64.306082 | L6: =IF($R6="","",IF(INDEX(시장분석!$AK$2:$AK$601,$R6)="","",INDEX(시장분석!$AK$2:$AK$601,$R6))) -> 4.1422881 | M6: =IF($R6="","",IF(INDEX(시장분석!$AM$2:$AM$601,$R6)="","",INDEX(시장분석!$AM$2:$AM$601,$R6))) -> 0 | N6: =IF($R6="","",IF(INDEX(시장분석!$AO$2:$AO$601,$R6)="","",INDEX(시장분석!$AO$2:$AO$601,$R6))) -> 4.76132 | O6: =IF($R6="","",IF(INDEX(시장분석!$AP$2:$AP$601,$R6)="","",INDEX(시장분석!$AP$2:$AP$601,$R6))) | Q6: =LARGE(시장분석!$AQ$2:$AQ$601,A6) -> 4.1422882 | R6: =IF(Q6<-900,"",MATCH(Q6,시장분석!$AQ$2:$AQ$601,0)) -> 150
A7: 2 | B7: =IF($R7="","",IF(INDEX(시장분석!$A$2:$A$601,$R7)="","",INDEX(시장분석!$A$2:$A$601,$R7))) -> SOCGEN 5.249 05/22/29 | C7: =IF($R7="","",IF(INDEX(시장분석!$B$2:$B$601,$R7)="","",INDEX(시장분석!$B$2:$B$601,$R7))) -> SOCIETE GENERALE | D7: =IF($R7="","",IF(INDEX(시장분석!$W$2:$W$601,$R7)="","",INDEX(시장분석!$W$2:$W$601,$R7))) -> 프랑스 | E7: =IF($R7="","",IF(INDEX(시장분석!$L$2:$L$601,$R7)="","",INDEX(시장분석!$L$2:$L$601,$R7))) -> 금융기관 | F7: =IF($R7="","",IF(INDEX(시장분석!$M$2:$M$601,$R7)="","",INDEX(시장분석!$M$2:$M$601,$R7))) -> BBB | G7: =IF($R7="","",IF(INDEX(시장분석!$K$2:$K$601,$R7)="","",INDEX(시장분석!$K$2:$K$601,$R7))) -> 1.563 | H7: =IF($R7="","",IF(INDEX(시장분석!$D$2:$D$601,$R7)="","",INDEX(시장분석!$D$2:$D$601,$R7))) -> 5.607 | I7: =IF($R7="","",IF(INDEX(시장분석!$E$2:$E$601,$R7)="","",INDEX(시장분석!$E$2:$E$601,$R7))) -> 87.451 | J7: =IF($R7="","",IF(INDEX(시장분석!$AI$2:$AI$601,$R7)="","",INDEX(시장분석!$AI$2:$AI$601,$R7))) -> 57.024617 | K7: =IF($R7="","",IF(INDEX(시장분석!$AJ$2:$AJ$601,$R7)="","",INDEX(시장분석!$AJ$2:$AJ$601,$R7))) -> 30.426383 | L7: =IF($R7="","",IF(INDEX(시장분석!$AK$2:$AK$601,$R7)="","",INDEX(시장분석!$AK$2:$AK$601,$R7))) -> 2.7689848 | M7: =IF($R7="","",IF(INDEX(시장분석!$AM$2:$AM$601,$R7)="","",INDEX(시장분석!$AM$2:$AM$601,$R7))) -> 0 | N7: =IF($R7="","",IF(INDEX(시장분석!$AO$2:$AO$601,$R7)="","",INDEX(시장분석!$AO$2:$AO$601,$R7))) -> 0.992107 | O7: =IF($R7="","",IF(INDEX(시장분석!$AP$2:$AP$601,$R7)="","",INDEX(시장분석!$AP$2:$AP$601,$R7))) | Q7: =LARGE(시장분석!$AQ$2:$AQ$601,A7) -> 2.7689849 | R7: =IF(Q7<-900,"",MATCH(Q7,시장분석!$AQ$2:$AQ$601,0)) -> 114
A8: 3 | B8: =IF($R8="","",IF(INDEX(시장분석!$A$2:$A$601,$R8)="","",INDEX(시장분석!$A$2:$A$601,$R8))) -> KOMRMR 5 3/8 05/11/28 | C8: =IF($R8="","",IF(INDEX(시장분석!$B$2:$B$601,$R8)="","",INDEX(시장분석!$B$2:$B$601,$R8))) -> KOREAREHABNRESOURCE | D8: =IF($R8="","",IF(INDEX(시장분석!$W$2:$W$601,$R8)="","",INDEX(시장분석!$W$2:$W$601,$R8))) -> 한국 | E8: =IF($R8="","",IF(INDEX(시장분석!$L$2:$L$601,$R8)="","",INDEX(시장분석!$L$2:$L$601,$R8))) -> 정부 | F8: =IF($R8="","",IF(INDEX(시장분석!$M$2:$M$601,$R8)="","",INDEX(시장분석!$M$2:$M$601,$R8))) | G8: =IF($R8="","",IF(INDEX(시장분석!$K$2:$K$601,$R8)="","",INDEX(시장분석!$K$2:$K$601,$R8))) -> 1.523 | H8: =IF($R8="","",IF(INDEX(시장분석!$D$2:$D$601,$R8)="","",INDEX(시장분석!$D$2:$D$601,$R8))) -> 5.277 | I8: =IF($R8="","",IF(INDEX(시장분석!$E$2:$E$601,$R8)="","",INDEX(시장분석!$E$2:$E$601,$R8))) -> 38.777 | J8: =IF($R8="","",IF(INDEX(시장분석!$AI$2:$AI$601,$R8)="","",INDEX(시장분석!$AI$2:$AI$601,$R8))) -> 6.8092994 | K8: =IF($R8="","",IF(INDEX(시장분석!$AJ$2:$AJ$601,$R8)="","",INDEX(시장분석!$AJ$2:$AJ$601,$R8))) -> 31.967701 | L8: =IF($R8="","",IF(INDEX(시장분석!$AK$2:$AK$601,$R8)="","",INDEX(시장분석!$AK$2:$AK$601,$R8))) -> 2.3345976 | M8: =IF($R8="","",IF(INDEX(시장분석!$AM$2:$AM$601,$R8)="","",INDEX(시장분석!$AM$2:$AM$601,$R8))) -> 16.90119 | N8: =IF($R8="","",IF(INDEX(시장분석!$AO$2:$AO$601,$R8)="","",INDEX(시장분석!$AO$2:$AO$601,$R8))) -> 0 | O8: =IF($R8="","",IF(INDEX(시장분석!$AP$2:$AP$601,$R8)="","",INDEX(시장분석!$AP$2:$AP$601,$R8))) -> 등급미입력 | Q8: =LARGE(시장분석!$AQ$2:$AQ$601,A8) -> 2.3345978 | R8: =IF(Q8<-900,"",MATCH(Q8,시장분석!$AQ$2:$AQ$601,0)) -> 219
A9: 4 | B9: =IF($R9="","",IF(INDEX(시장분석!$A$2:$A$601,$R9)="","",INDEX(시장분석!$A$2:$A$601,$R9))) -> HYNMTR 4 1/4 01/08/29 | C9: =IF($R9="","",IF(INDEX(시장분석!$B$2:$B$601,$R9)="","",INDEX(시장분석!$B$2:$B$601,$R9))) -> HYUNDAI CAPITAL AMERICA | D9: =IF($R9="","",IF(INDEX(시장분석!$W$2:$W$601,$R9)="","",INDEX(시장분석!$W$2:$W$601,$R9))) -> 미국 | E9: =IF($R9="","",IF(INDEX(시장분석!$L$2:$L$601,$R9)="","",INDEX(시장분석!$L$2:$L$601,$R9))) -> 자유 소비재 | F9: =IF($R9="","",IF(INDEX(시장분석!$M$2:$M$601,$R9)="","",INDEX(시장분석!$M$2:$M$601,$R9))) -> A- | G9: =IF($R9="","",IF(INDEX(시장분석!$K$2:$K$601,$R9)="","",INDEX(시장분석!$K$2:$K$601,$R9))) -> 2.163 | H9: =IF($R9="","",IF(INDEX(시장분석!$D$2:$D$601,$R9)="","",INDEX(시장분석!$D$2:$D$601,$R9))) -> 5.68 | I9: =IF($R9="","",IF(INDEX(시장분석!$E$2:$E$601,$R9)="","",INDEX(시장분석!$E$2:$E$601,$R9))) -> 68.024 | J9: =IF($R9="","",IF(INDEX(시장분석!$AI$2:$AI$601,$R9)="","",INDEX(시장분석!$AI$2:$AI$601,$R9))) -> 57.913134 | K9: =IF($R9="","",IF(INDEX(시장분석!$AJ$2:$AJ$601,$R9)="","",INDEX(시장분석!$AJ$2:$AJ$601,$R9))) -> 10.110866 | L9: =IF($R9="","",IF(INDEX(시장분석!$AK$2:$AK$601,$R9)="","",INDEX(시장분석!$AK$2:$AK$601,$R9))) -> 2.3311662 | M9: =IF($R9="","",IF(INDEX(시장분석!$AM$2:$AM$601,$R9)="","",INDEX(시장분석!$AM$2:$AM$601,$R9))) -> 10.110866 | N9: =IF($R9="","",IF(INDEX(시장분석!$AO$2:$AO$601,$R9)="","",INDEX(시장분석!$AO$2:$AO$601,$R9))) -> 0.971293 | O9: =IF($R9="","",IF(INDEX(시장분석!$AP$2:$AP$601,$R9)="","",INDEX(시장분석!$AP$2:$AP$601,$R9))) | Q9: =LARGE(시장분석!$AQ$2:$AQ$601,A9) -> 2.3311663 | R9: =IF(Q9<-900,"",MATCH(Q9,시장분석!$AQ$2:$AQ$601,0)) -> 70
A10: 5 | B10: =IF($R10="","",IF(INDEX(시장분석!$A$2:$A$601,$R10)="","",INDEX(시장분석!$A$2:$A$601,$R10))) -> KOMRMR 4 7/8 04/13/31 | C10: =IF($R10="","",IF(INDEX(시장분석!$B$2:$B$601,$R10)="","",INDEX(시장분석!$B$2:$B$601,$R10))) -> KOREA MINE REHAB MINERAL | D10: =IF($R10="","",IF(INDEX(시장분석!$W$2:$W$601,$R10)="","",INDEX(시장분석!$W$2:$W$601,$R10))) -> 한국 | E10: =IF($R10="","",IF(INDEX(시장분석!$L$2:$L$601,$R10)="","",INDEX(시장분석!$L$2:$L$601,$R10))) -> 정부 | F10: =IF($R10="","",IF(INDEX(시장분석!$M$2:$M$601,$R10)="","",INDEX(시장분석!$M$2:$M$601,$R10))) -> A+ | G10: =IF($R10="","",IF(INDEX(시장분석!$K$2:$K$601,$R10)="","",INDEX(시장분석!$K$2:$K$601,$R10))) -> 4.009 | H10: =IF($R10="","",IF(INDEX(시장분석!$D$2:$D$601,$R10)="","",INDEX(시장분석!$D$2:$D$601,$R10))) -> 5.651 | I10: =IF($R10="","",IF(INDEX(시장분석!$E$2:$E$601,$R10)="","",INDEX(시장분석!$E$2:$E$601,$R10))) -> 56.385 | J10: =IF($R10="","",IF(INDEX(시장분석!$AI$2:$AI$601,$R10)="","",INDEX(시장분석!$AI$2:$AI$601,$R10))) -> 26.038253 | K10: =IF($R10="","",IF(INDEX(시장분석!$AJ$2:$AJ$601,$R10)="","",INDEX(시장분석!$AJ$2:$AJ$601,$R10))) -> 30.346747 | L10: =IF($R10="","",IF(INDEX(시장분석!$AK$2:$AK$601,$R10)="","",INDEX(시장분석!$AK$2:$AK$601,$R10))) -> 2.2162195 | M10: =IF($R10="","",IF(INDEX(시장분석!$AM$2:$AM$601,$R10)="","",INDEX(시장분석!$AM$2:$AM$601,$R10))) -> 0 | N10: =IF($R10="","",IF(INDEX(시장분석!$AO$2:$AO$601,$R10)="","",INDEX(시장분석!$AO$2:$AO$601,$R10))) -> 0 | O10: =IF($R10="","",IF(INDEX(시장분석!$AP$2:$AP$601,$R10)="","",INDEX(시장분석!$AP$2:$AP$601,$R10))) | Q10: =LARGE(시장분석!$AQ$2:$AQ$601,A10) -> 2.2162198 | R10: =IF(Q10<-900,"",MATCH(Q10,시장분석!$AQ$2:$AQ$601,0)) -> 255
A11: 6 | B11: =IF($R11="","",IF(INDEX(시장분석!$A$2:$A$601,$R11)="","",INDEX(시장분석!$A$2:$A$601,$R11))) -> POINTL 5 1/8 06/29/31 | C11: =IF($R11="","",IF(INDEX(시장분석!$B$2:$B$601,$R11)="","",INDEX(시장분석!$B$2:$B$601,$R11))) -> POSCO INTERNATIONAL CORP | D11: =IF($R11="","",IF(INDEX(시장분석!$W$2:$W$601,$R11)="","",INDEX(시장분석!$W$2:$W$601,$R11))) -> 한국 | E11: =IF($R11="","",IF(INDEX(시장분석!$L$2:$L$601,$R11)="","",INDEX(시장분석!$L$2:$L$601,$R11))) -> 원자재 | F11: =IF($R11="","",IF(INDEX(시장분석!$M$2:$M$601,$R11)="","",INDEX(시장분석!$M$2:$M$601,$R11))) -> BBB | G11: =IF($R11="","",IF(INDEX(시장분석!$K$2:$K$601,$R11)="","",INDEX(시장분석!$K$2:$K$601,$R11))) -> 4.202 | H11: =IF($R11="","",IF(INDEX(시장분석!$D$2:$D$601,$R11)="","",INDEX(시장분석!$D$2:$D$601,$R11))) -> 6.111 | I11: =IF($R11="","",IF(INDEX(시장분석!$E$2:$E$601,$R11)="","",INDEX(시장분석!$E$2:$E$601,$R11))) -> 102.421 | J11: =IF($R11="","",IF(INDEX(시장분석!$AI$2:$AI$601,$R11)="","",INDEX(시장분석!$AI$2:$AI$601,$R11))) -> 83.607755 | K11: =IF($R11="","",IF(INDEX(시장분석!$AJ$2:$AJ$601,$R11)="","",INDEX(시장분석!$AJ$2:$AJ$601,$R11))) -> 18.813245 | L11: =IF($R11="","",IF(INDEX(시장분석!$AK$2:$AK$601,$R11)="","",INDEX(시장분석!$AK$2:$AK$601,$R11))) -> 1.6994738 | M11: =IF($R11="","",IF(INDEX(시장분석!$AM$2:$AM$601,$R11)="","",INDEX(시장분석!$AM$2:$AM$601,$R11))) -> 0 | N11: =IF($R11="","",IF(INDEX(시장분석!$AO$2:$AO$601,$R11)="","",INDEX(시장분석!$AO$2:$AO$601,$R11))) -> 14.446515 | O11: =IF($R11="","",IF(INDEX(시장분석!$AP$2:$AP$601,$R11)="","",INDEX(시장분석!$AP$2:$AP$601,$R11))) | Q11: =LARGE(시장분석!$AQ$2:$AQ$601,A11) -> 1.699474 | R11: =IF(Q11<-900,"",MATCH(Q11,시장분석!$AQ$2:$AQ$601,0)) -> 197
